Workbook
Name CQ: '[1]Roll-Forward Dates'!$C$124
Name CQ_and_PY_Date: '[1]Roll-Forward Dates'!$C$153
Name CQ_CAPS: '[1]Roll-Forward Dates'!$C$125
Name CQ_Comparative: '[1]Roll-Forward Dates'!$C$148
Name CY_FiHis_ETFA: #REF!
Name CY_FiHis_ETFB: #REF!
Name CY_FiHis_ETFC: #REF!
Name CY_FiHis_ETFCIA: #REF!
Name CY_FiHis_ETFCIB: #REF!
Name CY_FiHis_ETFCIC: #REF!
Name CY_FiHis_ETFCIE: #REF!
Name CY_FiHis_ETFCombined: #REF!
Name CY_FiHis_ETFE: #REF!
Name CY_FiHis_ETFSCA: #REF!
Name CY_FiHis_ETFSCB: #REF!
Name CY_FiHis_ETFSCC: #REF!
Name CY_FiHis_FF1: 'Fund X-C'!$C$163:$E$174
Name CY_FiHis_FF2: 'Fund X-D'!$C$163:$E$174
Name CY_FiHis_FF3: 'VIII-D'!$C$146:$E$157
Name CY_FiHis_MF: 'Fund X'!$C$163:$E$174
Name CYTD: '[1]Roll-Forward Dates'!$C$147
Name CYTD_and_YE_PY_Date: '[1]Roll-Forward Dates'!$C$152
Name FS_Stm_Oprations: [1]Inc!$A$7:$C$30
Name Period_05: '[1]Roll-Forward Dates'!$C$126
Name PY: '[1]Roll-Forward Dates'!$C$122
Name PY_Date: '[1]Roll-Forward Dates'!$C$140

Sheet Combined A Funds
B4: Financial Highlights EETF - Combined A Funds
E8: 44561 | I8: INPUT CELLS
G9: INPUT CELLS | I9: =29562500/35776020.41 -> 0.82632164 | J9: INPUT CELLS
C10: Net investment income/loss | E10: =I10/(J33) -> #DIV/0! | G10: =0-129939-241022 -> -370961 | I10: =(G10*$I$9)+J10 -> -752400.1 | J10: -445867 | K10: Mgmt fees
C12: Expense ratios
C13: Operating expenses | E13: =I13/(J33) -> #DIV/0! | G13: =129939+241022 -> 370961 | I13: =G13*$I$9+J13 -> 752400.1 | J13: =-J10 -> 445867
C14: Incentive allocation | E14: =(I14)/(J33) -> #DIV/0! | G14: 0 | I14: =G14*$I$9 -> 0
C15: Total expenses and incentive allocation | E15: =E13+E14 -> #DIV/0!
C17: Internal rate of return
C18: Internal rate of return after incentive allocation | E18: =G68 -> #REF!
C19: ROI | E19: =-(G66+I67)/I66 -> #REF!
J20: INPUT CELLS
J21: =L21+M21+N21+O21+P21+Q21+R21+S21+T21+U21+V21 -> 0 | K21: Jan
J22: =L22+M22+N22+O22+P22+Q22+R22+S22+T22+U22+V22 -> 0 | K22: Feb
J23: =L23+M23+N23+O23+P23+Q23+R23+S23+T23+U23+V23 -> 0 | K23: Mar
C24: Contributions | E24: 43857 | G24: -693875 | J24: =L24+M24+N24+O24+P24+Q24+R24+S24+T24+U24+V24 -> 0 | K24: Apr
C25: All Activity pasted in from subsequent tabs | E25: 43985 | G25: -7416500 | J25: =L25+M25+N25+O25+P25+Q25+R25+S25+T25+U25+V25 -> 0 | K25: May
E26: 44076 | G26: -4382625 | J26: =L26+M26+N26+O26+P26+Q26+R26+S26+T26+U26+V26 -> 0 | K26: Jun
E27: 44141 | G27: -3082950 | J27: =L27+M27+N27+O27+P27+Q27+R27+S27+T27+U27+V27 -> 0 | K27: Jul
E28: 44148 | G28: -7275862.5 | J28: =L28+M28+N28+O28+P28+Q28+R28+S28+T28+U28+V28 -> 0 | K28: Aug
E29: 44187 | G29: -1892000 | J29: =L29+M29+N29+O29+P29+Q29+R29+S29+T29+U29+V29 -> 0 | K29: Sep
E30: 44203 | G30: -24296301 | J30: =L30+M30+N30+O30+P30+Q30+R30+S30+T30+U30+V30 -> 0 | K30: Oct
E31: 44250 | G31: 5859033.8 | J31: =L31+M31+N31+O31+P31+Q31+R31+S31+T31+U31+V31 -> 0 | K31: Nov
E32: 44265 | G32: -20755762 | J32: =L32+M32+N32+O32+P32+Q32+R32+S32+T32+U32+V32 -> 0 | K32: Dec
E33: 44291 | G33: -29642140 | J33: =SUM(J21:J32)/12 -> 0 | K33: AVG NAV
E34: 44307 | G34: -35880618
E35: 44319 | G35: 37809430
E36: 44335 | G36: -4205628.6
E37: 44344 | G37: 20268178
E38: 44375 | G38: -6218476.1
E39: 44405 | G39: -3521086
E40: 44468 | G40: -1653652.9
E41: 44148 | G41: -2425287.5
E42: 44187 | G42: -200800
E43: 44203 | G43: -7819766.9
E44: 44250 | G44: 1248011.3
E45: 44265 | G45: -4375937.5
... E60: 44375 | G60: -2219396.2
C66: Net assets | E66: =+E8 -> 44561 | G66: =#REF!+#REF!+#REF! -> #REF! | I66: =SUM(G24:G60) -> -1.4833891e+08 | J66: check figure-Contributions
I67: 0 | J67: check figure-Distributions
C68: Total return | G68: =+XIRR(G24:G66,E24:E66,0.1) -> #REF!
C77: Net investment loss ratio | E77: =E10 -> #DIV/0!
C79: Expense ratios:
C80: Operating expenses | E80: =E13 -> #DIV/0!
C81: Unearned incentive allocation | E81: =E14 -> #DIV/0!
C82: Operating expenses and unearned incentive allocation ratio | E82: =SUM(E80:E81) -> #DIV/0!
C84: Internal rate of return net of incentive allocation | E84: =+E18 -> #REF!

Sheet Combined A Hypo
B4: Financial Highlights EETF - Combined A Funds (Hypothetical CFs)
E8: 44561 | I8: INPUT CELLS
G9: INPUT CELLS | I9: =29562500/35776020.41 -> 0.82632164 | J9: INPUT CELLS
C10: Net investment income/loss | E10: =I10/(J33) -> #DIV/0! | G10: =0-129939-241022 -> -370961 | I10: =(G10*$I$9)+J10 -> -752400.1 | J10: -445867 | K10: Mgmt fees
C12: Expense ratios
C13: Operating expenses | E13: =I13/(J33) -> #DIV/0! | G13: =129939+241022 -> 370961 | I13: =G13*$I$9+J13 -> 752400.1 | J13: =-J10 -> 445867
C14: Incentive allocation | E14: =(I14)/(J33) -> #DIV/0! | G14: 0 | I14: =G14*$I$9 -> 0
C15: Total expenses and incentive allocation | E15: =E13+E14 -> #DIV/0!
C17: Internal rate of return
C18: Internal rate of return after incentive allocation | E18: =G87 -> #REF!
C19: ROI | E19: =-(G85+I86)/I85 -> #REF!
J20: INPUT CELLS
J21: =L21+M21+N21+O21+P21+Q21+R21+S21+T21+U21+V21 -> 0 | K21: Jan
J22: =L22+M22+N22+O22+P22+Q22+R22+S22+T22+U22+V22 -> 0 | K22: Feb
J23: =L23+M23+N23+O23+P23+Q23+R23+S23+T23+U23+V23 -> 0 | K23: Mar
C24: Contributions | E24: 43857 | G24: -7574109.8 | J24: =L24+M24+N24+O24+P24+Q24+R24+S24+T24+U24+V24 -> 0 | K24: Apr
C25: All Activity pasted in from subsequent tabs | E25: 43985 | G25: -8109565.2 | J25: =L25+M25+N25+O25+P25+Q25+R25+S25+T25+U25+V25 -> 0 | K25: May
E26: 44076 | G26: -9256083.2 | J26: =L26+M26+N26+O26+P26+Q26+R26+S26+T26+U26+V26 -> 0 | K26: Jun
E27: 44117 | G27: -9231367.2 | J27: =L27+M27+N27+O27+P27+Q27+R27+S27+T27+U27+V27 -> 0 | K27: Jul
E28: 44141 | G28: -8243800.9 | J28: =L28+M28+N28+O28+P28+Q28+R28+S28+T28+U28+V28 -> 0 | K28: Aug
E29: 44148 | G29: -4300137.9 | J29: =L29+M29+N29+O29+P29+Q29+R29+S29+T29+U29+V29 -> 0 | K29: Sep
E30: 44187 | G30: -3920928.2 | J30: =L30+M30+N30+O30+P30+Q30+R30+S30+T30+U30+V30 -> 0 | K30: Oct
E31: 44203 | G31: -16776927 | J31: =L31+M31+N31+O31+P31+Q31+R31+S31+T31+U31+V31 -> 0 | K31: Nov
E32: 44217 | G32: -2194068.1 | J32: =L32+M32+N32+O32+P32+Q32+R32+S32+T32+U32+V32 -> 0 | K32: Dec
E33: 44250 | G33: 7925754.3 | J33: =SUM(J21:J32)/12 -> 0 | K33: AVG NAV
E34: 44265 | G34: -4940200.2
E35: 44291 | G35: -11743015
E36: 44307 | G36: -26632769
E37: 44319 | G37: 26987928
E38: 44335 | G38: -12755537
E39: 44344 | G39: 14731457
E40: 44361 | G40: 445749.22
E41: 44375 | G41: -6218476.1
E42: 44405 | G42: -3521086
E43: 44468 | G43: -1653652.9
E44: 43857 | G44: -1916207.2
E45: 43985 | G45: -2051674.4
... E73: 44250 | G73: 4272371.4
E74: 44265 | G74: =-2252124.74360582-327074.700190716 -> -2579199.4
E75: 44291 | G75: -6226211.2
E76: 44307 | G76: -13927597
E77: 44319 | G77: 14547821
E78: 44335 | G78: -6629243.6
E79: 44344 | G79: =8538694.07299078-597714.174819936 -> 7940979.9
E80: 44361 | G80: =-213231.101774318+416864.853389408 -> 203633.75
E81: 44375 | G81: -2219396.2
C85: Net assets | E85: =+E8 -> 44561 | G85: ='EETF I-A'!G69+'EETF Co Inv I-A Hypo'!G49+'EETF Sidecar I-A Hypo'!G46 -> #REF! | I85: =SUM(G24:G81) -> -1.4833891e+08 | J85: check figure-Contributions
I86: 0 | J86: check figure-Distributions
C87: Total return | G87: =+XIRR(G24:G85,E24:E85,0.1) -> #REF!
C96: Net investment loss ratio | E96: =E10 -> #DIV/0!
C98: Expense ratios:
C99: Operating expenses | E99: =E13 -> #DIV/0!
C100: Unearned incentive allocation | E100: =E14 -> #DIV/0!
C101: Operating expenses and unearned incentive allocation ratio | E101: =SUM(E99:E100) -> #DIV/0!
C103: Internal rate of return net of incentive allocation | E103: =+E18 -> #REF!

Sheet ETF Main Co A funds hypo
B4: Financial Highlights EETF I-A
C8: Internal rate of return
C9: Internal rate of return after incentive allocation | E9: =G43 -> #REF!
C10: ROI | E10: =-(G41+I42)/I41 -> #REF!
C15: Contributions 2020 | E15: 43857 | G15: ='EETF I-A'!G24+'EETF Co Inv I-A Hypo'!G21 -> -9490317
E16: 43985 | G16: ='EETF I-A'!G25+'EETF Co Inv I-A Hypo'!G22 -> -10161240
E17: 44076 | G17: ='EETF I-A'!G26+'EETF Co Inv I-A Hypo'!G23 -> -11185362
E18: 44117 | G18: ='EETF I-A'!G27+'EETF Co Inv I-A Hypo'!G24 -> -11566851
E19: 44141 | G19: ='EETF I-A'!G28+'EETF Co Inv I-A Hypo'!G25 -> -10329436
E20: 44148 | G20: ='EETF I-A'!G29+'EETF Co Inv I-A Hypo'!G26 -> -5388048.7
E21: 44187 | G21: ='EETF I-A'!G30+'EETF Co Inv I-A Hypo'!G27 -> -4849321.5
C22: Contributions 2021 | E22: 44203 | G22: ='EETF I-A'!G31+'EETF Co Inv I-A Hypo'!G28 -> -20915253
E23: 44217 | G23: ='EETF I-A'!G32+'EETF Co Inv I-A Hypo'!G29 -> -2749155
E24: 44250 | G24: ='EETF I-A'!G33+'EETF Co Inv I-A Hypo'!G30 -> 9930925.6
E25: 44265 | G25: ='EETF I-A'!G34+'EETF Co Inv I-A Hypo'!G31 -> -6156511.2
E26: 44291 | G26: ='EETF I-A'!G35+'EETF Co Inv I-A Hypo'!G32 -> -14655944
E27: 44307 | G27: ='EETF I-A'!G36+'EETF Co Inv I-A Hypo'!G33 -> -33199163
E28: 44319 | G28: ='EETF I-A'!G37+'EETF Co Inv I-A Hypo'!G34 -> 33815722
E29: 44335 | G29: ='EETF I-A'!G38+'EETF Co Inv I-A Hypo'!G35 -> -15883947
E30: 44344 | G30: ='EETF I-A'!G39+'EETF Co Inv I-A Hypo'!G36 -> 18458433
E31: 44361 | G31: ='EETF I-A'!G40+'EETF Co Inv I-A Hypo'!G37 -> 541321.57
E32: 44375 | G32: ='EETF I-A'!G41+'EETF Co Inv I-A Hypo'!G38 -> -7483634.6
E33: 44405 | G33: ='EETF I-A'!G42+'EETF Co Inv I-A Hypo'!G39 -> -4410936.6
E34: 44468 | G34: ='EETF I-A'!G43+'EETF Co Inv I-A Hypo'!G40 -> -1935800.6
... E39: 44558 | G39: ='EETF I-A'!G48+'EETF Co Inv I-A Hypo'!G45 -> 51543245
C41: Net assets | E41: 44561 | G41: ='EETF I-A'!G69+'EETF Co Inv I-A Hypo'!G49 -> #REF! | I41: =+SUMIF($G$15:$G$40,"<0",$G$15:$G$40)+G24+G28+G30+G31 -> -1.2697116e+08 | J41: check figure-Contributions
I42: =+SUMIF($G$15:$G$40,">0",$G$15:$G$40)-G24-G28-G30-G31 -> 51543245 | J42: check figure-Distributions
C43: Total return | G43: =+XIRR(G15:G41,E15:E41,0.1) -> #REF!

Sheet ETF A funds Combined hypo
B4: Financial Highlights EETF I-A
C8: Internal rate of return
C9: Internal rate of return after incentive allocation | E9: =G45 -> #REF!
C10: ROI | E10: =-(G43+I44)/I43 -> #REF!
C15: Contributions 2020 | E15: 43857 | G15: ='EETF I-A'!G24+'EETF Co Inv I-A Hypo'!G21+'EETF Sidecar I-A Hypo'!G21 -> -13573135
E16: 43985 | G16: ='EETF I-A'!G25+'EETF Co Inv I-A Hypo'!G22+'EETF Sidecar I-A Hypo'!G22 -> -14532694
E17: 44076 | G17: ='EETF I-A'!G26+'EETF Co Inv I-A Hypo'!G23+'EETF Sidecar I-A Hypo'!G23 -> -15143927
E18: 44117 | G18: ='EETF I-A'!G27+'EETF Co Inv I-A Hypo'!G24+'EETF Sidecar I-A Hypo'!G24 -> -16543012
E19: 44141 | G19: ='EETF I-A'!G28+'EETF Co Inv I-A Hypo'!G25+'EETF Sidecar I-A Hypo'!G25 -> -14773250
E20: 44148 | G20: ='EETF I-A'!G29+'EETF Co Inv I-A Hypo'!G26+'EETF Sidecar I-A Hypo'!G26 -> -7706034.5
E21: 44187 | G21: ='EETF I-A'!G30+'EETF Co Inv I-A Hypo'!G27+'EETF Sidecar I-A Hypo'!G27 -> -6803980.6
C22: Contributions 2021 | E22: 44203 | G22: ='EETF I-A'!G31+'EETF Co Inv I-A Hypo'!G28+'EETF Sidecar I-A Hypo'!G28 -> -29693544
E23: 44217 | G23: ='EETF I-A'!G32+'EETF Co Inv I-A Hypo'!G29+'EETF Sidecar I-A Hypo'!G29 -> -3972951
E24: 44250 | G24: ='EETF I-A'!G33+'EETF Co Inv I-A Hypo'!G30+'EETF Sidecar I-A Hypo'!G30 -> 14203297
E25: 44265 | G25: ='EETF I-A'!G34+'EETF Co Inv I-A Hypo'!G31+'EETF Sidecar I-A Hypo'!G31 -> -8735710.6
E26: 44291 | G26: ='EETF I-A'!G35+'EETF Co Inv I-A Hypo'!G32+'EETF Sidecar I-A Hypo'!G32 -> -20882156
E27: 44307 | G27: ='EETF I-A'!G36+'EETF Co Inv I-A Hypo'!G33+'EETF Sidecar I-A Hypo'!G33 -> -47126760
E28: 44319 | G28: ='EETF I-A'!G37+'EETF Co Inv I-A Hypo'!G34+'EETF Sidecar I-A Hypo'!G34 -> 48363543
E29: 44335 | G29: ='EETF I-A'!G38+'EETF Co Inv I-A Hypo'!G35+'EETF Sidecar I-A Hypo'!G35 -> -22513190
E30: 44344 | G30: ='EETF I-A'!G39+'EETF Co Inv I-A Hypo'!G36+'EETF Sidecar I-A Hypo'!G36 -> 26399413
E31: 44361 | G31: ='EETF I-A'!G40+'EETF Co Inv I-A Hypo'!G37+'EETF Sidecar I-A Hypo'!G37 -> 744955.32
E32: 44375 | G32: ='EETF I-A'!G41+'EETF Co Inv I-A Hypo'!G38+'EETF Sidecar I-A Hypo'!G38 -> -9703030.8
E33: 44405 | G33: ='EETF I-A'!G42+'EETF Co Inv I-A Hypo'!G39 -> -4410936.6
E34: 44468 | G34: ='EETF I-A'!G43+'EETF Co Inv I-A Hypo'!G40 -> -1935800.6
E35: 44475 | G35: ='EETF I-A'!G44+'EETF Co Inv I-A Hypo'!G41+'EETF Sidecar I-A Hypo'!G39 -> -7188775.3
E36: 44483 | G36: ='EETF I-A'!G45+'EETF Co Inv I-A Hypo'!G42+'EETF Sidecar I-A Hypo'!G40 -> -6315014.1
E37: 44505 | G37: ='EETF I-A'!G46+'EETF Co Inv I-A Hypo'!G43+'EETF Sidecar I-A Hypo'!G41 -> -7363013.7
E38: 44551 | G38: ='EETF I-A'!G47+'EETF Co Inv I-A Hypo'!G44+'EETF Sidecar I-A Hypo'!G42 -> -4273521.1
C39: Distributions 2021 | E39: 44558 | G39: ='EETF I-A'!G48+'EETF Co Inv I-A Hypo'!G45+'EETF Sidecar I-A Hypo'!G43 -> 72289581
C40: Contributions 2022 | E40: 44599 | G40: ='EETF I-A'!G49+'EETF Co Inv I-A Hypo'!G46 -> -2191169.5
E41: 44635 | G41: ='EETF I-A'!G50+'EETF Co Inv I-A Hypo'!G47+'EETF Sidecar I-A Hypo'!G44 -> -8436152.7
C43: Net assets | E43: =#REF! -> #REF! | G43: ='EETF I-A'!G69+'EETF Co Inv I-A Hypo'!G49+'EETF Sidecar I-A Hypo'!G46 -> #REF! | I43: =+SUMIF($G$15:$G$42,"<0",$G$15:$G$42)+G24+G28+G30+G31 -> -1.8410655e+08 | J43: check figure-Contributions | K43: =I43-('EETF I-A'!I69+'EETF Co Inv I-A Hypo'!I49+'EETF Sidecar I-A Hypo'!I46) -> 75025771 | L43: =I43-(#REF!+#REF!+#REF!) -> #REF!
I44: =+SUMIF($G$15:$G$42,">0",$G$15:$G$42)-G24-G28-G30-G31 -> 72289581 | J44: check figure-Distributions | K44: =I44-('EETF I-A'!I70+'EETF Co Inv I-A Hypo'!I50+'EETF Sidecar I-A Hypo'!I47) -> -90628832 | L44: =I44-(#REF!+#REF!+#REF!) -> #REF!
C45: Total return | G45: =+XIRR(G15:G43,E15:E43,0.1) -> #REF!

Sheet Actual Hypo %s
B6: A | C6: B | D6: C* | E6: E | F6: CIA | G6: CIB | H6: CIC* | I6: CIE | J6: SCA | K6: SCB | L6: SCC*
A7: Total LP - Actual | B7: =#REF! -> #REF! | C7: =#REF! -> #REF! | D7: =#REF! -> #REF! | E7: =#REF! -> #REF! | F7: =#REF! -> #REF! | G7: =#REF! -> #REF! | H7: =#REF! -> #REF! | I7: =#REF! -> #REF! | ... L7: =#REF! -> #REF!
A8: Total LP - Hypo | B8: ='EETF I-A'!G71 -> 0.25984918 | C8: ='EETF I-B hypo'!G52 -> 0.37967424 | D8: ='EETF I-C hypo'!G52 -> 0.27906733 | E8: ='EETF I-E hypo'!G52 -> 0.38163324 | F8: ='EETF Co Inv I-A Hypo'!G51 -> #REF! | G8: ='EETF Co Inv I-B hypo'!G49 -> #REF! | H8: ='EETF Co Inv I-C hypo'!G49 -> #REF! | I8: ='EETF Co Inv I-E hypo'!G49 -> #REF! | J8: ='EETF Sidecar I-A Hypo'!G48 -> #REF! | K8: ='EETF Sidecar I-B hypo'!G47 -> #REF! | L8: ='EETF Sidecar I-C hypo'!G47 -> #REF!
A9: * Note Broad Reach tax provision only impacts the C funds

Sheet EETF I-A w INT
B4: Financial Highlights EETF I-A
E8: 44561 | I8: INPUT CELLS
G9: INPUT CELLS | I9: =29562500/35776020.41 -> 0.82632164 | J9: INPUT CELLS
C10: Net investment income/loss | E10: =I10/(J33) -> -0.051530979 | G10: =0-129939-241022 -> -370961 | I10: =(G10*$I$9)+J10 -> -752400.1 | J10: -445867 | K10: Mgmt fees
C12: Expense ratios
C13: Operating expenses | E13: =I13/(J33) -> 0.051530979 | G13: =129939+241022 -> 370961 | I13: =G13*$I$9+J13 -> 752400.1 | J13: =-J10 -> 445867
C14: Incentive allocation | E14: =(I14)/(J33) -> 0 | G14: 0 | I14: =G14*$I$9 -> 0
C15: Total expenses and incentive allocation | E15: =E13+E14 -> 0.051530979
C17: Internal rate of return
C18: Internal rate of return after incentive allocation | E18: =G55 -> 0.44265724
C19: ROI | E19: =-(G53+I54)/I53 -> 1.3823748
J20: INPUT CELLS
J21: =693875 -> 693875 | K21: Jan
J22: =693875 -> 693875 | K22: Feb
J23: =674251 -> 674251 | K23: Mar
C24: Contributions 2020 | E24: 43857 | G24: -693875 | J24: =662813 -> 662813 | K24: Apr
E25: 43985 | G25: -7416500 | J25: =550875 -> 550875 | K25: May
E26: 44076 | G26: -4382625 | J26: =7912747 -> 7912747 | K26: Jun
E27: 44141 | G27: -3082950 | J27: =7837185 -> 7837185 | K27: Jul
E28: 44148 | G28: -7275862.5 | J28: =7837185 -> 7837185 | K28: Aug
E29: 44187 | G29: -1892000 | J29: =12208967 -> 12208967 | K29: Sep
C30: Contributions 2021 | E30: 44203 | G30: -24296301 | J30: =12133404 -> 12133404 | K30: Oct
E31: 44250 | G31: 5859033.8 | J31: =21943654 -> 21943654 | K31: Nov
E32: 44265 | G32: -20755762 | J32: =G53 -> 102062302 | K32: Dec
E33: 44291 | G33: -29642140 | J33: =SUM(J21:J32)/12 -> 14600928 | K33: AVG NAV
E34: 44307 | G34: -35880618
E35: 44319 | G35: 37809430
E36: 44335 | G36: -4205628.6
E37: 44344 | G37: =20268177.93+830538.11-1675268.66 -> 19423447
E38: 44375 | G38: =-6218476.1-209162.1 -> -6427638.2
E39: 44405 | G39: -3521086
E40: 44468 | G40: -1653652.9
E41: 44475 | G41: -4024098.3
E42: 44483 | G42: -4703164.9
E43: 44505 | G43: -4225303.2
E44: 44551 | G44: -2584225.6
E45: 44558 | G45: 41112360
C53: Net assets | E53: =+E8 -> 44561 | G53: 102062302 | I53: =+SUMIF($G$24:$G$52,"<0",$G$24:$G$52)+G31+G35+G37 -> -1.0357152e+08 | J53: check figure-Contributions
I54: =+SUMIF($G$24:$G$52,">0",$G$24:$G$52)-G31-G35-G37 -> 41112360 | J54: check figure-Distributions
C55: Total return | G55: =+XIRR(G24:G53,E24:E53,0.1) -> 0.44265724
C64: Net investment loss ratio | E64: =E10 -> -0.051530979
C66: Expense ratios:
C67: Operating expenses | E67: =E13 -> 0.051530979
C68: Unearned incentive allocation | E68: =E14 -> 0
C69: Operating expenses and unearned incentive allocation ratio | E69: =SUM(E67:E68) -> 0.051530979
C71: Internal rate of return net of incentive allocation | E71: =+E18 -> 0.44265724

Sheet EETF I-A 1st close LP
B4: Financial Highlights EETF I-A
E8: 44561 | I8: INPUT CELLS
G9: INPUT CELLS | I9: =29562500/35776020.41 -> 0.82632164 | J9: INPUT CELLS
C10: Net investment income/loss | E10: =I10/(J33) -> -0.12254834 | G10: =0-129939-241022 -> -370961 | I10: =(G10*$I$9)+J10 -> -752400.1 | J10: -445867 | K10: Mgmt fees
C12: Expense ratios
C13: Operating expenses | E13: =I13/(J33) -> 0.12254834 | G13: =129939+241022 -> 370961 | I13: =G13*$I$9+J13 -> 752400.1 | J13: =-J10 -> 445867
C14: Incentive allocation | E14: =(I14)/(J33) -> 0 | G14: 0 | I14: =G14*$I$9 -> 0
C15: Total expenses and incentive allocation | E15: =E13+E14 -> 0.12254834
C17: Internal rate of return
C18: Internal rate of return after incentive allocation | E18: =G45 -> 0.19971798
C19: ROI | E19: =-(G43+I50)/I49 -> 1.3965858
J20: INPUT CELLS
J21: =693875 -> 693875 | K21: Jan
C22: Serapis | J22: =693875 -> 693875 | K22: Feb
J23: =674251 -> 674251 | K23: Mar
C24: Contributions 2020 | E24: 43857 | G24: -227500 | J24: =662813 -> 662813 | K24: Apr
E25: 43985 | G25: -175000 | J25: =550875 -> 550875 | K25: May
E26: 44076 | G26: -217500 | J26: =7912747 -> 7912747 | K26: Jun
E27: 44141 | G27: -153000 | J27: =7837185 -> 7837185 | K27: Jul
E28: 44187 | G28: -64000 | J28: =7837185 -> 7837185 | K28: Aug
C29: Contributions 2021 | E29: 44250 | G29: 100000 | J29: =12208967 -> 12208967 | K29: Sep
E30: 44319 | G30: 237000 | J30: =12133404 -> 12133404 | K30: Oct
E31: 44344 | G31: 110000 | J31: =21943654 -> 21943654 | K31: Nov
E32: 44375 | G32: -32084.7 | J32: =G43 -> 526598.12 | K32: Dec
E33: 44405 | G33: -18167.31 | J33: =SUM(J21:J32)/12 -> 6139619.1 | K33: AVG NAV
E34: 44468 | G34: -8532.15
E35: 44475 | G35: -20762.64
E36: 44483 | G36: -24266.33
E37: 44505 | G37: -21800.77
E38: 44551 | G38: -13333.51
E39: 44558 | G39: 212122.31
C43: Net assets | E43: =+E8 -> 44561 | G43: 526598.12
C45: Total return | G45: =+XIRR(G24:G43,E24:E43,0.1) -> 0.19971798
I49: =+SUMIF($G$24:$G$42,"<0",$G$24:$G$42)+G29+G30+G31 -> -528947.41 | J49: check figure-Contributions
I50: =+SUMIF($G$24:$G$42,">0",$G$24:$G$42)-G29-G30-G31 -> 212122.31 | J50: check figure-Distributions
C54: Net investment loss ratio | E54: =E10 -> -0.12254834
C56: Expense ratios:
C57: Operating expenses | E57: =E13 -> 0.12254834
C58: Unearned incentive allocation | E58: =E14 -> 0
C59: Operating expenses and unearned incentive allocation ratio | E59: =SUM(E57:E58) -> 0.12254834
C61: Internal rate of return net of incentive allocation | E61: =+E18 -> 0.19971798

Sheet EETF I-A 1st close LP w INT
B4: Financial Highlights EETF I-A
E8: 44561 | I8: INPUT CELLS
G9: INPUT CELLS | I9: =29562500/35776020.41 -> 0.82632164 | J9: INPUT CELLS
C10: Net investment income/loss | E10: =I10/(J33) -> -0.12254834 | G10: =0-129939-241022 -> -370961 | I10: =(G10*$I$9)+J10 -> -752400.1 | J10: -445867 | K10: Mgmt fees
C12: Expense ratios
C13: Operating expenses | E13: =I13/(J33) -> 0.12254834 | G13: =129939+241022 -> 370961 | I13: =G13*$I$9+J13 -> 752400.1 | J13: =-J10 -> 445867
C14: Incentive allocation | E14: =(I14)/(J33) -> 0 | G14: 0 | I14: =G14*$I$9 -> 0
C15: Total expenses and incentive allocation | E15: =E13+E14 -> 0.12254834
C17: Internal rate of return
C18: Internal rate of return after incentive allocation | E18: =G45 -> 0.23668283
C19: ROI | E19: =-(G43+I50)/I49 -> 1.5016662
J20: INPUT CELLS
J21: =693875 -> 693875 | K21: Jan
C22: Serapis | J22: =693875 -> 693875 | K22: Feb
J23: =674251 -> 674251 | K23: Mar
C24: Contributions 2020 | E24: 43857 | G24: -227500 | J24: =662813 -> 662813 | K24: Apr
E25: 43985 | G25: -175000 | J25: =550875 -> 550875 | K25: May
E26: 44076 | G26: -217500 | J26: =7912747 -> 7912747 | K26: Jun
E27: 44141 | G27: -153000 | J27: =7837185 -> 7837185 | K27: Jul
E28: 44187 | G28: -64000 | J28: =7837185 -> 7837185 | K28: Aug
C29: Contributions 2021 | E29: 44250 | G29: 100000 | J29: =12208967 -> 12208967 | K29: Sep
E30: 44319 | G30: 237000 | J30: =12133404 -> 12133404 | K30: Oct
E31: 44344 | G31: =110000+37013.57 -> 147013.57 | J31: =21943654 -> 21943654 | K31: Nov
E32: 44375 | G32: -32084.7 | J32: =G43 -> 526598.12 | K32: Dec
E33: 44405 | G33: -18167.31 | J33: =SUM(J21:J32)/12 -> 6139619.1 | K33: AVG NAV
E34: 44468 | G34: -8532.15
E35: 44475 | G35: -20762.64
E36: 44483 | G36: -24266.33
E37: 44505 | G37: -21800.77
E38: 44551 | G38: -13333.51
E39: 44558 | G39: 212122.31
C43: Net assets | E43: =+E8 -> 44561 | G43: 526598.12
C45: Total return | G45: =+XIRR(G24:G43,E24:E43,0.1) -> 0.23668283
I49: =+SUMIF($G$24:$G$42,"<0",$G$24:$G$42)+G29+G30+G31 -> -491933.84 | J49: check figure-Contributions
I50: =+SUMIF($G$24:$G$42,">0",$G$24:$G$42)-G29-G30-G31 -> 212122.31 | J50: check figure-Distributions
C54: Net investment loss ratio | E54: =E10 -> -0.12254834
C56: Expense ratios:
C57: Operating expenses | E57: =E13 -> 0.12254834
C58: Unearned incentive allocation | E58: =E14 -> 0
C59: Operating expenses and unearned incentive allocation ratio | E59: =SUM(E57:E58) -> 0.12254834
C61: Internal rate of return net of incentive allocation | E61: =+E18 -> 0.23668283

Sheet VIII
E8: 45107
C17: Internal rate of return
C18: Internal rate of return after incentive allocation | E18: =G138 -> 0.0053216249
C19: ROI | E19: =(G136+I137)/-I136 -> 1.0259583
C21: Sample Investor Ownership Percentage (Pro-rata share of commitments - to calculate fund level amounts divide the cash flows in column G by the ownership % below)
C22: 0.000831429
C23: Contributions 2010 | E23: 40512 | G23: -63000
C24: Contributions 2011 | E24: 40570 | G24: -31500
E25: 40661 | G25: -24194.61
E26: 40704 | G26: -38162.64
E27: 40751 | G27: -36499.78
E28: 40765 | G28: -60694.39
E29: 40813 | G29: -53460.95
E30: 40879 | G30: -25691.19
E31: 40886 | G31: -35003.2
C32: Contributions 2012 | E32: 40927 | G32: -58532.67
E33: 40942 | G33: -274371.9
E34: 40970 | G34: -43650.08
E35: 41001 | G35: -25524.9
E36: 41024 | G36: -30264.05
E37: 41054 | G37: -39409.78
E38: 41080 | G38: -73082.7
E39: 41103 | G39: -23695.76
E40: 41121 | G40: -22864.33
E41: 41152 | G41: -30264
E42: 41180 | G42: -57368.58
E43: 41194 | G43: -28185.43
E44: 41250 | G44: -127125.41
E45: 41264 | G45: -112908
C46: Distribution 2012 | E46: 41030 | G46: 112056.47
E47: 41108 | G47: 24215.98
E48: 41137 | G48: 10363.64
E49: 41173 | G49: 223637.66
C50: Contributions 2013 | E50: 41284 | G50: -33340.28
E51: 41298 | G51: -42652.29
E52: 41345 | G52: -43733.14
E53: 41360 | G53: -39160.28
E54: 41393 | G54: -31511.15
E55: 41404 | G55: -42901.72
E56: 41423 | G56: -37164.86
E57: 41446 | G57: -113573.14
E58: 41481 | G58: -35502
E59: 41501 | G59: -33423.42
E60: 41514 | G60: -48472.28
E61: 41551 | G61: -28933.72
E62: 41577 | G62: -46310.57
... E64: 41624 | G64: -58532.56
C65: Distributions 2013 | E65: 41418 | G65: 13529.21
E66: 41618 | G66: 32263.89
C67: Contributions 2014 | E67: 41646 | G67: -41322
E68: 41670 | G68: -30679.72
E69: 41697 | G69: -54624.85
E70: 41704 | G70: -39576
E71: 41718 | G71: -34587.43
E72: 41750 | G72: -54957.43
E73: 41779 | G73: -54874.28
E74: 41814 | G74: -40490.57
E75: 41877 | G75: -63770.57
E76: 41913 | G76: -26439.43
E77: 41943 | G77: -33755.99
E78: 41990 | G78: -35335.71
C79: Distributions 2014 | E79: 41816 | G79: 87804.85
E80: 41857 | G80: 358214.75
C81: Contributions 2015 | E81: 42011 | G81: -27769.71
E82: 42027 | G82: -35834.57
E83: 42075 | G83: -35917.71
E84: 42138 | G84: -53211.43
E85: 42265 | G85: -24028.29
E86: 42297 | G86: -41987.13
E87: 42352 | G87: -37663.71
C88: Distributions 2015 | E88: 42055 | G88: 27318.78
E89: 42150 | G89: 28614.74
E90: 42251 | G90: 85826.47
C91: Contributions 2016 | E91: 42424 | G91: -37746.86
E92: 42452 | G92: -28185.43
E93: 42485 | G93: -35003.14
E94: 42558 | G94: -21783.44
E95: 42578 | G95: -21617.15
E96: 42636 | G96: -28351.72
E97: 42664 | G97: -27270.85
E98: 42697 | G98: -16628.57
E99: 42727 | G99: -48056.58
C100: Distributions 2016 | E100: 42404 | G100: 17201.94
E101: 42451 | G101: 16945.08
E102: 42549 | G102: 9603.11
E103: 42584 | G103: 235463.57
E104: 42632 | G104: 15345.25
E105: 42656 | G105: 60038.88
E106: 42723 | G106: 57485.25
C107: Contributions 2017 | E107: 42795 | G107: -22531.71
E108: 42822 | G108: -12471.43
E109: 42843 | G109: -22116
E110: 42909 | G110: -32342.57
E111: 43054 | G111: -21783.43
E112: 43090 | G112: -27187.72
C113: Distributions 2017 | E113: 42823 | G113: 87512.22
E114: 42859 | G114: 13701.77
E115: 43020 | G115: 34363.08
C116: Contributions 2018 | E116: 43364 | G116: -68177.15
E117: 43454 | G117: -69258
...

Sheet VIII-B
E8: =+VIII!E8 -> 45107
C17: Internal rate of return
C18: Internal rate of return after incentive allocation | E18: =+G138 -> 0.0031879216
C19: ROI | E19: =(G136+I137)/-I136 -> 1.01579
C21: Sample Investor Ownership Percentage (Pro-rata share of commitments - to calculate fund level amounts divide the cash flows in column G by the ownership % below)
C22: 0.033025234
C23: Contributions 2010 | E23: 40512 | G23: -157500
C24: Contributions 2011 | E24: 40570 | G24: -78750
E25: 40661 | G25: -60486.43
E26: 40704 | G26: -95406.42
E27: 40751 | G27: -91249.28
E28: 40765 | G28: -151735.71
E29: 40813 | G29: -133652.14
E30: 40879 | G30: -64227.85
E31: 40886 | G31: -87507.85
C32: Contributions 2012 | E32: 40927 | G32: -146331.42
E33: 40942 | G33: -685928.54
E34: 40970 | G34: -109124.99
E35: 41001 | G35: -63812.14
E36: 41024 | G36: -75660
E37: 41054 | G37: -98524.28
E38: 41080 | G38: -182706.42
E39: 41103 | G39: -59239.28
E40: 41121 | G40: -57160.71
E41: 41152 | G41: -75660.01
E42: 41180 | G42: -143421.43
E43: 41194 | G43: -70463.57
E44: 41250 | G44: -317813.58
E45: 41264 | G45: -282270
C46: Distribution 2012 | E46: 41030 | G46: 235528.56
E47: 41108 | G47: 59889.22
E48: 41137 | G48: 25909.14
E49: 41173 | G49: 519144.04
C50: Contributions 2013 | E50: 41284 | G50: -83350.73
E51: 41298 | G51: -106630.71
E52: 41345 | G52: -109332.86
E53: 41360 | G53: -97900.71
E54: 41393 | G54: -78777.85
E55: 41404 | G55: -107254.28
E56: 41423 | G56: -92912.15
E57: 41446 | G57: -283932.86
E58: 41481 | G58: -88755
E59: 41501 | G59: -83558.57
E60: 41514 | G60: -121180.72
E61: 41551 | G61: -72334.28
E62: 41577 | G62: -115776.43
... E64: 41624 | G64: -146331.43
C65: Distributions 2013 | E65: 41418 | G65: 32143.76
E66: 41618 | G66: 120407.15
C67: Contributions 2014 | E67: 41646 | G67: -103305.01
E68: 41670 | G68: -76699.29
E69: 41697 | G69: -136562.13
E70: 41704 | G70: -98940
E71: 41718 | G71: -86468.56
E72: 41750 | G72: -137393.57
E73: 41779 | G73: -137185.7
E74: 41814 | G74: -101226.43
E75: 41877 | G75: -159426.43
E76: 41913 | G76: -66098.57
E77: 41943 | G77: -84390.01
E78: 41990 | G78: -88339.29
C79: Distributions 2014 | E79: 41816 | G79: 199985.24
E80: 41857 | G80: 809416.3
C81: Contributions 2015 | E81: 42011 | G81: -69424.29
E82: 42027 | G82: -89586.43
E83: 42075 | G83: -89794.29
E84: 42138 | G84: -133028.58
E85: 42265 | G85: -60070.7
E86: 42297 | G86: -104967.86
E87: 42352 | G87: -94159.28
C88: Distributions 2015 | E88: 42055 | G88: 0
E89: 42150 | G89: 133058.82
E90: 42251 | G90: 214566.18
C91: Contributions 2016 | E91: 42424 | G91: -94367.15
E92: 42452 | G92: -70463.56
E93: 42485 | G93: -87507.85
E94: 42558 | G94: -54458.57
E95: 42578 | G95: -54042.86
E96: 42636 | G96: -70879.29
E97: 42664 | G97: -68177.14
E98: 42697 | G98: -41571.43
E99: 42727 | G99: -120141.43
C100: Distributions 2016 | E100: 42404 | G100: 125567.95
E101: 42451 | G101: 42362.7
E102: 42549 | G102: 22061.54
E103: 42584 | G103: 588658.97
E104: 42632 | G104: 37306.49
E105: 42656 | G105: 150097.2
E106: 42723 | G106: 143473.42
C107: Contributions 2017 | E107: 42795 | G107: -56329.29
E108: 42822 | G108: -31178.57
E109: 42843 | G109: -55290
E110: 42909 | G110: -80856.42
E111: 43054 | G111: -54458.58
E112: 43090 | G112: -67969.28
C113: Distributions 2017 | E113: 42823 | G113: 217020.23
E114: 42859 | G114: 32505.74
E115: 43020 | G115: 82653.95
C116: Contributions 2018 | E116: 43364 | G116: -170442.86
E117: 43454 | G117: -173145
...

Sheet VIII-C
E8: =+VIII!E8 -> 45107
C17: Internal rate of return
C18: Internal rate of return after incentive allocation | E18: =+G137 -> 0.0038677067
C19: ROI | E19: =(G135+I136)/-I135 -> 1.019048
C21: Sample Investor Ownership Percentage (Pro-rata share of commitments - to calculate fund level amounts divide the cash flows in column G by the ownership % below)
C22: 0.15163002
C23: Contributions 2011 | E23: 40590 | G23: -3150000
E24: 40661 | G24: -806485.68
E25: 40704 | G25: -1272085.7
E26: 40751 | G26: -1216657.1
E27: 40765 | G27: -2023142.8
E28: 40813 | G28: -1782028.5
E29: 40879 | G29: -856371.39
E30: 40886 | G30: -1166771.4
C31: Contributions 2012 | E31: 40927 | G31: -1951085.6
E32: 40942 | G32: -9145713.9
E33: 40970 | G33: -1454999.9
E34: 41001 | G34: -850828.54
E35: 41024 | G35: -1008800
E36: 41054 | G36: -1313657.1
E37: 41080 | G37: -2436085.6
E38: 41103 | G38: -789857.11
E39: 41121 | G39: -762142.83
E40: 41152 | G40: -1008800
E41: 41180 | G41: -1912285.7
E42: 41194 | G42: -939514.29
E43: 41250 | G43: -4237514.3
E44: 41264 | G44: -3763600
C45: Distribution 2012 | E45: 41030 | G45: 3231985.6
E46: 41108 | G46: 805926.42
E47: 41137 | G47: 345455.13
E48: 41173 | G48: 7058897.3
C49: Contributions 2013 | E49: 41284 | G49: -1111342.9
E50: 41298 | G50: -1421742.9
E51: 41345 | G51: -1457771.4
E52: 41360 | G52: -1305342.8
E53: 41393 | G53: -1050371.4
E54: 41404 | G54: -1430057.1
E55: 41423 | G55: -1238828.6
E56: 41446 | G56: -3785771.4
E57: 41481 | G57: -1183400
E58: 41501 | G58: -1114114.3
E59: 41514 | G59: -1615742.9
E60: 41551 | G60: -964457.14
E61: 41577 | G61: -1543685.7
... E63: 41624 | G63: -1951085.7
C64: Distributions 2013 | E64: 41418 | G64: 442046.13
E65: 41618 | G65: 1627880.2
C66: Contributions 2014 | E66: 41646 | G66: -1377400
E67: 41670 | G67: -1022657.1
E68: 41697 | G68: -1820828.4
E69: 41704 | G69: -1319200
E70: 41718 | G70: -1152914.3
E71: 41750 | G71: -1831914.3
E72: 41779 | G72: -1829142.9
E73: 41814 | G73: -1349685.7
E74: 41877 | G74: -2125685.7
E75: 41913 | G75: -881314.29
E76: 41943 | G76: -1125200
E77: 41990 | G77: -1177857.1
C78: Distributions 2014 | E78: 41816 | G78: 2837711.5
E79: 41857 | G79: 10225721
C80: Contributions 2015 | E80: 42011 | G80: -925657.15
E81: 42027 | G81: -1194485.7
E82: 42075 | G82: -1197257.1
E83: 42138 | G83: -1773714.3
E84: 42265 | G84: -800942.85
E85: 42297 | G85: -1399571.4
E86: 42352 | G86: -1255457.1
C87: Distributions 2015 | E87: 42055 | G87: 341725.53
E88: 42150 | G88: 2090988.9
E89: 42251 | G89: 2860882.4
C90: Contributions 2016 | E90: 42424 | G90: -1258228.6
E91: 42452 | G91: -939514.29
E92: 42485 | G92: -1166771.4
E93: 42558 | G93: -726114.28
E94: 42578 | G94: -720571.43
E95: 42636 | G95: -945057.13
E96: 42664 | G96: -909028.57
E97: 42697 | G97: -554285.71
E98: 42727 | G98: -1601885.7
C99: Distributions 2016 | E99: 42404 | G99: 1521700.2
E100: 42451 | G100: 564835.99
E101: 42549 | G101: 308748.75
E102: 42584 | G102: 7848786
E103: 42632 | G103: 504739.76
E104: 42656 | G104: 2001296.1
E105: 42723 | G105: 1913313.9
C106: Contributions 2017 | E106: 42795 | G106: -751057.15
E107: 42822 | G107: -415714.29
E108: 42843 | G108: -737200
E109: 42909 | G109: -1078085.7
E110: 43054 | G110: -726114.28
E111: 43090 | G111: -906257.14
C112: Distributions 2017 | E112: 42823 | G112: 2905216.1
E113: 42859 | G113: 448540.14
E114: 43020 | G114: 1124900.6
C115: Contributions 2018 | E115: 43364 | G115: -2272571.4
E116: 43454 | G116: -2308600
C117: Distributions 2018 | E117: 43152 | G117: 6769084.6
...

Sheet VIII-D
E8: =+VIII!E8 -> 45107
C17: Internal rate of return
C18: Internal rate of return after incentive allocation | E18: =+G137 -> 0.0045827895
C19: ROI | E19: =(G135+I136)/-I135 -> 1.0223455
C21: Sample Investor Ownership Percentage (Pro-rata share of commitments - to calculate fund level amounts divide the cash flows in column G by the ownership % below)
C22: 0.028643258
C23: Contributions 2011 | E23: 40590 | G23: -244125
E24: 40661 | G24: -62502.65
E25: 40704 | G25: -98586.65
E26: 40751 | G26: -94290.93
E27: 40765 | G27: -156793.58
E28: 40813 | G28: -138107.22
E29: 40879 | G29: -66368.79
E30: 40886 | G30: -90424.79
C31: Contributions 2012 | E31: 40927 | G31: -151209.15
E32: 40942 | G32: -708792.89
E33: 40970 | G33: -112762.51
E34: 41001 | G34: -65939.22
E35: 41024 | G35: -78182
E36: 41030 | G36: 288418.75
E37: 41054 | G37: -101808.43
E38: 41080 | G38: -188796.65
E39: 41103 | G39: -61213.93
E40: 41108 | G40: 62022.65
E41: 41121 | G41: -59066.07
E42: 41137 | G42: 26772.78
E43: 41152 | G43: -78182.01
E44: 41173 | G44: 577612.2
C45: Distribution 2012 | E45: 41180 | G45: -148202.14
E46: 41194 | G46: -72812.36
E47: 41250 | G47: -328407.36
E48: 41264 | G48: -291678.99
C49: Contributions 2013 | E49: 41284 | G49: -86129.08
E50: 41298 | G50: -110185.07
E51: 41345 | G51: -112977.29
E52: 41360 | G52: -101164.06
E53: 41393 | G53: -81403.8
E54: 41404 | G54: -110829.43
E55: 41418 | G55: 33721.7
E56: 41423 | G56: -96009.23
E57: 41446 | G57: -293397.29
E58: 41481 | G58: -91713.51
E59: 41501 | G59: -86343.86
E60: 41514 | G60: -125220.07
E61: 41551 | G61: -74745.43
... E63: 41599 | G63: -75604.57
C64: Distributions 2013 | E64: 41618 | G64: 81562.51
E65: 41624 | G65: -151209.15
C66: Contributions 2014 | E66: 41646 | G66: -106748.5
E67: 41670 | G67: -79255.94
E68: 41697 | G68: -141114.19
E69: 41704 | G69: -102238
E70: 41718 | G70: -89350.86
E71: 41750 | G71: -141973.37
E72: 41779 | G72: -141758.57
E73: 41814 | G73: -104600.65
E74: 41816 | G74: 224314.23
E75: 41857 | G75: 925110.26
E76: 41877 | G76: -164740.63
E77: 41913 | G77: -68301.86
C78: Distributions 2014 | E78: 41943 | G78: -87203
E79: 41990 | G79: -91283.93
C80: Contributions 2015 | E80: 42011 | G80: -71738.43
E81: 42027 | G81: -92572.64
E82: 42055 | G82: 69906.86
E83: 42075 | G83: -92787.43
E84: 42138 | G84: -137462.86
E85: 42150 | G85: 72217.5
E86: 42251 | G86: 221326.52
C87: Distributions 2015 | E87: 42265 | G87: -62073.07
E88: 42297 | G88: -108466.79
E89: 42352 | G89: -97297.93
C90: Contributions 2016 | E90: 42404 | G90: 43539.31
E91: 42424 | G91: -97512.72
E92: 42451 | G92: 43774.79
E93: 42452 | G93: -72812.36
E94: 42485 | G94: -90424.77
E95: 42549 | G95: 23005.35
E96: 42558 | G96: -56273.86
E97: 42578 | G97: -55844.29
E98: 42584 | G98: 608280.91
C99: Distributions 2016 | E99: 42632 | G99: 39248.07
E100: 42636 | G100: -73241.93
E101: 42656 | G101: 155100.44
E102: 42664 | G102: -70449.71
E103: 42697 | G103: -42957.14
E104: 42723 | G104: 148394.72
E105: 42727 | G105: -124146.13
C106: Contributions 2017 | E106: 42795 | G106: -58206.93
E107: 42822 | G107: -32217.86
E108: 42823 | G108: 225802.36
E109: 42843 | G109: -57132.99
E110: 42859 | G110: 34804.76
E111: 42909 | G111: -83551.64
C112: Distributions 2017 | E112: 43020 | G112: 86533.37
E113: 43054 | G113: -56273.86
E114: 43090 | G114: -70234.93
C115: Contributions 2018 | E115: 43152 | G115: 526301.6
E116: 43186 | G116: 317547.57
C117: Distributions 2018 | E117: 43262 | G117: 44950.31
...

Sheet Fund IX
E8: 45107
C17: Internal rate of return
C18: Internal rate of return after incentive allocation | E18: =G161 -> 0.10392523
C19: ROI | E19: =(G159+I160)/-I159 -> 1.454375
C21: Sample Investor Ownership Percentage (Pro-rata share of commitments - to calculate fund level amounts divide the cash flows in column G by the ownership % below)
C22: 0.000194
C23: Contributions 2013 | E23: 41282 | G23: -6000
E24: 41359 | G24: -4947
E25: 41381 | G25: -1920.6
E26: 41424 | G26: -1610.2
E27: 41446 | G27: -58665.6
E28: 41498 | G28: -3918.8
E29: 41527 | G29: -9855.2
E30: 41534 | G30: -5024.6
E31: 41551 | G31: -4772.4
E32: 41585 | G32: -9137.4
E33: 41621 | G33: -16625.8
E34: 41635 | G34: -6770.6
C35: Contributions 2014 | E35: 41670 | G35: -5781.2
E36: 41712 | G36: -14666.47
E37: 41724 | G37: -5315.6
E38: 41733 | G38: -8380.8
E39: 41764 | G39: -7333.21
E40: 41774 | G40: -10320.8
E41: 41788 | G41: -8012.19
E42: 41817 | G42: -14394.8
E43: 41830 | G43: -9098.61
E44: 41851 | G44: -5121.6
E45: 41859 | G45: -9777.6
E46: 41880 | G46: -6052.8
E47: 41900 | G47: -24948.41
... E51: 41977 | G51: -19109
C52: Distributions 2014 | E52: 41817 | G52: 14124.6
C53: Contributions 2015 | E53: 42009 | G53: -61672.6
E54: 42027 | G54: -29216.4
E55: 42048 | G55: -13075.61
E56: 42061 | G56: -9525.4
E57: 42088 | G57: -20331.2
E58: 42111 | G58: -16431.79
E59: 42138 | G59: -14200.8
E60: 42156 | G60: -17440.59
E61: 42187 | G61: -13812.8
E62: 42230 | G62: -9292.6
E63: 42258 | G63: -18410.59
E64: 42272 | G64: -25743.81
E65: 42293 | G65: -24579.8
... E67: 42361 | G67: -8865.81
C68: Distributions 2015 | E68: 42249 | G68: 19359.94
C69: Contributions 2016 | E69: 42382 | G69: -16101.99
E70: 42457 | G70: -17983.81
E71: 42468 | G71: -20796.8
E72: 42507 | G72: -74864.6
E73: 42543 | G73: -38528.4
E74: 42557 | G74: -8594.19
E75: 42590 | G75: -18003.21
E76: 42607 | G76: -31951.8
E77: 42628 | G77: -18216.6
E78: 42634 | G78: -11872.81
E79: 42663 | G79: -21049
E80: 42731 | G80: -23862
C81: Distributions 2016 | E81: 42377 | G81: 112997.82
E82: 42542 | G82: 14181.9
E83: 42570 | G83: 4479.96
E84: 42586 | G84: 52988.38
E85: 42634 | G85: 11287.1
E86: 42677 | G86: 7607.96
E87: 42709 | G87: 17704.01
E88: 42726 | G88: 155129.46
C89: Contributions 2017 | E89: 42753 | G89: -15772.21
E90: 42816 | G90: -12241.4
E91: 42838 | G91: -12125
E92: 42879 | G92: -13114.4
E93: 42908 | G93: -8497.2
E94: 42933 | G94: -8303.19
E95: 42963 | G95: -23862
E96: 42997 | G96: -11834
E97: 43014 | G97: -14821.6
E98: 43091 | G98: -8691.2
C99: Distributions 2017 | E99: 42745 | G99: 145791.53
E100: 42775 | G100: 8665.25
E101: 42824 | G101: 5425.33
E102: 42877 | G102: 6038.39
E103: 42914 | G103: 54409.63
E104: 42936 | G104: 5808.96
E105: 43019 | G105: 4861.67
E106: 43052 | G106: 3105.78
C107: Contributions 2018 | E107: 43178 | G107: -7003.4
E108: 43194 | G108: -10223.8
E109: 43251 | G109: -8439
E110: 43342 | G110: -11058.01
E111: 43434 | G111: -12571.2
C112: Distributions 2018 | E112: 43116 | G112: 26108.63
E113: 43145 | G113: 8058.97
E114: 43222 | G114: 16229.8
E115: 43314 | G115: 17321.99
E116: 43341 | G116: 48223.37
E117: 43398 | G117: 15335.35
C118: Contributions 2019 | E118: 43529 | G118: -5800.6
E119: 43564 | G119: -7197.4
E120: 43782 | G120: -6227.4
...

Sheet Fund IX-C
E8: =+'Fund IX'!E8 -> 45107
C17: Internal rate of return
C18: Internal rate of return after incentive allocation | E18: =G162 -> 0.090281627
C19: ROI | E19: =(G160+I161)/-I160 -> 1.4232576
C21: Sample Investor Ownership Percentage (Pro-rata share of commitments - to calculate fund level amounts divide the cash flows in column G by the ownership % below)
C22: 0.013382981
C23: Contributions 2013 | E23: 41282 | G23: -90000
E24: 41359 | G24: -74205
E25: 41381 | G25: -28809
E26: 41424 | G26: -24153.01
E27: 41446 | G27: -879983.99
E28: 41498 | G28: -58782
E29: 41527 | G29: -147828
E30: 41534 | G30: -75369.01
E31: 41551 | G31: -71586
E32: 41585 | G32: -137061
E33: 41621 | G33: -249387
E34: 41635 | G34: -101559
C35: Contributions 2014 | E35: 41670 | G35: -86718
E36: 41712 | G36: -219997.24
E37: 41724 | G37: -79734
E38: 41733 | G38: -125712
E39: 41764 | G39: -109998
E40: 41774 | G40: -154812
E41: 41788 | G41: -120183.01
E42: 41817 | G42: -215922
E43: 41830 | G43: -136478.99
E44: 41851 | G44: -76824
E45: 41859 | G45: -146664
E46: 41880 | G46: -90792
E47: 41900 | G47: -374226
... E51: 41977 | G51: -286635
C52: Distributions 2014 | E52: 41817 | G52: 197235.54
C53: Contributions 2015 | E53: 42009 | G53: -925089.01
E54: 42027 | G54: -438246
E55: 42048 | G55: -196133.99
E56: 42061 | G56: -142881
E57: 42088 | G57: -304968.01
E58: 42111 | G58: -246477.01
E59: 42138 | G59: -213012
E60: 42156 | G60: -261608.99
E61: 42187 | G61: -207192
E62: 42230 | G62: -139389.01
E63: 42258 | G63: -276159
E64: 42272 | G64: -386156.99
E65: 42293 | G65: -368696.99
... E67: 42361 | G67: -132987
C68: Distributions 2015 | E68: 42249 | G68: 288567.1
C69: Contributions 2016 | E69: 42382 | G69: -241530
E70: 42457 | G70: -269757.01
E71: 42468 | G71: -311952
E72: 42507 | G72: -1122969
E73: 42543 | G73: -577926
E74: 42557 | G74: -128913
E75: 42590 | G75: -270048
E76: 42607 | G76: -479277
E77: 42628 | G77: -273249
E78: 42634 | G78: -178092
E79: 42663 | G79: -315735
E80: 42731 | G80: -357929.99
C81: Distributions 2016 | E81: 42377 | G81: 1014530.4
E82: 42486 | G82: 401489.44
E83: 42542 | G83: 210673.2
E84: 42570 | G84: 66041.17
E85: 42586 | G85: 527166.21
E86: 42634 | G86: 249347.58
E87: 42677 | G87: 113721.19
E88: 42709 | G88: 265560.19
E89: 42726 | G89: 1590878.1
C90: Contributions 2017 | E90: 42753 | G90: -236583
E91: 42816 | G91: -183621
E92: 42838 | G92: -181875
E93: 42879 | G93: -196716
E94: 42908 | G94: -127458
E95: 42933 | G95: -124547.99
E96: 42963 | G96: -357929.99
E97: 42997 | G97: -177510
E98: 43014 | G98: -222324
E99: 43091 | G99: -130367.99
C100: Distributions 2017 | E100: 42745 | G100: 1517724
E101: 42775 | G101: 127992.01
E102: 42824 | G102: 215209.81
E103: 42877 | G103: 89851.49
E104: 42914 | G104: 815427.31
E105: 42936 | G105: 86694.1
E106: 43019 | G106: 71768.57
E107: 43052 | G107: 312687.29
C108: Contributions 2018 | E108: 43178 | G108: -105051
E109: 43194 | G109: -153356.99
E110: 43251 | G110: -126585
E111: 43342 | G111: -165870
E112: 43434 | G112: -188568.01
C113: Distributions 2018 | E113: 43116 | G113: 389832.04
E114: 43145 | G114: 120707.31
E115: 43222 | G115: 249398.55
E116: 43314 | G116: 259408.59
E117: 43341 | G117: 723326.43
E118: 43398 | G118: 556911.08
C119: Contributions 2019 | E119: 43529 | G119: -87009.01
E120: 43564 | G120: -107961
...

Sheet Fund IX-D
E8: =+'Fund IX'!E8 -> 45107
C17: Internal rate of return
C18: Internal rate of return after incentive allocation | E18: =G161 -> 0.10348694
C19: ROI | E19: =(G159+I160)/-I159 -> 1.4525535
C21: Sample Investor Ownership Percentage (Pro-rata share of commitments - to calculate fund level amounts divide the cash flows in column G by the ownership % below)
C22: 0.0030979702
C23: Contributions 2013 | E23: 41282 | G23: -6000
E24: 41359 | G24: -4947
E25: 41381 | G25: -1920.6
E26: 41424 | G26: -1610.2
E27: 41446 | G27: -58665.6
E28: 41498 | G28: -3918.8
E29: 41527 | G29: -9855.2
E30: 41534 | G30: -5024.6
E31: 41551 | G31: -4772.4
E32: 41585 | G32: -9137.4
E33: 41621 | G33: -16625.8
E34: 41635 | G34: -6770.6
C35: Contributions 2014 | E35: 41670 | G35: -5781.2
E36: 41712 | G36: -14666.47
E37: 41724 | G37: -5315.6
E38: 41733 | G38: -8380.8
E39: 41764 | G39: -7333.21
E40: 41774 | G40: -10320.8
E41: 41788 | G41: -8012.2
E42: 41817 | G42: -14394.8
E43: 41830 | G43: -9098.61
E44: 41851 | G44: -5121.6
E45: 41859 | G45: -9777.6
E46: 41880 | G46: -6052.8
E47: 41900 | G47: -24948.41
... E51: 41977 | G51: -19109
C52: Distributions 2014 | E52: 41817 | G52: 13980.57
C53: Contributions 2015 | E53: 42009 | G53: -61672.6
E54: 42027 | G54: -29216.4
E55: 42048 | G55: -13075.61
E56: 42061 | G56: -9525.4
E57: 42088 | G57: -20331.2
E58: 42111 | G58: -16431.8
E59: 42138 | G59: -14200.8
E60: 42156 | G60: -17440.6
E61: 42187 | G61: -13812.8
E62: 42230 | G62: -9292.6
E63: 42258 | G63: -18410.59
E64: 42272 | G64: -25743.81
E65: 42293 | G65: -24579.8
... E67: 42361 | G67: -8865.81
C68: Distributions 2015 | E68: 42249 | G68: 19173.78
C69: Contributions 2016 | E69: 42382 | G69: -16101.99
E70: 42457 | G70: -17983.81
E71: 42468 | G71: -20796.8
E72: 42507 | G72: -74864.6
E73: 42543 | G73: -38528.4
E74: 42557 | G74: -8594.19
E75: 42590 | G75: -18003.21
E76: 42607 | G76: -31951.8
E77: 42628 | G77: -18216.6
E78: 42634 | G78: -11872.81
E79: 42663 | G79: -21049
E80: 42731 | G80: -23862
C81: Distributions 2016 | E81: 42377 | G81: 112925.78
E82: 42542 | G82: 14043.42
E83: 42570 | G83: 4460.6
E84: 42586 | G84: 52988.38
E85: 42634 | G85: 11280.9
E86: 42677 | G86: 7598.56
E87: 42709 | G87: 17704.01
E88: 42726 | G88: 155129.46
C89: Contributions 2017 | E89: 42753 | G89: -15772.21
E90: 42816 | G90: -12241.4
E91: 42838 | G91: -12125
E92: 42879 | G92: -13114.4
E93: 42908 | G93: -8497.2
E94: 42933 | G94: -8303.21
E95: 42963 | G95: -23862
E96: 42997 | G96: -11834
E97: 43014 | G97: -14821.6
E98: 43091 | G98: -8691.21
C99: Distributions 2017 | E99: 42745 | G99: 145791.53
E100: 42775 | G100: 8650.21
E101: 42824 | G101: 5425.33
E102: 42877 | G102: 5979.52
E103: 42914 | G103: 54363.16
E104: 42936 | G104: 5767.47
E105: 43019 | G105: 4812.14
E106: 43052 | G106: 3102.4
C107: Contributions 2018 | E107: 43178 | G107: -7003.4
E108: 43194 | G108: -10223.81
E109: 43251 | G109: -8439
E110: 43342 | G110: -11058.01
E111: 43434 | G111: -12571.2
C112: Distributions 2018 | E112: 43116 | G112: 26087.71
E113: 43145 | G113: 8035.12
E114: 43222 | G114: 16037.4
E115: 43314 | G115: 17282.37
E116: 43341 | G116: 48223.37
E117: 43398 | G117: 15331.47
C118: Contributions 2019 | E118: 43529 | G118: -5800.6
E119: 43564 | G119: -7197.4
E120: 43782 | G120: -6227.4
...

Sheet Fund X
E8: 45107
C17: Internal rate of return
C18: Internal rate of return after incentive allocation | E18: =G154 -> 0.15457376
C19: ROI | E19: =-(G152+J155)/J154 -> 1.8695651
C21: Sample Investor Ownership Percentage (Pro-rata share of commitments - to calculate fund level amounts divide the cash flows in column G by the ownership % below)
C22: 0.000223846
C24: Contributions 2015 | E24: 42089 | G24: -71700
E25: 42118 | G25: 23052.4
E26: 42180 | G26: -7095.93
E27: 42201 | G27: -2216.09
E28: 42271 | G28: -6961.62
E29: 42324 | G29: -10587.93
E30: 42367 | G30: -28316.54
C31: Contributions 2016 | E31: 42396 | G31: -46425.69
E32: 42453 | G32: -10319.32
E33: 42461 | G33: -7476.46
E34: 42500 | G34: -6446.76
E35: 42513 | G35: -21354.92
E36: 42524 | G36: -50052
E37: 42544 | G37: -73690.16
E38: 42564 | G38: -8058.46
E39: 42585 | G39: -35860.15
E40: 42614 | G40: -13676.99
E41: 42641 | G41: -20952
E42: 42656 | G42: -22362.23
E43: 42704 | G43: -19183.62
... E45: 42733 | G45: -13318.84
C46: Distributions 2016 | E46: 42716 | G46: 17744.73
C47: Contributions 2017 | E47: 42754 | G47: -12983.08
E48: 42765 | G48: -13251.7
E49: 42773 | G49: -22608.46
E50: 42797 | G50: -31629.46
E51: 42817 | G51: -18758.31
E52: 42828 | G52: -16296
E53: 42851 | G53: -71496.45
E54: 42863 | G54: -15087.24
E55: 42878 | G55: -17057.08
E56: 42893 | G56: -32032.38
E57: 42907 | G57: -16989.92
E58: 42915 | G58: -38949.24
E59: 42927 | G59: -13878.47
... E68: 43083 | G68: -20996.77
C69: Distributions 2017 | E69: 42780 | G69: 101415.12
E70: 42822 | G70: 72434.42
E71: 42906 | G71: 12538.72
E72: 42970 | G72: 4971.53
C73: Contributions 2018 | E73: 43104 | G73: -19586.53
E74: 43157 | G74: -18825.46
E75: 43181 | G75: -51798
E76: 43256 | G76: -20772.92
E77: 43278 | G77: -16564.61
E78: 43336 | G78: -21511.63
E79: 43367 | G79: -36509.3
E80: 43439 | G80: -22787.54
C81: Distributions 2018 | E81: 43167 | G81: 5659.93
E82: 43255 | G82: 13720.21
E83: 43444 | G83: 8033.52
C84: Contributions 2019 | E84: 43481 | G84: -12983.08
E85: 43544 | G85: -14370.91
E86: 43591 | G86: -12826.38
E87: 43675 | G87: -20056.62
E88: 43707 | G88: -34427.54
E89: 43769 | G89: -15781.16
E90: 43804 | G90: -15758.78
C91: Distributions 2019 | E91: 43550 | G91: 4511.33
E92: 43629 | G92: 5034.82
E93: 43760 | G93: 28035.04
E94: 43816 | G94: 5278.68
C95: Contributions 2020 | E95: 43896 | G95: -9759.68
E96: 43922 | G96: -7297.39
E97: 43979 | G97: -9513.47
E98: 44015 | G98: -8259.92
E99: 44109 | G99: -5842.39
E100: 44160 | G100: -11080.38
C101: Distributions 2020 | E101: 43885 | G101: 16738.8
E102: 44082 | G102: 9918.1
C103: Contributions 2021 | E103: 44201 | G103: -5909.54
E104: 44246 | G104: -33576.92
E105: 44267 | G105: -3335.31
E106: 44285 | G106: -4208.31
E107: 44308 | G107: -11147.53
E108: 44348 | G108: -24690.23
E109: 44467 | G109: -3626.31
E110: 44546 | G110: -16564.61
C111: Distributions 2021 | E111: 44217 | G111: 15809.21
E112: 44256 | G112: 127901.59
E113: 44279 | G113: 27339.2
E114: 44295 | G114: 35769.09
E115: 44371 | G115: 4987.34
E116: 44386 | G116: 8549.05
E117: 44417 | G117: 9288.05
E118: 44446 | G118: 8948.94
E119: 44473 | G119: 14044.16
E120: 44489 | G120: 36522.88
E121: 44496 | G121: 75188.57
E122: 44505 | G122: 7588.54
E123: 44547 | G123: 57433.86
C124: Contributions 2022 | E124: 44585 | G124: -6872.07
E125: 44630 | G125: -8282.31
E126: 44741 | G126: -3492
...

Sheet Fund X-C
E8: =+'Fund X'!E8 -> 45107
C17: Internal rate of return
C18: Internal rate of return after incentive allocation | E18: =G154 -> 0.14180315
C19: ROI | E19: =-(G152+J155)/J154 -> 1.7697093
C21: Sample Investor Ownership Percentage (Pro-rata share of commitments - to calculate fund level amounts divide the cash flows in column G by the ownership % below)
C22: 0.001086909
C24: Contributions 2015 | E24: 42089 | G24: -71700
E25: 42118 | G25: 23052.4
E26: 42180 | G26: -7095.93
E27: 42201 | G27: -2216.09
E28: 42271 | G28: -6961.62
E29: 42324 | G29: -10587.93
E30: 42367 | G30: -28316.54
C31: Contributions 2016 | E31: 42396 | G31: -46425.69
E32: 42453 | G32: -10319.32
E33: 42461 | G33: -7476.46
E34: 42500 | G34: -6446.76
E35: 42513 | G35: -21354.92
E36: 42524 | G36: -50052
E37: 42544 | G37: -73690.16
E38: 42564 | G38: -8058.46
E39: 42585 | G39: -35860.16
E40: 42614 | G40: -13676.99
E41: 42641 | G41: -20952
E42: 42656 | G42: -22362.23
E43: 42704 | G43: -19183.62
... E45: 42733 | G45: -13318.84
C46: Distributions 2016 | E46: 42716 | G46: 17585.47
C47: Contributions 2017 | E47: 42754 | G47: -12983.08
E48: 42765 | G48: -13251.7
E49: 42773 | G49: -22608.46
E50: 42797 | G50: -31629.46
E51: 42817 | G51: -18758.31
E52: 42828 | G52: -16296
E53: 42851 | G53: -71496.45
E54: 42863 | G54: -15087.24
E55: 42878 | G55: -17057.08
E56: 42893 | G56: -32032.38
E57: 42907 | G57: -16989.92
E58: 42915 | G58: -38949.24
E59: 42927 | G59: -13878.47
... E68: 43083 | G68: -20996.77
C69: Distributions 2017 | E69: 42780 | G69: 101364.7
E70: 42822 | G70: 70252.75
E71: 42906 | G71: 12442.49
E72: 42970 | G72: 4910.85
C73: Contributions 2018 | E73: 43104 | G73: -19586.53
E74: 43157 | G74: -18825.46
E75: 43181 | G75: -51798
E76: 43256 | G76: -20772.92
E77: 43278 | G77: -16564.61
E78: 43336 | G78: -21511.63
E79: 43367 | G79: -36509.3
C80: Distributions 2018 | E80: 43439 | G80: -22787.54
E81: 43167 | G81: 4586.18
E82: 43255 | G82: 13656.12
E83: 43444 | G83: 9094.49
C84: Contributions 2019 | E84: 43481 | G84: -12983.08
E85: 43544 | G85: -14370.91
E86: 43591 | G86: -12826.38
E87: 43675 | G87: -20056.62
E88: 43707 | G88: -34427.54
E89: 43769 | G89: -15781.16
E90: 43804 | G90: -15758.78
C91: Distributions 2019 | E91: 43550 | G91: 4493.27
E92: 43629 | G92: 5024.01
E93: 43760 | G93: 27971.27
E94: 43816 | G94: 5278.68
C95: Contributions 2020 | E95: 43896 | G95: -9759.68
E96: 43922 | G96: -7297.39
E97: 43979 | G97: -9513.47
E98: 44015 | G98: -8259.92
E99: 44109 | G99: -5842.39
E100: 44160 | G100: -11080.38
C101: Distributions 2020 | E101: 43885 | G101: 16180.48
E102: 44082 | G102: 9793.01
C103: Contributions 2021 | E103: 44201 | G103: -5909.54
E104: 44246 | G104: -33576.92
E105: 44267 | G105: -3335.31
E106: 44285 | G106: -4208.31
E107: 44308 | G107: -11147.53
E108: 44348 | G108: -24690.23
E109: 44467 | G109: -3626.31
E110: 44546 | G110: -16564.61
C111: Distributions 2021 | E111: 44217 | G111: 16848.9
E112: 44256 | G112: 127881.02
E113: 44279 | G113: 27339.2
E114: 44295 | G114: 35769.09
E115: 44371 | G115: 5986.33
E116: 44386 | G116: 8536.12
E117: 44417 | G117: 9278.22
E118: 44446 | G118: 8939.64
E119: 44473 | G119: 14044.16
E120: 44489 | G120: 36503.26
E121: 44496 | G121: 75188.57
E122: 44505 | G122: 7588.54
E123: 44547 | G123: 57433.86
C124: Contributions 2022 | E124: 44585 | G124: -6872.07
E125: 44630 | G125: -8282.31
E126: 44741 | G126: -3492
...

Sheet Fund X-D
E8: =+'Fund X'!E8 -> 45107
C17: Internal rate of return
C18: Internal rate of return after incentive allocation | E18: =G154 -> 0.15421506
C19: ROI | E19: =-(G152+J155)/(J154) -> 1.86785
C21: Sample Investor Ownership Percentage (Pro-rata share of commitments - to calculate fund level amounts divide the cash flows in column G by the ownership % below)
C22: 0.009989242
C24: Contributions 2015 | E24: 42089 | G24: -155350
E25: 42118 | G25: 49946.86
E26: 42180 | G26: -15374.51
E27: 42201 | G27: -4801.51
E28: 42271 | G28: -15083.5
E29: 42324 | G29: -22940.5
E30: 42367 | G30: -61352.5
C31: Contributions 2016 | E31: 42396 | G31: -100589
E32: 42453 | G32: -22358.5
E33: 42461 | G33: -16199
E34: 42500 | G34: -13968
E35: 42513 | G35: -46268.99
E36: 42524 | G36: -108446
E37: 42544 | G37: -159662
E38: 42564 | G38: -17460
E39: 42585 | G39: -77697.02
E40: 42614 | G40: -29633.49
E41: 42641 | G41: -45396
E42: 42656 | G42: -48451.5
E43: 42704 | G43: -41564.5
... E45: 42733 | G45: -28857.49
C46: Distributions 2016 | E46: 42716 | G46: 37881.4
C47: Contributions 2017 | E47: 42754 | G47: -28130
E48: 42765 | G48: -28711.99
E49: 42773 | G49: -48985
E50: 42797 | G50: -68530.51
E51: 42817 | G51: -40643
E52: 42828 | G52: -35308
E53: 42851 | G53: -154909
E54: 42863 | G54: -32689.01
E55: 42878 | G55: -36957
E56: 42893 | G56: -69403.5
E57: 42907 | G57: -36811.5
E58: 42915 | G58: -84390
E59: 42927 | G59: -30070
... E68: 43083 | G68: -45493
C69: Distributions 2017 | E69: 42780 | G69: 219636.89
E70: 42822 | G70: 156941.24
E71: 42906 | G71: 26826.13
E72: 42970 | G72: 10515.41
C73: Contributions 2018 | E73: 43104 | G73: -42437.51
E74: 43157 | G74: -40788.5
E75: 43181 | G75: -112229
E76: 43256 | G76: -45007.99
E77: 43278 | G77: -35890.01
E78: 43336 | G78: -46608.51
E79: 43367 | G79: -79103.5
E80: 43439 | G80: -49373
C81: Distributions 2018 | E81: 43167 | G81: 11812.57
E82: 43255 | G82: 29353.12
E83: 43444 | G83: 17341.6
C84: Contributions 2019 | E84: 43481 | G84: -28129.99
E85: 43544 | G85: -31137
E86: 43591 | G86: -27790.5
E87: 43675 | G87: -43456
E88: 43707 | G88: -74593
E89: 43769 | G89: -34192.5
E90: 43804 | G90: -34144
C91: Distributions 2019 | E91: 43550 | G91: 9634.96
E92: 43629 | G92: 10836.58
E93: 43760 | G93: 60129.25
E94: 43816 | G94: 11437.15
C95: Contributions 2020 | E95: 43896 | G95: -21146
E96: 43922 | G96: -15811
E97: 43979 | G97: -20612.5
E98: 44015 | G98: -17896.5
E99: 44109 | G99: -12658.5
E100: 44160 | G100: -24007.5
C101: Distributions 2020 | E101: 43885 | G101: 36192.72
E102: 44082 | G102: 21489.23
C103: Contributions 2021 | E103: 44201 | G103: -12804
E104: 44246 | G104: -72750
E105: 44267 | G105: -7226.5
E106: 44285 | G106: -9118
E107: 44308 | G107: -24153
E108: 44348 | G108: -53495.5
E109: 44467 | G109: -7857
E110: 44546 | G110: -35890
C111: Distributions 2021 | E111: 44217 | G111: 33239.26
E112: 44256 | G112: 276993.05
E113: 44279 | G113: 59234.92
E114: 44295 | G114: 77499.69
E115: 44371 | G115: 10182.89
E116: 44386 | G116: 18470.01
E117: 44417 | G117: 20081.81
E118: 44446 | G118: 19372.3
E119: 44473 | G119: 30429
E120: 44489 | G120: 79017.88
E121: 44496 | G121: 162908.57
E122: 44505 | G122: 16441.85
E123: 44547 | G123: 124440.06
C124: Contributions 2022 | E124: 44585 | G124: -14889.5
E125: 44630 | G125: -17945
E126: 44741 | G126: -7566
...

Sheet Fund XI
E8: 45107
C17: Internal rate of return
C18: Internal rate of return after incentive allocation | E18: =G116 -> 0.18790023
C19: ROI | E19: =-(G114+J117)/J116 -> 1.5264786
C21: Sample Investor Ownership Percentage (Pro-rata share of commitments - to calculate fund level amounts divide the cash flows in column G by the ownership % below)
C22: =2000000/6961190721.65 -> 0.00028730717
C24: Contributions 2017 | E24: 42933 | G24: -33800
E25: 43010 | G25: -8200
E26: 43052 | G26: -3600
E27: 43087 | G27: -15835.83
E28: 43096 | G28: -9710.99
C29: Contributions 2018 | E29: 43182 | G29: -70246.61
E30: 43276 | G30: -24938.27
E31: 43363 | G31: -18588.78
E32: 43398 | G32: -16290.31
E33: 43433 | G33: -13216.14
C34: Contributions 2019 | E34: 43468 | G34: -22438.69
E35: 43495 | G35: -36976.44
E36: 43510 | G36: -14853.79
E37: 43559 | G37: -20599.93
E38: 43593 | G38: -20542.46
E39: 43642 | G39: -32810.49
E40: 43656 | G40: -24363.64
E41: 43684 | G41: -21260.73
E42: 43768 | G42: -21030.88
E43: 43817 | G43: -161696.48
C44: Contributions 2020 | E44: 44006 | G44: -11980.7
E45: 44026 | G45: -29621.37
E46: 44106 | G46: -10170.67
E47: 44182 | G47: -41228.58
E48: 44188 | G48: -9596.06
C49: Contributions 2021 | E49: 44246 | G49: -8849.07
E50: 44250 | G50: -9337.48
E51: 44274 | G51: -14710.13
E52: 44305 | G52: -163880.01
E53: 44362 | G53: 25713.99
E54: 44400 | G54: -20111.5
E55: 44407 | G55: -21548.04
E56: 44440 | G56: -10285.59
E57: 44453 | G57: -16979.85
E58: 44473 | G58: -10831.48
E59: 44496 | G59: -12354.21
E60: 44537 | G60: -48928.42
E61: 44550 | G61: -115928.44
C62: Distributions 2021 | E62: 44396 | G62: 5204.69
E63: 44476 | G63: 4954.93
E64: 44512 | G64: 15882.82
C65: Contributions 2022 | E65: 44565 | G65: -5717.42
E66: 44602 | G66: -17669.4
E67: 44628 | G67: -13158.66
E68: 44641 | G68: -86192.15
E69: 44645 | G69: -186088.86
E70: 44670 | G70: 77659.12
E71: 44694 | G71: -3936.11
E72: 44701 | G72: -10027.02
E73: 44727 | G73: -32207.13
E74: 44750 | G74: -31316.48
E75: 44764 | G75: -4539.45
E76: 44790 | G76: -5343.92
E77: 44797 | G77: -15485.86
... E87: 44909 | G87: -55996.17
C88: Distributions 2022 | E88: 44575 | G88: 20090.68
E89: 44601 | G89: 15699.9
E90: 44628 | G90: 40970.06
E91: 44659 | G91: 20791.02
E92: 44692 | G92: 17582.41
E93: 44719 | G93: 21829.37
E94: 44761 | G94: 33935.96
E95: 44776 | G95: 29980.31
E96: 44817 | G96: 10413.17
E97: 44841 | G97: 7569.79
E98: 44872 | G98: 5737.35
E99: 44902 | G99: 9742.93
C100: Contributions 2023 | E100: 44960 | G100: -9596.06
E101: 44979 | G101: -11176.25
E102: 45013 | G102: -22984.57
E103: 45022 | G103: -13819.48
E104: 45028 | G104: -4194.69
E105: 45047 | G105: -49876.52
E106: 45061 | G106: -15083.62
C107: Distributions 2023 | E107: 44939 | G107: 8083.49
E108: 44966 | G108: 8423.23
E109: 44995 | G109: 12010.54
E110: 45027 | G110: 17176.38
E111: 45055 | G111: 10405.26
E112: 45090 | G112: 335778.39
C114: Net assets | E114: =+E8 -> 45107 | G114: =L114/0.97*C22 -> 2107837.5 | L114: 7116433644
C116: Total return | G116: =XIRR(G24:G114,E24:E114,0.1) -> 0.18790023 | J116: =+SUMIF($G$24:$G$113,"<0",$G$24:$G$113)+G53+G70 -> -1808148.6 | K116: check figure-Contributions
J117: =+SUMIF($G$24:$G$113,">0",$G$24:$G$113)-G53-G70 -> 652262.68 | K117: check figure-Distributions

Sheet Fund XI-C
E8: ='Fund XI'!E8 -> 45107
C17: Internal rate of return
C18: Internal rate of return after incentive allocation | E18: =G116 -> 0.16441737
C19: ROI | E19: =-(G114+J117)/J116 -> 1.4463268
C21: Sample Investor Ownership Percentage (Pro-rata share of commitments - to calculate fund level amounts divide the cash flows in column G by the ownership % below)
C22: 0.027350044
C24: Contributions 2017 | E24: 42933 | G24: -422500
E25: 43010 | G25: -102500
E26: 43052 | G26: -45000
E27: 43087 | G27: -197947.88
E28: 43096 | G28: -121387.29
C29: Contributions 2018 | E29: 43182 | G29: -878082.53
E30: 43276 | G30: -311728.27
E31: 43363 | G31: -232359.67
E32: 43398 | G32: -203628.95
E33: 43433 | G33: -165201.61
C34: Contributions 2019 | E34: 43468 | G34: -280483.64
E35: 43495 | G35: -462205.41
E36: 43510 | G36: -185672.25
E37: 43559 | G37: -257499.03
E38: 43593 | G38: -256780.77
E39: 43642 | G39: -410130.99
E40: 43656 | G40: -304545.62
E41: 43684 | G41: -265759.16
E42: 43768 | G42: -262886.05
E43: 43817 | G43: -2021205.9
C44: Contributions 2020 | E44: 44006 | G44: -149758.87
E45: 44026 | G45: -370267.11
E46: 44105 | G46: -127133.42
E47: 44182 | G47: -515357.25
E48: 44188 | G48: -119950.73
C49: Contributions 2021 | E49: 44246 | G49: -110613.25
E50: 44250 | G50: -116718.53
E51: 44274 | G51: -183876.57
E52: 44305 | G52: -2048500.1
E53: 44362 | G53: 321424.89
E54: 44400 | G54: -251393.78
E55: 44407 | G55: -269350.47
E56: 44440 | G56: -128569.95
E57: 44453 | G57: -212248.17
E58: 44473 | G58: -135393.5
E59: 44496 | G59: -154427.59
E60: 44537 | G60: -611605.14
E61: 44550 | G61: -1449105.5
C62: Distributions 2021 | E62: 44396 | G62: 58254.94
E63: 44476 | G63: 53658.19
E64: 44512 | G64: 198424.12
C65: Contributions 2022 | E65: 44565 | G65: -71467.65
E66: 44602 | G66: -220867.36
E67: 44628 | G67: -164483.36
E68: 44641 | G68: -1077401.9
E69: 44645 | G69: -2326110.7
E70: 44670 | G70: 970739.1
E71: 44694 | G71: -49201.35
E72: 44701 | G72: -125337.73
E73: 44727 | G73: -402589.17
E74: 44750 | G74: -391456.02
E75: 44764 | G75: -56743.17
E76: 44790 | G76: -66798.92
E77: 44797 | G77: -193573.22
... E87: 44909 | G87: -699952.1
C88: Distributions 2022 | E88: 44575 | G88: 251133.34
E89: 44601 | G89: 195115.32
E90: 44628 | G90: 512125.65
E91: 44659 | G91: 259887.72
E92: 44692 | G92: 219484.73
E93: 44719 | G93: 271197.35
E94: 44761 | G94: 424199.43
E95: 44776 | G95: 373876.58
E96: 44817 | G96: 129981.04
E97: 44841 | G97: 94622.35
E98: 44872 | G98: 71716.91
E99: 44902 | G99: 120626.61
C100: Contributions 2023 | E100: 44960 | G100: -119950.76
E101: 44979 | G101: -139703.11
E102: 45013 | G102: -287307.18
E103: 45022 | G103: -172743.44
E104: 45028 | G104: -52433.55
E105: 45047 | G105: -623456.56
E106: 45061 | G106: -188545.35
C107: Distributions 2023 | E107: 44939 | G107: 101043.53
E108: 44966 | G108: 105290.37
E109: 44995 | G109: 150131.69
E110: 45027 | G110: 206979.39
E111: 45055 | G111: 130065.72
E112: 45090 | G112: 4187884.9
C114: Net assets | E114: =+E8 -> 45107 | G114: =L114*C22 -> 24573971 | L114: 898498419
C116: Total return | G116: =+XIRR(G24:G114,E24:E114,0.1) -> 0.16441737 | J116: =+SUMIF($G$24:$G$113,"<0",$G$24:$G$113)+G53+G70 -> -22601856 | K116: check figure-Contributions
J117: =+SUMIF($G$24:$G$113,">0",$G$24:$G$113)-G53-G70 -> 8115699.9 | K117: check figure-Distributions

Sheet Fund XI-D
E8: ='Fund XI'!E8 -> 45107
C17: Internal rate of return
C18: Internal rate of return after incentive allocation | E18: =G116 -> 0.18758237
C19: ROI | E19: =-(G114+J117)/J116 -> 1.5256429
C21: Sample Investor Ownership Percentage (Pro-rata share of commitments - to calculate fund level amounts divide the cash flows in column G by the ownership % below)
C22: 0.012144909
C24: Contributions 2017 | E24: 42933 | G24: -118300
E25: 43010 | G25: -28700
E26: 43052 | G26: -12600
E27: 43087 | G27: -55425.4
E28: 43096 | G28: -33988.44
C29: Contributions 2018 | E29: 43182 | G29: -245863.11
E30: 43276 | G30: -87283.92
E31: 43363 | G31: -65060.71
E32: 43398 | G32: -57016.11
E33: 43433 | G33: -46256.45
C34: Contributions 2019 | E34: 43468 | G34: -78535.4
E35: 43495 | G35: -129417.52
E36: 43510 | G36: -51988.23
E37: 43559 | G37: -72099.73
E38: 43593 | G38: -71898.61
E39: 43642 | G39: -114836.68
E40: 43656 | G40: -85272.77
E41: 43684 | G41: -74412.54
E42: 43768 | G42: -73608.09
E43: 43817 | G43: -565937.67
C44: Contributions 2020 | E44: 44006 | G44: -41932.49
E45: 44026 | G45: -103674.79
E46: 44105 | G46: -35597.36
E47: 44182 | G47: -144300.02
E48: 44188 | G48: -33586.21
C49: Contributions 2021 | E49: 44246 | G49: -30971.71
E50: 44250 | G50: -32681.18
E51: 44274 | G51: -51485.45
E52: 44305 | G52: -573580.03
E53: 44362 | G53: 89998.97
E54: 44400 | G54: -70390.26
E55: 44407 | G55: -75418.13
E56: 44440 | G56: -35999.59
E57: 44453 | G57: -59429.49
E58: 44473 | G58: -37910.19
E59: 44496 | G59: -43239.73
E60: 44537 | G60: -171249.44
E61: 44550 | G61: -405749.55
C62: Distributions 2021 | E62: 44396 | G62: 14478.55
E63: 44476 | G63: 17147.06
E64: 44512 | G64: 55569.08
C65: Contributions 2022 | E65: 44565 | G65: -20010.94
E66: 44602 | G66: -61842.87
E67: 44628 | G67: -46055.35
E68: 44641 | G68: -301672.53
E69: 44645 | G69: -651310.98
E70: 44670 | G70: 271806.95
E71: 44694 | G71: -13776.38
E72: 44701 | G72: -35094.57
E73: 44727 | G73: -112724.96
E74: 44750 | G74: -109607.68
E75: 44764 | G75: -15888.08
E76: 44790 | G76: -18703.69
E77: 44797 | G77: -54200.49
... E87: 44909 | G87: -195986.58
C88: Distributions 2022 | E88: 44575 | G88: 70317.36
E89: 44601 | G89: 54777.98
E90: 44628 | G90: 143395.19
E91: 44659 | G91: 72768.56
E92: 44692 | G92: 61434.59
E93: 44719 | G93: 76039.47
E94: 44761 | G94: 118775.84
E95: 44776 | G95: 104734.96
E96: 44817 | G96: 36369.32
E97: 44841 | G97: 26494.26
E98: 44872 | G98: 20080.73
E99: 44902 | G99: 33882.87
C100: Contributions 2023 | E100: 44960 | G100: -33586.21
E101: 44979 | G101: -39116.87
E102: 45013 | G102: -80446.01
E103: 45022 | G103: -48368.16
E104: 45028 | G104: -14681.39
E105: 45047 | G105: -174567.84
E106: 45061 | G106: -52792.69
C107: Distributions 2023 | E107: 44939 | G107: 28292.19
E108: 44966 | G108: 29481.31
E109: 44995 | G109: 42036.88
E110: 45027 | G110: 60117.34
E111: 45055 | G111: 36418.4
E112: 45090 | G112: 1174373.9
C114: Net assets | E114: =+E8 -> 45107 | G114: =L114*C22 -> 7378075.1 | L114: 607503535
C116: Total return | G116: =+XIRR(G24:G114,E24:E114,0.1) -> 0.18758237 | J116: =+SUMIF($G$24:$G$113,"<0",$G$24:$G$113)+G53+G70 -> -6328519.7 | K116: check figure-Contributions
J117: =+SUMIF($G$24:$G$113,">0",$G$24:$G$113)-G53-G70 -> 2276985.8 | K117: check figure-Distributions

Sheet EETF I-A
E8: 45107
C17: Internal rate of return
C18: Internal rate of return after incentive allocation | E18: =G71 -> 0.25984918
C19: ROI | E19: =-(G69+I70)/I69 -> 1.3753157
C21: Sample Investor Ownership Percentage (Pro-rata share of commitments - to calculate fund level amounts divide the cash flows in column G by the ownership % below)
C22: 1
C24: Contributions 2020 | E24: 43857 | G24: =-8355693.57*193814409.75/213814409.75 -> -7574109.8
E25: 43985 | G25: =-8946403.4*193814409.75/213814409.75 -> -8109565.2
E26: 44076 | G26: =-8101403.91*193814409.75/213814409.75-1912477.07 -> -9256083.2
E27: 44117 | G27: =-10183965.83*193814409.75/213814409.75 -> -9231367.2
E28: 44141 | G28: =-9094491.06*193814409.75/213814409.75 -> -8243800.9
E29: 44148 | G29: =-4743875.63*193814409.75/213814409.75 -> -4300137.9
E30: 44187 | G30: =-4000309.07*193814409.75/213814409.75-294804.35 -> -3920928.2
C31: Contributions 2021 | E31: 44203 | G31: =-17965219.19*193814409.75/213814409.75-492157.19 -> -16776927
E32: 44217 | G32: =-2420477.32*193814409.75/213814409.75 -> -2194068.1
E33: 44250 | G33: =8743624.8*193814409.75/213814409.75 -> 7925754.3
E34: 44265 | G34: =-5278462.5*193814409.75/213814409.75-155480.19 -> -4940200.2
E35: 44291 | G35: =-12658173.89*193814409.75/213814409.75-268874.97 -> -11743015
E36: 44307 | G36: =-28503534.36*193814409.75/213814409.75-795428.94 -> -26632769
E37: 44319 | G37: =29772852.87*193814409.75/213814409.75 -> 26987928
E38: 44335 | G38: =-13567083.21*193814409.75/213814409.75-457505.62 -> -12755537
E39: 44344 | G39: =16251618.18*193814409.75/213814409.75 -> 14731457
E40: 44361 | G40: =416746.8*193814409.75/213814409.75+67984.53 -> 445749.22
E41: 44375 | G41: -6218476.1
E42: 44405 | G42: -3521086
E43: 44468 | G43: -1653652.9
E44: 44475 | G44: -4024098.3
E45: 44483 | G45: -4703164.9
E46: 44505 | G46: -4225303.2
E47: 44551 | G47: -2584225.6
C48: Distributions 2021 | E48: 44558 | G48: 41112360
C49: Contributions 2022 | E49: 44599 | G49: -1735392.4
E50: 44635 | G50: -5023835.2
E51: 44676 | G51: -2842019.4
E52: 44686 | G52: -6312804.1
E53: 44701 | G53: -6438557.2
E54: 44728 | G54: -3414195.9
E55: 44781 | G55: -8173949.6
E56: 44817 | G56: -11771667
E57: 44852 | G57: -2791718.2
E58: 44859 | G58: -14537055
E59: 44902 | G59: -5860093.1
C60: Distributions 2022 | E60: 44861 | G60: 4795541.2
E61: 44917 | G61: 80724803
C62: Contributions 2023 | E62: 44932 | G62: -7772124.6
E63: 44984 | G63: -915285.33
E64: 45049 | G64: -1796240.1
E65: 45089 | G65: -2400061.7
C66: Distributions 2023 | E66: 44980 | G66: 1627036.5
E67: 45042 | G67: 3481451.2
C69: Net assets | E69: 45107 | G69: 1.217331e+08 | I69: =+SUMIF($G$24:$G$68,"<0",$G$24:$G$68)+G33+G37+G39+G40 -> -1.8430263e+08 | J69: check figure-Contributions
I70: =+SUMIF($G$24:$G$68,">0",$G$24:$G$68)-G33-G37-G39-G40 -> 1.3174119e+08 | J70: check figure-Distributions
C71: Total return | G71: =+XIRR(G24:G69,E24:E69,0.1) -> 0.25984918

Sheet EFM II
E8: 45107
C17: Internal rate of return
C18: Internal rate of return after incentive allocation | E18: =G98 -> 0.2597451
C19: ROI | E19: =-(G96+J99)/(J98) -> 1.6236627
C21: Sample Investor Ownership Percentage (Pro-rata share of commitments - to calculate fund level amounts divide the cash flows in column G by the ownership % below)
C22: 0.0056
C23: Contributions 2012 | E23: 41089 | G23: -75000
E24: 41166 | G24: -94080
E25: 41270 | G25: -273280
C26: Contributions 2013 | E26: 41311 | G26: -97440
E27: 41341 | G27: -140000
E28: 41361 | G28: -62720
E29: 41387 | G29: -136640
E30: 41408 | G30: -58800
E31: 41439 | G31: -136080
E32: 41479 | G32: -150640
E33: 41515 | G33: -94640
E34: 41543 | G34: -352800
E35: 41605 | G35: -83440
E36: 41638 | G36: -59920
C37: Contributions 2014 | E37: 41683 | G37: -61600
E38: 41701 | G38: -89599.99
E39: 41729 | G39: -115360
E40: 41751 | G40: -81200
E41: 41782 | G41: -138320
E42: 41808 | G42: -332080
E43: 41894 | G43: -69440
E44: 41942 | G44: -98560
E45: 41962 | G45: -218960
E46: 41975 | G46: -257600
C47: Distributions 2014 | E47: 41969 | G47: 950190.04
C48: Contributions 2015 | E48: 42037 | G48: -216720
E49: 42094 | G49: -188160
E50: 42110 | G50: -157360
E51: 42145 | G51: -196560
E52: 42158 | G52: -563360
E53: 42261 | G53: -423920
E54: 42366 | G54: -105840
C55: Distributions 2015 | E55: 42341 | G55: 167083.98
C56: Contributions 2016 | E56: 42397 | G56: -152880
E57: 42447 | G57: -192080
E58: 42494 | G58: -149520
E59: 42556 | G59: -130480
E60: 42605 | G60: -1252720
E61: 42661 | G61: -119280
C62: Distributions 2016 | E62: 42381 | G62: 1368658
E63: 42549 | G63: 182010.75
E64: 42640 | G64: 267565.96
E65: 42654 | G65: 109364.79
C66: Contributions 2017 | E66: 42793 | G66: -118720
E67: 42870 | G67: -119840
E68: 42992 | G68: -113120
E69: 43048 | G69: -217280
C70: Distributions 2017 | E70: 42746 | G70: 405584.79
E71: 42802 | G71: 606119.09
E72: 42885 | G72: 224558.85
E73: 42913 | G73: 5827248.3
E74: 42999 | G74: 397158.17
C75: Contributions 2018 | E75: 43132 | G75: -150080
E76: 43147 | G76: -330400
E77: 43370 | G77: -106400
C78: Distributions 2018 | E78: 43122 | G78: 1706867.5
E79: 43300 | G79: 423504.53
C80: Contributions 2019 | E80: 43490 | G80: -146720
E81: 43517 | G81: -166320
E82: 43560 | G82: -454160
E83: 43623 | G83: -117600
E84: 43733 | G84: -111440
E85: 43825 | G85: -66080
C86: Distributions 2019 | E86: 43545 | G86: 177644.72
C87: Contributions 2020 | E87: 43950 | G87: -90160
C88: Distributions 2020 | E88: 44084 | G88: 98641.36
E89: 44158 | G89: 456197.97
C90: Contributions 2021 | E90: 44203 | G90: -56000
C91: Distributions 2021 | E91: 44284 | G91: 52464.24
E92: 44546 | G92: 86158.79
C93: Distributions 2022 | E93: 44624 | G93: 753227.11
C94: Distributions 2023 | E94: 45078 | G94: 93829.53
C96: Net assets | E96: =+E8 -> 45107 | G96: =L96/0.98*C22 -> 1056753.4 | L96: 1.8493184e+08
C98: Total return | G98: =+XIRR(G23:G96,E23:E96,0.1) -> 0.2597451 | J98: =+SUMIF($G$23:$G$95,"<0",$G$23:$G$95) -> -9491400 | K98: check figure-Contributions
J99: =+SUMIF($G$23:$G$95,">0",$G$23:$G$95) -> 14354078 | K99: check figure-Distributions

Sheet EFM II-C
E8: =+'EFM II'!E8 -> 45107
C17: Internal rate of return
C18: Internal rate of return after incentive allocation | E18: =G98 -> 0.20956618
C19: ROI | E19: =-(G96+J99)/(J98) -> 1.5243279
C21: Sample Investor Ownership Percentage (Pro-rata share of commitments - to calculate fund level amounts divide the cash flows in column G by the ownership % below)
C22: 0.01538501
C23: Contributions 2012 | E23: 41089 | G23: -22500
E24: 41166 | G24: -28224
E25: 41270 | G25: -81984
C26: Contributions 2013 | E26: 41311 | G26: -29232
E27: 41341 | G27: -42000
E28: 41361 | G28: -18816
E29: 41387 | G29: -40992
E30: 41408 | G30: -17640
E31: 41439 | G31: -40824
E32: 41479 | G32: -45192
E33: 41515 | G33: -28392
E34: 41543 | G34: -105840
E35: 41605 | G35: -25032
E36: 41638 | G36: -17976
C37: Contributions 2014 | E37: 41683 | G37: -18480
E38: 41701 | G38: -26880
E39: 41729 | G39: -34608
E40: 41751 | G40: -24360
E41: 41782 | G41: -41496
E42: 41808 | G42: -99624
E43: 41894 | G43: -20832
E44: 41942 | G44: -29568
E45: 41962 | G45: -65688
E46: 41975 | G46: -77280
C47: Distributions 2014 | E47: 41969 | G47: 273860.4
C48: Contributions 2015 | E48: 42037 | G48: -65016.01
E49: 42094 | G49: -56448
E50: 42110 | G50: -47208
E51: 42145 | G51: -58968
E52: 42158 | G52: -169008
E53: 42261 | G53: -127176
E54: 42366 | G54: -31752
C55: Distributions 2015 | E55: 42341 | G55: 48606.68
C56: Contributions 2016 | E56: 42397 | G56: -45864
E57: 42447 | G57: -57623.99
E58: 42494 | G58: -44855.99
E59: 42556 | G59: -39144
E60: 42605 | G60: -375816
E61: 42661 | G61: -35784
C62: Distributions 2016 | E62: 42381 | G62: 379609.17
E63: 42549 | G63: 53637.61
E64: 42640 | G64: 79938.61
E65: 42654 | G65: 32809.44
C66: Contributions 2017 | E66: 42793 | G66: -35616
E67: 42870 | G67: -35952
E68: 42992 | G68: -33936
E69: 43048 | G69: -65184
C70: Distributions 2017 | E70: 42746 | G70: 121675.44
E71: 42802 | G71: 180369.63
E72: 42885 | G72: 66707.12
E73: 42913 | G73: 1393927.3
E74: 42999 | G74: 146090.75
C75: Contributions 2018 | E75: 43132 | G75: -45024
E76: 43147 | G76: -99120
E77: 43370 | G77: -31920
C78: Distributions 2018 | E78: 43122 | G78: 373197.71
E79: 43300 | G79: 155647.92
C80: Contributions 2019 | E80: 43490 | G80: -44016
E81: 43517 | G81: -49896
E82: 43560 | G82: -136248
E83: 43623 | G83: -35280
E84: 43733 | G84: -33432
E85: 43825 | G85: -19824
C86: Distributions 2019 | E86: 43545 | G86: 174846.1
C87: Contributions 2020 | E87: 43950 | G87: =-27048 -> -27048
C88: Distributions 2020 | E88: 44084 | G88: 44977.42
E89: 44158 | G89: 218496.06
C90: Contributions 2021 | E90: 44203 | G90: -16800
C91: Distributions 2021 | E91: 44284 | G91: 7755.01
E92: 44546 | G92: 31787.79
C93: Distributions 2022 | E93: 44624 | G93: 190113.52
C94: Distributions 2023 | E94: 45078 | G94: 25955.93
C96: Net assets | E96: =+E8 -> 45107 | G96: =L96*C22 -> 340392.02 | L96: 22124914
C98: Total return | G98: =+XIRR(G23:G96,E23:E96) -> 0.20956618 | J98: =+SUMIF($G$23:$G$95,"<0",$G$23:$G$95) -> -2847420 | K98: check figure-Contributions
J99: =+SUMIF($G$23:$G$95,">0",$G$23:$G$95) -> 4000009.7 | K99: check figure-Distributions

Sheet EFM II-D
E8: =+'EFM II'!E8 -> 45107
C17: Internal rate of return
C18: Internal rate of return after incentive allocation | E18: =G98 -> 0.25706856
C19: ROI | E19: =-(G96+J99)/(J98) -> 1.6161491
C21: Sample Investor Ownership Percentage (Pro-rata share of commitments - to calculate fund level amounts divide the cash flows in column G by the ownership % below)
C22: 0.012345679
C23: Contributions 2012 | E23: 41089 | G23: -7500
E24: 41166 | G24: -9408
E25: 41270 | G25: -27328
C26: Contributions 2013 | E26: 41311 | G26: -9744
E27: 41341 | G27: -14000
E28: 41361 | G28: -6272
E29: 41387 | G29: -13664
E30: 41408 | G30: -5880
E31: 41439 | G31: -13608
E32: 41479 | G32: -15064
E33: 41515 | G33: -9464
E34: 41543 | G34: -35280
E35: 41605 | G35: -8344
E36: 41638 | G36: -5992
C37: Contributions 2014 | E37: 41683 | G37: -6160
E38: 41701 | G38: -8960
E39: 41729 | G39: -11536
E40: 41751 | G40: -8120
E41: 41782 | G41: -13832
E42: 41808 | G42: -33208
E43: 41894 | G43: -6944
E44: 41942 | G44: -9856
E45: 41962 | G45: -21896
E46: 41975 | G46: -25760
C47: Distributions 2014 | E47: 41969 | G47: 93993.46
C48: Contributions 2015 | E48: 42037 | G48: -21672
E49: 42094 | G49: -18816
E50: 42110 | G50: -15736
E51: 42145 | G51: -19656
E52: 42158 | G52: -56336
E53: 42261 | G53: -42391.99
E54: 42366 | G54: -10584
C55: Distributions 2015 | E55: 42341 | G55: 15844.88
C56: Contributions 2016 | E56: 42397 | G56: -15288
E57: 42447 | G57: -19207.99
E58: 42494 | G58: -14952
E59: 42556 | G59: -13048
E60: 42605 | G60: -125272
E61: 42661 | G61: -11928
C62: Distributions 2016 | E62: 42381 | G62: 136789.24
E63: 42549 | G63: 17692.82
E64: 42640 | G64: 26680.06
E65: 42654 | G65: 10936.48
C66: Contributions 2017 | E66: 42793 | G66: -11872
E67: 42870 | G67: -11983.99
E68: 42992 | G68: -11312
E69: 43048 | G69: -21728
C70: Distributions 2017 | E70: 42746 | G70: 40558.48
E71: 42802 | G71: 60485.01
E72: 42885 | G72: 22259.21
E73: 42913 | G73: 582576.68
E74: 42999 | G74: 39339.92
C75: Contributions 2018 | E75: 43132 | G75: -15008
E76: 43147 | G76: -33040
E77: 43370 | G77: -10640
C78: Distributions 2018 | E78: 43122 | G78: 170614.91
E79: 43300 | G79: 41585.63
C80: Contributions 2019 | E80: 43490 | G80: -14672
E81: 43517 | G81: -16632
E82: 43560 | G82: -45416
E83: 43623 | G83: -11760
E84: 43733 | G84: -11144
E85: 43825 | G85: -6608
C86: Distributions 2019 | E86: 43545 | G86: 17572.34
C87: Contributions 2020 | E87: 43950 | G87: -9016
C88: Distributions 2020 | E88: 44084 | G88: 8234.01
E89: 44158 | G89: 45614.54
C90: Contributions 2021 | E90: 44203 | G90: -5600
C91: Distributions 2021 | E91: 44284 | G91: 5074.89
E92: 44546 | G92: 8151.91
C93: Distributions 2022 | E93: 44624 | G93: 75156.74
C94: Distributions 2023 | E94: 45078 | G94: 9041.13
C96: Net assets | E96: =+E8 -> 45107 | G96: =L96*C22 -> 105749.32 | L96: 8565695
C98: Total return | G98: =+XIRR(G23:G96,E23:E96) -> 0.25706856 | J98: =+SUMIF($G$23:$G$95,"<0",$G$23:$G$95) -> -949139.97 | K98: check figure-Contributions
J99: =+SUMIF($G$23:$G$95,">0",$G$23:$G$95) -> 1428202.3 | K99: check figure-Distributions

Sheet EFM III
E8: 45107
C17: Internal rate of return
C18: Internal rate of return after incentive allocation | E18: =G118 -> 0.10411286
C19: ROI | E19: =-(G116+I117)/I116 -> 1.3910247
C21: Sample Investor Ownership Percentage (Pro-rata share of commitments - to calculate fund level amounts divide the cash flows in column G by the ownership % below)
C22: 0.0049
C24: Contributions 2014 | E24: 41829 | G24: -169050
E25: 41894 | G25: -87710
E26: 41942 | G26: -46060
E27: 41999 | G27: -65660
C28: Contributions 2015 | E28: 42037 | G28: -64680
E29: 42093 | G29: -83790
E30: 42109 | G30: -62720
E31: 42144 | G31: -36750
E32: 42184 | G32: -56350
E33: 42227 | G33: -74970
E34: 42261 | G34: -98980
E35: 42368 | G35: -80850
C36: Contributions 2016 | E36: 42396 | G36: -1416590
E37: 42445 | G37: -120050
E38: 42549 | G38: -194530
E39: 42586 | G39: -149450
E40: 42607 | G40: -113190
E41: 42613 | G41: -2398550
E42: 42640 | G42: -56350
E43: 42732 | G43: -78400
C44: Distributions 2016 | E44: 42377 | G44: 711402.14
E45: 42551 | G45: 75179.43
E46: 42642 | G46: 140484.82
E47: 42655 | G47: 57417.44
C48: Contributions 2017 | E48: 42765 | G48: -258720
E49: 42822 | G49: -143570
E50: 42852 | G50: -149940
E51: 42913 | G51: -601720
E52: 42991 | G52: -264600
E53: 43006 | G53: -188650
E54: 43080 | G54: -94080
E55: 43095 | G55: -187180
C56: Distributions 2017 | E56: 42747 | G56: 212932.02
C57: Contributions 2018 | E57: 43130 | G57: -1817900
E58: 43143 | G58: 503401.5
E59: 43173 | G59: -137200
E60: 43216 | G60: -245000
E61: 43265 | G61: -140139.99
E62: 43292 | G62: -245000
E63: 43328 | G63: -890819.99
E64: 43360 | G64: -135240
E65: 43369 | G65: -2935590
E66: 43389 | G66: 196000.01
E67: 43445 | G67: -468930
C68: Distributions 2018 | E68: 43111 | G68: 203913.13
E69: 43153 | G69: 4714276.2
E70: 43446 | G70: 225200.29
C71: Contributions 2019 | E71: 43522 | G71: -790860
E72: 43563 | G72: -397390
E73: 43600 | G73: -242550
E74: 43643 | G74: -137690
E75: 43655 | G75: -215600
E76: 43685 | G76: -242060
E77: 43697 | G77: -72765
E78: 43727 | G78: -200900
E79: 43756 | G79: -108780
E80: 43783 | G80: -121275
E81: 43795 | G81: -297920
E82: 43830 | G82: -85260
C83: Distributions 2019 | E83: 43620 | G83: 91335.19
E84: 43669 | G84: 354698.98
E85: 43717 | G85: 120815.6
C86: Contributions 2020 | E86: 43858 | G86: -129850
E87: 43860 | G87: -146020
E88: 43915 | G88: -138180
E89: 43917 | G89: -33957
E90: 43980 | G90: -143570
E91: 43999 | G91: -196000
E92: 44047 | G92: -15863.29
C93: Distributions 2020 | E93: 43888 | G93: 455928.93
E94: 44089 | G94: 67815.69
C95: Contributions 2021 | E95: 44202 | G95: -95550
E96: 44377 | G96: -46060
E97: 44469 | G97: -45570
E98: 44545 | G98: -45570
C99: Distributions 2021 | E99: 44265 | G99: 226087.04
E100: 44376 | G100: 116286.97
E101: 44449 | G101: 200808.29
E102: 44488 | G102: 2852325.8
E103: 44540 | G103: 267815.6
C104: Contributions 2022 | E104: 44650 | G104: -40180
E105: 44742 | G105: -36260
E106: 44827 | G106: -36260
E107: 44925 | G107: -35770
C108: Distributions 2022 | E108: 44645 | G108: 253427.3
E109: 44721 | G109: 125159.36
E110: 44791 | G110: 531625.45
E111: 44888 | G111: 113135.23
C112: Contributions 2023 | E112: 45009 | G112: -35770
C113: Distributions 2023 | E113: 45001 | G113: 615405.61
E114: 45050 | G114: 1802114.4
C116: Net assets | E116: =+E8 -> 45107 | G116: =L116/0.98*C22 -> 10214965 | I116: =+SUMIF($G$24:$G$115,"<0",$G$24:$G$115)+G58+G66 -> -17793039 | J116: check figure-Contributions | L116: 2042992984
I117: =+SUMIF($G$24:$G$115,">0",$G$24:$G$115)-G58-G66 -> 14535591 | J117: check figure-Distributions
C118: Total return | G118: =+XIRR(G24:G116,E24:E116,0.1) -> 0.10411286

Sheet EFM III-C
E8: =+'EFM III'!E8 -> 45107
C17: Internal rate of return
C18: Internal rate of return after incentive allocation | E18: =G118 -> 0.10070497
C19: ROI | E19: =-(G116+I117)/I116 -> 1.382999
C21: Sample Investor Ownership Percentage (Pro-rata share of commitments - to calculate fund level amounts divide the cash flows in column G by the ownership % below)
C22: 0.017131137
C24: Contributions 2014 | E24: 41829 | G24: -84525
E25: 41894 | G25: -43855
E26: 41942 | G26: -23030
E27: 41999 | G27: -32830
C28: Contributions 2015 | E28: 42037 | G28: -32340
E29: 42093 | G29: -41895
E30: 42109 | G30: -31360
E31: 42144 | G31: -18375
E32: 42184 | G32: -28175
E33: 42227 | G33: -37485
E34: 42261 | G34: -49489.99
E35: 42368 | G35: -40425
C36: Contributions 2016 | E36: 42396 | G36: -708295
E37: 42445 | G37: -60024.99
E38: 42549 | G38: -97265.01
E39: 42586 | G39: -74725
E40: 42607 | G40: -56595.01
E41: 42613 | G41: -1199275
E42: 42640 | G42: -28175
E43: 42732 | G43: -39200
C44: Distributions 2016 | E44: 42377 | G44: 259838.31
E45: 42551 | G45: 74232.03
E46: 42642 | G46: 70073.67
E47: 42655 | G47: 28437.88
C48: Contributions 2017 | E48: 42765 | G48: -129360
E49: 42822 | G49: -71785
E50: 42852 | G50: -74970
E51: 42913 | G51: -300860.01
E52: 42991 | G52: -132300
E53: 43006 | G53: -94325
E54: 43080 | G54: -47040
E55: 43095 | G55: -93590
C56: Distributions 2017 | E56: 42747 | G56: 106466.01
C57: Contributions 2018 | E57: 43130 | G57: -908950
E58: 43143 | G58: 251700.75
E59: 43173 | G59: -68600.01
E60: 43216 | G60: -122500
E61: 43265 | G61: -70070
E62: 43292 | G62: -122500.01
E63: 43328 | G63: -445410
E64: 43360 | G64: -67620
E65: 43369 | G65: -1467795
E66: 43389 | G66: 98000
E67: 43445 | G67: -234465.01
C68: Distributions 2018 | E68: 43111 | G68: 96449.74
E69: 43153 | G69: 2225110.8
E70: 43446 | G70: 229234.64
C71: Contributions 2019 | E71: 43522 | G71: -395430.01
E72: 43563 | G72: -198695
E73: 43600 | G73: -121275
E74: 43643 | G74: -68845
E75: 43655 | G75: -107800
E76: 43685 | G76: -121029.99
E77: 43697 | G77: -36382.5
E78: 43727 | G78: -100450
E79: 43756 | G79: -54390
E80: 43783 | G80: -60637.5
E81: 43795 | G81: -148960
E82: 43830 | G82: -42630
C83: Distributions 2019 | E83: 43620 | G83: 56403.62
E84: 43669 | G84: 177349.49
E85: 43717 | G85: 60087.89
C86: Contributions 2020 | E86: 43858 | G86: -64925
E87: 43860 | G87: -73010
E88: 43915 | G88: -69090
E89: 43917 | G89: -16978.5
E90: 43980 | G90: -71785.01
E91: 43999 | G91: -98000
E92: 44047 | G92: -7931.65
C93: Distributions 2020 | E93: 43888 | G93: 260950.61
E94: 44089 | G94: 42773.6
C95: Contributions 2021 | E95: 44202 | G95: -47775
E96: 44377 | G96: -23030
E97: 44469 | G97: -22785
E98: 44545 | G98: -22785
C99: Distributions 2021 | E99: 44265 | G99: 112223.84
E100: 44376 | G100: 67089.93
E101: 44449 | G101: 100059.73
E102: 44488 | G102: 1401819.5
E103: 44540 | G103: 133540.19
C104: Contributions 2022 | E104: 44650 | G104: -20090
E105: 44742 | G105: -18130
E106: 44827 | G106: -18130
E107: 44925 | G107: -17885
C108: Distributions 2022 | E108: 44645 | G108: 126154.99
E109: 44721 | G109: 78975.38
E110: 44791 | G110: 265374.57
E111: 44888 | G111: 55715.46
C112: Contributions 2023 | E112: 45009 | G112: -17885
C113: Distributions 2023 | E113: 45001 | G113: 307461.81
E114: 45050 | G114: 866555.89
C116: Net assets | E116: =+E8 -> 45107 | G116: =L117*C22 -> 5101497.6 | I116: =+SUMIF($G$24:$G$115,"<0",$G$24:$G$115)+G58+G66 -> -8896519.5 | J116: check figure-Contributions
I117: =+SUMIF($G$24:$G$115,">0",$G$24:$G$115)-G58-G66 -> 7202379.6 | J117: check figure-Distributions | L117: 297790951
C118: Total return | G118: =+XIRR(G24:G116,E24:E116) -> 0.10070497

Sheet EFM III-D
E8: =+'EFM III'!E8 -> 45107
C17: Internal rate of return
C18: Internal rate of return after incentive allocation | E18: =G118 -> 0.10336152
C19: ROI | E19: =-(G116+I117)/(I116) -> 1.3888874
C21: Sample Investor Ownership Percentage (Pro-rata share of commitments - to calculate fund level amounts divide the cash flows in column G by the ownership % below)
C22: 0.005037783
C24: Contributions 2014 | E24: 41829 | G24: -11269.99
E25: 41894 | G25: -5847.33
E26: 41942 | G26: -3070.67
E27: 41999 | G27: -4377.33
C28: Contributions 2015 | E28: 42037 | G28: -4312
E29: 42093 | G29: -5586
E30: 42109 | G30: -4181.33
E31: 42144 | G31: -2450
E32: 42184 | G32: -3756.67
E33: 42227 | G33: -4998
E34: 42261 | G34: -6598.67
E35: 42368 | G35: -5390
C36: Contributions 2016 | E36: 42396 | G36: -94439.34
E37: 42445 | G37: -8003.34
E38: 42549 | G38: -12968.67
E39: 42586 | G39: -9963.33
E40: 42607 | G40: -7546
E41: 42613 | G41: -159903.33
E42: 42640 | G42: -3756.67
E43: 42732 | G43: -5226.67
C44: Distributions 2016 | E44: 42377 | G44: 47121.98
E45: 42551 | G45: 4861.16
E46: 42642 | G46: 9354.83
E47: 42655 | G47: 3825.81
C48: Contributions 2017 | E48: 42765 | G48: -17248
E49: 42822 | G49: -9571.33
E50: 42852 | G50: -9996
E51: 42913 | G51: -40114.67
E52: 42991 | G52: -17640
E53: 43006 | G53: -12576.67
E54: 43080 | G54: -6272
E55: 43095 | G55: -12478.67
C56: Distributions 2017 | E56: 42747 | G56: 14195.47
C57: Contributions 2018 | E57: 43130 | G57: -121193.33
E58: 43143 | G58: 33560.1
E59: 43173 | G59: -9146.66
E60: 43216 | G60: -16333.33
E61: 43265 | G61: -9342.67
E62: 43292 | G62: -16333.33
E63: 43328 | G63: -59388
E64: 43360 | G64: -9015.99
E65: 43369 | G65: -195706
E66: 43389 | G66: 13066.66
E67: 43445 | G67: -31261.99
C68: Distributions 2018 | E68: 43111 | G68: 12442.59
E69: 43153 | G69: 314282.78
E70: 43446 | G70: 14771.51
C71: Contributions 2019 | E71: 43522 | G71: -52724
E72: 43563 | G72: -26492.67
E73: 43600 | G73: -16170.01
E74: 43643 | G74: -9179.34
E75: 43655 | G75: -14373.34
E76: 43685 | G76: -16137.34
E77: 43697 | G77: -4851
E78: 43727 | G78: -13393.33
E79: 43756 | G79: -7252
E80: 43783 | G80: -8085
E81: 43795 | G81: -19861.33
E82: 43830 | G82: -5684
C83: Distributions 2019 | E83: 43620 | G83: 5990.27
E84: 43669 | G84: 23646.6
E85: 43717 | G85: 8039.89
C86: Contributions 2020 | E86: 43858 | G86: -8656.67
E87: 43860 | G87: -9734.67
E88: 43915 | G88: -9211.99
E89: 43917 | G89: -2263.8
E90: 43980 | G90: -9571.33
E91: 43999 | G91: -13066.67
E92: 44047 | G92: -1057.55
C93: Distributions 2020 | E93: 43888 | G93: 30158.41
E94: 44089 | G94: 4248.9
C95: Contributions 2021 | E95: 44202 | G95: -6370
E96: 44377 | G96: -3070.67
E97: 44469 | G97: -3038
E98: 44545 | G98: -3038
C99: Distributions 2021 | E99: 44265 | G99: 15001.02
E100: 44376 | G100: 7531.51
E101: 44449 | G101: 13342.52
E102: 44488 | G102: 190071.21
E103: 44540 | G103: 17853.65
C104: Contributions 2022 | E104: 44650 | G104: -2678.67
E105: 44742 | G105: -2417.33
E106: 44827 | G106: -2417.33
E107: 44925 | G107: -2384.66
C108: Distributions 2022 | E108: 44645 | G108: 16817.66
E109: 44721 | G109: 8138.11
E110: 44791 | G110: 35303.34
E111: 44888 | G111: 7447.47
C112: Contributions 2023 | E112: 45009 | G112: -2384.67
C113: Distributions 2023 | E113: 45001 | G113: 40983.09
E114: 45050 | G114: 120100.42
C116: Net assets | E116: =+E8 -> 45107 | G116: =L117*C22 -> 681971.62 | I116: =+SUMIF($G$24:$G$115,"<0",$G$24:$G$115)+G58+G66 -> -1186202.6 | J116: check figure-Contributions
I117: =+SUMIF($G$24:$G$115,">0",$G$24:$G$115)-G58-G66 -> 965530.2 | J117: check figure-Distributions | L117: 135371377
C118: Total return | G118: =+XIRR(G24:G116,E24:E116) -> 0.10336152

Sheet EFM IV
E8: 45107
C17: Internal rate of return
C18: Internal rate of return after incentive allocation | E18: =G66 -> 0.079917642
C19: ROI | E19: =-(G64+I65)/I64 -> 1.1912212
C21: Sample Investor Ownership Percentage (Pro-rata share of commitments - to calculate fund level amounts divide the cash flows in column G by the ownership % below)
C22: 0.000753846
C24: Contributions 2018 | E24: 43136 | G24: -100336.92
E25: 43193 | G25: -10327.69
E26: 43286 | G26: -9423.08
E27: 43328 | G27: -35355.39
E28: 43369 | G28: -734246.17
E29: 43391 | G29: 196000
E30: 43461 | G30: -12740.01
C31: Contributions 2019 | E31: 43494 | G31: -19675.39
E32: 43622 | G32: -13116.92
E33: 43670 | G33: -19750.78
E34: 43742 | G34: -14323.08
E35: 43794 | G35: -35053.83
E36: 43801 | G36: -67167.69
C37: Distributions 2019 | E37: 43671 | G37: 65298.04
C38: Contributions 2020 | E38: 43859 | G38: -18996.92
E39: 43916 | G39: -18619.99
E40: 44103 | G40: -24047.7
E41: 44126 | G41: -80661.55
C42: Contributions 2021 | E42: 44200 | G42: -13267.7
E43: 44376 | G43: -14323.07
E44: 44466 | G44: -9423.08
E45: 44530 | G45: -18619.99
C46: Distributions 2021 | E46: 44463 | G46: 12662.99
E47: 44484 | G47: 484615.55
E48: 44539 | G48: 39200
C49: Contributions 2022 | E49: 44606 | G49: -237386.15
E50: 44649 | G50: -9423.08
E51: 44672 | G51: -3844.61
E52: 44736 | G52: -30983.07
E53: 44764 | G53: -150090.78
E54: 44819 | G54: -340587.69
E55: 44875 | G55: -16810.77
E56: 44915 | G56: -152880.01
C57: Distributions 2022 | E57: 44615 | G57: 8403.74
E58: 44785 | G58: 27814.57
E59: 44895 | G59: 13016.39
C60: Contributions 2023 | E60: 44931 | G60: -16283.08
E61: 45107 | G61: -6483.08
C62: Distributions 2023 | E62: 45051 | G62: 203518.33
C64: Net assets | E64: =+E8 -> 45107 | G64: =L64/0.98*C22 -> 1573476.1 | I64: =+SUMIF($G$24:$G$63,"<0",$G$24:$G$63)+G29 -> -2038249.3 | J64: check figure-Contributions | L64: 2045519388
I65: =+SUMIF($G$24:$G$63,">0",$G$24:$G$63)-G29 -> 854529.61 | J65: check figure-Distributions
C66: Total return | G66: =+XIRR(G24:G64,E24:E64,0.1) -> 0.079917642

Sheet EFM IV-C
E8: =+'EFM IV'!E8 -> 45107
C17: Internal rate of return
C18: Internal rate of return after incentive allocation | E18: =G66 -> 0.075756285
C19: ROI | E19: =-(G64+I65)/I64 -> 1.1808249
C21: Sample Investor Ownership Percentage (Pro-rata share of commitments - to calculate fund level amounts divide the cash flows in column G by the ownership % below)
C22: 0.003167063
C24: Contributions 2018 | E24: 43136 | G24: -40134.77
E25: 43193 | G25: -4131.08
E26: 43286 | G26: -3769.23
E27: 43328 | G27: -14142.15
E28: 43369 | G28: -293698.46
E29: 43391 | G29: 78400
E30: 43461 | G30: -5096.01
C31: Contributions 2019 | E31: 43494 | G31: -7870.16
E32: 43622 | G32: -5246.77
E33: 43670 | G33: -7900.31
E34: 43742 | G34: -5729.23
E35: 43794 | G35: -14021.53
E36: 43801 | G36: -26867.08
C37: Distributions 2019 | E37: 43671 | G37: 25873.43
C38: Contributions 2020 | E38: 43859 | G38: -7598.78
E39: 43916 | G39: -7447.99
E40: 44103 | G40: -9619.08
E41: 44126 | G41: -32264.62
C42: Contributions 2021 | E42: 44200 | G42: -5307.07
E43: 44376 | G43: -5729.22
E44: 44466 | G44: -3769.23
E45: 44530 | G45: -7448.01
C46: Distributions 2021 | E46: 44463 | G46: 4310.1
E47: 44484 | G47: 190670.31
E48: 44539 | G48: 15666.13
C49: Contributions 2022 | E49: 44606 | G49: -94954.46
E50: 44649 | G50: -3769.23
E51: 44672 | G51: -1537.85
E52: 44736 | G52: -12393.23
E53: 44764 | G53: -60036.31
E54: 44819 | G54: -136235.06
E55: 44875 | G55: -6724.31
E56: 44915 | G56: -61152.01
C57: Distributions 2022 | E57: 44615 | G57: 3257.23
E58: 44785 | G58: 10883.37
E59: 44895 | G59: 5060.8
C60: Contributions 2023 | E60: 44931 | G60: -6513.23
E61: 45107 | G61: -2593.23
C62: Distributions 2023 | E62: 45051 | G62: 74979.18
C64: Net assets | E64: =+E8 -> 45107 | G64: =L64*C22 -> 632025.67 | I64: =+SUMIF($G$24:$G$63,"<0",$G$24:$G$63)+G29 -> -815299.7 | J64: check figure-Contributions | L64: 199562077
I65: =+SUMIF($G$24:$G$63,">0",$G$24:$G$63)-G29 -> 330700.55 | J65: check figure-Distributions
C66: Total return | G66: =+XIRR(G24:G64,E24:E64) -> 0.075756285

Sheet EFM IV-D
E8: =+'EFM IV'!E8 -> 45107
C17: Internal rate of return
C18: Internal rate of return after incentive allocation | E18: =G66 -> 0.0793349
C19: ROI | E19: =-(G64+I65)/(I64) -> 1.1898423
C21: Sample Investor Ownership Percentage (Pro-rata share of commitments - to calculate fund level amounts divide the cash flows in column G by the ownership % below)
C22: 0.017458101
C24: Contributions 2018 | E24: 43136 | G24: -200673.85
E25: 43193 | G25: -20655.39
E26: 43286 | G26: -18846.15
E27: 43328 | G27: -70710.78
E28: 43369 | G28: -1468492.3
E29: 43391 | G29: 392000
E30: 43461 | G30: -25480
C31: Contributions 2019 | E31: 43494 | G31: -39350.78
E32: 43622 | G32: -26233.85
E33: 43670 | G33: -39501.54
E34: 43742 | G34: -28646.15
E35: 43794 | G35: -70107.7
E36: 43801 | G36: -134335.38
C37: Distributions 2019 | E37: 43671 | G37: 129646.89
C38: Contributions 2020 | E38: 43859 | G38: -37993.85
E39: 43916 | G39: -37240
E40: 44103 | G40: -48095.38
E41: 44126 | G41: -161323.07
C42: Contributions 2021 | E42: 44200 | G42: -26535.39
E43: 44376 | G43: -28646.16
E44: 44466 | G44: -18846.15
E45: 44530 | G45: -37240.01
C46: Distributions 2021 | E46: 44463 | G46: 22626.91
E47: 44484 | G47: 969199.17
E48: 44539 | G48: 78313.97
C49: Contributions 2022 | E49: 44606 | G49: -474772.3
E50: 44649 | G50: -18846.15
E51: 44672 | G51: -7689.23
E52: 44736 | G52: -61966.16
E53: 44764 | G53: -300181.54
E54: 44819 | G54: -681175.39
E55: 44875 | G55: -33621.54
E56: 44915 | G56: -305760
C57: Distributions 2022 | E57: 44615 | G57: 16557.02
E58: 44785 | G58: 54642.34
E59: 44895 | G59: 25685.79
C60: Contributions 2023 | E60: 44931 | G60: -32566.16
E61: 45107 | G61: -12966.16
C62: Distributions 2023 | E62: 45051 | G62: 406750
C64: Net assets | E64: =+E8 -> 45107 | G64: =L64*C22 -> 3146968.3 | I64: =+SUMIF($G$24:$G$63,"<0",$G$24:$G$63)+G29 -> -4076498.5 | J64: check figure-Contributions | L64: 180258339
I65: =+SUMIF($G$24:$G$63,">0",$G$24:$G$63)-G29 -> 1703422.1 | J65: check figure-Distributions
C66: Total return | G66: =+XIRR(G24:G64,E24:E64) -> 0.0793349

Sheet EETF I-A hypo w INT
B4: Financial Highlights EETF I-A
E8: 44561 | I8: INPUT CELLS
G9: INPUT CELLS | I9: =1-(20000000/213814409.75) -> 0.90646093 | J9: INPUT CELLS
C10: Net investment income/loss | E10: =I10/(J35) -> -0.079751738 | G10: =-6132648-J10 -> -748190 | I10: =(G10*$I$9)+J10 -> -6062663 | J10: -5384458 | K10: Mgmt fees
C12: Expense ratios
C13: Operating expenses | E13: =I13/(J35) -> 0.080862552 | G13: =6225805-J13 -> 841347 | I13: =G13*$I$9+J13 -> 6147106.2 | J13: =-J10 -> 5384458
C14: Incentive allocation | E14: =(G14)/(J35) -> 0.13550001 | G14: 10300602
C15: Total expenses and incentive allocation | E15: =E13+E14 -> 0.21636256
C17: Internal rate of return
C18: Internal rate of return after incentive allocation | E18: =G52 -> 0.37472666
C19: ROI | E19: =-(G50+I51)/I50 -> 1.3823748
J20: INPUT CELLS
C24: Contributions 2020 | E24: 43857 | G24: =-8355693.57*193814409.75/213814409.75 -> -7574109.8
E25: 43985 | G25: =-8946403.4*193814409.75/213814409.75 -> -8109565.2
E26: 44076 | G26: =-8101403.91*193814409.75/213814409.75-1912477.07 -> -9256083.2
E27: 44117 | G27: =-10183965.83*193814409.75/213814409.75 -> -9231367.2
E28: 44141 | G28: =-9094491.06*193814409.75/213814409.75 -> -8243800.9
E29: 44148 | G29: =-4743875.63*193814409.75/213814409.75 -> -4300137.9
E30: 44187 | G30: =-4000309.07*193814409.75/213814409.75-294804.35 -> -3920928.2 | J30: 23429675 | K30: PY NAV
C31: Contributions 2021 | E31: 44203 | G31: =-17965219.19*193814409.75/213814409.75-492157.19 -> -16776927 | J31: 60571194 | K31: 3/31 NAV
E32: 44217 | G32: =-2420477.32*193814409.75/213814409.75 -> -2194068.1 | J32: 95593774 | K32: 6/30 NAV
E33: 44250 | G33: =8743624.8*193814409.75/213814409.75 -> 7925754.3 | J33: 98439035 | K33: 9/30 NAV
E34: 44265 | G34: =-5278462.5*193814409.75/213814409.75-155480.19 -> -4940200.2 | J34: =G50 -> 102062302 | K34: CY NAV
E35: 44291 | G35: =-12658173.89*193814409.75/213814409.75-268874.97 -> -11743015 | J35: =SUM(J30:J34)/5 -> 76019196 | K35: AVG NAV
E36: 44307 | G36: =-28503534.36*193814409.75/213814409.75-795428.94 -> -26632769
E37: 44319 | G37: =29772852.87*193814409.75/213814409.75 -> 26987928
E38: 44335 | G38: =-13567083.21*193814409.75/213814409.75-457505.62 -> -12755537
E39: 44344 | G39: =16251618.18*193814409.75/213814409.75+830538.11-1675268.66 -> 13886726
E40: 44361 | G40: =416746.8*193814409.75/213814409.75+67984.53 -> 445749.22
E41: 44375 | G41: =-6218476.1-209162.1 -> -6427638.2
E42: 44405 | G42: -3521086
E43: 44468 | G43: -1653652.9
E44: 44475 | G44: -4024098.3
E45: 44483 | G45: -4703164.9
E46: 44505 | G46: -4225303.2
E47: 44551 | G47: -2584225.6
E48: 44558 | G48: 41112360
C50: Net assets | E50: =+E8 -> 44561 | G50: 102062302 | I50: =+SUMIF($G$24:$G$49,"<0",$G$24:$G$49)+G33+G37+G39+G40 -> -1.0357152e+08 | J50: check figure-Contributions
I51: =+SUMIF($G$24:$G$49,">0",$G$24:$G$49)-G33-G37-G39-G40 -> 41112360 | J51: check figure-Distributions
C52: Total return | G52: =+XIRR(G24:G50,E24:E50,0.1) -> 0.37472666
I53: =I50-#REF! -> #REF!
C61: Net investment loss ratio | E61: =E10 -> -0.079751738
C63: Expense ratios:
C64: Operating expenses | E64: =E13 -> 0.080862552
C65: Unearned incentive allocation | E65: =E14 -> 0.13550001
C66: Operating expenses and unearned incentive allocation ratio | E66: =SUM(E64:E65) -> 0.21636256
C68: Internal rate of return net of incentive allocation | E68: =+E18 -> 0.37472666

Sheet EETF I-B hypo
B4: Financial Highlights EETF I-B
E8: 44561
G9: INPUT CELLS
C10: Net investment income/loss | E10: =I10/(J35) -> 0 | G10: =-6132648-J10 -> -6132648
C12: Expense ratios
C13: Operating expenses | E13: =I13/(J35) -> 0 | G13: =6225805-J13 -> 6225805
C14: Incentive allocation | E14: =(G14)/(J35) -> 0.14150342 | G14: 10300602
C15: Total expenses and incentive allocation | E15: =E13+E14 -> 0.14150342
C17: Internal rate of return
C18: Internal rate of return after incentive allocation | E18: =G52 -> 0.37967424
C19: ROI | E19: =-(G50+I51)/I50 -> 1.3892632
J20: INPUT CELLS
C24: Contributions 2020 | E24: 43857 | G24: -6869196.6
E25: 43985 | G25: -7354817.8
E26: 44076 | G26: -8396286.7
E27: 44117 | G27: -8372215.1
E28: 44141 | G28: -7476560.3
E29: 44148 | G29: -3899929.3
E30: 44187 | G30: -3556267.5 | J30: 23869519 | K30: PY NAV
C31: Contributions 2021 | E31: 44203 | G31: -15215945 | J31: 72564673 | K31: 3/31 NAV
E32: 44217 | G32: -1989868.9 | J32: 86518493 | K32: 6/30 NAV
E33: 44250 | G33: 7188114 | J33: 89013713 | K33: 9/30 NAV
E34: 44265 | G34: -4480556.4 | J34: =G50 -> 92003681 | K34: CY NAV
E35: 44291 | G35: -10650340 | J35: =SUM(J30:J34)/5 -> 72794016 | K35: AVG NAV
E36: 44307 | G36: -24154779
E37: 44319 | G37: 24476194
E38: 44335 | G38: -11568790
E39: 44344 | G39: 13360418
E40: 44361 | G40: 342606.6
E41: 44375 | G41: -5666306.5
E42: 44405 | G42: -3196431.5
E43: 44468 | G43: -1501181.2
E44: 44475 | G44: -3653064.6
E45: 44483 | G45: -4269519.2
E46: 44505 | G46: -3835717.8
E47: 44551 | G47: -2345952.4
E48: 44558 | G48: 37317814
C50: Net assets | E50: =+E8 -> 44561 | G50: 92003681 | I50: =+SUMIF($G$24:$G$49,"<0",$G$24:$G$49)+G33+G37+G39+G40 -> -93086392 | J50: check figure-Contributions
I51: =+SUMIF($G$24:$G$49,">0",$G$24:$G$49)-G33-G37-G39-G40 -> 37317814 | J51: check figure-Distributions
C52: Total return | G52: =+XIRR(G24:G50,E24:E50,0.1) -> 0.37967424
I53: =I50-#REF! -> #REF!
C61: Net investment loss ratio | E61: =E10 -> 0
C63: Expense ratios:
C64: Operating expenses | E64: =E13 -> 0
C65: Unearned incentive allocation | E65: =E14 -> 0.14150342
C66: Operating expenses and unearned incentive allocation ratio | E66: =SUM(E64:E65) -> 0.14150342
C68: Internal rate of return net of incentive allocation | E68: =+E18 -> 0.37967424

Sheet EETF I-C hypo
B4: Financial Highlights EETF I-C
E8: 44561
G9: INPUT CELLS
C10: Net investment income/loss | E10: =I10/(J35) -> 0 | G10: =-6132648-J10 -> -6132648
C12: Expense ratios
C13: Operating expenses | E13: =I13/(J35) -> 0 | G13: =6225805-J13 -> 6225805
C14: Incentive allocation | E14: =(G14)/(J35) -> 0.15717178 | G14: 10300602
C15: Total expenses and incentive allocation | E15: =E13+E14 -> 0.15717178
C17: Internal rate of return
C18: Internal rate of return after incentive allocation | E18: =G52 -> 0.27906733
C19: ROI | E19: =-(G50+I51)/I50 -> 1.2835123
J20: INPUT CELLS
C24: Contributions 2020 | E24: 43857 | G24: -3877114.2
E25: 43985 | G25: -4151208.7
E26: 44076 | G26: -4739034.9
E27: 44117 | G27: -4725448.3
E28: 44141 | G28: -4219922.6
E29: 44148 | G29: -2201199.4
E30: 44187 | G30: -2007229.6 | J30: 23429675 | K30: PY NAV
C31: Contributions 2021 | E31: 44203 | G31: -8588188.4 | J31: 60571194 | K31: 3/31 NAV
E32: 44217 | G32: -1123122.4 | J32: 95593774 | K32: 6/30 NAV
E33: 44250 | G33: 4057117.6 | J33: 98439035 | K33: 9/30 NAV
E34: 44265 | G34: -2528917.1 | J34: =G50 -> 49652432 | K34: CY NAV
E35: 44291 | G35: -6011268.2 | J35: =SUM(J30:J34)/5 -> 65537222 | K35: AVG NAV
E36: 44307 | G36: -13633448
E37: 44319 | G37: 13814862
E38: 44335 | G38: -6529660.4
E39: 44344 | G39: 7540891.6
E40: 44361 | G40: 193374.13
E41: 44375 | G41: -3046769.2
E42: 44405 | G42: -1804130.9
E43: 44468 | G43: -847297.2
E44: 44475 | G44: -2061863.9
E45: 44483 | G45: -2409803.4
E46: 44505 | G46: -2164957.1
E47: 44551 | G47: -1324103.2
E48: 44558 | G48: 17588777
C50: Net assets | E50: =+E8 -> 44561 | G50: 49652432 | I50: =+SUMIF($G$24:$G$49,"<0",$G$24:$G$49)+G33+G37+G39+G40 -> -52388442 | J50: check figure-Contributions
I51: =+SUMIF($G$24:$G$49,">0",$G$24:$G$49)-G33-G37-G39-G40 -> 17588777 | J51: check figure-Distributions
C52: Total return | G52: =+XIRR(G24:G50,E24:E50,0.1) -> 0.27906733
I53: =I50-#REF! -> #REF!
C61: Net investment loss ratio | E61: =E10 -> 0
C63: Expense ratios:
C64: Operating expenses | E64: =E13 -> 0
C65: Unearned incentive allocation | E65: =E14 -> 0.15717178
C66: Operating expenses and unearned incentive allocation ratio | E66: =SUM(E64:E65) -> 0.15717178
C68: Internal rate of return net of incentive allocation | E68: =+E18 -> 0.27906733

Sheet EETF I-E 1st close LP
B4: Financial Highlights EETF I-E
E8: =#REF! -> #REF!
G9: INPUT CELLS
C10: Net investment income/loss | E10: =G10*C20/(J28) -> -0.078781974 | G10: -5698523
C12: Operating expenses | E12: =G12*C20/(J28) -> 0.078781974 | G12: =3676284+380104+1642135 -> 5698523
C13: Incentive allocation | E13: 0
C14: Total expenses and incentive allocation | E14: =SUM(E12:E13) -> 0.078781974
C15: Internal rate of return | J15: INPUT CELLS
C16: Internal rate of return after incentive allocation | E16: =G44 -> #REF! | J16: =34193250*C20 -> 34193250 | K16: Jan
C17: ROI | E17: =-(G42+I45)/I44 -> 1.3913423 | J17: =34193250*C20 -> 34193250 | K17: Feb
J18: =33243002*C20 -> 33243002 | K18: Mar
C19: TX GLO | J19: =32679377*C20 -> 32679377 | K19: Apr
C20: 1 | J20: =32679377*C20 -> 32679377 | K20: May
J21: =59038065*C20 -> 59038065 | K21: Jun
C22: Contributions 2020 | E22: 43857 | G22: -34125000 | J22: =58474440*C20 -> 58474440 | K22: Jul
E23: 43985 | G23: -26250000 | J23: =58474440*C20 -> 58474440 | K23: Aug
E24: 44076 | G24: -32625000 | J24: =91095475*C20 -> 91095475 | K24: Sep
E25: 44117 | G25: -46500000 | J25: =135900685*C20 -> 135900685 | K25: Oct
E26: 44141 | G26: -34425000 | J26: =180110402*C20 -> 180110402 | K26: Nov
E27: 44187 | G27: -14400000 | J27: =G42 -> 1.1791218e+08 | K27: Dec
C28: Contributions 2021 | E28: 44250 | G28: 22500000 | J28: =SUM(J16:J27)/12 -> 72332828 | K28: AVG NAV
E29: 44319 | G29: 53325000
E30: 44344 | G30: 24750000
E31: 44375 | G31: -7253666.2
E32: 44405 | G32: -4087644.2
E33: 44468 | G33: -1919732.9
E34: 44475 | G34: -4671593.4
E35: 44483 | G35: -5459924.8
E36: 44505 | G36: -4905173
E37: 44551 | G37: -3000038.9
E38: 44558 | G38: 47724024
C42: Net assets | E42: =+E8 -> #REF! | G42: 1.1791218e+08
C44: Total return | G44: =+XIRR(G22:G42,E22:E42,0.1) -> #REF! | I44: =+SUMIF($G$22:$G$41,"<0",$G$22:$G$41)+G28+G29+G30 -> -1.1904777e+08 | J44: check figure-Contributions
I45: =+SUMIF($G$22:$G$41,">0",$G$22:$G$41)-G28-G29-G30 -> 47724024 | J45: check figure-Distributions
C53: Net investment loss ratio | E53: =E10 -> -0.078781974
C55: Expense ratios:
C56: Operating expenses | E56: =E12 -> 0.078781974
C57: Unearned incentive allocation | E57: =E11 -> 0
C58: Operating expenses and unearned incentive allocation ratio | E58: =SUM(E56:E57) -> 0.078781974
C60: Internal rate of return net of incentive allocation | E60: =+E16 -> #REF!

Sheet EETF I-E 1st close LP w INT
B4: Financial Highlights EETF I-E
E8: =#REF! -> #REF!
G9: INPUT CELLS
C10: Net investment income/loss | E10: =G10*C20/(J28) -> -0.078781974 | G10: -5698523
C12: Operating expenses | E12: =G12*C20/(J28) -> 0.078781974 | G12: =3676284+380104+1642135 -> 5698523
C13: Incentive allocation | E13: 0
C14: Total expenses and incentive allocation | E14: =SUM(E12:E13) -> 0.078781974
C15: Internal rate of return | J15: INPUT CELLS
C16: Internal rate of return after incentive allocation | E16: =G44 -> #REF! | J16: =34193250*C20 -> 34193250 | K16: Jan
C17: ROI | E17: =-(G42+I45)/I44 -> 1.4761003 | J17: =34193250*C20 -> 34193250 | K17: Feb
J18: =33243002*C20 -> 33243002 | K18: Mar
C19: TX GLO | J19: =32679377*C20 -> 32679377 | K19: Apr
C20: 1 | J20: =32679377*C20 -> 32679377 | K20: May
J21: =59038065*C20 -> 59038065 | K21: Jun
C22: Contributions 2020 | E22: 43857 | G22: -34125000 | J22: =58474440*C20 -> 58474440 | K22: Jul
E23: 43985 | G23: -26250000 | J23: =58474440*C20 -> 58474440 | K23: Aug
E24: 44076 | G24: -32625000 | J24: =91095475*C20 -> 91095475 | K24: Sep
E25: 44117 | G25: -46500000 | J25: =135900685*C20 -> 135900685 | K25: Oct
E26: 44141 | G26: -34425000 | J26: =180110402*C20 -> 180110402 | K26: Nov
E27: 44187 | G27: -14400000 | J27: =G42 -> 1.1791218e+08 | K27: Dec
C28: Contributions 2021 | E28: 44250 | G28: 22500000 | J28: =SUM(J16:J27)/12 -> 72332828 | K28: AVG NAV
E29: 44319 | G29: 53325000
E30: 44344 | G30: =24750000+6835746.71 -> 31585747
E31: 44375 | G31: =-7253666.2 -> -7253666.2
E32: 44405 | G32: -4087644.2
E33: 44468 | G33: -1919732.9
E34: 44475 | G34: -4671593.4
E35: 44483 | G35: -5459924.8
E36: 44505 | G36: -4905173
E37: 44551 | G37: -3000038.9
E38: 44558 | G38: 47724024
C42: Net assets | E42: =+E8 -> #REF! | G42: 1.1791218e+08
C44: Total return | G44: =+XIRR(G22:G42,E22:E42,0.1) -> #REF! | I44: =+SUMIF($G$22:$G$41,"<0",$G$22:$G$41)+G28+G29+G30 -> -1.1221203e+08 | J44: check figure-Contributions
I45: =+SUMIF($G$22:$G$41,">0",$G$22:$G$41)-G28-G29-G30 -> 47724024 | J45: check figure-Distributions
C53: Net investment loss ratio | E53: =E10 -> -0.078781974
C55: Expense ratios:
C56: Operating expenses | E56: =E12 -> 0.078781974
C57: Unearned incentive allocation | E57: =E11 -> 0
C58: Operating expenses and unearned incentive allocation ratio | E58: =SUM(E56:E57) -> 0.078781974
C60: Internal rate of return net of incentive allocation | E60: =+E16 -> #REF!

Sheet EETF I-E w INT
B4: Financial Highlights EETF I-E
E8: =#REF! -> #REF!
G9: INPUT CELLS
C10: Net investment income/loss | E10: =G10*C20/(J28) -> -0.076180984 | G10: -5698523
C12: Operating expenses | E12: =G12*C20/(J28) -> 0.076180984 | G12: =3676284+380104+1642135 -> 5698523
C13: Incentive allocation | E13: 0
C14: Total expenses and incentive allocation | E14: =SUM(E12:E13) -> 0.076180984
C15: Internal rate of return | J15: INPUT CELLS
C16: Internal rate of return after incentive allocation | E16: =G46 -> #REF! | J16: =34193250*C20 -> 34193250 | K16: Jan
C17: ROI | E17: =-(G44+I45)/I44 -> 1.4544333 | J17: =34193250*C20 -> 34193250 | K17: Feb
J18: =33243002*C20 -> 33243002 | K18: Mar
J19: =32679377*C20 -> 32679377 | K19: Apr
C20: 1 | J20: =32679377*C20 -> 32679377 | K20: May
J21: =59038065*C20 -> 59038065 | K21: Jun
C22: Contributions 2020 | E22: 43857 | G22: -34193250 | J22: =58474440*C20 -> 58474440 | K22: Jul
E23: 43985 | G23: -26302500 | J23: =58474440*C20 -> 58474440 | K23: Aug
E24: 44076 | G24: -32690250 | J24: =91095475*C20 -> 91095475 | K24: Sep
E25: 44117 | G25: -46500000 | J25: =135900685*C20 -> 135900685 | K25: Oct
E26: 44141 | G26: -34470900 | J26: =180110402*C20 -> 180110402 | K26: Nov
E27: 44148 | G27: -14261850 | J27: =G44 -> 1.4754744e+08 | K27: Dec
E28: 44187 | G28: -15600000 | J28: =SUM(J16:J27)/12 -> 74802433 | K28: AVG NAV
C29: Contributions 2021 | E29: 44250 | G29: 24375000
E30: 44307 | G30: -24078600
E31: 44319 | G31: 62947350
E32: 44344 | G32: =30970500+7070162.56-608146.04 -> 37432517
E33: 44375 | G33: -9076754.3
E34: 44405 | G34: -5115005.5
E35: 44468 | G35: -2402225.8
E36: 44475 | G36: -5845720.5
E37: 44483 | G37: -6832185.8
E38: 44505 | G38: -6138006.5
E39: 44551 | G39: -3754048.6
E40: 44558 | G40: 59718662
C44: Net assets | E44: =+E8 -> #REF! | G44: 1.4754744e+08 | I44: =+SUMIF($G$22:$G$43,"<0",$G$22:$G$43)+G29+G31+G32 -> -1.4250643e+08 | J44: check figure-Contributions
I45: =+SUMIF($G$22:$G$43,">0",$G$22:$G$43)-G29-G31-G32 -> 59718662 | J45: check figure-Distributions
C46: Total return | G46: =+XIRR(G22:G44,E22:E44,0.1) -> #REF!
C55: Net investment loss ratio | E55: =E10 -> -0.076180984
C57: Expense ratios:
C58: Operating expenses | E58: =E12 -> 0.076180984
C59: Unearned incentive allocation | E59: =E11 -> 0
C60: Operating expenses and unearned incentive allocation ratio | E60: =SUM(E58:E59) -> 0.076180984
C62: Internal rate of return net of incentive allocation | E62: =+E16 -> #REF!

Sheet EETF I-E hypo
B4: Financial Highlights EETF I-A
E8: 44561 | I8: INPUT CELLS
G9: INPUT CELLS | I9: =1-(20000000/213814409.75) -> 0.90646093 | J9: INPUT CELLS
C10: Net investment income/loss | E10: =I10/(J35) -> -0.071228055 | G10: =-6132648-J10 -> -748190 | I10: =(G10*$I$9)+J10 -> -6062663 | J10: -5384458 | K10: Mgmt fees
C12: Expense ratios
C13: Operating expenses | E13: =I13/(J35) -> 0.072220147 | G13: =6225805-J13 -> 841347 | I13: =G13*$I$9+J13 -> 6147106.2 | J13: =-J10 -> 5384458
C14: Incentive allocation | E14: =(G14)/(J35) -> 0.12101808 | G14: 10300602
C15: Total expenses and incentive allocation | E15: =E13+E14 -> 0.19323823
C17: Internal rate of return
C18: Internal rate of return after incentive allocation | E18: =G52 -> 0.38163324
C19: ROI | E19: =-(G50+I51)/I50 -> 1.3913423
J20: INPUT CELLS
C24: Contributions 2020 | E24: 43857 | G24: -10992251
E25: 43985 | G25: -11769354
E26: 44076 | G26: -13435937
E27: 44117 | G27: -13397417
E28: 44141 | G28: -11964169
E29: 44148 | G29: -6240759.3
E30: 44187 | G30: -5690823.5 | J30: 23429675 | K30: PY NAV
C31: Contributions 2021 | E31: 44203 | G31: -24348915 | J31: 60571194 | K31: 3/31 NAV
E32: 44217 | G32: -3184235.3 | J32: 95593774 | K32: 6/30 NAV
E33: 44250 | G33: 11502590 | J33: 98439035 | K33: 9/30 NAV
E34: 44265 | G34: -7169892.6 | J34: =G50 -> 1.4754744e+08 | K34: CY NAV
E35: 44291 | G35: -17042926 | J35: =SUM(J30:J34)/5 -> 85116223 | K35: AVG NAV
E36: 44307 | G36: -38653049
E37: 44319 | G37: 39167386
E38: 44335 | G38: -18512653
E39: 44344 | G39: 21379658
E40: 44361 | G40: 548247.19
E41: 44375 | G41: -9076754.3
E42: 44405 | G42: -5115005.5
E43: 44468 | G43: -2402225.8
E44: 44475 | G44: -5845720.5
E45: 44483 | G45: -6832185.8
E46: 44505 | G46: -6138006.5
E47: 44551 | G47: -3754048.6
E48: 44558 | G48: 59718662
C50: Net assets | E50: =+E8 -> 44561 | G50: 1.4754744e+08 | I50: =+SUMIF($G$24:$G$49,"<0",$G$24:$G$49)+G33+G37+G39+G40 -> -1.4896845e+08 | J50: check figure-Contributions
I51: =+SUMIF($G$24:$G$49,">0",$G$24:$G$49)-G33-G37-G39-G40 -> 59718662 | J51: check figure-Distributions
C52: Total return | G52: =+XIRR(G24:G50,E24:E50,0.1) -> 0.38163324
I53: =I50-#REF! -> #REF!
C61: Net investment loss ratio | E61: =E10 -> -0.071228055
C63: Expense ratios:
C64: Operating expenses | E64: =E13 -> 0.072220147
C65: Unearned incentive allocation | E65: =E14 -> 0.12101808
C66: Operating expenses and unearned incentive allocation ratio | E66: =SUM(E64:E65) -> 0.19323823
C68: Internal rate of return net of incentive allocation | E68: =+E18 -> 0.38163324

Sheet EETF I-E hypo w INT
B4: Financial Highlights EETF I-A
E8: 44561 | I8: INPUT CELLS
G9: INPUT CELLS | I9: =1-(20000000/213814409.75) -> 0.90646093 | J9: INPUT CELLS
C10: Net investment income/loss | E10: =I10/(J35) -> -0.071228055 | G10: =-6132648-J10 -> -748190 | I10: =(G10*$I$9)+J10 -> -6062663 | J10: -5384458 | K10: Mgmt fees
C12: Expense ratios
C13: Operating expenses | E13: =I13/(J35) -> 0.072220147 | G13: =6225805-J13 -> 841347 | I13: =G13*$I$9+J13 -> 6147106.2 | J13: =-J10 -> 5384458
C14: Incentive allocation | E14: =(G14)/(J35) -> 0.12101808 | G14: 10300602
C15: Total expenses and incentive allocation | E15: =E13+E14 -> 0.19323823
C17: Internal rate of return
C18: Internal rate of return after incentive allocation | E18: =G52 -> 0.43163177
C19: ROI | E19: =-(G50+I51)/I50 -> 1.4544333
J20: INPUT CELLS
C24: Contributions 2020 | E24: 43857 | G24: -10992251
E25: 43985 | G25: -11769354
E26: 44076 | G26: -13435937
E27: 44117 | G27: -13397417
E28: 44141 | G28: -11964169
E29: 44148 | G29: -6240759.3
E30: 44187 | G30: -5690823.5 | J30: 23429675 | K30: PY NAV
C31: Contributions 2021 | E31: 44203 | G31: -24348915 | J31: 60571194 | K31: 3/31 NAV
E32: 44217 | G32: -3184235.3 | J32: 95593774 | K32: 6/30 NAV
E33: 44250 | G33: 11502590 | J33: 98439035 | K33: 9/30 NAV
E34: 44265 | G34: -7169892.6 | J34: =G50 -> 1.4754744e+08 | K34: CY NAV
E35: 44291 | G35: -17042926 | J35: =SUM(J30:J34)/5 -> 85116223 | K35: AVG NAV
E36: 44307 | G36: -38653049
E37: 44319 | G37: 39167386
E38: 44335 | G38: -18512653
E39: 44344 | G39: =21379657.88+7070162.56-608146.04 -> 27841674
E40: 44361 | G40: 548247.19
E41: 44375 | G41: -9076754.3
E42: 44405 | G42: -5115005.5
E43: 44468 | G43: -2402225.8
E44: 44475 | G44: -5845720.5
E45: 44483 | G45: -6832185.8
E46: 44505 | G46: -6138006.5
E47: 44551 | G47: -3754048.6
E48: 44558 | G48: 59718662
C50: Net assets | E50: =+E8 -> 44561 | G50: 1.4754744e+08 | I50: =+SUMIF($G$24:$G$49,"<0",$G$24:$G$49)+G33+G37+G39+G40 -> -1.4250643e+08 | J50: check figure-Contributions
I51: =+SUMIF($G$24:$G$49,">0",$G$24:$G$49)-G33-G37-G39-G40 -> 59718662 | J51: check figure-Distributions
C52: Total return | G52: =+XIRR(G24:G50,E24:E50,0.1) -> 0.43163177
I53: =I50-#REF! -> #REF!
C61: Net investment loss ratio | E61: =E10 -> -0.071228055
C63: Expense ratios:
C64: Operating expenses | E64: =E13 -> 0.072220147
C65: Unearned incentive allocation | E65: =E14 -> 0.12101808
C66: Operating expenses and unearned incentive allocation ratio | E66: =SUM(E64:E65) -> 0.19323823
C68: Internal rate of return net of incentive allocation | E68: =+E18 -> 0.43163177

Sheet EETF Co Inv I-A Hypo
B4: Financial Highlights EETF Co Invest I-A
E8: =#REF! -> #REF!
C14: Internal rate of return
C15: Internal rate of return after incentive allocation | E15: =G51 -> #REF!
C16: ROI | E16: =-(G49+I50)/I49 -> #REF!
C19: 1
C21: Contributions 2020 | E21: 43857 | G21: -1916207.2
E22: 43985 | G22: -2051674.4
E23: 44076 | G23: -1929279
E24: 44117 | G24: -2335484
E25: 44141 | G25: -2085635.3
E26: 44148 | G26: -1087910.7
E27: 44187 | G27: -928393.27
C28: Contributions 2021 | E28: 44203 | G28: -4138326.1
E29: 44217 | G29: -555086.91
E30: 44250 | G30: 2005171.3
E31: 44265 | G31: =-1062803.51988888-153507.440563768 -> -1216311
E32: 44291 | G32: -2912929.4
E33: 44307 | G33: -6566393.2
E34: 44319 | G34: 6827794.1
E35: 44335 | G35: -3128410.2
E36: 44344 | G36: =4007503.70523165-280527.882810231 -> 3726975.8
E37: 44361 | G37: =-100076.712331714+195649.057134302 -> 95572.345
E38: 44375 | G38: -1265158.5
E39: 44405 | G39: -889850.64
E40: 44468 | G40: -282147.76
E41: 44475 | G41: -1041776.4
E42: 44483 | G42: -1193702.1
E43: 44505 | G43: -1085183.7
E44: 44551 | G44: -499184.5
E45: 44558 | G45: 10430885
E46: 44599 | G46: -455777.16
E47: 44635 | G47: -1128591.1
C49: Net assets | E49: =+E8 -> #REF! | G49: =#REF! -> #REF! | I49: =+SUMIF($G$21:$G$48,"<0",$G$21:$G$48)+G30+G34+G36+G37 -> -26037899 | J49: check figure-Contributions
I50: =+SUMIF($G$21:$G$48,">0",$G$21:$G$48)-G30-G34-G36-G37 -> 10430885 | J50: check figure-Distributions
C51: Total return | G51: =+XIRR(G21:G49,E21:E49,0.1) -> #REF!
G52: =G49-#REF! -> #REF! | I52: =I49-#REF! -> #REF!
I53: =I50-#REF! -> #REF!

Sheet EETF Co Inv I-B hypo
B4: Financial Highlights EETF Co Invest I-B
E8: =#REF! -> #REF!
G9: INPUT CELLS
C10: Net investment income/loss | E10: =G10*C19/(J30) -> -0.022605132 | G10: -425383
C12: Operating expenses | E12: =G12*C19/(J30) -> 0.023743405 | G12: 446803
C14: Internal rate of return
C15: Internal rate of return after incentive allocation | E15: =G49 -> #REF!
C16: ROI | E16: =-(G47+I48)/I47 -> 1.5662821
C19: 1
C21: Contributions 2020 | E21: 43857 | G21: -2012378.3
E22: 43985 | G22: -2154644.3
E23: 44076 | G23: -2026106.1
E24: 44117 | G24: -2452697.8 | J24: INPUT CELLS
E25: 44141 | G25: -2190309.6 | J25: 2474504 | K25: PY NAV
E26: 44148 | G26: -1142511 | J26: 13084702 | K26: 3/31 NAV
E27: 44187 | G27: -974987.68 | J27: 23875861 | K27: 6/30 NAV
C28: Contributions 2021 | E28: 44203 | G28: -4346021.4 | J28: 25377815 | K28: 9/30 NAV
E29: 44217 | G29: -582945.73 | J29: =G47 -> 29277036 | K29: CY NAV
E30: 44250 | G30: 2105807.3 | J30: =SUM(J25:J29)/5 -> 18817984 | K30: AVG NAV
E31: 44265 | G31: -1277355.4
E32: 44291 | G32: -3059124.1
E33: 44307 | G33: -6895948.9
E34: 44319 | G34: 7170469
E35: 44335 | G35: -3285419.6
E36: 44344 | G36: 3914026.1
E37: 44361 | G37: 100368.95
E38: 44375 | G38: -1333769.9
E39: 44405 | G39: -934510.66
E40: 44468 | G40: -296308.27
E41: 44475 | G41: -1094061.3
E42: 44483 | G42: -1253611.9
... E45: 44558 | G45: 10954368
C47: Net assets | E47: =+E8 -> #REF! | G47: 29277036 | I47: =+SUMIF($G$21:$G$46,"<0",$G$21:$G$46)+G30+G34+G36+G37 -> -25685925 | J47: check figure-Contributions
I48: =+SUMIF($G$21:$G$46,">0",$G$21:$G$46)-G30-G34-G36-G37 -> 10954368 | J48: check figure-Distributions
C49: Total return | G49: =+XIRR(G21:G47,E21:E47,0.1) -> #REF!
C58: Net investment loss ratio | E58: =E10 -> -0.022605132
C60: Operating expenses ratio | E60: =E12 -> 0.023743405
C62: Internal rate of return | E62: =+E15 -> #REF!

Sheet EETF Co Inv I-C hypo
B4: Financial Highlights EETF Co Invest I-C
E8: =#REF! -> #REF!
G9: INPUT CELLS
C10: Net investment income/loss | E10: =G10*C19/(J30) -> -0.025818614 | G10: -425383
C12: Operating expenses | E12: =G12*C19/(J30) -> 0.0271187 | G12: 446803
C14: Internal rate of return
C15: Internal rate of return after incentive allocation | E15: =G49 -> #REF!
C16: ROI | E16: =-(G47+I48)/I47 -> 1.4612901
C19: 1
C21: Contributions 2020 | E21: 43857 | G21: -1247558.7
E22: 43985 | G22: -1335755.4
E23: 44076 | G23: -1256069.2
E24: 44117 | G24: -1520531.5 | J24: INPUT CELLS
E25: 44141 | G25: -1357865.9 | J25: 2474504 | K25: PY NAV
E26: 44148 | G26: -708291.08 | J26: 13084702 | K26: 3/31 NAV
E27: 44187 | G27: -604436.24 | J27: 23875861 | K27: 6/30 NAV
C28: Contributions 2021 | E28: 44203 | G28: -2694283.1 | J28: 25377815 | K28: 9/30 NAV
E29: 44217 | G29: -361392.8 | J29: =G47 -> 17566250 | K29: CY NAV
E30: 44250 | G30: 1305479.3 | J30: =SUM(J25:J29)/5 -> 16475826 | K30: AVG NAV
E31: 44265 | G31: -791886.85
E32: 44291 | G32: -1896480.9
E33: 44307 | G33: -4275091.4
E34: 44319 | G34: 4445278
E35: 44335 | G35: -2036771
E36: 44344 | G36: 2426470.9
E37: 44361 | G37: 62222.97
E38: 44375 | G38: -776499.45
E39: 44405 | G39: -579342.82
E40: 44468 | G40: -183694.06
E41: 44475 | G41: -678255.01
E42: 44483 | G42: -777167.2
... E45: 44558 | G45: 5629442.1
C47: Net assets | E47: =+E8 -> #REF! | G47: 17566250 | I47: =+SUMIF($G$21:$G$46,"<0",$G$21:$G$46)+G30+G34+G36+G37 -> -15873434 | J47: check figure-Contributions
I48: =+SUMIF($G$21:$G$46,">0",$G$21:$G$46)-G30-G34-G36-G37 -> 5629442.1 | J48: check figure-Distributions
C49: Total return | G49: =+XIRR(G21:G47,E21:E47,0.1) -> #REF!
C58: Net investment loss ratio | E58: =E10 -> -0.025818614
C60: Operating expenses ratio | E60: =E12 -> 0.0271187
C62: Internal rate of return | E62: =+E15 -> #REF!

Sheet EETF Co Inv I-E hypo
B4: Financial Highlights EETF Co Invest I-E
E8: =#REF! -> #REF!
G9: INPUT CELLS
C10: Net investment income/loss | E10: =G10*C19/(J30) -> -0.018002424 | G10: -425383
C12: Operating expenses | E12: =G12*C19/(J30) -> 0.018908929 | G12: 446803
C14: Internal rate of return
C15: Internal rate of return after incentive allocation | E15: =G49 -> #REF!
C16: ROI | E16: =-(G47+I48)/I47 -> 1.5703085
C19: 1
C21: Contributions 2020 | E21: 43857 | G21: -3652809
E22: 43985 | G22: -3911046.1
E23: 44076 | G23: -3677727.3
E24: 44117 | G24: -4452063.9 | J24: INPUT CELLS
E25: 44141 | G25: -3975784.7 | J25: 2474504 | K25: PY NAV
E26: 44148 | G26: -2073852 | J26: 13084702 | K26: 3/31 NAV
E27: 44187 | G27: -1769768.5 | J27: 23875861 | K27: 6/30 NAV
C28: Contributions 2021 | E28: 44203 | G28: -7888768.3 | J28: 25377815 | K28: 9/30 NAV
E29: 44217 | G29: -1058145.7 | J29: =G47 -> 53333151 | K29: CY NAV
E30: 44250 | G30: 3822398.6 | J30: =SUM(J25:J29)/5 -> 23629207 | K30: AVG NAV
E31: 44265 | G31: -2318617.5
E32: 44291 | G32: -5552830.9
E33: 44307 | G33: -12517321
E34: 44319 | G34: 13015621
E35: 44335 | G35: -5963595.6
E36: 44344 | G36: 7104623.5
E37: 44361 | G37: 182186.73
E38: 44375 | G38: -2424572.2
E39: 44405 | G39: -1696295.9
E40: 44468 | G40: -537849.91
E41: 44475 | G41: -1985907.4
E42: 44483 | G42: -2275518.9
... E45: 44558 | G45: 19887002
C47: Net assets | E47: =+E8 -> #REF! | G47: 53333151 | I47: =+SUMIF($G$21:$G$46,"<0",$G$21:$G$46)+G30+G34+G36+G37 -> -46627878 | J47: check figure-Contributions
I48: =+SUMIF($G$21:$G$46,">0",$G$21:$G$46)-G30-G34-G36-G37 -> 19887002 | J48: check figure-Distributions
C49: Total return | G49: =+XIRR(G21:G47,E21:E47,0.1) -> #REF!
C58: Net investment loss ratio | E58: =E10 -> -0.018002424
C60: Operating expenses ratio | E60: =E12 -> 0.018908929
C62: Internal rate of return | E62: =+E15 -> #REF!

Sheet EETF Sidecar I-A Hypo
B4: Financial Highlights EETF Sidecar I-A
E8: =#REF! -> #REF!
C14: Internal rate of return
C15: Internal rate of return after incentive allocation | E15: =G48 -> #REF!
C16: ROI | E16: =-(G46+I47)/I46 -> #REF!
C19: 1
C21: Contributions 2020 | E21: 43857 | G21: -4082817.7
E22: 43985 | G22: -4371454.5
E23: 44076 | G23: -3958564.9
E24: 44117 | G24: -4976161
E25: 44141 | G25: -4443814.1
E26: 44148 | G26: -2317985.9
E27: 44187 | G27: -1954659.1
C28: Contributions 2021 | E28: 44203 | G28: -8778291.7
E29: 44217 | G29: -1223795.9
E30: 44250 | G30: 4272371.4
E31: 44265 | G31: =-2252124.74360582-327074.700190716 -> -2579199.4
E32: 44291 | G32: -6226211.2
E33: 44307 | G33: -13927597
E34: 44319 | G34: 14547821
E35: 44335 | G35: -6629243.6
E36: 44344 | G36: =8538694.07299078-597714.174819936 -> 7940979.9
E37: 44361 | G37: =-213231.101774318+416864.853389408 -> 203633.75
E38: 44375 | G38: -2219396.2
E39: 44475 | G39: -2122900.7
E40: 44483 | G40: -418147.1
E41: 44505 | G41: -2052526.8
E42: 44551 | G42: -1190111
C43: Distributions 2021 | E43: 44558 | G43: 20746336
C44: Contributions 2022 | E44: 44635 | G44: -2283726.5
C46: Net assets | E46: =+E8 -> #REF! | G46: =#REF! -> #REF! | I46: =+SUMIF($G$21:$G$45,"<0",$G$21:$G$45)+G30+G34+G36+G37 -> -48791799 | J46: check figure-Contributions
I47: =+SUMIF($G$21:$G$45,">0",$G$21:$G$45)-G30-G34-G36-G37 -> 20746336 | J47: check figure-Distributions
C48: Total return | G48: =+XIRR(G21:G46,E21:E46,0.1) -> #REF!
G49: =G46-#REF! -> #REF! | I49: =I46-#REF! -> #REF!
I50: =I47-#REF! -> #REF!

Sheet EETF Sidecar I-B hypo
B4: Financial Highlights EETF Sidecar I-B
E8: =#REF! -> #REF!
G9: INPUT CELLS
C10: Net investment income/loss | E10: =G10*C19/(J30) -> -0.016114942 | G10: -425383
C12: Operating expenses | E12: =G12*C19/(J30) -> 0.016926403 | G12: 446803
C14: Internal rate of return
C15: Internal rate of return after incentive allocation | E15: =G47 -> #REF!
C16: ROI | E16: =-(G45+I46)/I45 -> 1.6542476
C19: 1
C21: Contributions 2020 | E21: 43857 | G21: -4880810.3
E22: 43985 | G22: -5225861.5
E23: 44076 | G23: -4732272.1
E24: 44117 | G24: -5948758.7 | J24: INPUT CELLS
E25: 44141 | G25: -5312363.9 | J25: 2474504 | K25: PY NAV
E26: 44148 | G26: -2771039.5 | J26: 13084702 | K26: 3/31 NAV
E27: 44187 | G27: -2336700 | J27: 23875861 | K27: 6/30 NAV
C28: Contributions 2021 | E28: 44203 | G28: -10494021 | J28: 25377815 | K28: 9/30 NAV
E29: 44217 | G29: -1462988.6 | J29: =G45 -> 67171152 | K29: CY NAV
E30: 44250 | G30: 5107412.5 | J30: =SUM(J25:J29)/5 -> 26396807 | K30: AVG NAV
E31: 44265 | G31: -3083307.6
E32: 44291 | G32: -7443133
E33: 44307 | G33: -16649766
E34: 44319 | G34: 17391213
E35: 44335 | G35: -7924938.6
E36: 44344 | G36: 9493055.7
E37: 44361 | G37: 243434.26
E38: 44375 | G38: -2653180.3
E39: 44475 | G39: -2537824.7
E40: 44483 | G40: -499874.56
E41: 44505 | G41: -2453305.3
E42: 44551 | G42: -1422719.9
E43: 44558 | G43: 24801293
C45: Net assets | E45: =+E8 -> #REF! | G45: 67171152 | I45: =+SUMIF($G$21:$G$44,"<0",$G$21:$G$44)+G30+G34+G36+G37 -> -55597751 | J45: check figure-Contributions
I46: =+SUMIF($G$21:$G$44,">0",$G$21:$G$44)-G30-G34-G36-G37 -> 24801293 | J46: check figure-Distributions
C47: Total return | G47: =+XIRR(G21:G45,E21:E45,0.1) -> #REF!
C56: Net investment loss ratio | E56: =E10 -> -0.016114942
C58: Operating expenses ratio | E58: =E12 -> 0.016926403
C60: Internal rate of return | E60: =+E15 -> #REF!

Sheet EETF Sidecar I-C hypo
B4: Financial Highlights EETF Sidecar I-C
E8: =#REF! -> #REF!
G9: INPUT CELLS
C10: Net investment income/loss | E10: =G10*C19/(J30) -> -0.018644895 | G10: -425383
C12: Operating expenses | E12: =G12*C19/(J30) -> 0.019583752 | G12: 446803
C14: Internal rate of return
C15: Internal rate of return after incentive allocation | E15: =G47 -> #REF!
C16: ROI | E16: =-(G45+I46)/I45 -> 1.5354541
C19: 1
C21: Contributions 2020 | E21: 43857 | G21: -3729663.3
E22: 43985 | G22: -3993333.7
E23: 44076 | G23: -3616158.1
E24: 44117 | G24: -4545734.4 | J24: INPUT CELLS
E25: 44141 | G25: -4059434.4 | J25: 2474504 | K25: PY NAV
E26: 44148 | G26: -2117485.4 | J26: 13084702 | K26: 3/31 NAV
E27: 44187 | G27: -1785585.6 | J27: 23875861 | K27: 6/30 NAV
C28: Contributions 2021 | E28: 44203 | G28: -8018989.5 | J28: 25377815 | K28: 9/30 NAV
E29: 44217 | G29: -1117940.4 | J29: =G45 -> 49262040 | K29: CY NAV
E30: 44250 | G30: 3902821.1 | J30: =SUM(J25:J29)/5 -> 22814984 | K30: AVG NAV
E31: 44265 | G31: -2356104.6
E32: 44291 | G32: -5687658.2
E33: 44307 | G33: -12722892
E34: 44319 | G34: 13289467
E35: 44335 | G35: -6055829.2
E36: 44344 | G36: 7254103.3
E37: 44361 | G37: 186019.9
E38: 44375 | G38: -2027423.5
E39: 44475 | G39: -1939274.6
E40: 44483 | G40: -381978.34
E41: 44505 | G41: -1894167.9
E42: 44551 | G42: -1087169.1
E43: 44558 | G43: 16001533
C45: Net assets | E45: =+E8 -> #REF! | G45: 49262040 | I45: =+SUMIF($G$21:$G$44,"<0",$G$21:$G$44)+G30+G34+G36+G37 -> -42504411 | J45: check figure-Contributions
I46: =+SUMIF($G$21:$G$44,">0",$G$21:$G$44)-G30-G34-G36-G37 -> 16001533 | J46: check figure-Distributions
C47: Total return | G47: =+XIRR(G21:G45,E21:E45,0.1) -> #REF!
C56: Net investment loss ratio | E56: =E10 -> -0.018644895
C58: Operating expenses ratio | E58: =E12 -> 0.019583752
C60: Internal rate of return | E60: =+E15 -> #REF!
