Workbook

Sheet DEI Questionnaire
A1: Diversity and Inclusion Questionnaire Responses
A3: Community Involvement
B4: Describe your firm’s practices and incentives related to charitable giving, community involvement, and volunteer programs | C4: We believe that to whom much is given, much is expected. We express this philosophy by giving back in the form of donating through our Charitable Contribution & Sponsorship Program, which is a dollar for dollar matching program and volunteering with organizations via our EnCap Engage program. Many of our employees are also involved in charities beyond our corporate programs.
A5: DEI
B6: Describe any DEI initiatives. | C6: We believe that diversity and inclusion can contribute to improved performance and try to foster an environment in which diversity can flourish. We recognize that genuine value is added to an organization when thoughts are shared among individuals with varying perspectives in an effort to generate better ideas. It is a responsibility shared by eveyone at EnCap to foster an inclusive and respectful work environment. We recently began offering DEI training to EnCap employees.
B7: Does the firm have a policy that addresses harassment, discrimination, and/or workplace violence? Are there procedures in place for reporting and investigating cases of policy violations? | C7: Yes. Please see Sections I-D, III-A, III-C of the Employee Handbook provided.
B8: Does firm conduct gender & ethnicity pay gap studies? What policies are in play to ensure equal pay? | C8: Per section I-D of the EnCap Employee Handbook: EnCap is an equal opportunity employer and maintains a policy of non-discrimination with respect to all Employees and applicants for employment. All work-related decisions, such as recruitment, hiring, training, promotion, transfer, layoff, recall, compensation and benefits, discipline, and termination of employment, and educational, recreational, and social programs, are made and administered without regard to race, color, sex (including pregnancy), religion, national origin, citizenship status, age, physical or mental disability of an otherwise qualified individual, genetic information, membership or application for membership in a uniformed service, veteran status, protected activity as defined by applicable law, or other category or characteristic protected by federal, state, or local law or ordinance. Work-related decisions, subject to the legitimate business requirements of EnCap, are based solely on an individual’s qualifications, merit, and performance. No person is authorized to act in a manner contrary to this commitment to equal employment opportunity.
B9: Have there been any claims of sexual or general harassment, misconduct, or discrimination against any current or former Firm employees (while employed by the Firm) within the last 5 years? | C9: We have had one harassment complaint over the last 5 years. This incident was investigated by outside counsel and as a result the employee went through sensitivity training, is no longer in a supervisory role over the complainant and was moved to a different office as to not be in close proximity. The complainant was satisfied with this outcome and there have been no further issues.
A10: Employee Wellness
B11: Does the firm have a family leave or parental leave policy? Please provide the details. | C11: Please see Section IV-L of the EnCap Employee Handbook.
B12: Employee Wellbeing - Does the firm offer benefits that are family friendly and promote work-life balance (such as child care)? | C12: EnCap offers a range of benefits aimed at supporting our employees, including a retirement savings program, fitness program, flexible spending accounts, flexible work arrangements, and parental leave to care for a newborn child or placement of child for adoption or foster care for up to 16 work-weeks.
B13: Does the Firm have a formal mentorship, sponsorship or employer affinity program for women and/or minorities? | C13: Not currently.
A14: Engagement
B15: Does the firm engage with portfolio companies on ESG topics? What is the approach to engagement? If relevant, please provide an Engagement Report. | C15: Yes, ESG is discussed quarterly with portfolio companies at board meetings. Please reference our annual sustainability report for more information.
B16: Does the firm encourage portfolio companies to adopt ESG standards? Does the firm track ESG metrics for all portfolio companies? If yes, does the firm report these metrics to clients? What goals are in place to further ESG at the companies you invest in and how do you plan to measure progress? | C16: Please reference our sustainability report for detailed information on ESG at our portfolio companies.
A17: Firm Structure
B18: Does the firm have a Chief Diversity Officer (or Equivalent)? | C18: Not currently.
B19: Describe whistleblower mechanism and policies for non-retaliation | C19: Please see section I-D of the EnCap Employee Handbook.
B20: Are employees trained on firm policies? How are policies enforced and employees educated on policies? | C20: EnCap's Employee Handbook and Compliance Manual are updated biannually and employees provide signed acknowledgments of those changes.

Sheet RTP Data Matrix
A1: Retention, Turnover, and Promotion Matrix
A2: Retention, Turnover, and Promotion by Ethnicity, Gender, Veteran Status
C4: White | E4: Black or African American | G4: Hispanic or Latino | I4: Asian | K4: Hawaiian or Pacific Islander | M4: American Indian or Alaskan Native | O4: Two or More Races | Q4: Other Ethnic Group | S4: Veteran Status
C5: Female | D5: Male | E5: Female | F5: Male | G5: Female | H5: Male | I5: Female | J5: Male | K5: Female | L5: Male | M5: Female | N5: Male | O5: Female | P5: Male | Q5: Female | R5: Male | S5: Female | T5: Male
A6: Employees at Beginning of Year | C6: 13 | D6: 38 | E6: 2 | G6: 3 | H6: 1 | I6: 3 | J6: 2 | S6: 1 | T6: 2
B7: - Employees Terminated / Resigned | D7: 1 | E7: 1 | G7: 1 | I7: 1
B8: Employees Retained | C8: =C6-C7 -> 13 | D8: =D6-D7 -> 37 | E8: =E6-E7 -> 1 | F8: =F6-F7 -> 0 | G8: =G6-G7 -> 2 | H8: =H6-H7 -> 1 | I8: =I6-I7 -> 2 | J8: =J6-J7 -> 2 | ... T8: =T6-T7 -> 2
B9: Employees Promoted* | C9: 2 | D9: 5
B10: + New Hires | C10: 3 | D10: 3 | F10: 1 | J10: 1
A11: Employees at End of Year | C11: =C6-C7+C10 -> 16 | D11: =D6-D7+D10 -> 40 | E11: =E6-E7+E10 -> 1 | F11: =F6-F7+F10 -> 1 | G11: =G6-G7+G10 -> 2 | H11: =H6-H7+H10 -> 1 | I11: =I6-I7+I10 -> 2 | J11: =J6-J7+J10 -> 3 | ... T11: =T6-T7+T10 -> 2
A13: % Employees Were Terminated / Resigned | C13: =IFERROR(C7/C6,0) -> 0 | D13: =IFERROR(D7/D6,0) -> 0.026315789 | E13: =IFERROR(E7/E6,0) -> 0.5 | F13: =IFERROR(F7/F6,0) -> 0 | G13: =IFERROR(G7/G6,0) -> 0.33333333 | H13: =IFERROR(H7/H6,0) -> 0 | I13: =IFERROR(I7/I6,0) -> 0.33333333 | J13: =IFERROR(J7/J6,0) -> 0 | ... T13: =IFERROR(T7/T6,0) -> 0
A14: % Employees Retained | C14: =IFERROR(C8/C6,0) -> 1 | D14: =IFERROR(D8/D6,0) -> 0.97368421 | E14: =IFERROR(E8/E6,0) -> 0.5 | F14: =IFERROR(F8/F6,0) -> 0 | G14: =IFERROR(G8/G6,0) -> 0.66666667 | H14: =IFERROR(H8/H6,0) -> 1 | I14: =IFERROR(I8/I6,0) -> 0.66666667 | J14: =IFERROR(J8/J6,0) -> 1 | ... T14: =IFERROR(T8/T6,0) -> 1
A15: % Employees Were Promoted | C15: =IFERROR(C9/C6,0) -> 0.15384615 | D15: =IFERROR(D9/D6,0) -> 0.13157895 | E15: =IFERROR(E9/E6,0) -> 0 | F15: =IFERROR(F9/F6,0) -> 0 | G15: =IFERROR(G9/G6,0) -> 0 | H15: =IFERROR(H9/H6,0) -> 0 | I15: =IFERROR(I9/I6,0) -> 0 | J15: =IFERROR(J9/J6,0) -> 0 | ... T15: =IFERROR(T9/T6,0) -> 0
A16: Net Employment Creation | C16: =C10-C7 -> 3 | D16: =D10-D7 -> 2 | E16: =E10-E7 -> -1 | F16: =F10-F7 -> 1 | G16: =G10-G7 -> -1 | H16: =H10-H7 -> 0 | I16: =I10-I7 -> -1 | J16: =J10-J7 -> 1 | ... T16: =T10-T7 -> 0

Sheet Ownership Data Matrix
A1: Ownership Data Matrix
A2: Owner Breakdown by Ethnicity, Gender, Veteran Status
B4: White | D4: Black or African American | F4: Hispanic or Latino | H4: Asian | J4: Hawaiian or Pacific Islander | L4: American Indian or Alaskan Native | N4: Two or More Races | P4: Other Ethnic Group
B5: Female | C5: Male | D5: Female | E5: Male | F5: Female | G5: Male | H5: Female | I5: Male | J5: Female | K5: Male | L5: Female | M5: Male | N5: Female | O5: Male | P5: Female | Q5: Male
A6: Firm Owners # | B6: 1 | C6: 12
A7: % of Firm Owners | B7: 0.08 | C7: 0.92
A8: EnCap Transition Fund GP is owned 55% by EnCap and 45% by Transition Fund management team.
A9: The diversity break down for the Transition Fund GP is 25% Female and 75% male.
A10: EnCap has 13 Partners and not one Partner owns more than 20%
B12: Veteran Status
B13: Female | C13: Male
A14: Firm Owners # | B14: 1 | C14: 2
A15: % of Firm Owners | B15: 0.08 | C15: 0.15

Sheet Employee Data Matrix
A1: Employee Diversity Matrix
A2: Employee Breakdown by Employee Type, Ethnicity, Gender, Veteran Status
D4: White | F4: Black or African American | H4: Hispanic or Latino | J4: Asian | L4: Hawaiian or Pacific Islander | N4: American Indian or Alaskan Native | P4: Two or More Races | R4: Other Ethnic Group | T4: Veteran Status
D5: Female | E5: Male | F5: Female | G5: Male | H5: Female | I5: Male | J5: Female | K5: Male | L5: Female | M5: Male | N5: Female | O5: Male | P5: Female | Q5: Male | R5: Female | S5: Male | T5: Female | U5: Male
A6: Full Time
B7: Leadership
C8: Board of Directors | D8: 0 | E8: 0
C9: Partners | D9: 1 | E9: 12 | T9: 1 | U9: 2
C10: Executives | D10: 1 | E10: 3 | J10: 1 | K10: 1
B11: ="Total "&B7 -> Total Leadership | D11: =SUM(D8:D10) -> 2 | E11: =SUM(E8:E10) -> 15 | F11: =SUM(F8:F10) -> 0 | G11: =SUM(G8:G10) -> 0 | H11: =SUM(H8:H10) -> 0 | I11: =SUM(I8:I10) -> 0 | J11: =SUM(J8:J10) -> 1 | K11: =SUM(K8:K10) -> 1 | ... U11: =SUM(U8:U10) -> 2
B13: Investment Team
C14: Portfolio Managers | D14: 1 | E14: 11
C15: Analysts | D15: 0 | E15: 5 | G15: 1 | K15: 1
B16: ="Total "&B13 -> Total Investment Team | D16: =SUM(D14:D15) -> 1 | E16: =SUM(E14:E15) -> 16 | F16: =SUM(F14:F15) -> 0 | G16: =SUM(G14:G15) -> 1 | H16: =SUM(H14:H15) -> 0 | I16: =SUM(I14:I15) -> 0 | J16: =SUM(J14:J15) -> 0 | K16: =SUM(K14:K15) -> 1 | ... U16: =SUM(U14:U15) -> 0
B18: Operations & Administrative Staff
C19: Operations Leadership | D19: 0 | E19: 0
C20: Marketing/Investor Relations | D20: 1 | E20: 1
C21: Finance/Accounting | D21: 4 | E21: 7 | J21: 1
C22: Legal/Compliance | D22: 0 | E22: 0 | F22: 1
C23: Administrative | D23: 7 | E23: 0 | H23: 2 | I23: 1
C24: Other Operations | D24: 1 | E24: 1 | K24: 1
B25: ="Total "&B18 -> Total Operations & Administrative Staff | D25: =SUM(D19:D24) -> 13 | E25: =SUM(E19:E24) -> 9 | F25: =SUM(F19:F24) -> 1 | G25: =SUM(G19:G24) -> 0 | H25: =SUM(H19:H24) -> 2 | I25: =SUM(I19:I24) -> 1 | J25: =SUM(J19:J24) -> 1 | K25: =SUM(K19:K24) -> 1 | ... U25: =SUM(U19:U24) -> 0
A27: Part Time
C28: Interns | D28: 0 | E28: 0
C29: Other Part Time | D29: 0 | E29: 0
D30: =SUM(D28:D29) -> 0 | E30: =SUM(E28:E29) -> 0 | F30: =SUM(F28:F29) -> 0 | G30: =SUM(G28:G29) -> 0 | H30: =SUM(H28:H29) -> 0 | I30: =SUM(I28:I29) -> 0 | J30: =SUM(J28:J29) -> 0 | K30: =SUM(K28:K29) -> 0 | ... U30: =SUM(U28:U29) -> 0
A33: Total Full Time | D33: =SUM(D11,D16,D25) -> 16 | E33: =SUM(E11,E16,E25) -> 40 | F33: =SUM(F11,F16,F25) -> 1 | G33: =SUM(G11,G16,G25) -> 1 | H33: =SUM(H11,H16,H25) -> 2 | I33: =SUM(I11,I16,I25) -> 1 | J33: =SUM(J11,J16,J25) -> 2 | K33: =SUM(K11,K16,K25) -> 3 | ... U33: =SUM(U11,U16,U25) -> 2
A34: Total Part Time | D34: =D30 -> 0 | E34: =E30 -> 0 | F34: =F30 -> 0 | G34: =G30 -> 0 | H34: =H30 -> 0 | I34: =I30 -> 0 | J34: =J30 -> 0 | K34: =K30 -> 0 | ... U34: =U30 -> 0
A35: All Employees | D35: =SUM(D33:D34) -> 16 | E35: =SUM(E33:E34) -> 40 | F35: =SUM(F33:F34) -> 1 | G35: =SUM(G33:G34) -> 1 | H35: =SUM(H33:H34) -> 2 | I35: =SUM(I33:I34) -> 1 | J35: =SUM(J33:J34) -> 2 | K35: =SUM(K33:K34) -> 3 | ... U35: =SUM(U33:U34) -> 2

Sheet Percentage Matrix
A1: Employee Diversity Matrix
A2: Employee Breakdown by Employee Type, Ethnicity, Gender, Veteran Status, Disability Status, and LGBTQ+ Identification
D4: White | F4: Black or African American | H4: Hispanic or Latino | J4: Asian | L4: Hawaiian or Pacific Islander | N4: American Indian or Alaskan Native | P4: Two or More Races | R4: Other Ethnic Group
D5: Female | E5: Male | F5: Female | G5: Male | H5: Female | I5: Male | J5: Female | K5: Male | L5: Female | M5: Male | N5: Female | O5: Male | P5: Female | Q5: Male | R5: Female | S5: Male
A6: Full Time | D6: =IFERROR('Employee Data Matrix'!D33/SUM('Employee Data Matrix'!$D$33:$S$33),0) -> 0.24242424 | E6: =IFERROR('Employee Data Matrix'!E33/SUM('Employee Data Matrix'!$D$33:$S$33),0) -> 0.60606061 | F6: =IFERROR('Employee Data Matrix'!F33/SUM('Employee Data Matrix'!$D$33:$S$33),0) -> 0.015151515 | G6: =IFERROR('Employee Data Matrix'!G33/SUM('Employee Data Matrix'!$D$33:$S$33),0) -> 0.015151515 | H6: =IFERROR('Employee Data Matrix'!H33/SUM('Employee Data Matrix'!$D$33:$S$33),0) -> 0.03030303 | I6: =IFERROR('Employee Data Matrix'!I33/SUM('Employee Data Matrix'!$D$33:$S$33),0) -> 0.015151515 | J6: =IFERROR('Employee Data Matrix'!J33/SUM('Employee Data Matrix'!$D$33:$S$33),0) -> 0.03030303 | K6: =IFERROR('Employee Data Matrix'!K33/SUM('Employee Data Matrix'!$D$33:$S$33),0) -> 0.045454545 | ... S6: =IFERROR('Employee Data Matrix'!S33/SUM('Employee Data Matrix'!$D$33:$S$33),0) -> 0
B7: Leadership | D7: =IFERROR('Employee Data Matrix'!D11/SUM('Employee Data Matrix'!$D$33:$S$33),0) -> 0.03030303 | E7: =IFERROR('Employee Data Matrix'!E11/SUM('Employee Data Matrix'!$D$33:$S$33),0) -> 0.22727273 | F7: =IFERROR('Employee Data Matrix'!F11/SUM('Employee Data Matrix'!$D$33:$S$33),0) -> 0 | G7: =IFERROR('Employee Data Matrix'!G11/SUM('Employee Data Matrix'!$D$33:$S$33),0) -> 0 | H7: =IFERROR('Employee Data Matrix'!H11/SUM('Employee Data Matrix'!$D$33:$S$33),0) -> 0 | I7: =IFERROR('Employee Data Matrix'!I11/SUM('Employee Data Matrix'!$D$33:$S$33),0) -> 0 | J7: =IFERROR('Employee Data Matrix'!J11/SUM('Employee Data Matrix'!$D$33:$S$33),0) -> 0.015151515 | K7: =IFERROR('Employee Data Matrix'!K11/SUM('Employee Data Matrix'!$D$33:$S$33),0) -> 0.015151515 | ... S7: =IFERROR('Employee Data Matrix'!S11/SUM('Employee Data Matrix'!$D$33:$S$33),0) -> 0
B8: Investment Team | D8: =IFERROR('Employee Data Matrix'!D16/SUM('Employee Data Matrix'!$D$33:$S$33),0) -> 0.015151515 | E8: =IFERROR('Employee Data Matrix'!E16/SUM('Employee Data Matrix'!$D$33:$S$33),0) -> 0.24242424 | F8: =IFERROR('Employee Data Matrix'!F16/SUM('Employee Data Matrix'!$D$33:$S$33),0) -> 0 | G8: =IFERROR('Employee Data Matrix'!G16/SUM('Employee Data Matrix'!$D$33:$S$33),0) -> 0.015151515 | H8: =IFERROR('Employee Data Matrix'!H16/SUM('Employee Data Matrix'!$D$33:$S$33),0) -> 0 | I8: =IFERROR('Employee Data Matrix'!I16/SUM('Employee Data Matrix'!$D$33:$S$33),0) -> 0 | J8: =IFERROR('Employee Data Matrix'!J16/SUM('Employee Data Matrix'!$D$33:$S$33),0) -> 0 | K8: =IFERROR('Employee Data Matrix'!K16/SUM('Employee Data Matrix'!$D$33:$S$33),0) -> 0.015151515 | ... S8: =IFERROR('Employee Data Matrix'!S16/SUM('Employee Data Matrix'!$D$33:$S$33),0) -> 0
B9: Operations & Administrative Staff | D9: =IFERROR('Employee Data Matrix'!D25/SUM('Employee Data Matrix'!$D$33:$S$33),0) -> 0.1969697 | E9: =IFERROR('Employee Data Matrix'!E25/SUM('Employee Data Matrix'!$D$33:$S$33),0) -> 0.13636364 | F9: =IFERROR('Employee Data Matrix'!F25/SUM('Employee Data Matrix'!$D$33:$S$33),0) -> 0.015151515 | G9: =IFERROR('Employee Data Matrix'!G25/SUM('Employee Data Matrix'!$D$33:$S$33),0) -> 0 | H9: =IFERROR('Employee Data Matrix'!H25/SUM('Employee Data Matrix'!$D$33:$S$33),0) -> 0.03030303 | I9: =IFERROR('Employee Data Matrix'!I25/SUM('Employee Data Matrix'!$D$33:$S$33),0) -> 0.015151515 | J9: =IFERROR('Employee Data Matrix'!J25/SUM('Employee Data Matrix'!$D$33:$S$33),0) -> 0.015151515 | K9: =IFERROR('Employee Data Matrix'!K25/SUM('Employee Data Matrix'!$D$33:$S$33),0) -> 0.015151515 | ... S9: =IFERROR('Employee Data Matrix'!S25/SUM('Employee Data Matrix'!$D$33:$S$33),0) -> 0
A10: Part Time | D10: =IFERROR('Employee Data Matrix'!D34/SUM('Employee Data Matrix'!$D$34:$S$34),0) -> 0 | E10: =IFERROR('Employee Data Matrix'!E34/SUM('Employee Data Matrix'!$D$34:$S$34),0) -> 0 | F10: =IFERROR('Employee Data Matrix'!F34/SUM('Employee Data Matrix'!$D$34:$S$34),0) -> 0 | G10: =IFERROR('Employee Data Matrix'!G34/SUM('Employee Data Matrix'!$D$34:$S$34),0) -> 0 | H10: =IFERROR('Employee Data Matrix'!H34/SUM('Employee Data Matrix'!$D$34:$S$34),0) -> 0 | I10: =IFERROR('Employee Data Matrix'!I34/SUM('Employee Data Matrix'!$D$34:$S$34),0) -> 0 | J10: =IFERROR('Employee Data Matrix'!J34/SUM('Employee Data Matrix'!$D$34:$S$34),0) -> 0 | K10: =IFERROR('Employee Data Matrix'!K34/SUM('Employee Data Matrix'!$D$34:$S$34),0) -> 0 | ... S10: =IFERROR('Employee Data Matrix'!S34/SUM('Employee Data Matrix'!$D$34:$S$34),0) -> 0
A11: All Employees | D11: =IFERROR('Employee Data Matrix'!D35/SUM('Employee Data Matrix'!$D$35:$S$35),0) -> 0.24242424 | E11: =IFERROR('Employee Data Matrix'!E35/SUM('Employee Data Matrix'!$D$35:$S$35),0) -> 0.60606061 | F11: =IFERROR('Employee Data Matrix'!F35/SUM('Employee Data Matrix'!$D$35:$S$35),0) -> 0.015151515 | G11: =IFERROR('Employee Data Matrix'!G35/SUM('Employee Data Matrix'!$D$35:$S$35),0) -> 0.015151515 | H11: =IFERROR('Employee Data Matrix'!H35/SUM('Employee Data Matrix'!$D$35:$S$35),0) -> 0.03030303 | I11: =IFERROR('Employee Data Matrix'!I35/SUM('Employee Data Matrix'!$D$35:$S$35),0) -> 0.015151515 | J11: =IFERROR('Employee Data Matrix'!J35/SUM('Employee Data Matrix'!$D$35:$S$35),0) -> 0.03030303 | K11: =IFERROR('Employee Data Matrix'!K35/SUM('Employee Data Matrix'!$D$35:$S$35),0) -> 0.045454545 | ... S11: =IFERROR('Employee Data Matrix'!S35/SUM('Employee Data Matrix'!$D$35:$S$35),0) -> 0
D13: Veteran Status
D14: Female | E14: Male
A15: Full Time | D15: =IFERROR('Employee Data Matrix'!T33/SUM('Employee Data Matrix'!$D$33:$S$33),0) -> 0.015151515 | E15: =IFERROR('Employee Data Matrix'!U33/SUM('Employee Data Matrix'!$D$33:$S$33),0) -> 0.03030303
B16: Leadership | D16: =IFERROR('Employee Data Matrix'!T11/SUM('Employee Data Matrix'!$D$33:$S$33),0) -> 0.015151515 | E16: =IFERROR('Employee Data Matrix'!U11/SUM('Employee Data Matrix'!$D$33:$S$33),0) -> 0.03030303
B17: Investment Team | D17: =IFERROR('Employee Data Matrix'!T16/SUM('Employee Data Matrix'!$D$33:$S$33),0) -> 0 | E17: =IFERROR('Employee Data Matrix'!U16/SUM('Employee Data Matrix'!$D$33:$S$33),0) -> 0
B18: Operations & Administrative Staff | D18: =IFERROR('Employee Data Matrix'!T25/SUM('Employee Data Matrix'!$D$33:$S$33),0) -> 0 | E18: =IFERROR('Employee Data Matrix'!U25/SUM('Employee Data Matrix'!$D$33:$S$33),0) -> 0
A19: Part Time | D19: =IFERROR('Employee Data Matrix'!T34/SUM('Employee Data Matrix'!$D$34:$S$34),0) -> 0 | E19: =IFERROR('Employee Data Matrix'!U34/SUM('Employee Data Matrix'!$D$34:$S$34),0) -> 0
A20: All Employees | D20: =IFERROR('Employee Data Matrix'!T35/SUM('Employee Data Matrix'!$D$35:$S$35),0) -> 0.015151515 | E20: =IFERROR('Employee Data Matrix'!U35/SUM('Employee Data Matrix'!$D$35:$S$35),0) -> 0.03030303

Sheet Key
A1: RACE/ETHNIC CATEGORY DESCRIPTIONS
A3: UNITED STATES
A4: White | B4: A person having origins in any of the original peoples of Europe, the Middle East, or North Africa
A5: Black or African American | B5: A person having origins in any of the black racial groups of Africa
A6: Hispanic or Latino | B6: A person of Cuban, Mexican, Puerto Rican, South or Central American, or other Spanish culture or origin, regardless of race
A7: Asian | B7: A person having origins in any of the original peoples of the Far East, Southeast Asia, or the Indian subcontinent including, for example, Cambodia, China, India, Japan, Korea, Malaysia, Pakistan, the Philippine Islands, Thailand, and Vietnam
A8: Hawaiian or Pacific Islander | B8: A person having origins in any of the original peoples of Hawaii, Guam, Samoa, or other Pacific Islands
A9: American Indian or Alaskan Native | B9: A person having origins in any of the original peoples of North and South America (including Central America), and who maintains tribal affiliation or community attachment
A10: Two or More Races | B10: A person having origins that include two or more of the categories above
A11: Other Ethnic Group | B11: A person of any ethnic group not categorized by the above
A13: CANADA
A14: White | B14: A person having origins in any of the original peoples of Europe, the Middle East, or North Africa
A15: Black | B15: A person having origins of black African decent, Caribbean, or African American
A16: Latin American | B16: A person having origins of Argentina, Bolivia, Brazil, Chile, Colombia, Costa Rica, Cuba, Dominican Republic, Ecuador, El Salvador, Guatemala, Haiti, Honduras, Mexico, Nicaragua, Panama, Paraguay, Peru, Uruguay, and Venezuela. Puerto Rico, the French West Indies, and other islands of the West Indies may also be considered part of Latin America
A17: Asian | B17: A person having origins in any of the original peoples of the Far East, Southeast Asia, or the Indian subcontinent including, for example, Cambodia, China, India, Japan, Korea, Malaysia, Pakistan, the Philippine Islands, Thailand, and Vietnam
A18: Arab/West Asian | B18: A person having origins of the Levant, Mesopotamia, Anatolia, Iran, the Armenian Highlands, the South Caucasus, the Arabian peninsula as well as the Sinai Peninsula
A19: Aboriginal | B19: A person who is North American Native Indians (Status or Non-Status), Inuit or Métis. These are three separate peoples with unique heritages, languages, cultural practices and spiritual beliefs
A20: Two or More Races | B20: Relating to people of many races
A21: Other Ethnic Group | B21: A person of any ethnic group not categorized by the above
A23: UNITED KINGDOM
A24: White | B24: A person having Scottish, English, Welsh, Northern Irish, British, Irish Gypsy Traveler, or any other White background
A25: Mixed/Multiple | B25: A person having two or more backgrounds including White and Black Caribbean, White and Black African or any other Mixed / Multiple ethnic background
A26: Asian/Asian British | B26: A person having Indian, Pakistani, Bangladeshi, Chinese or other Asian origins
A27: Black/African/Caribbean/Black British | B27: A person having Caribbean, African or any other black background
A28: Middle Eastern | B28: A person having a Middle Eastern or Arab background
A29: Other Ethnic Group | B29: A person of any ethnic group not categorized by the above
A31: AUSTRALIA
A32: Australian | B32: A person with an Australian background
A33: Anglo Celtic | B33: A person with a British or Irish (English, Scottish, Welsh or Irish) background
A34: European | B34: A person with a European background other than Anglo-Celtic – including North-West European (e.g. German, French, Dutch) or Southern or Eastern European (e.g. Italian, Greek, Polish)
A35: Asian | B35: A person with a South East Asian (e.g. Vietnamese, Malaysian), North-East Asian (e.g. Chinese, Japanese, Korean), or Southern or Central Asian (e.g. Indian, Sri Lankan, Afghani) background
A36: Middle Eastern | B36: A person with a background from North Africa (e.g. Egyptian, Turkish) or from countries such as Bahrain, Cyprus, Iran, Iraq, Israel, Jordan, Kuwait, Lebanon, Syria, Saudi
A37: African | B37: A person with a background from African region other than North Africa
A38: The Americas | B38: A person with a North America, Central America, South America and the Caribbean
A39: Indigenous | B39: A person with an Aboriginal or Torres Strait Islander background
A40: Two or More Races | B40: A person having two or more backgrounds
A41: Other Ethnic Group | B41: A person of any ethnic group not categorized by the above
