Workbook

Sheet Fund Performance Summary
B1: Fund Performance Summary
B2: As of July 31, 2024
D5: Fund | E5: ='Share Price'!B3 -> QQQ | H5: ='Share Price'!B4 -> SPY | K5: ='Share Price'!B5 -> XOP
C6: Vintage | D6: Net IRR | E6: PME IRR (1) | F6: Direct Alpha (2) | G6: KS-PME (3) | H6: PME IRR (1) | I6: Direct Alpha (2) | J6: KS-PME (3) | K6: PME IRR (1) | L6: Direct Alpha (2) | M6: KS-PME (3) | N6: Average
B7: Fund VI | D7: ='Fund VI'!F3 -> 0.32462801 | E7: ='Fund VI'!F4 -> 0.32462801 | F7: ='Fund VI'!F5 -> 0.21730986 | G7: ='Fund VI'!F6 -> 1.7534771 | H7: ='Fund VI'!G4 -> 0.32462801 | I7: ='Fund VI'!G5 -> 0.30923399 | J7: ='Fund VI'!G6 -> 2.1415444 | K7: ='Fund VI'!H4 -> 0.32462801 | L7: ='Fund VI'!H5 -> 0.24109132 | M7: ='Fund VI'!H6 -> 1.9764966 | N7: =AVERAGE(F7,I7,L7) -> 0.25587839
B8: Fund VII | D8: ='Fund VII'!F3 -> 0.24436759 | E8: ='Fund VII'!F4 -> 0.24436759 | F8: ='Fund VII'!F5 -> 0.081310822 | G8: ='Fund VII'!F6 -> 1.2152952 | H8: ='Fund VII'!G4 -> 0.24436759 | I8: ='Fund VII'!G5 -> 0.15234383 | J8: ='Fund VII'!G6 -> 1.4137469 | K8: ='Fund VII'!H4 -> 0.24436759 | L8: ='Fund VII'!H5 -> 0.16453523 | M8: ='Fund VII'!H6 -> 1.6027353 | N8: =AVERAGE(F8,I8,L8) -> 0.13272996
B9: Fund VIII | D9: ='Fund VIII'!F3 -> 0.023659725 | E9: ='Fund VIII'!F4 -> 0.18215999 | F9: ='Fund VIII'!F5 -> -0.13168127 | G9: ='Fund VIII'!F6 -> 0.52329248 | H9: ='Fund VIII'!G4 -> 0.11802168 | I9: ='Fund VIII'!G5 -> -0.083309886 | J9: ='Fund VIII'!G6 -> 0.64747542 | K9: ='Fund VIII'!H4 -> -0.036528256 | L9: ='Fund VIII'!H5 -> 0.062880971 | M9: ='Fund VIII'!H6 -> 1.3859008 | N9: =AVERAGE(F9,I9,L9) -> -0.050703395
B10: Fund IX | D10: ='Fund IX'!F3 -> 0.15310315 | E10: ='Fund IX'!F4 -> 0.16759952 | F10: ='Fund IX'!F5 -> -0.011538256 | G10: ='Fund IX'!F6 -> 0.95536431 | H10: ='Fund IX'!G4 -> 0.097506179 | I10: ='Fund IX'!G5 -> 0.046227242 | J10: ='Fund IX'!G6 -> 1.2114416 | K10: ='Fund IX'!H4 -> NA | L10: ='Fund IX'!H5 -> 0.24801998 | M10: ='Fund IX'!H6 -> 2.6225664 | N10: =AVERAGE(F10,I10,L10) -> 0.094236323
B11: Fund X | D11: ='Fund X'!F3 -> 0.21164303 | E11: ='Fund X'!F4 -> 0.19019977 | F11: ='Fund X'!F5 -> 0.017402668 | G11: ='Fund X'!F6 -> 1.096657 | H11: ='Fund X'!G4 -> 0.11435677 | I11: ='Fund X'!G5 -> 0.082901131 | J11: ='Fund X'!G6 -> 1.5384708 | K11: ='Fund X'!H4 -> NA | L11: ='Fund X'!H5 -> 0.22493974 | M11: ='Fund X'!H6 -> 2.8489337 | N11: =AVERAGE(F11,I11,L11) -> 0.10841451
B12: Fund XI | D12: ='Fund XI'!F3 -> 0.31047553 | E12: ='Fund XI'!F4 -> 0.31047553 | F12: ='Fund XI'!F5 -> 0.11373373 | G12: ='Fund XI'!F6 -> 1.5037103 | H12: ='Fund XI'!G4 -> 0.31047553 | I12: ='Fund XI'!G5 -> 0.17190406 | J12: ='Fund XI'!G6 -> 1.7954824 | K12: ='Fund XI'!H4 -> 0.31047553 | L12: ='Fund XI'!H5 -> 0.20389054 | M12: ='Fund XI'!H6 -> 1.8900904 | N12: =AVERAGE(F12,I12,L12) -> 0.16317611
B14: Notes
B15: (1) PME IRR is the IRR of the hypothetical public portfolio built with cash flows of the fund. It should be compared directly to the fund IRR.
B16: (2) Direct Alpha calculates the annualized return earned by the fund manager in excess of the benchmark (i.e., alpha of the fund manager). A positive number shows that the fund cash flows outperformed the benchmark.
B17: (3) KS-PME measures final wealth created by the fund manager compared to what would have been achieved by investing in the benchmark.

Sheet Fund VI
B1: Inputs | E1: Outputs | K1: Cash Flow Summary
B2: Fund Name | C2: Fund VI | F2: PME Index 1 | G2: PME Index 2 | H2: PME Index 3 | L2: Actual | M2: PME Index 1 | N2: PME Index 2 | O2: PME Index 3
B3: End Date | C3: =B152 -> 44834 | E3: Actual IRR | F3: =IFERROR(XIRR(C11:C152, B11:B152, IF(SUM(C11:C152) > 0, 0.15, -0.15)), "NA") -> 0.32462801 | G3: =IFERROR(XIRR(C11:C152, B11:B152, IF(SUM(C11:C152) > 0, 0.15, -0.15)), "NA") -> 0.32462801 | H3: =IFERROR(XIRR(C11:C152, B11:B152, IF(SUM(C11:C152) > 0, 0.15, -0.15)), "NA") -> 0.32462801 | K3: Distribution | L3: =SUMIFS(C11:C152, D11:D152, K3) -> 2909973.4 | M3: =SUMIFS(H11:H152, D11:D152, K3) -> 13119010 | N3: =SUMIFS(N11:N152, D11:D152, K3) -> 7755987.6 | O3: =SUMIFS(T11:T152, D11:D152, K3) -> 1794538.2
B4: Index 1 | C4: ='Share Price'!B3 -> QQQ | E4: PME IRR | F4: =IFERROR(XIRR(J11:J152, B11:B152, IF(SUM(J11:J152) > 0, 0.15, -0.15)), "NA") -> 0.32462801 | G4: =IFERROR(XIRR(P11:P152, B11:B152, IF(SUM(P11:P152) > 0, 0.15, -0.15)), "NA") -> 0.32462801 | H4: =IFERROR(XIRR(V11:V152, B11:B152, IF(SUM(V11:V152) > 0, 0.15, -0.15)), "NA") -> 0.32462801 | K4: Contribution | L4: =SUMIFS(C11:C152, D11:D152, K4) -> -1187575 | M4: =SUMIFS(H11:H152, D11:D152, K4) -> -7481711.6 | N4: =SUMIFS(N11:N152, D11:D152, K4) -> -3621679.6 | O4: =SUMIFS(T11:T152, D11:D152, K4) -> -907938.94
B5: Index 2 | C5: ='Share Price'!B4 -> SPY | E5: Direct Alpha IRR | F5: =IFERROR(XIRR(H11:H152, B11:B152, IF(SUM(H11:H152) > 0, 0.15, -0.15)), "NA") -> 0.21730986 | G5: =IFERROR(XIRR(N11:N152, B11:B152, IF(SUM(N11:N152) > 0, 0.15, -0.15)), "NA") -> 0.30923399 | H5: =IFERROR(XIRR(T11:T152, B11:B152, IF(SUM(T11:T152) > 0, 0.15, -0.15)), "NA") -> 0.24109132 | K5: Net Asset Value | L5: =SUMIFS(C11:C152, D11:D152, K5) -> 0 | M5: =SUMIFS(H11:H152, D11:D152, K5) -> 0 | N5: =SUMIFS(N11:N152, D11:D152, K5) -> 0 | O5: =SUMIFS(T11:T152, D11:D152, K5) -> 0
B6: Index 3 | C6: ='Share Price'!B5 -> XOP | E6: KS-PME | F6: =(M3 + M5) / -M4 -> 1.7534771 | G6: =(N3 + N5) / -N4 -> 2.1415444 | H6: =(O3 + O5) / -O4 -> 1.9764966
B8: Cash Flow Data | E8: Index 1 Portfolio | K8: Index 2 Portfolio | Q8: Index 3 Portfolio
E9: Index Value at | H9: NAV | I9: End Date | J9: PME | K9: Index Value at | N9: NAV | O9: End Date | P9: PME | Q9: Index Value at | T9: NAV | U9: End Date | V9: PME
B10: Date | C10: Amount | D10: Type | E10: CF Date | F10: End Date | G10: Factor | H10: Contribution | I10: NAV | J10: Cash Flow | K10: CF Date | L10: End Date | M10: Factor | N10: Contribution | O10: NAV | P10: Cash Flow | Q10: CF Date | R10: End Date | S10: Factor | T10: Contribution | U10: NAV | V10: Cash Flow
B11: 38960 | C11: -1000 | D11: Contribution | E11: =_xlfn.XLOOKUP(B11,'Share Price'!D:D,'Share Price'!E:E) -> 38.7093 | F11: =_xlfn.XLOOKUP(C3,'Share Price'!D:D,'Share Price'!E:E) -> 267.26 | G11: =F11/E11 -> 6.904284 | H11: =C11 * G11 -> -6904.284 | I11: =IF(D11="Net Asset Value",I10,-SUM(H11:H11)) -> 6904.284 | J11: =IF(D11="Net Asset Value", I11, C11) -> -1000 | K11: =_xlfn.XLOOKUP(B11,'Share Price'!D:D,'Share Price'!F:F) -> 130.64 | L11: =_xlfn.XLOOKUP(C3,'Share Price'!D:D,'Share Price'!F:F) -> 357.18 | M11: =L11/K11 -> 2.7340784 | N11: =C11 * M11 -> -2734.0784 | O11: =IF(D11="Net Asset Value",O10,-SUM(N11:N11)) -> 2734.0784 | P11: =IF(D11="Net Asset Value", O11, C11) -> -1000 | Q11: =_xlfn.XLOOKUP(B11,'Share Price'!D:D,'Share Price'!G:G) -> 154.56 | R11: =_xlfn.XLOOKUP(C3,'Share Price'!D:D,'Share Price'!G:G) -> 124.72 | S11: =R11/Q11 -> 0.80693582 | T11: =C11 * S11 -> -806.93582 | U11: =IF(D11="Net Asset Value",U10,-SUM(T11:T11)) -> 806.93582 | V11: =IF(D11="Net Asset Value", U11, C11) -> -1000
B12: 38990 | C12: -27828.819 | D12: Contribution | E12: =_xlfn.XLOOKUP(B12,'Share Price'!D:D,'Share Price'!E:E) -> 40.4819 | F12: =_xlfn.XLOOKUP(C3,'Share Price'!D:D,'Share Price'!E:E) -> 267.26 | G12: =F12/E12 -> 6.6019629 | H12: =C12 * G12 -> -183724.83 | I12: =IF(D12="Net Asset Value",I11,-SUM(H11:H12)) -> 190629.11 | J12: =IF(D12="Net Asset Value", I12, C12) -> -27828.819 | K12: =_xlfn.XLOOKUP(B12,'Share Price'!D:D,'Share Price'!F:F) -> 133.58 | L12: =_xlfn.XLOOKUP(C3,'Share Price'!D:D,'Share Price'!F:F) -> 357.18 | M12: =L12/K12 -> 2.6739033 | N12: =C12 * M12 -> -74411.57 | O12: =IF(D12="Net Asset Value",O11,-SUM(N11:N12)) -> 77145.648 | P12: =IF(D12="Net Asset Value", O12, C12) -> -27828.819 | Q12: =_xlfn.XLOOKUP(B12,'Share Price'!D:D,'Share Price'!G:G) -> 142.12 | R12: =_xlfn.XLOOKUP(C3,'Share Price'!D:D,'Share Price'!G:G) -> 124.72 | S12: =R12/Q12 -> 0.87756825 | T12: =C12 * S12 -> -24421.688 | U12: =IF(D12="Net Asset Value",U11,-SUM(T11:T12)) -> 25228.624 | V12: =IF(D12="Net Asset Value", U12, C12) -> -27828.819
B13: 39051 | C13: -52562.722 | D13: Contribution | E13: =_xlfn.XLOOKUP(B13,'Share Price'!D:D,'Share Price'!E:E) -> 43.8579 | F13: =_xlfn.XLOOKUP(C3,'Share Price'!D:D,'Share Price'!E:E) -> 267.26 | G13: =F13/E13 -> 6.093771 | H13: =C13 * G13 -> -320305.19 | I13: =IF(D13="Net Asset Value",I12,-SUM(H11:H13)) -> 510934.3 | J13: =IF(D13="Net Asset Value", I13, C13) -> -52562.722 | K13: =_xlfn.XLOOKUP(B13,'Share Price'!D:D,'Share Price'!F:F) -> 140.53 | L13: =_xlfn.XLOOKUP(C3,'Share Price'!D:D,'Share Price'!F:F) -> 357.18 | M13: =L13/K13 -> 2.5416637 | N13: =C13 * M13 -> -133596.76 | O13: =IF(D13="Net Asset Value",O12,-SUM(N11:N13)) -> 210742.41 | P13: =IF(D13="Net Asset Value", O13, C13) -> -52562.722 | Q13: =_xlfn.XLOOKUP(B13,'Share Price'!D:D,'Share Price'!G:G) -> 164.84 | R13: =_xlfn.XLOOKUP(C3,'Share Price'!D:D,'Share Price'!G:G) -> 124.72 | S13: =R13/Q13 -> 0.75661247 | T13: =C13 * S13 -> -39769.611 | U13: =IF(D13="Net Asset Value",U12,-SUM(T11:T13)) -> 64998.234 | V13: =IF(D13="Net Asset Value", U13, C13) -> -52562.722
B14: 39082 | C14: -2816.7793 | D14: Contribution | E14: =_xlfn.XLOOKUP(B14,'Share Price'!D:D,'Share Price'!E:E) -> 42.9815 | F14: =_xlfn.XLOOKUP(C3,'Share Price'!D:D,'Share Price'!E:E) -> 267.26 | G14: =F14/E14 -> 6.218024 | H14: =C14 * G14 -> -17514.802 | I14: =IF(D14="Net Asset Value",I13,-SUM(H11:H14)) -> 528449.1 | J14: =IF(D14="Net Asset Value", I14, C14) -> -2816.7793 | K14: =_xlfn.XLOOKUP(B14,'Share Price'!D:D,'Share Price'!F:F) -> 141.62 | L14: =_xlfn.XLOOKUP(C3,'Share Price'!D:D,'Share Price'!F:F) -> 357.18 | M14: =L14/K14 -> 2.5221014 | N14: =C14 * M14 -> -7104.2031 | O14: =IF(D14="Net Asset Value",O13,-SUM(N11:N14)) -> 217846.61 | P14: =IF(D14="Net Asset Value", O14, C14) -> -2816.7793 | Q14: =_xlfn.XLOOKUP(B14,'Share Price'!D:D,'Share Price'!G:G) -> 152.28 | R14: =_xlfn.XLOOKUP(C3,'Share Price'!D:D,'Share Price'!G:G) -> 124.72 | S14: =R14/Q14 -> 0.8190176 | T14: =C14 * S14 -> -2306.9919 | U14: =IF(D14="Net Asset Value",U13,-SUM(T11:T14)) -> 67305.226 | V14: =IF(D14="Net Asset Value", U14, C14) -> -2816.7793
B15: 39113 | C15: -4295.7939 | D15: Contribution | E15: =_xlfn.XLOOKUP(B15,'Share Price'!D:D,'Share Price'!E:E) -> 43.8878 | F15: =_xlfn.XLOOKUP(C3,'Share Price'!D:D,'Share Price'!E:E) -> 267.26 | G15: =F15/E15 -> 6.0896194 | H15: =C15 * G15 -> -26159.75 | I15: =IF(D15="Net Asset Value",I14,-SUM(H11:H15)) -> 554608.85 | J15: =IF(D15="Net Asset Value", I15, C15) -> -4295.7939 | K15: =_xlfn.XLOOKUP(B15,'Share Price'!D:D,'Share Price'!F:F) -> 143.75 | L15: =_xlfn.XLOOKUP(C3,'Share Price'!D:D,'Share Price'!F:F) -> 357.18 | M15: =L15/K15 -> 2.4847304 | N15: =C15 * M15 -> -10673.89 | O15: =IF(D15="Net Asset Value",O14,-SUM(N11:N15)) -> 228520.5 | P15: =IF(D15="Net Asset Value", O15, C15) -> -4295.7939 | Q15: =_xlfn.XLOOKUP(B15,'Share Price'!D:D,'Share Price'!G:G) -> 156.88 | R15: =_xlfn.XLOOKUP(C3,'Share Price'!D:D,'Share Price'!G:G) -> 124.72 | S15: =R15/Q15 -> 0.79500255 | T15: =C15 * S15 -> -3415.1671 | U15: =IF(D15="Net Asset Value",U14,-SUM(T11:T15)) -> 70720.393 | V15: =IF(D15="Net Asset Value", U15, C15) -> -4295.7939
B16: 39141 | C16: -13222.388 | D16: Contribution | E16: =_xlfn.XLOOKUP(B16,'Share Price'!D:D,'Share Price'!E:E) -> 43.1508 | F16: =_xlfn.XLOOKUP(C3,'Share Price'!D:D,'Share Price'!E:E) -> 267.26 | G16: =F16/E16 -> 6.1936279 | H16: =C16 * G16 -> -81894.554 | I16: =IF(D16="Net Asset Value",I15,-SUM(H11:H16)) -> 636503.41 | J16: =IF(D16="Net Asset Value", I16, C16) -> -13222.388 | K16: =_xlfn.XLOOKUP(B16,'Share Price'!D:D,'Share Price'!F:F) -> 140.93 | L16: =_xlfn.XLOOKUP(C3,'Share Price'!D:D,'Share Price'!F:F) -> 357.18 | M16: =L16/K16 -> 2.5344497 | N16: =C16 * M16 -> -33511.479 | O16: =IF(D16="Net Asset Value",O15,-SUM(N11:N16)) -> 262031.98 | P16: =IF(D16="Net Asset Value", O16, C16) -> -13222.388 | Q16: =_xlfn.XLOOKUP(B16,'Share Price'!D:D,'Share Price'!G:G) -> 154.64 | R16: =_xlfn.XLOOKUP(C3,'Share Price'!D:D,'Share Price'!G:G) -> 124.72 | S16: =R16/Q16 -> 0.80651837 | T16: =C16 * S16 -> -10664.099 | U16: =IF(D16="Net Asset Value",U15,-SUM(T11:T16)) -> 81384.492 | V16: =IF(D16="Net Asset Value", U16, C16) -> -13222.388
B17: 39172 | C17: -3338.4201 | D17: Contribution | E17: =_xlfn.XLOOKUP(B17,'Share Price'!D:D,'Share Price'!E:E) -> 43.35 | F17: =_xlfn.XLOOKUP(C3,'Share Price'!D:D,'Share Price'!E:E) -> 267.26 | G17: =F17/E17 -> 6.1651672 | H17: =C17 * G17 -> -20581.918 | I17: =IF(D17="Net Asset Value",I16,-SUM(H11:H17)) -> 657085.33 | J17: =IF(D17="Net Asset Value", I17, C17) -> -3338.4201 | K17: =_xlfn.XLOOKUP(B17,'Share Price'!D:D,'Share Price'!F:F) -> 142 | L17: =_xlfn.XLOOKUP(C3,'Share Price'!D:D,'Share Price'!F:F) -> 357.18 | M17: =L17/K17 -> 2.5153521 | N17: =C17 * M17 -> -8397.3021 | O17: =IF(D17="Net Asset Value",O16,-SUM(N11:N17)) -> 270429.28 | P17: =IF(D17="Net Asset Value", O17, C17) -> -3338.4201 | Q17: =_xlfn.XLOOKUP(B17,'Share Price'!D:D,'Share Price'!G:G) -> 162.92 | R17: =_xlfn.XLOOKUP(C3,'Share Price'!D:D,'Share Price'!G:G) -> 124.72 | S17: =R17/Q17 -> 0.76552909 | T17: =C17 * S17 -> -2555.6577 | U17: =IF(D17="Net Asset Value",U16,-SUM(T11:T17)) -> 83940.15 | V17: =IF(D17="Net Asset Value", U17, C17) -> -3338.4201
B18: 39202 | C18: -33321.393 | D18: Contribution | E18: =_xlfn.XLOOKUP(B18,'Share Price'!D:D,'Share Price'!E:E) -> 45.77 | F18: =_xlfn.XLOOKUP(C3,'Share Price'!D:D,'Share Price'!E:E) -> 267.26 | G18: =F18/E18 -> 5.839196 | H18: =C18 * G18 -> -194570.14 | I18: =IF(D18="Net Asset Value",I17,-SUM(H11:H18)) -> 851655.47 | J18: =IF(D18="Net Asset Value", I18, C18) -> -33321.393 | K18: =_xlfn.XLOOKUP(B18,'Share Price'!D:D,'Share Price'!F:F) -> 148.29 | L18: =_xlfn.XLOOKUP(C3,'Share Price'!D:D,'Share Price'!F:F) -> 357.18 | M18: =L18/K18 -> 2.4086587 | N18: =C18 * M18 -> -80259.862 | O18: =IF(D18="Net Asset Value",O17,-SUM(N11:N18)) -> 350689.15 | P18: =IF(D18="Net Asset Value", O18, C18) -> -33321.393 | Q18: =_xlfn.XLOOKUP(B18,'Share Price'!D:D,'Share Price'!G:G) -> 173 | R18: =_xlfn.XLOOKUP(C3,'Share Price'!D:D,'Share Price'!G:G) -> 124.72 | S18: =R18/Q18 -> 0.72092486 | T18: =C18 * S18 -> -24022.22 | U18: =IF(D18="Net Asset Value",U17,-SUM(T11:T18)) -> 107962.37 | V18: =IF(D18="Net Asset Value", U18, C18) -> -33321.393
B19: 39233 | C19: -26212.894 | D19: Contribution | E19: =_xlfn.XLOOKUP(B19,'Share Price'!D:D,'Share Price'!E:E) -> 47.214 | F19: =_xlfn.XLOOKUP(C3,'Share Price'!D:D,'Share Price'!E:E) -> 267.26 | G19: =F19/E19 -> 5.6606091 | H19: =C19 * G19 -> -148380.95 | I19: =IF(D19="Net Asset Value",I18,-SUM(H11:H19)) -> 1000036.4 | J19: =IF(D19="Net Asset Value", I19, C19) -> -26212.894 | K19: =_xlfn.XLOOKUP(B19,'Share Price'!D:D,'Share Price'!F:F) -> 153.32 | L19: =_xlfn.XLOOKUP(C3,'Share Price'!D:D,'Share Price'!F:F) -> 357.18 | M19: =L19/K19 -> 2.3296374 | N19: =C19 * M19 -> -61066.537 | O19: =IF(D19="Net Asset Value",O18,-SUM(N11:N19)) -> 411755.68 | P19: =IF(D19="Net Asset Value", O19, C19) -> -26212.894 | Q19: =_xlfn.XLOOKUP(B19,'Share Price'!D:D,'Share Price'!G:G) -> 186 | R19: =_xlfn.XLOOKUP(C3,'Share Price'!D:D,'Share Price'!G:G) -> 124.72 | S19: =R19/Q19 -> 0.67053763 | T19: =C19 * S19 -> -17576.732 | U19: =IF(D19="Net Asset Value",U18,-SUM(T11:T19)) -> 125539.1 | V19: =IF(D19="Net Asset Value", U19, C19) -> -26212.894
B20: 39263 | C20: -82161.834 | D20: Contribution | E20: =_xlfn.XLOOKUP(B20,'Share Price'!D:D,'Share Price'!E:E) -> 47.4032 | F20: =_xlfn.XLOOKUP(C3,'Share Price'!D:D,'Share Price'!E:E) -> 267.26 | G20: =F20/E20 -> 5.638016 | H20: =C20 * G20 -> -463229.74 | I20: =IF(D20="Net Asset Value",I19,-SUM(H11:H20)) -> 1463266.2 | J20: =IF(D20="Net Asset Value", I20, C20) -> -82161.834 | K20: =_xlfn.XLOOKUP(B20,'Share Price'!D:D,'Share Price'!F:F) -> 150.43 | L20: =_xlfn.XLOOKUP(C3,'Share Price'!D:D,'Share Price'!F:F) -> 357.18 | M20: =L20/K20 -> 2.3743934 | N20: =C20 * M20 -> -195084.52 | O20: =IF(D20="Net Asset Value",O19,-SUM(N11:N20)) -> 606840.2 | P20: =IF(D20="Net Asset Value", O20, C20) -> -82161.834 | Q20: =_xlfn.XLOOKUP(B20,'Share Price'!D:D,'Share Price'!G:G) -> 183.4796 | R20: =_xlfn.XLOOKUP(C3,'Share Price'!D:D,'Share Price'!G:G) -> 124.72 | S20: =R20/Q20 -> 0.67974859 | T20: =C20 * S20 -> -55849.391 | U20: =IF(D20="Net Asset Value",U19,-SUM(T11:T20)) -> 181388.49 | V20: =IF(D20="Net Asset Value", U20, C20) -> -82161.834
B21: 39294 | C21: -16106.633 | D21: Contribution | E21: =_xlfn.XLOOKUP(B21,'Share Price'!D:D,'Share Price'!E:E) -> 47.3335 | F21: =_xlfn.XLOOKUP(C3,'Share Price'!D:D,'Share Price'!E:E) -> 267.26 | G21: =F21/E21 -> 5.6463181 | H21: =C21 * G21 -> -90943.173 | I21: =IF(D21="Net Asset Value",I20,-SUM(H11:H21)) -> 1554209.3 | J21: =IF(D21="Net Asset Value", I21, C21) -> -16106.633 | K21: =_xlfn.XLOOKUP(B21,'Share Price'!D:D,'Share Price'!F:F) -> 145.72 | L21: =_xlfn.XLOOKUP(C3,'Share Price'!D:D,'Share Price'!F:F) -> 357.18 | M21: =L21/K21 -> 2.4511392 | N21: =C21 * M21 -> -39479.599 | O21: =IF(D21="Net Asset Value",O20,-SUM(N11:N21)) -> 646319.8 | P21: =IF(D21="Net Asset Value", O21, C21) -> -16106.633 | Q21: =_xlfn.XLOOKUP(B21,'Share Price'!D:D,'Share Price'!G:G) -> 175.72 | R21: =_xlfn.XLOOKUP(C3,'Share Price'!D:D,'Share Price'!G:G) -> 124.72 | S21: =R21/Q21 -> 0.70976554 | T21: =C21 * S21 -> -11431.933 | U21: =IF(D21="Net Asset Value",U20,-SUM(T11:T21)) -> 192820.43 | V21: =IF(D21="Net Asset Value", U21, C21) -> -16106.633
B22: 39325 | C22: -57051.775 | D22: Contribution | E22: =_xlfn.XLOOKUP(B22,'Share Price'!D:D,'Share Price'!E:E) -> 48.6679 | F22: =_xlfn.XLOOKUP(C3,'Share Price'!D:D,'Share Price'!E:E) -> 267.26 | G22: =F22/E22 -> 5.4915047 | H22: =C22 * G22 -> -313300.09 | I22: =IF(D22="Net Asset Value",I21,-SUM(H11:H22)) -> 1867509.4 | J22: =IF(D22="Net Asset Value", I22, C22) -> -57051.775 | K22: =_xlfn.XLOOKUP(B22,'Share Price'!D:D,'Share Price'!F:F) -> 147.59 | L22: =_xlfn.XLOOKUP(C3,'Share Price'!D:D,'Share Price'!F:F) -> 357.18 | M22: =L22/K22 -> 2.4200827 | N22: =C22 * M22 -> -138070.01 | O22: =IF(D22="Net Asset Value",O21,-SUM(N11:N22)) -> 784389.81 | P22: =IF(D22="Net Asset Value", O22, C22) -> -57051.775 | Q22: =_xlfn.XLOOKUP(B22,'Share Price'!D:D,'Share Price'!G:G) -> 172.44 | R22: =_xlfn.XLOOKUP(C3,'Share Price'!D:D,'Share Price'!G:G) -> 124.72 | S22: =R22/Q22 -> 0.72326606 | T22: =C22 * S22 -> -41263.612 | U22: =IF(D22="Net Asset Value",U21,-SUM(T11:T22)) -> 234084.04 | V22: =IF(D22="Net Asset Value", U22, C22) -> -57051.775
B23: 39355 | C23: -9917.9641 | D23: Contribution | E23: =_xlfn.XLOOKUP(B23,'Share Price'!D:D,'Share Price'!E:E) -> 51.1974 | F23: =_xlfn.XLOOKUP(C3,'Share Price'!D:D,'Share Price'!E:E) -> 267.26 | G23: =F23/E23 -> 5.220187 | H23: =C23 * G23 -> -51773.627 | I23: =IF(D23="Net Asset Value",I22,-SUM(H11:H23)) -> 1919283 | J23: =IF(D23="Net Asset Value", I23, C23) -> -9917.9641 | K23: =_xlfn.XLOOKUP(B23,'Share Price'!D:D,'Share Price'!F:F) -> 152.58 | L23: =_xlfn.XLOOKUP(C3,'Share Price'!D:D,'Share Price'!F:F) -> 357.18 | M23: =L23/K23 -> 2.3409359 | N23: =C23 * M23 -> -23217.318 | O23: =IF(D23="Net Asset Value",O22,-SUM(N11:N23)) -> 807607.13 | P23: =IF(D23="Net Asset Value", O23, C23) -> -9917.9641 | Q23: =_xlfn.XLOOKUP(B23,'Share Price'!D:D,'Share Price'!G:G) -> 188.12 | R23: =_xlfn.XLOOKUP(C3,'Share Price'!D:D,'Share Price'!G:G) -> 124.72 | S23: =R23/Q23 -> 0.66298108 | T23: =C23 * S23 -> -6575.4225 | U23: =IF(D23="Net Asset Value",U22,-SUM(T11:T23)) -> 240659.46 | V23: =IF(D23="Net Asset Value", U23, C23) -> -9917.9641
B24: 39386 | C24: -20441.058 | D24: Contribution | E24: =_xlfn.XLOOKUP(B24,'Share Price'!D:D,'Share Price'!E:E) -> 54.8025 | F24: =_xlfn.XLOOKUP(C3,'Share Price'!D:D,'Share Price'!E:E) -> 267.26 | G24: =F24/E24 -> 4.8767848 | H24: =C24 * G24 -> -99686.64 | I24: =IF(D24="Net Asset Value",I23,-SUM(H11:H24)) -> 2018969.7 | J24: =IF(D24="Net Asset Value", I24, C24) -> -20441.058 | K24: =_xlfn.XLOOKUP(B24,'Share Price'!D:D,'Share Price'!F:F) -> 154.65 | L24: =_xlfn.XLOOKUP(C3,'Share Price'!D:D,'Share Price'!F:F) -> 357.18 | M24: =L24/K24 -> 2.3096023 | N24: =C24 * M24 -> -47210.714 | O24: =IF(D24="Net Asset Value",O23,-SUM(N11:N24)) -> 854817.84 | P24: =IF(D24="Net Asset Value", O24, C24) -> -20441.058 | Q24: =_xlfn.XLOOKUP(B24,'Share Price'!D:D,'Share Price'!G:G) -> 211.64 | R24: =_xlfn.XLOOKUP(C3,'Share Price'!D:D,'Share Price'!G:G) -> 124.72 | S24: =R24/Q24 -> 0.58930259 | T24: =C24 * S24 -> -12045.968 | U24: =IF(D24="Net Asset Value",U23,-SUM(T11:T24)) -> 252705.43 | V24: =IF(D24="Net Asset Value", U24, C24) -> -20441.058
B25: 39416 | C25: -50808.142 | D25: Contribution | E25: =_xlfn.XLOOKUP(B25,'Share Price'!D:D,'Share Price'!E:E) -> 51.0978 | F25: =_xlfn.XLOOKUP(C3,'Share Price'!D:D,'Share Price'!E:E) -> 267.26 | G25: =F25/E25 -> 5.2303622 | H25: =C25 * G25 -> -265744.98 | I25: =IF(D25="Net Asset Value",I24,-SUM(H11:H25)) -> 2284714.7 | J25: =IF(D25="Net Asset Value", I25, C25) -> -50808.142 | K25: =_xlfn.XLOOKUP(B25,'Share Price'!D:D,'Share Price'!F:F) -> 148.66 | L25: =_xlfn.XLOOKUP(C3,'Share Price'!D:D,'Share Price'!F:F) -> 357.18 | M25: =L25/K25 -> 2.4026638 | N25: =C25 * M25 -> -122074.88 | O25: =IF(D25="Net Asset Value",O24,-SUM(N11:N25)) -> 976892.73 | P25: =IF(D25="Net Asset Value", O25, C25) -> -50808.142 | Q25: =_xlfn.XLOOKUP(B25,'Share Price'!D:D,'Share Price'!G:G) -> 194.08 | R25: =_xlfn.XLOOKUP(C3,'Share Price'!D:D,'Share Price'!G:G) -> 124.72 | S25: =R25/Q25 -> 0.6426216 | T25: =C25 * S25 -> -32650.41 | U25: =IF(D25="Net Asset Value",U24,-SUM(T11:T25)) -> 285355.84 | V25: =IF(D25="Net Asset Value", U25, C25) -> -50808.142
B26: 39447 | C26: -41812.195 | D26: Contribution | E26: =_xlfn.XLOOKUP(B26,'Share Price'!D:D,'Share Price'!E:E) -> 51.0082 | F26: =_xlfn.XLOOKUP(C3,'Share Price'!D:D,'Share Price'!E:E) -> 267.26 | G26: =F26/E26 -> 5.2395497 | H26: =C26 * G26 -> -219077.07 | I26: =IF(D26="Net Asset Value",I25,-SUM(H11:H26)) -> 2503791.7 | J26: =IF(D26="Net Asset Value", I26, C26) -> -41812.195 | K26: =_xlfn.XLOOKUP(B26,'Share Price'!D:D,'Share Price'!F:F) -> 146.21 | L26: =_xlfn.XLOOKUP(C3,'Share Price'!D:D,'Share Price'!F:F) -> 357.18 | M26: =L26/K26 -> 2.4429246 | N26: =C26 * M26 -> -102144.04 | O26: =IF(D26="Net Asset Value",O25,-SUM(N11:N26)) -> 1079036.8 | P26: =IF(D26="Net Asset Value", O26, C26) -> -41812.195 | Q26: =_xlfn.XLOOKUP(B26,'Share Price'!D:D,'Share Price'!G:G) -> 208 | R26: =_xlfn.XLOOKUP(C3,'Share Price'!D:D,'Share Price'!G:G) -> 124.72 | S26: =R26/Q26 -> 0.59961538 | T26: =C26 * S26 -> -25071.235 | U26: =IF(D26="Net Asset Value",U25,-SUM(T11:T26)) -> 310427.07 | V26: =IF(D26="Net Asset Value", U26, C26) -> -41812.195
B27: 39478 | C27: -6612.6642 | D27: Contribution | E27: =_xlfn.XLOOKUP(B27,'Share Price'!D:D,'Share Price'!E:E) -> 44.9434 | F27: =_xlfn.XLOOKUP(C3,'Share Price'!D:D,'Share Price'!E:E) -> 267.26 | G27: =F27/E27 -> 5.9465906 | H27: =C27 * G27 -> -39322.807 | I27: =IF(D27="Net Asset Value",I26,-SUM(H11:H27)) -> 2543114.5 | J27: =IF(D27="Net Asset Value", I27, C27) -> -6612.6642 | K27: =_xlfn.XLOOKUP(B27,'Share Price'!D:D,'Share Price'!F:F) -> 137.37 | L27: =_xlfn.XLOOKUP(C3,'Share Price'!D:D,'Share Price'!F:F) -> 357.18 | M27: =L27/K27 -> 2.600131 | N27: =C27 * M27 -> -17193.793 | O27: =IF(D27="Net Asset Value",O26,-SUM(N11:N27)) -> 1096230.6 | P27: =IF(D27="Net Asset Value", O27, C27) -> -6612.6642 | Q27: =_xlfn.XLOOKUP(B27,'Share Price'!D:D,'Share Price'!G:G) -> 192.16 | R27: =_xlfn.XLOOKUP(C3,'Share Price'!D:D,'Share Price'!G:G) -> 124.72 | S27: =R27/Q27 -> 0.64904246 | T27: =C27 * S27 -> -4291.8999 | U27: =IF(D27="Net Asset Value",U26,-SUM(T11:T27)) -> 314718.97 | V27: =IF(D27="Net Asset Value", U27, C27) -> -6612.6642
B28: 39507 | C28: 44960.843 | D28: Distribution | E28: =_xlfn.XLOOKUP(B28,'Share Price'!D:D,'Share Price'!E:E) -> 42.7724 | F28: =_xlfn.XLOOKUP(C3,'Share Price'!D:D,'Share Price'!E:E) -> 267.26 | G28: =F28/E28 -> 6.2484219 | H28: =C28 * G28 -> 280934.31 | I28: =IF(D28="Net Asset Value",I27,-SUM(H11:H28)) -> 2262180.2 | J28: =IF(D28="Net Asset Value", I28, C28) -> 44960.843 | K28: =_xlfn.XLOOKUP(B28,'Share Price'!D:D,'Share Price'!F:F) -> 133.82 | L28: =_xlfn.XLOOKUP(C3,'Share Price'!D:D,'Share Price'!F:F) -> 357.18 | M28: =L28/K28 -> 2.6691078 | N28: =C28 * M28 -> 120005.33 | O28: =IF(D28="Net Asset Value",O27,-SUM(N11:N28)) -> 976225.22 | P28: =IF(D28="Net Asset Value", O28, C28) -> 44960.843 | Q28: =_xlfn.XLOOKUP(B28,'Share Price'!D:D,'Share Price'!G:G) -> 217.9196 | R28: =_xlfn.XLOOKUP(C3,'Share Price'!D:D,'Share Price'!G:G) -> 124.72 | S28: =R28/Q28 -> 0.57232117 | T28: =C28 * S28 -> 25732.042 | U28: =IF(D28="Net Asset Value",U27,-SUM(T11:T28)) -> 288986.93 | V28: =IF(D28="Net Asset Value", U28, C28) -> 44960.843
B29: 39538 | C29: -10755.949 | D29: Contribution | E29: =_xlfn.XLOOKUP(B29,'Share Price'!D:D,'Share Price'!E:E) -> 43.5392 | F29: =_xlfn.XLOOKUP(C3,'Share Price'!D:D,'Share Price'!E:E) -> 267.26 | G29: =F29/E29 -> 6.1383765 | H29: =C29 * G29 -> -66024.066 | I29: =IF(D29="Net Asset Value",I28,-SUM(H11:H29)) -> 2328204.3 | J29: =IF(D29="Net Asset Value", I29, C29) -> -10755.949 | K29: =_xlfn.XLOOKUP(B29,'Share Price'!D:D,'Share Price'!F:F) -> 131.97 | L29: =_xlfn.XLOOKUP(C3,'Share Price'!D:D,'Share Price'!F:F) -> 357.18 | M29: =L29/K29 -> 2.7065242 | N29: =C29 * M29 -> -29111.237 | O29: =IF(D29="Net Asset Value",O28,-SUM(N11:N29)) -> 1005336.5 | P29: =IF(D29="Net Asset Value", O29, C29) -> -10755.949 | Q29: =_xlfn.XLOOKUP(B29,'Share Price'!D:D,'Share Price'!G:G) -> 215 | R29: =_xlfn.XLOOKUP(C3,'Share Price'!D:D,'Share Price'!G:G) -> 124.72 | S29: =R29/Q29 -> 0.58009302 | T29: =C29 * S29 -> -6239.4511 | U29: =IF(D29="Net Asset Value",U28,-SUM(T11:T29)) -> 295226.38 | V29: =IF(D29="Net Asset Value", U29, C29) -> -10755.949
B30: 39568 | C30: 9343.6776 | D30: Distribution | E30: =_xlfn.XLOOKUP(B30,'Share Price'!D:D,'Share Price'!E:E) -> 47.0148 | F30: =_xlfn.XLOOKUP(C3,'Share Price'!D:D,'Share Price'!E:E) -> 267.26 | G30: =F30/E30 -> 5.6845929 | H30: =C30 * G30 -> 53115.004 | I30: =IF(D30="Net Asset Value",I29,-SUM(H11:H30)) -> 2275089.3 | J30: =IF(D30="Net Asset Value", I30, C30) -> 9343.6776 | K30: =_xlfn.XLOOKUP(B30,'Share Price'!D:D,'Share Price'!F:F) -> 138.26 | L30: =_xlfn.XLOOKUP(C3,'Share Price'!D:D,'Share Price'!F:F) -> 357.18 | M30: =L30/K30 -> 2.5833936 | N30: =C30 * M30 -> 24138.397 | O30: =IF(D30="Net Asset Value",O29,-SUM(N11:N30)) -> 981198.06 | P30: =IF(D30="Net Asset Value", O30, C30) -> 9343.6776 | Q30: =_xlfn.XLOOKUP(B30,'Share Price'!D:D,'Share Price'!G:G) -> 235.56 | R30: =_xlfn.XLOOKUP(C3,'Share Price'!D:D,'Share Price'!G:G) -> 124.72 | S30: =R30/Q30 -> 0.52946171 | T30: =C30 * S30 -> 4947.1195 | U30: =IF(D30="Net Asset Value",U29,-SUM(T11:T30)) -> 290279.26 | V30: =IF(D30="Net Asset Value", U30, C30) -> 9343.6776
B31: 39599 | C31: -45647.186 | D31: Contribution | E31: =_xlfn.XLOOKUP(B31,'Share Price'!D:D,'Share Price'!E:E) -> 49.8032 | F31: =_xlfn.XLOOKUP(C3,'Share Price'!D:D,'Share Price'!E:E) -> 267.26 | G31: =F31/E31 -> 5.3663218 | H31: =C31 * G31 -> -244957.49 | I31: =IF(D31="Net Asset Value",I30,-SUM(H11:H31)) -> 2520046.8 | J31: =IF(D31="Net Asset Value", I31, C31) -> -45647.186 | K31: =_xlfn.XLOOKUP(B31,'Share Price'!D:D,'Share Price'!F:F) -> 140.35 | L31: =_xlfn.XLOOKUP(C3,'Share Price'!D:D,'Share Price'!F:F) -> 357.18 | M31: =L31/K31 -> 2.5449234 | N31: =C31 * M31 -> -116168.59 | O31: =IF(D31="Net Asset Value",O30,-SUM(N11:N31)) -> 1097366.7 | P31: =IF(D31="Net Asset Value", O31, C31) -> -45647.186 | Q31: =_xlfn.XLOOKUP(B31,'Share Price'!D:D,'Share Price'!G:G) -> 259.08 | R31: =_xlfn.XLOOKUP(C3,'Share Price'!D:D,'Share Price'!G:G) -> 124.72 | S31: =R31/Q31 -> 0.48139571 | T31: =C31 * S31 -> -21974.359 | U31: =IF(D31="Net Asset Value",U30,-SUM(T11:T31)) -> 312253.62 | V31: =IF(D31="Net Asset Value", U31, C31) -> -45647.186
B32: 39629 | C32: -24462.446 | D32: Contribution | E32: =_xlfn.XLOOKUP(B32,'Share Price'!D:D,'Share Price'!E:E) -> 44.9832 | F32: =_xlfn.XLOOKUP(C3,'Share Price'!D:D,'Share Price'!E:E) -> 267.26 | G32: =F32/E32 -> 5.9413292 | H32: =C32 * G32 -> -145339.44 | I32: =IF(D32="Net Asset Value",I31,-SUM(H11:H32)) -> 2665386.2 | J32: =IF(D32="Net Asset Value", I32, C32) -> -24462.446 | K32: =_xlfn.XLOOKUP(B32,'Share Price'!D:D,'Share Price'!F:F) -> 127.98 | L32: =_xlfn.XLOOKUP(C3,'Share Price'!D:D,'Share Price'!F:F) -> 357.18 | M32: =L32/K32 -> 2.7909048 | N32: =C32 * M32 -> -68272.358 | O32: =IF(D32="Net Asset Value",O31,-SUM(N11:N32)) -> 1165639 | P32: =IF(D32="Net Asset Value", O32, C32) -> -24462.446 | Q32: =_xlfn.XLOOKUP(B32,'Share Price'!D:D,'Share Price'!G:G) -> 281.12 | R32: =_xlfn.XLOOKUP(C3,'Share Price'!D:D,'Share Price'!G:G) -> 124.72 | S32: =R32/Q32 -> 0.44365396 | T32: =C32 * S32 -> -10852.861 | U32: =IF(D32="Net Asset Value",U31,-SUM(T11:T32)) -> 323106.48 | V32: =IF(D32="Net Asset Value", U32, C32) -> -24462.446
B33: 39660 | C33: -8388.337 | D33: Contribution | E33: =_xlfn.XLOOKUP(B33,'Share Price'!D:D,'Share Price'!E:E) -> 45.272 | F33: =_xlfn.XLOOKUP(C3,'Share Price'!D:D,'Share Price'!E:E) -> 267.26 | G33: =F33/E33 -> 5.9034282 | H33: =C33 * G33 -> -49519.945 | I33: =IF(D33="Net Asset Value",I32,-SUM(H11:H33)) -> 2714906.2 | J33: =IF(D33="Net Asset Value", I33, C33) -> -8388.337 | K33: =_xlfn.XLOOKUP(B33,'Share Price'!D:D,'Share Price'!F:F) -> 126.83 | L33: =_xlfn.XLOOKUP(C3,'Share Price'!D:D,'Share Price'!F:F) -> 357.18 | M33: =L33/K33 -> 2.8162107 | N33: =C33 * M33 -> -23623.324 | O33: =IF(D33="Net Asset Value",O32,-SUM(N11:N33)) -> 1189262.3 | P33: =IF(D33="Net Asset Value", O33, C33) -> -8388.337 | Q33: =_xlfn.XLOOKUP(B33,'Share Price'!D:D,'Share Price'!G:G) -> 216.32 | R33: =_xlfn.XLOOKUP(C3,'Share Price'!D:D,'Share Price'!G:G) -> 124.72 | S33: =R33/Q33 -> 0.57655325 | T33: =C33 * S33 -> -4836.323 | U33: =IF(D33="Net Asset Value",U32,-SUM(T11:T33)) -> 327942.81 | V33: =IF(D33="Net Asset Value", U33, C33) -> -8388.337
B34: 39691 | C34: -50070.06 | D34: Contribution | E34: =_xlfn.XLOOKUP(B34,'Share Price'!D:D,'Share Price'!E:E) -> 45.9293 | F34: =_xlfn.XLOOKUP(C3,'Share Price'!D:D,'Share Price'!E:E) -> 267.26 | G34: =F34/E34 -> 5.8189435 | H34: =C34 * G34 -> -291354.85 | I34: =IF(D34="Net Asset Value",I33,-SUM(H11:H34)) -> 3006261 | J34: =IF(D34="Net Asset Value", I34, C34) -> -50070.06 | K34: =_xlfn.XLOOKUP(B34,'Share Price'!D:D,'Share Price'!F:F) -> 128.79 | L34: =_xlfn.XLOOKUP(C3,'Share Price'!D:D,'Share Price'!F:F) -> 357.18 | M34: =L34/K34 -> 2.773352 | N34: =C34 * M34 -> -138861.9 | O34: =IF(D34="Net Asset Value",O33,-SUM(N11:N34)) -> 1328124.2 | P34: =IF(D34="Net Asset Value", O34, C34) -> -50070.06 | Q34: =_xlfn.XLOOKUP(B34,'Share Price'!D:D,'Share Price'!G:G) -> 220.12 | R34: =_xlfn.XLOOKUP(C3,'Share Price'!D:D,'Share Price'!G:G) -> 124.72 | S34: =R34/Q34 -> 0.56660004 | T34: =C34 * S34 -> -28369.698 | U34: =IF(D34="Net Asset Value",U33,-SUM(T11:T34)) -> 356312.5 | V34: =IF(D34="Net Asset Value", U34, C34) -> -50070.06
B35: 39721 | C35: -11172.275 | D35: Contribution | E35: =_xlfn.XLOOKUP(B35,'Share Price'!D:D,'Share Price'!E:E) -> 38.7491 | F35: =_xlfn.XLOOKUP(C3,'Share Price'!D:D,'Share Price'!E:E) -> 267.26 | G35: =F35/E35 -> 6.8971925 | H35: =C35 * G35 -> -77057.333 | I35: =IF(D35="Net Asset Value",I34,-SUM(H11:H35)) -> 3083318.4 | J35: =IF(D35="Net Asset Value", I35, C35) -> -11172.275 | K35: =_xlfn.XLOOKUP(B35,'Share Price'!D:D,'Share Price'!F:F) -> 115.99 | L35: =_xlfn.XLOOKUP(C3,'Share Price'!D:D,'Share Price'!F:F) -> 357.18 | M35: =L35/K35 -> 3.0794034 | N35: =C35 * M35 -> -34403.943 | O35: =IF(D35="Net Asset Value",O34,-SUM(N11:N35)) -> 1362528.2 | P35: =IF(D35="Net Asset Value", O35, C35) -> -11172.275 | Q35: =_xlfn.XLOOKUP(B35,'Share Price'!D:D,'Share Price'!G:G) -> 179.32 | R35: =_xlfn.XLOOKUP(C3,'Share Price'!D:D,'Share Price'!G:G) -> 124.72 | S35: =R35/Q35 -> 0.6955164 | T35: =C35 * S35 -> -7770.5007 | U35: =IF(D35="Net Asset Value",U34,-SUM(T11:T35)) -> 364083.01 | V35: =IF(D35="Net Asset Value", U35, C35) -> -11172.275
B36: 39752 | C36: -20435.805 | D36: Contribution | E36: =_xlfn.XLOOKUP(B36,'Share Price'!D:D,'Share Price'!E:E) -> 32.754 | F36: =_xlfn.XLOOKUP(C3,'Share Price'!D:D,'Share Price'!E:E) -> 267.26 | G36: =F36/E36 -> 8.1596141 | H36: =C36 * G36 -> -166748.28 | I36: =IF(D36="Net Asset Value",I35,-SUM(H11:H36)) -> 3250066.6 | J36: =IF(D36="Net Asset Value", I36, C36) -> -20435.805 | K36: =_xlfn.XLOOKUP(B36,'Share Price'!D:D,'Share Price'!F:F) -> 96.83 | L36: =_xlfn.XLOOKUP(C3,'Share Price'!D:D,'Share Price'!F:F) -> 357.18 | M36: =L36/K36 -> 3.6887328 | N36: =C36 * M36 -> -75382.224 | O36: =IF(D36="Net Asset Value",O35,-SUM(N11:N36)) -> 1437910.4 | P36: =IF(D36="Net Asset Value", O36, C36) -> -20435.805 | Q36: =_xlfn.XLOOKUP(B36,'Share Price'!D:D,'Share Price'!G:G) -> 136.04 | R36: =_xlfn.XLOOKUP(C3,'Share Price'!D:D,'Share Price'!G:G) -> 124.72 | S36: =R36/Q36 -> 0.91678918 | T36: =C36 * S36 -> -18735.325 | U36: =IF(D36="Net Asset Value",U35,-SUM(T11:T36)) -> 382818.33 | V36: =IF(D36="Net Asset Value", U36, C36) -> -20435.805
B37: 39782 | C37: -18180.183 | D37: Contribution | E37: =_xlfn.XLOOKUP(B37,'Share Price'!D:D,'Share Price'!E:E) -> 28.9996 | F37: =_xlfn.XLOOKUP(C3,'Share Price'!D:D,'Share Price'!E:E) -> 267.26 | G37: =F37/E37 -> 9.2159892 | H37: =C37 * G37 -> -167548.37 | I37: =IF(D37="Net Asset Value",I36,-SUM(H11:H37)) -> 3417615 | J37: =IF(D37="Net Asset Value", I37, C37) -> -18180.183 | K37: =_xlfn.XLOOKUP(B37,'Share Price'!D:D,'Share Price'!F:F) -> 90.09 | L37: =_xlfn.XLOOKUP(C3,'Share Price'!D:D,'Share Price'!F:F) -> 357.18 | M37: =L37/K37 -> 3.964702 | N37: =C37 * M37 -> -72079.007 | O37: =IF(D37="Net Asset Value",O36,-SUM(N11:N37)) -> 1509989.4 | P37: =IF(D37="Net Asset Value", O37, C37) -> -18180.183 | Q37: =_xlfn.XLOOKUP(B37,'Share Price'!D:D,'Share Price'!G:G) -> 124.32 | R37: =_xlfn.XLOOKUP(C3,'Share Price'!D:D,'Share Price'!G:G) -> 124.72 | S37: =R37/Q37 -> 1.0032175 | T37: =C37 * S37 -> -18238.678 | U37: =IF(D37="Net Asset Value",U36,-SUM(T11:T37)) -> 401057.01 | V37: =IF(D37="Net Asset Value", U37, C37) -> -18180.183
B38: 39813 | C38: -15674.56 | D38: Contribution | E38: =_xlfn.XLOOKUP(B38,'Share Price'!D:D,'Share Price'!E:E) -> 29.617 | F38: =_xlfn.XLOOKUP(C3,'Share Price'!D:D,'Share Price'!E:E) -> 267.26 | G38: =F38/E38 -> 9.0238714 | H38: =C38 * G38 -> -141445.22 | I38: =IF(D38="Net Asset Value",I37,-SUM(H11:H38)) -> 3559060.2 | J38: =IF(D38="Net Asset Value", I38, C38) -> -15674.56 | K38: =_xlfn.XLOOKUP(B38,'Share Price'!D:D,'Share Price'!F:F) -> 90.24 | L38: =_xlfn.XLOOKUP(C3,'Share Price'!D:D,'Share Price'!F:F) -> 357.18 | M38: =L38/K38 -> 3.9581117 | N38: =C38 * M38 -> -62041.66 | O38: =IF(D38="Net Asset Value",O37,-SUM(N11:N38)) -> 1572031.1 | P38: =IF(D38="Net Asset Value", O38, C38) -> -15674.56 | Q38: =_xlfn.XLOOKUP(B38,'Share Price'!D:D,'Share Price'!G:G) -> 118.56 | R38: =_xlfn.XLOOKUP(C3,'Share Price'!D:D,'Share Price'!G:G) -> 124.72 | S38: =R38/Q38 -> 1.0519568 | T38: =C38 * S38 -> -16488.96 | U38: =IF(D38="Net Asset Value",U37,-SUM(T11:T38)) -> 417545.97 | V38: =IF(D38="Net Asset Value", U38, C38) -> -15674.56
B39: 39844 | C39: -35731.622 | D39: Contribution | E39: =_xlfn.XLOOKUP(B39,'Share Price'!D:D,'Share Price'!E:E) -> 28.9398 | F39: =_xlfn.XLOOKUP(C3,'Share Price'!D:D,'Share Price'!E:E) -> 267.26 | G39: =F39/E39 -> 9.2350327 | H39: =C39 * G39 -> -329982.7 | I39: =IF(D39="Net Asset Value",I38,-SUM(H11:H39)) -> 3889042.9 | J39: =IF(D39="Net Asset Value", I39, C39) -> -35731.622 | K39: =_xlfn.XLOOKUP(B39,'Share Price'!D:D,'Share Price'!F:F) -> 82.83 | L39: =_xlfn.XLOOKUP(C3,'Share Price'!D:D,'Share Price'!F:F) -> 357.18 | M39: =L39/K39 -> 4.3122057 | N39: =C39 * M39 -> -154082.1 | O39: =IF(D39="Net Asset Value",O38,-SUM(N11:N39)) -> 1726113.2 | P39: =IF(D39="Net Asset Value", O39, C39) -> -35731.622 | Q39: =_xlfn.XLOOKUP(B39,'Share Price'!D:D,'Share Price'!G:G) -> 119.64 | R39: =_xlfn.XLOOKUP(C3,'Share Price'!D:D,'Share Price'!G:G) -> 124.72 | S39: =R39/Q39 -> 1.0424607 | T39: =C39 * S39 -> -37248.812 | U39: =IF(D39="Net Asset Value",U38,-SUM(T11:T39)) -> 454794.78 | V39: =IF(D39="Net Asset Value", U39, C39) -> -35731.622
B40: 39872 | C40: -9630.1874 | D40: Contribution | E40: =_xlfn.XLOOKUP(B40,'Share Price'!D:D,'Share Price'!E:E) -> 27.4162 | F40: =_xlfn.XLOOKUP(C3,'Share Price'!D:D,'Share Price'!E:E) -> 267.26 | G40: =F40/E40 -> 9.748251 | H40: =C40 * G40 -> -93877.485 | I40: =IF(D40="Net Asset Value",I39,-SUM(H11:H40)) -> 3982920.4 | J40: =IF(D40="Net Asset Value", I40, C40) -> -9630.1874 | K40: =_xlfn.XLOOKUP(B40,'Share Price'!D:D,'Share Price'!F:F) -> 73.93 | L40: =_xlfn.XLOOKUP(C3,'Share Price'!D:D,'Share Price'!F:F) -> 357.18 | M40: =L40/K40 -> 4.8313269 | N40: =C40 * M40 -> -46526.584 | O40: =IF(D40="Net Asset Value",O39,-SUM(N11:N40)) -> 1772639.8 | P40: =IF(D40="Net Asset Value", O40, C40) -> -9630.1874 | Q40: =_xlfn.XLOOKUP(B40,'Share Price'!D:D,'Share Price'!G:G) -> 104.04 | R40: =_xlfn.XLOOKUP(C3,'Share Price'!D:D,'Share Price'!G:G) -> 124.72 | S40: =R40/Q40 -> 1.1987697 | T40: =C40 * S40 -> -11544.377 | U40: =IF(D40="Net Asset Value",U39,-SUM(T11:T40)) -> 466339.16 | V40: =IF(D40="Net Asset Value", U40, C40) -> -9630.1874
B41: 39903 | C41: -22454.967 | D41: Contribution | E41: =_xlfn.XLOOKUP(B41,'Share Price'!D:D,'Share Price'!E:E) -> 30.1946 | F41: =_xlfn.XLOOKUP(C3,'Share Price'!D:D,'Share Price'!E:E) -> 267.26 | G41: =F41/E41 -> 8.8512515 | H41: =C41 * G41 -> -198754.56 | I41: =IF(D41="Net Asset Value",I40,-SUM(H11:H41)) -> 4181675 | J41: =IF(D41="Net Asset Value", I41, C41) -> -22454.967 | K41: =_xlfn.XLOOKUP(B41,'Share Price'!D:D,'Share Price'!F:F) -> 79.52 | L41: =_xlfn.XLOOKUP(C3,'Share Price'!D:D,'Share Price'!F:F) -> 357.18 | M41: =L41/K41 -> 4.4917002 | N41: =C41 * M41 -> -100860.98 | O41: =IF(D41="Net Asset Value",O40,-SUM(N11:N41)) -> 1873500.7 | P41: =IF(D41="Net Asset Value", O41, C41) -> -22454.967 | Q41: =_xlfn.XLOOKUP(B41,'Share Price'!D:D,'Share Price'!G:G) -> 106.4 | R41: =_xlfn.XLOOKUP(C3,'Share Price'!D:D,'Share Price'!G:G) -> 124.72 | S41: =R41/Q41 -> 1.1721805 | T41: =C41 * S41 -> -26321.273 | U41: =IF(D41="Net Asset Value",U40,-SUM(T11:T41)) -> 492660.43 | V41: =IF(D41="Net Asset Value", U41, C41) -> -22454.967
B42: 39933 | C42: -24866.429 | D42: Contribution | E42: =_xlfn.XLOOKUP(B42,'Share Price'!D:D,'Share Price'!E:E) -> 34.1383 | F42: =_xlfn.XLOOKUP(C3,'Share Price'!D:D,'Share Price'!E:E) -> 267.26 | G42: =F42/E42 -> 7.8287437 | H42: =C42 * G42 -> -194672.9 | I42: =IF(D42="Net Asset Value",I41,-SUM(H11:H42)) -> 4376347.9 | J42: =IF(D42="Net Asset Value", I42, C42) -> -24866.429 | K42: =_xlfn.XLOOKUP(B42,'Share Price'!D:D,'Share Price'!F:F) -> 87.42 | L42: =_xlfn.XLOOKUP(C3,'Share Price'!D:D,'Share Price'!F:F) -> 357.18 | M42: =L42/K42 -> 4.0857927 | N42: =C42 * M42 -> -101599.08 | O42: =IF(D42="Net Asset Value",O41,-SUM(N11:N42)) -> 1975099.8 | P42: =IF(D42="Net Asset Value", O42, C42) -> -24866.429 | Q42: =_xlfn.XLOOKUP(B42,'Share Price'!D:D,'Share Price'!G:G) -> 123.44 | R42: =_xlfn.XLOOKUP(C3,'Share Price'!D:D,'Share Price'!G:G) -> 124.72 | S42: =R42/Q42 -> 1.0103694 | T42: =C42 * S42 -> -25124.279 | U42: =IF(D42="Net Asset Value",U41,-SUM(T11:T42)) -> 517784.71 | V42: =IF(D42="Net Asset Value", U42, C42) -> -24866.429
B43: 39964 | C43: -35058.86 | D43: Contribution | E43: =_xlfn.XLOOKUP(B43,'Share Price'!D:D,'Share Price'!E:E) -> 35.2337 | F43: =_xlfn.XLOOKUP(C3,'Share Price'!D:D,'Share Price'!E:E) -> 267.26 | G43: =F43/E43 -> 7.5853515 | H43: =C43 * G43 -> -265933.77 | I43: =IF(D43="Net Asset Value",I42,-SUM(H11:H43)) -> 4642281.6 | J43: =IF(D43="Net Asset Value", I43, C43) -> -35058.86 | K43: =_xlfn.XLOOKUP(B43,'Share Price'!D:D,'Share Price'!F:F) -> 92.53 | L43: =_xlfn.XLOOKUP(C3,'Share Price'!D:D,'Share Price'!F:F) -> 357.18 | M43: =L43/K43 -> 3.8601535 | N43: =C43 * M43 -> -135332.58 | O43: =IF(D43="Net Asset Value",O42,-SUM(N11:N43)) -> 2110432.4 | P43: =IF(D43="Net Asset Value", O43, C43) -> -35058.86 | Q43: =_xlfn.XLOOKUP(B43,'Share Price'!D:D,'Share Price'!G:G) -> 144.52 | R43: =_xlfn.XLOOKUP(C3,'Share Price'!D:D,'Share Price'!G:G) -> 124.72 | S43: =R43/Q43 -> 0.86299474 | T43: =C43 * S43 -> -30255.612 | U43: =IF(D43="Net Asset Value",U42,-SUM(T11:T43)) -> 548040.32 | V43: =IF(D43="Net Asset Value", U43, C43) -> -35058.86
B44: 39994 | C44: -135074.84 | D44: Contribution | E44: =_xlfn.XLOOKUP(B44,'Share Price'!D:D,'Share Price'!E:E) -> 36.2296 | F44: =_xlfn.XLOOKUP(C3,'Share Price'!D:D,'Share Price'!E:E) -> 267.26 | G44: =F44/E44 -> 7.376841 | H44: =C44 * G44 -> -996425.65 | I44: =IF(D44="Net Asset Value",I43,-SUM(H11:H44)) -> 5638707.3 | J44: =IF(D44="Net Asset Value", I44, C44) -> -135074.84 | K44: =_xlfn.XLOOKUP(B44,'Share Price'!D:D,'Share Price'!F:F) -> 91.95 | L44: =_xlfn.XLOOKUP(C3,'Share Price'!D:D,'Share Price'!F:F) -> 357.18 | M44: =L44/K44 -> 3.8845024 | N44: =C44 * M44 -> -524698.56 | O44: =IF(D44="Net Asset Value",O43,-SUM(N11:N44)) -> 2635131 | P44: =IF(D44="Net Asset Value", O44, C44) -> -135074.84 | Q44: =_xlfn.XLOOKUP(B44,'Share Price'!D:D,'Share Price'!G:G) -> 126.88 | R44: =_xlfn.XLOOKUP(C3,'Share Price'!D:D,'Share Price'!G:G) -> 124.72 | S44: =R44/Q44 -> 0.98297604 | T44: =C44 * S44 -> -132775.34 | U44: =IF(D44="Net Asset Value",U43,-SUM(T11:T44)) -> 680815.66 | V44: =IF(D44="Net Asset Value", U44, C44) -> -135074.84
B45: 40025 | C45: -9539.9798 | D45: Contribution | E45: =_xlfn.XLOOKUP(B45,'Share Price'!D:D,'Share Price'!E:E) -> 39.2869 | F45: =_xlfn.XLOOKUP(C3,'Share Price'!D:D,'Share Price'!E:E) -> 267.26 | G45: =F45/E45 -> 6.8027765 | H45: =C45 * G45 -> -64898.351 | I45: =IF(D45="Net Asset Value",I44,-SUM(H11:H45)) -> 5703605.6 | J45: =IF(D45="Net Asset Value", I45, C45) -> -9539.9798 | K45: =_xlfn.XLOOKUP(B45,'Share Price'!D:D,'Share Price'!F:F) -> 98.81 | L45: =_xlfn.XLOOKUP(C3,'Share Price'!D:D,'Share Price'!F:F) -> 357.18 | M45: =L45/K45 -> 3.6148163 | N45: =C45 * M45 -> -34485.275 | O45: =IF(D45="Net Asset Value",O44,-SUM(N11:N45)) -> 2669616.2 | P45: =IF(D45="Net Asset Value", O45, C45) -> -9539.9798 | Q45: =_xlfn.XLOOKUP(B45,'Share Price'!D:D,'Share Price'!G:G) -> 139.68 | R45: =_xlfn.XLOOKUP(C3,'Share Price'!D:D,'Share Price'!G:G) -> 124.72 | S45: =R45/Q45 -> 0.89289805 | T45: =C45 * S45 -> -8518.2294 | U45: =IF(D45="Net Asset Value",U44,-SUM(T11:T45)) -> 689333.89 | V45: =IF(D45="Net Asset Value", U45, C45) -> -9539.9798
B46: 40056 | C46: -11408.723 | D46: Contribution | E46: =_xlfn.XLOOKUP(B46,'Share Price'!D:D,'Share Price'!E:E) -> 39.8645 | F46: =_xlfn.XLOOKUP(C3,'Share Price'!D:D,'Share Price'!E:E) -> 267.26 | G46: =F46/E46 -> 6.7042105 | H46: =C46 * G46 -> -76486.48 | I46: =IF(D46="Net Asset Value",I45,-SUM(H11:H46)) -> 5780092.1 | J46: =IF(D46="Net Asset Value", I46, C46) -> -11408.723 | K46: =_xlfn.XLOOKUP(B46,'Share Price'!D:D,'Share Price'!F:F) -> 102.46 | L46: =_xlfn.XLOOKUP(C3,'Share Price'!D:D,'Share Price'!F:F) -> 357.18 | M46: =L46/K46 -> 3.4860433 | N46: =C46 * M46 -> -39771.302 | O46: =IF(D46="Net Asset Value",O45,-SUM(N11:N46)) -> 2709387.5 | P46: =IF(D46="Net Asset Value", O46, C46) -> -11408.723 | Q46: =_xlfn.XLOOKUP(B46,'Share Price'!D:D,'Share Price'!G:G) -> 140.84 | R46: =_xlfn.XLOOKUP(C3,'Share Price'!D:D,'Share Price'!G:G) -> 124.72 | S46: =R46/Q46 -> 0.88554388 | T46: =C46 * S46 -> -10102.925 | U46: =IF(D46="Net Asset Value",U45,-SUM(T11:T46)) -> 699436.81 | V46: =IF(D46="Net Asset Value", U46, C46) -> -11408.723
B47: 40086 | C47: -29196.308 | D47: Contribution | E47: =_xlfn.XLOOKUP(B47,'Share Price'!D:D,'Share Price'!E:E) -> 42.0753 | F47: =_xlfn.XLOOKUP(C3,'Share Price'!D:D,'Share Price'!E:E) -> 267.26 | G47: =F47/E47 -> 6.3519452 | H47: =C47 * G47 -> -185453.35 | I47: =IF(D47="Net Asset Value",I46,-SUM(H11:H47)) -> 5965545.5 | J47: =IF(D47="Net Asset Value", I47, C47) -> -29196.308 | K47: =_xlfn.XLOOKUP(B47,'Share Price'!D:D,'Share Price'!F:F) -> 105.59 | L47: =_xlfn.XLOOKUP(C3,'Share Price'!D:D,'Share Price'!F:F) -> 357.18 | M47: =L47/K47 -> 3.3827067 | N47: =C47 * M47 -> -98762.547 | O47: =IF(D47="Net Asset Value",O46,-SUM(N11:N47)) -> 2808150.1 | P47: =IF(D47="Net Asset Value", O47, C47) -> -29196.308 | Q47: =_xlfn.XLOOKUP(B47,'Share Price'!D:D,'Share Price'!G:G) -> 154.64 | R47: =_xlfn.XLOOKUP(C3,'Share Price'!D:D,'Share Price'!G:G) -> 124.72 | S47: =R47/Q47 -> 0.80651837 | T47: =C47 * S47 -> -23547.359 | U47: =IF(D47="Net Asset Value",U46,-SUM(T11:T47)) -> 722984.17 | V47: =IF(D47="Net Asset Value", U47, C47) -> -29196.308
B48: 40117 | C48: 81106.98 | D48: Distribution | E48: =_xlfn.XLOOKUP(B48,'Share Price'!D:D,'Share Price'!E:E) -> 40.7906 | F48: =_xlfn.XLOOKUP(C3,'Share Price'!D:D,'Share Price'!E:E) -> 267.26 | G48: =F48/E48 -> 6.5519997 | H48: =C48 * G48 -> 531412.91 | I48: =IF(D48="Net Asset Value",I47,-SUM(H11:H48)) -> 5434132.6 | J48: =IF(D48="Net Asset Value", I48, C48) -> 81106.98 | K48: =_xlfn.XLOOKUP(B48,'Share Price'!D:D,'Share Price'!F:F) -> 103.56 | L48: =_xlfn.XLOOKUP(C3,'Share Price'!D:D,'Share Price'!F:F) -> 357.18 | M48: =L48/K48 -> 3.4490151 | N48: =C48 * M48 -> 279739.2 | O48: =IF(D48="Net Asset Value",O47,-SUM(N11:N48)) -> 2528410.9 | P48: =IF(D48="Net Asset Value", O48, C48) -> 81106.98 | Q48: =_xlfn.XLOOKUP(B48,'Share Price'!D:D,'Share Price'!G:G) -> 153.8 | R48: =_xlfn.XLOOKUP(C3,'Share Price'!D:D,'Share Price'!G:G) -> 124.72 | S48: =R48/Q48 -> 0.81092328 | T48: =C48 * S48 -> 65771.538 | U48: =IF(D48="Net Asset Value",U47,-SUM(T11:T48)) -> 657212.63 | V48: =IF(D48="Net Asset Value", U48, C48) -> 81106.98
B49: 40147 | C49: 41297.719 | D49: Distribution | E49: =_xlfn.XLOOKUP(B49,'Share Price'!D:D,'Share Price'!E:E) -> 43.3799 | F49: =_xlfn.XLOOKUP(C3,'Share Price'!D:D,'Share Price'!E:E) -> 267.26 | G49: =F49/E49 -> 6.1609178 | H49: =C49 * G49 -> 254431.85 | I49: =IF(D49="Net Asset Value",I48,-SUM(H11:H49)) -> 5179700.7 | J49: =IF(D49="Net Asset Value", I49, C49) -> 41297.719 | K49: =_xlfn.XLOOKUP(B49,'Share Price'!D:D,'Share Price'!F:F) -> 109.94 | L49: =_xlfn.XLOOKUP(C3,'Share Price'!D:D,'Share Price'!F:F) -> 357.18 | M49: =L49/K49 -> 3.248863 | N49: =C49 * M49 -> 134170.63 | O49: =IF(D49="Net Asset Value",O48,-SUM(N11:N49)) -> 2394240.2 | P49: =IF(D49="Net Asset Value", O49, C49) -> 41297.719 | Q49: =_xlfn.XLOOKUP(B49,'Share Price'!D:D,'Share Price'!G:G) -> 153.64 | R49: =_xlfn.XLOOKUP(C3,'Share Price'!D:D,'Share Price'!G:G) -> 124.72 | S49: =R49/Q49 -> 0.81176777 | T49: =C49 * S49 -> 33524.157 | U49: =IF(D49="Net Asset Value",U48,-SUM(T11:T49)) -> 623688.47 | V49: =IF(D49="Net Asset Value", U49, C49) -> 41297.719
B50: 40178 | C50: -65925.993 | D50: Contribution | E50: =_xlfn.XLOOKUP(B50,'Share Price'!D:D,'Share Price'!E:E) -> 45.5608 | F50: =_xlfn.XLOOKUP(C3,'Share Price'!D:D,'Share Price'!E:E) -> 267.26 | G50: =F50/E50 -> 5.8660076 | H50: =C50 * G50 -> -386722.38 | I50: =IF(D50="Net Asset Value",I49,-SUM(H11:H50)) -> 5566423.1 | J50: =IF(D50="Net Asset Value", I50, C50) -> -65925.993 | K50: =_xlfn.XLOOKUP(B50,'Share Price'!D:D,'Share Price'!F:F) -> 111.44 | L50: =_xlfn.XLOOKUP(C3,'Share Price'!D:D,'Share Price'!F:F) -> 357.18 | M50: =L50/K50 -> 3.2051328 | N50: =C50 * M50 -> -211301.56 | O50: =IF(D50="Net Asset Value",O49,-SUM(N11:N50)) -> 2605541.8 | P50: =IF(D50="Net Asset Value", O50, C50) -> -65925.993 | Q50: =_xlfn.XLOOKUP(B50,'Share Price'!D:D,'Share Price'!G:G) -> 164.84 | R50: =_xlfn.XLOOKUP(C3,'Share Price'!D:D,'Share Price'!G:G) -> 124.72 | S50: =R50/Q50 -> 0.75661247 | T50: =C50 * S50 -> -49880.429 | U50: =IF(D50="Net Asset Value",U49,-SUM(T11:T50)) -> 673568.9 | V50: =IF(D50="Net Asset Value", U50, C50) -> -65925.993
B51: 40209 | C51: -4923.1157 | D51: Contribution | E51: =_xlfn.XLOOKUP(B51,'Share Price'!D:D,'Share Price'!E:E) -> 42.6131 | F51: =_xlfn.XLOOKUP(C3,'Share Price'!D:D,'Share Price'!E:E) -> 267.26 | G51: =F51/E51 -> 6.2717803 | H51: =C51 * G51 -> -30876.7 | I51: =IF(D51="Net Asset Value",I50,-SUM(H11:H51)) -> 5597299.8 | J51: =IF(D51="Net Asset Value", I51, C51) -> -4923.1157 | K51: =_xlfn.XLOOKUP(B51,'Share Price'!D:D,'Share Price'!F:F) -> 107.39 | L51: =_xlfn.XLOOKUP(C3,'Share Price'!D:D,'Share Price'!F:F) -> 357.18 | M51: =L51/K51 -> 3.326008 | N51: =C51 * M51 -> -16374.322 | O51: =IF(D51="Net Asset Value",O50,-SUM(N11:N51)) -> 2621916.1 | P51: =IF(D51="Net Asset Value", O51, C51) -> -4923.1157 | Q51: =_xlfn.XLOOKUP(B51,'Share Price'!D:D,'Share Price'!G:G) -> 157.84 | R51: =_xlfn.XLOOKUP(C3,'Share Price'!D:D,'Share Price'!G:G) -> 124.72 | S51: =R51/Q51 -> 0.79016726 | T51: =C51 * S51 -> -3890.0848 | U51: =IF(D51="Net Asset Value",U50,-SUM(T11:T51)) -> 677458.99 | V51: =IF(D51="Net Asset Value", U51, C51) -> -4923.1157
B52: 40237 | C52: -24316.109 | D52: Contribution | E52: =_xlfn.XLOOKUP(B52,'Share Price'!D:D,'Share Price'!E:E) -> 44.5749 | F52: =_xlfn.XLOOKUP(C3,'Share Price'!D:D,'Share Price'!E:E) -> 267.26 | G52: =F52/E52 -> 5.995751 | H52: =C52 * G52 -> -145793.33 | I52: =IF(D52="Net Asset Value",I51,-SUM(H11:H52)) -> 5743093.1 | J52: =IF(D52="Net Asset Value", I52, C52) -> -24316.109 | K52: =_xlfn.XLOOKUP(B52,'Share Price'!D:D,'Share Price'!F:F) -> 110.74 | L52: =_xlfn.XLOOKUP(C3,'Share Price'!D:D,'Share Price'!F:F) -> 357.18 | M52: =L52/K52 -> 3.2253928 | N52: =C52 * M52 -> -78429.003 | O52: =IF(D52="Net Asset Value",O51,-SUM(N11:N52)) -> 2700345.1 | P52: =IF(D52="Net Asset Value", O52, C52) -> -24316.109 | Q52: =_xlfn.XLOOKUP(B52,'Share Price'!D:D,'Share Price'!G:G) -> 164.12 | R52: =_xlfn.XLOOKUP(C3,'Share Price'!D:D,'Share Price'!G:G) -> 124.72 | S52: =R52/Q52 -> 0.75993176 | T52: =C52 * S52 -> -18478.583 | U52: =IF(D52="Net Asset Value",U51,-SUM(T11:T52)) -> 695937.57 | V52: =IF(D52="Net Asset Value", U52, C52) -> -24316.109
B53: 40268 | C53: -4478.5719 | D53: Contribution | E53: =_xlfn.XLOOKUP(B53,'Share Price'!D:D,'Share Price'!E:E) -> 47.9609 | F53: =_xlfn.XLOOKUP(C3,'Share Price'!D:D,'Share Price'!E:E) -> 267.26 | G53: =F53/E53 -> 5.5724559 | H53: =C53 * G53 -> -24956.644 | I53: =IF(D53="Net Asset Value",I52,-SUM(H11:H53)) -> 5768049.8 | J53: =IF(D53="Net Asset Value", I53, C53) -> -4478.5719 | K53: =_xlfn.XLOOKUP(B53,'Share Price'!D:D,'Share Price'!F:F) -> 117 | L53: =_xlfn.XLOOKUP(C3,'Share Price'!D:D,'Share Price'!F:F) -> 357.18 | M53: =L53/K53 -> 3.0528205 | N53: =C53 * M53 -> -13672.276 | O53: =IF(D53="Net Asset Value",O52,-SUM(N11:N53)) -> 2714017.4 | P53: =IF(D53="Net Asset Value", O53, C53) -> -4478.5719 | Q53: =_xlfn.XLOOKUP(B53,'Share Price'!D:D,'Share Price'!G:G) -> 168.52 | R53: =_xlfn.XLOOKUP(C3,'Share Price'!D:D,'Share Price'!G:G) -> 124.72 | S53: =R53/Q53 -> 0.7400902 | T53: =C53 * S53 -> -3314.5471 | U53: =IF(D53="Net Asset Value",U52,-SUM(T11:T53)) -> 699252.12 | V53: =IF(D53="Net Asset Value", U53, C53) -> -4478.5719
B54: 40298 | C54: -10950.645 | D54: Contribution | E54: =_xlfn.XLOOKUP(B54,'Share Price'!D:D,'Share Price'!E:E) -> 49.0339 | F54: =_xlfn.XLOOKUP(C3,'Share Price'!D:D,'Share Price'!E:E) -> 267.26 | G54: =F54/E54 -> 5.4505148 | H54: =C54 * G54 -> -59686.652 | I54: =IF(D54="Net Asset Value",I53,-SUM(H11:H54)) -> 5827736.4 | J54: =IF(D54="Net Asset Value", I54, C54) -> -10950.645 | K54: =_xlfn.XLOOKUP(B54,'Share Price'!D:D,'Share Price'!F:F) -> 118.8125 | L54: =_xlfn.XLOOKUP(C3,'Share Price'!D:D,'Share Price'!F:F) -> 357.18 | M54: =L54/K54 -> 3.0062493 | N54: =C54 * M54 -> -32920.369 | O54: =IF(D54="Net Asset Value",O53,-SUM(N11:N54)) -> 2746937.8 | P54: =IF(D54="Net Asset Value", O54, C54) -> -10950.645 | Q54: =_xlfn.XLOOKUP(B54,'Share Price'!D:D,'Share Price'!G:G) -> 178.72 | R54: =_xlfn.XLOOKUP(C3,'Share Price'!D:D,'Share Price'!G:G) -> 124.72 | S54: =R54/Q54 -> 0.69785139 | T54: =C54 * S54 -> -7641.9227 | U54: =IF(D54="Net Asset Value",U53,-SUM(T11:T54)) -> 706894.04 | V54: =IF(D54="Net Asset Value", U54, C54) -> -10950.645
B55: 40329 | C55: 151898.72 | D55: Distribution | E55: =_xlfn.XLOOKUP(B55,'Share Price'!D:D,'Share Price'!E:E) -> 45.4114 | F55: =_xlfn.XLOOKUP(C3,'Share Price'!D:D,'Share Price'!E:E) -> 267.26 | G55: =F55/E55 -> 5.8853063 | H55: =C55 * G55 -> 893970.48 | I55: =IF(D55="Net Asset Value",I54,-SUM(H11:H55)) -> 4933765.9 | J55: =IF(D55="Net Asset Value", I55, C55) -> 151898.72 | K55: =_xlfn.XLOOKUP(B55,'Share Price'!D:D,'Share Price'!F:F) -> 109.369 | L55: =_xlfn.XLOOKUP(C3,'Share Price'!D:D,'Share Price'!F:F) -> 357.18 | M55: =L55/K55 -> 3.2658249 | N55: =C55 * M55 -> 496074.61 | O55: =IF(D55="Net Asset Value",O54,-SUM(N11:N55)) -> 2250863.2 | P55: =IF(D55="Net Asset Value", O55, C55) -> 151898.72 | Q55: =_xlfn.XLOOKUP(B55,'Share Price'!D:D,'Share Price'!G:G) -> 163.88 | R55: =_xlfn.XLOOKUP(C3,'Share Price'!D:D,'Share Price'!G:G) -> 124.72 | S55: =R55/Q55 -> 0.76104467 | T55: =C55 * S55 -> 115601.71 | U55: =IF(D55="Net Asset Value",U54,-SUM(T11:T55)) -> 591292.33 | V55: =IF(D55="Net Asset Value", U55, C55) -> 151898.72
B56: 40359 | C56: 187890.76 | D56: Distribution | E56: =_xlfn.XLOOKUP(B56,'Share Price'!D:D,'Share Price'!E:E) -> 42.5334 | F56: =_xlfn.XLOOKUP(C3,'Share Price'!D:D,'Share Price'!E:E) -> 267.26 | G56: =F56/E56 -> 6.2835325 | H56: =C56 * G56 -> 1180617.7 | I56: =IF(D56="Net Asset Value",I55,-SUM(H11:H56)) -> 3753148.2 | J56: =IF(D56="Net Asset Value", I56, C56) -> 187890.76 | K56: =_xlfn.XLOOKUP(B56,'Share Price'!D:D,'Share Price'!F:F) -> 103.22 | L56: =_xlfn.XLOOKUP(C3,'Share Price'!D:D,'Share Price'!F:F) -> 357.18 | M56: =L56/K56 -> 3.4603759 | N56: =C56 * M56 -> 650172.67 | O56: =IF(D56="Net Asset Value",O55,-SUM(N11:N56)) -> 1600690.5 | P56: =IF(D56="Net Asset Value", O56, C56) -> 187890.76 | Q56: =_xlfn.XLOOKUP(B56,'Share Price'!D:D,'Share Price'!G:G) -> 155.96 | R56: =_xlfn.XLOOKUP(C3,'Share Price'!D:D,'Share Price'!G:G) -> 124.72 | S56: =R56/Q56 -> 0.79969223 | T56: =C56 * S56 -> 150254.78 | U56: =IF(D56="Net Asset Value",U55,-SUM(T11:T56)) -> 441037.55 | V56: =IF(D56="Net Asset Value", U56, C56) -> 187890.76
B57: 40390 | C57: -11939.367 | D57: Contribution | E57: =_xlfn.XLOOKUP(B57,'Share Price'!D:D,'Share Price'!E:E) -> 45.6206 | F57: =_xlfn.XLOOKUP(C3,'Share Price'!D:D,'Share Price'!E:E) -> 267.26 | G57: =F57/E57 -> 5.8583184 | H57: =C57 * G57 -> -69944.615 | I57: =IF(D57="Net Asset Value",I56,-SUM(H11:H57)) -> 3823092.8 | J57: =IF(D57="Net Asset Value", I57, C57) -> -11939.367 | K57: =_xlfn.XLOOKUP(B57,'Share Price'!D:D,'Share Price'!F:F) -> 110.27 | L57: =_xlfn.XLOOKUP(C3,'Share Price'!D:D,'Share Price'!F:F) -> 357.18 | M57: =L57/K57 -> 3.2391403 | N57: =C57 * M57 -> -38673.286 | O57: =IF(D57="Net Asset Value",O56,-SUM(N11:N57)) -> 1639363.8 | P57: =IF(D57="Net Asset Value", O57, C57) -> -11939.367 | Q57: =_xlfn.XLOOKUP(B57,'Share Price'!D:D,'Share Price'!G:G) -> 162.32 | R57: =_xlfn.XLOOKUP(C3,'Share Price'!D:D,'Share Price'!G:G) -> 124.72 | S57: =R57/Q57 -> 0.7683588 | T57: =C57 * S57 -> -9173.7179 | U57: =IF(D57="Net Asset Value",U56,-SUM(T11:T57)) -> 450211.27 | V57: =IF(D57="Net Asset Value", U57, C57) -> -11939.367
B58: 40421 | C58: 3563.9187 | D58: Distribution | E58: =_xlfn.XLOOKUP(B58,'Share Price'!D:D,'Share Price'!E:E) -> 43.2803 | F58: =_xlfn.XLOOKUP(C3,'Share Price'!D:D,'Share Price'!E:E) -> 267.26 | G58: =F58/E58 -> 6.1750958 | H58: =C58 * G58 -> 22007.539 | I58: =IF(D58="Net Asset Value",I57,-SUM(H11:H58)) -> 3801085.3 | J58: =IF(D58="Net Asset Value", I58, C58) -> 3563.9187 | K58: =_xlfn.XLOOKUP(B58,'Share Price'!D:D,'Share Price'!F:F) -> 105.31 | L58: =_xlfn.XLOOKUP(C3,'Share Price'!D:D,'Share Price'!F:F) -> 357.18 | M58: =L58/K58 -> 3.3917007 | N58: =C58 * M58 -> 12087.745 | O58: =IF(D58="Net Asset Value",O57,-SUM(N11:N58)) -> 1627276 | P58: =IF(D58="Net Asset Value", O58, C58) -> 3563.9187 | Q58: =_xlfn.XLOOKUP(B58,'Share Price'!D:D,'Share Price'!G:G) -> 154.08 | R58: =_xlfn.XLOOKUP(C3,'Share Price'!D:D,'Share Price'!G:G) -> 124.72 | S58: =R58/Q58 -> 0.80944964 | T58: =C58 * S58 -> 2884.8127 | U58: =IF(D58="Net Asset Value",U57,-SUM(T11:T58)) -> 447326.45 | V58: =IF(D58="Net Asset Value", U58, C58) -> 3563.9187
B59: 40451 | C59: -10857.242 | D59: Contribution | E59: =_xlfn.XLOOKUP(B59,'Share Price'!D:D,'Share Price'!E:E) -> 48.8671 | F59: =_xlfn.XLOOKUP(C3,'Share Price'!D:D,'Share Price'!E:E) -> 267.26 | G59: =F59/E59 -> 5.4691193 | H59: =C59 * G59 -> -59379.552 | I59: =IF(D59="Net Asset Value",I58,-SUM(H11:H59)) -> 3860464.8 | J59: =IF(D59="Net Asset Value", I59, C59) -> -10857.242 | K59: =_xlfn.XLOOKUP(B59,'Share Price'!D:D,'Share Price'!F:F) -> 114.13 | L59: =_xlfn.XLOOKUP(C3,'Share Price'!D:D,'Share Price'!F:F) -> 357.18 | M59: =L59/K59 -> 3.1295891 | N59: =C59 * M59 -> -33978.706 | O59: =IF(D59="Net Asset Value",O58,-SUM(N11:N59)) -> 1661254.7 | P59: =IF(D59="Net Asset Value", O59, C59) -> -10857.242 | Q59: =_xlfn.XLOOKUP(B59,'Share Price'!D:D,'Share Price'!G:G) -> 169.04 | R59: =_xlfn.XLOOKUP(C3,'Share Price'!D:D,'Share Price'!G:G) -> 124.72 | S59: =R59/Q59 -> 0.73781354 | T59: =C59 * S59 -> -8010.6201 | U59: =IF(D59="Net Asset Value",U58,-SUM(T11:T59)) -> 455337.07 | V59: =IF(D59="Net Asset Value", U59, C59) -> -10857.242
B60: 40482 | C60: -18569.467 | D60: Contribution | E60: =_xlfn.XLOOKUP(B60,'Share Price'!D:D,'Share Price'!E:E) -> 51.9642 | F60: =_xlfn.XLOOKUP(C3,'Share Price'!D:D,'Share Price'!E:E) -> 267.26 | G60: =F60/E60 -> 5.1431562 | H60: =C60 * G60 -> -95505.67 | I60: =IF(D60="Net Asset Value",I59,-SUM(H11:H60)) -> 3955970.5 | J60: =IF(D60="Net Asset Value", I60, C60) -> -18569.467 | K60: =_xlfn.XLOOKUP(B60,'Share Price'!D:D,'Share Price'!F:F) -> 118.49 | L60: =_xlfn.XLOOKUP(C3,'Share Price'!D:D,'Share Price'!F:F) -> 357.18 | M60: =L60/K60 -> 3.0144316 | N60: =C60 * M60 -> -55976.388 | O60: =IF(D60="Net Asset Value",O59,-SUM(N11:N60)) -> 1717231.1 | P60: =IF(D60="Net Asset Value", O60, C60) -> -18569.467 | Q60: =_xlfn.XLOOKUP(B60,'Share Price'!D:D,'Share Price'!G:G) -> 175.4 | R60: =_xlfn.XLOOKUP(C3,'Share Price'!D:D,'Share Price'!G:G) -> 124.72 | S60: =R60/Q60 -> 0.71106043 | T60: =C60 * S60 -> -13204.013 | U60: =IF(D60="Net Asset Value",U59,-SUM(T11:T60)) -> 468541.09 | V60: =IF(D60="Net Asset Value", U60, C60) -> -18569.467
B61: 40512 | C61: 983.91267 | D61: Distribution | E61: =_xlfn.XLOOKUP(B61,'Share Price'!D:D,'Share Price'!E:E) -> 51.8696 | F61: =_xlfn.XLOOKUP(C3,'Share Price'!D:D,'Share Price'!E:E) -> 267.26 | G61: =F61/E61 -> 5.1525364 | H61: =C61 * G61 -> 5069.6458 | I61: =IF(D61="Net Asset Value",I60,-SUM(H11:H61)) -> 3950900.9 | J61: =IF(D61="Net Asset Value", I61, C61) -> 983.91267 | K61: =_xlfn.XLOOKUP(B61,'Share Price'!D:D,'Share Price'!F:F) -> 118.4925 | L61: =_xlfn.XLOOKUP(C3,'Share Price'!D:D,'Share Price'!F:F) -> 357.18 | M61: =L61/K61 -> 3.014368 | N61: =C61 * M61 -> 2965.8749 | O61: =IF(D61="Net Asset Value",O60,-SUM(N11:N61)) -> 1714265.3 | P61: =IF(D61="Net Asset Value", O61, C61) -> 983.91267 | Q61: =_xlfn.XLOOKUP(B61,'Share Price'!D:D,'Share Price'!G:G) -> 192.96 | R61: =_xlfn.XLOOKUP(C3,'Share Price'!D:D,'Share Price'!G:G) -> 124.72 | S61: =R61/Q61 -> 0.64635158 | T61: =C61 * S61 -> 635.9535 | U61: =IF(D61="Net Asset Value",U60,-SUM(T11:T61)) -> 467905.13 | V61: =IF(D61="Net Asset Value", U61, C61) -> 983.91267
B62: 40543 | C62: 446817.92 | D62: Distribution | E62: =_xlfn.XLOOKUP(B62,'Share Price'!D:D,'Share Price'!E:E) -> 54.2348 | F62: =_xlfn.XLOOKUP(C3,'Share Price'!D:D,'Share Price'!E:E) -> 267.26 | G62: =F62/E62 -> 4.9278323 | H62: =C62 * G62 -> 2201843.8 | I62: =IF(D62="Net Asset Value",I61,-SUM(H11:H62)) -> 1749057.1 | J62: =IF(D62="Net Asset Value", I62, C62) -> 446817.92 | K62: =_xlfn.XLOOKUP(B62,'Share Price'!D:D,'Share Price'!F:F) -> 125.75 | L62: =_xlfn.XLOOKUP(C3,'Share Price'!D:D,'Share Price'!F:F) -> 357.18 | M62: =L62/K62 -> 2.8403976 | N62: =C62 * M62 -> 1269140.5 | O62: =IF(D62="Net Asset Value",O61,-SUM(N11:N62)) -> 445124.72 | P62: =IF(D62="Net Asset Value", O62, C62) -> 446817.92 | Q62: =_xlfn.XLOOKUP(B62,'Share Price'!D:D,'Share Price'!G:G) -> 211 | R62: =_xlfn.XLOOKUP(C3,'Share Price'!D:D,'Share Price'!G:G) -> 124.72 | S62: =R62/Q62 -> 0.59109005 | T62: =C62 * S62 -> 264109.62 | U62: =IF(D62="Net Asset Value",U61,-SUM(T11:T62)) -> 203795.51 | V62: =IF(D62="Net Asset Value", U62, C62) -> 446817.92
B63: 40574 | C63: -15461.941 | D63: Contribution | E63: =_xlfn.XLOOKUP(B63,'Share Price'!D:D,'Share Price'!E:E) -> 55.7684 | F63: =_xlfn.XLOOKUP(C3,'Share Price'!D:D,'Share Price'!E:E) -> 267.26 | G63: =F63/E63 -> 4.7923197 | H63: =C63 * G63 -> -74098.562 | I63: =IF(D63="Net Asset Value",I62,-SUM(H11:H63)) -> 1823155.7 | J63: =IF(D63="Net Asset Value", I63, C63) -> -15461.941 | K63: =_xlfn.XLOOKUP(B63,'Share Price'!D:D,'Share Price'!F:F) -> 128.68 | L63: =_xlfn.XLOOKUP(C3,'Share Price'!D:D,'Share Price'!F:F) -> 357.18 | M63: =L63/K63 -> 2.7757227 | N63: =C63 * M63 -> -42918.06 | O63: =IF(D63="Net Asset Value",O62,-SUM(N11:N63)) -> 488042.78 | P63: =IF(D63="Net Asset Value", O63, C63) -> -15461.941 | Q63: =_xlfn.XLOOKUP(B63,'Share Price'!D:D,'Share Price'!G:G) -> 227 | R63: =_xlfn.XLOOKUP(C3,'Share Price'!D:D,'Share Price'!G:G) -> 124.72 | S63: =R63/Q63 -> 0.54942731 | T63: =C63 * S63 -> -8495.2124 | U63: =IF(D63="Net Asset Value",U62,-SUM(T11:T63)) -> 212290.72 | V63: =IF(D63="Net Asset Value", U63, C63) -> -15461.941
B64: 40602 | C64: 16463.686 | D64: Distribution | E64: =_xlfn.XLOOKUP(B64,'Share Price'!D:D,'Share Price'!E:E) -> 57.53 | F64: =_xlfn.XLOOKUP(C3,'Share Price'!D:D,'Share Price'!E:E) -> 267.26 | G64: =F64/E64 -> 4.6455762 | H64: =C64 * G64 -> 76483.31 | I64: =IF(D64="Net Asset Value",I63,-SUM(H11:H64)) -> 1746672.3 | J64: =IF(D64="Net Asset Value", I64, C64) -> 16463.686 | K64: =_xlfn.XLOOKUP(B64,'Share Price'!D:D,'Share Price'!F:F) -> 133.15 | L64: =_xlfn.XLOOKUP(C3,'Share Price'!D:D,'Share Price'!F:F) -> 357.18 | M64: =L64/K64 -> 2.6825385 | N64: =C64 * M64 -> 44164.472 | O64: =IF(D64="Net Asset Value",O63,-SUM(N11:N64)) -> 443878.31 | P64: =IF(D64="Net Asset Value", O64, C64) -> 16463.686 | Q64: =_xlfn.XLOOKUP(B64,'Share Price'!D:D,'Share Price'!G:G) -> 246.76 | R64: =_xlfn.XLOOKUP(C3,'Share Price'!D:D,'Share Price'!G:G) -> 124.72 | S64: =R64/Q64 -> 0.50543038 | T64: =C64 * S64 -> 8321.2472 | U64: =IF(D64="Net Asset Value",U63,-SUM(T11:T64)) -> 203969.48 | V64: =IF(D64="Net Asset Value", U64, C64) -> 16463.686
B65: 40633 | C65: 45972.539 | D65: Distribution | E65: =_xlfn.XLOOKUP(B65,'Share Price'!D:D,'Share Price'!E:E) -> 57.1925 | F65: =_xlfn.XLOOKUP(C3,'Share Price'!D:D,'Share Price'!E:E) -> 267.26 | G65: =F65/E65 -> 4.6729903 | H65: =C65 * G65 -> 214829.23 | I65: =IF(D65="Net Asset Value",I64,-SUM(H11:H65)) -> 1531843.1 | J65: =IF(D65="Net Asset Value", I65, C65) -> 45972.539 | K65: =_xlfn.XLOOKUP(B65,'Share Price'!D:D,'Share Price'!F:F) -> 132.59 | L65: =_xlfn.XLOOKUP(C3,'Share Price'!D:D,'Share Price'!F:F) -> 357.18 | M65: =L65/K65 -> 2.6938683 | N65: =C65 * M65 -> 123843.97 | O65: =IF(D65="Net Asset Value",O64,-SUM(N11:N65)) -> 320034.34 | P65: =IF(D65="Net Asset Value", O65, C65) -> 45972.539 | Q65: =_xlfn.XLOOKUP(B65,'Share Price'!D:D,'Share Price'!G:G) -> 257.68 | R65: =_xlfn.XLOOKUP(C3,'Share Price'!D:D,'Share Price'!G:G) -> 124.72 | S65: =R65/Q65 -> 0.48401118 | T65: =C65 * S65 -> 22251.223 | U65: =IF(D65="Net Asset Value",U64,-SUM(T11:T65)) -> 181718.25 | V65: =IF(D65="Net Asset Value", U65, C65) -> 45972.539
B66: 40663 | C66: 9821.8844 | D66: Distribution | E66: =_xlfn.XLOOKUP(B66,'Share Price'!D:D,'Share Price'!E:E) -> 58.8357 | F66: =_xlfn.XLOOKUP(C3,'Share Price'!D:D,'Share Price'!E:E) -> 267.26 | G66: =F66/E66 -> 4.5424802 | H66: =C66 * G66 -> 44615.715 | I66: =IF(D66="Net Asset Value",I65,-SUM(H11:H66)) -> 1487227.4 | J66: =IF(D66="Net Asset Value", I66, C66) -> 9821.8844 | K66: =_xlfn.XLOOKUP(B66,'Share Price'!D:D,'Share Price'!F:F) -> 136.43 | L66: =_xlfn.XLOOKUP(C3,'Share Price'!D:D,'Share Price'!F:F) -> 357.18 | M66: =L66/K66 -> 2.6180459 | N66: =C66 * M66 -> 25714.144 | O66: =IF(D66="Net Asset Value",O65,-SUM(N11:N66)) -> 294320.2 | P66: =IF(D66="Net Asset Value", O66, C66) -> 9821.8844 | Q66: =_xlfn.XLOOKUP(B66,'Share Price'!D:D,'Share Price'!G:G) -> 254.88 | R66: =_xlfn.XLOOKUP(C3,'Share Price'!D:D,'Share Price'!G:G) -> 124.72 | S66: =R66/Q66 -> 0.48932831 | T66: =C66 * S66 -> 4806.1261 | U66: =IF(D66="Net Asset Value",U65,-SUM(T11:T66)) -> 176912.13 | V66: =IF(D66="Net Asset Value", U66, C66) -> 9821.8844
B67: 40694 | C67: 10154.563 | D67: Distribution | E67: =_xlfn.XLOOKUP(B67,'Share Price'!D:D,'Share Price'!E:E) -> 58.1187 | F67: =_xlfn.XLOOKUP(C3,'Share Price'!D:D,'Share Price'!E:E) -> 267.26 | G67: =F67/E67 -> 4.5985199 | H67: =C67 * G67 -> 46695.962 | I67: =IF(D67="Net Asset Value",I66,-SUM(H11:H67)) -> 1440531.4 | J67: =IF(D67="Net Asset Value", I67, C67) -> 10154.563 | K67: =_xlfn.XLOOKUP(B67,'Share Price'!D:D,'Share Price'!F:F) -> 134.9 | L67: =_xlfn.XLOOKUP(C3,'Share Price'!D:D,'Share Price'!F:F) -> 357.18 | M67: =L67/K67 -> 2.6477391 | N67: =C67 * M67 -> 26886.634 | O67: =IF(D67="Net Asset Value",O66,-SUM(N11:N67)) -> 267433.56 | P67: =IF(D67="Net Asset Value", O67, C67) -> 10154.563 | Q67: =_xlfn.XLOOKUP(B67,'Share Price'!D:D,'Share Price'!G:G) -> 243.6 | R67: =_xlfn.XLOOKUP(C3,'Share Price'!D:D,'Share Price'!G:G) -> 124.72 | S67: =R67/Q67 -> 0.51198686 | T67: =C67 * S67 -> 5199.003 | U67: =IF(D67="Net Asset Value",U66,-SUM(T11:T67)) -> 171713.12 | V67: =IF(D67="Net Asset Value", U67, C67) -> 10154.563
B68: 40724 | C68: 10339.933 | D68: Distribution | E68: =_xlfn.XLOOKUP(B68,'Share Price'!D:D,'Share Price'!E:E) -> 56.8141 | F68: =_xlfn.XLOOKUP(C3,'Share Price'!D:D,'Share Price'!E:E) -> 267.26 | G68: =F68/E68 -> 4.7041139 | H68: =C68 * G68 -> 48640.221 | I68: =IF(D68="Net Asset Value",I67,-SUM(H11:H68)) -> 1391891.2 | J68: =IF(D68="Net Asset Value", I68, C68) -> 10339.933 | K68: =_xlfn.XLOOKUP(B68,'Share Price'!D:D,'Share Price'!F:F) -> 131.97 | L68: =_xlfn.XLOOKUP(C3,'Share Price'!D:D,'Share Price'!F:F) -> 357.18 | M68: =L68/K68 -> 2.7065242 | N68: =C68 * M68 -> 27985.278 | O68: =IF(D68="Net Asset Value",O67,-SUM(N11:N68)) -> 239448.28 | P68: =IF(D68="Net Asset Value", O68, C68) -> 10339.933 | Q68: =_xlfn.XLOOKUP(B68,'Share Price'!D:D,'Share Price'!G:G) -> 235.12 | R68: =_xlfn.XLOOKUP(C3,'Share Price'!D:D,'Share Price'!G:G) -> 124.72 | S68: =R68/Q68 -> 0.53045253 | T68: =C68 * S68 -> 5484.8435 | U68: =IF(D68="Net Asset Value",U67,-SUM(T11:T68)) -> 166228.28 | V68: =IF(D68="Net Asset Value", U68, C68) -> 10339.933
B69: 40755 | C69: -6494.3255 | D69: Contribution | E69: =_xlfn.XLOOKUP(B69,'Share Price'!D:D,'Share Price'!E:E) -> 57.7602 | F69: =_xlfn.XLOOKUP(C3,'Share Price'!D:D,'Share Price'!E:E) -> 267.26 | G69: =F69/E69 -> 4.6270615 | H69: =C69 * G69 -> -30049.644 | I69: =IF(D69="Net Asset Value",I68,-SUM(H11:H69)) -> 1421940.9 | J69: =IF(D69="Net Asset Value", I69, C69) -> -6494.3255 | K69: =_xlfn.XLOOKUP(B69,'Share Price'!D:D,'Share Price'!F:F) -> 129.33 | L69: =_xlfn.XLOOKUP(C3,'Share Price'!D:D,'Share Price'!F:F) -> 357.18 | M69: =L69/K69 -> 2.7617722 | N69: =C69 * M69 -> -17935.848 | O69: =IF(D69="Net Asset Value",O68,-SUM(N11:N69)) -> 257384.13 | P69: =IF(D69="Net Asset Value", O69, C69) -> -6494.3255 | Q69: =_xlfn.XLOOKUP(B69,'Share Price'!D:D,'Share Price'!G:G) -> 248.8 | R69: =_xlfn.XLOOKUP(C3,'Share Price'!D:D,'Share Price'!G:G) -> 124.72 | S69: =R69/Q69 -> 0.50128617 | T69: =C69 * S69 -> -3255.5156 | U69: =IF(D69="Net Asset Value",U68,-SUM(T11:T69)) -> 169483.8 | V69: =IF(D69="Net Asset Value", U69, C69) -> -6494.3255
B70: 40786 | C70: 204495.09 | D70: Distribution | E70: =_xlfn.XLOOKUP(B70,'Share Price'!D:D,'Share Price'!E:E) -> 54.8323 | F70: =_xlfn.XLOOKUP(C3,'Share Price'!D:D,'Share Price'!E:E) -> 267.26 | G70: =F70/E70 -> 4.8741344 | H70: =C70 * G70 -> 996736.53 | I70: =IF(D70="Net Asset Value",I69,-SUM(H11:H70)) -> 425204.32 | J70: =IF(D70="Net Asset Value", I70, C70) -> 204495.09 | K70: =_xlfn.XLOOKUP(B70,'Share Price'!D:D,'Share Price'!F:F) -> 122.22 | L70: =_xlfn.XLOOKUP(C3,'Share Price'!D:D,'Share Price'!F:F) -> 357.18 | M70: =L70/K70 -> 2.922435 | N70: =C70 * M70 -> 597623.59 | O70: =IF(D70="Net Asset Value",O69,-SUM(N11:N70)) -> -340239.46 | P70: =IF(D70="Net Asset Value", O70, C70) -> 204495.09 | Q70: =_xlfn.XLOOKUP(B70,'Share Price'!D:D,'Share Price'!G:G) -> 214.68 | R70: =_xlfn.XLOOKUP(C3,'Share Price'!D:D,'Share Price'!G:G) -> 124.72 | S70: =R70/Q70 -> 0.5809577 | T70: =C70 * S70 -> 118803 | U70: =IF(D70="Net Asset Value",U69,-SUM(T11:T70)) -> 50680.8 | V70: =IF(D70="Net Asset Value", U70, C70) -> 204495.09
B71: 40816 | C71: -5381.1757 | D71: Contribution | E71: =_xlfn.XLOOKUP(B71,'Share Price'!D:D,'Share Price'!E:E) -> 52.273 | F71: =_xlfn.XLOOKUP(C3,'Share Price'!D:D,'Share Price'!E:E) -> 267.26 | G71: =F71/E71 -> 5.1127733 | H71: =C71 * G71 -> -27512.732 | I71: =IF(D71="Net Asset Value",I70,-SUM(H11:H71)) -> 452717.06 | J71: =IF(D71="Net Asset Value", I71, C71) -> -5381.1757 | K71: =_xlfn.XLOOKUP(B71,'Share Price'!D:D,'Share Price'!F:F) -> 113.15 | L71: =_xlfn.XLOOKUP(C3,'Share Price'!D:D,'Share Price'!F:F) -> 357.18 | M71: =L71/K71 -> 3.1566947 | N71: =C71 * M71 -> -16986.729 | O71: =IF(D71="Net Asset Value",O70,-SUM(N11:N71)) -> -323252.73 | P71: =IF(D71="Net Asset Value", O71, C71) -> -5381.1757 | Q71: =_xlfn.XLOOKUP(B71,'Share Price'!D:D,'Share Price'!G:G) -> 171.44 | R71: =_xlfn.XLOOKUP(C3,'Share Price'!D:D,'Share Price'!G:G) -> 124.72 | S71: =R71/Q71 -> 0.72748483 | T71: =C71 * S71 -> -3914.7237 | U71: =IF(D71="Net Asset Value",U70,-SUM(T11:T71)) -> 54595.524 | V71: =IF(D71="Net Asset Value", U71, C71) -> -5381.1757
B72: 40847 | C72: 16.87882 | D72: Distribution | E72: =_xlfn.XLOOKUP(B72,'Share Price'!D:D,'Share Price'!E:E) -> 57.7104 | F72: =_xlfn.XLOOKUP(C3,'Share Price'!D:D,'Share Price'!E:E) -> 267.26 | G72: =F72/E72 -> 4.6310544 | H72: =C72 * G72 -> 78.166733 | I72: =IF(D72="Net Asset Value",I71,-SUM(H11:H72)) -> 452638.89 | J72: =IF(D72="Net Asset Value", I72, C72) -> 16.87882 | K72: =_xlfn.XLOOKUP(B72,'Share Price'!D:D,'Share Price'!F:F) -> 125.5 | L72: =_xlfn.XLOOKUP(C3,'Share Price'!D:D,'Share Price'!F:F) -> 357.18 | M72: =L72/K72 -> 2.8460558 | N72: =C72 * M72 -> 48.038063 | O72: =IF(D72="Net Asset Value",O71,-SUM(N11:N72)) -> -323300.77 | P72: =IF(D72="Net Asset Value", O72, C72) -> 16.87882 | Q72: =_xlfn.XLOOKUP(B72,'Share Price'!D:D,'Share Price'!G:G) -> 215.4 | R72: =_xlfn.XLOOKUP(C3,'Share Price'!D:D,'Share Price'!G:G) -> 124.72 | S72: =R72/Q72 -> 0.57901578 | T72: =C72 * S72 -> 9.7731032 | U72: =IF(D72="Net Asset Value",U71,-SUM(T11:T72)) -> 54585.75 | V72: =IF(D72="Net Asset Value", U72, C72) -> 16.87882
B73: 40877 | C73: 88482.719 | D73: Distribution | E73: =_xlfn.XLOOKUP(B73,'Share Price'!D:D,'Share Price'!E:E) -> 56.1568 | F73: =_xlfn.XLOOKUP(C3,'Share Price'!D:D,'Share Price'!E:E) -> 267.26 | G73: =F73/E73 -> 4.7591743 | H73: =C73 * G73 -> 421104.68 | I73: =IF(D73="Net Asset Value",I72,-SUM(H11:H73)) -> 31534.207 | J73: =IF(D73="Net Asset Value", I73, C73) -> 88482.719 | K73: =_xlfn.XLOOKUP(B73,'Share Price'!D:D,'Share Price'!F:F) -> 124.99 | L73: =_xlfn.XLOOKUP(C3,'Share Price'!D:D,'Share Price'!F:F) -> 357.18 | M73: =L73/K73 -> 2.8576686 | N73: =C73 * M73 -> 252854.29 | O73: =IF(D73="Net Asset Value",O72,-SUM(N11:N73)) -> -576155.05 | P73: =IF(D73="Net Asset Value", O73, C73) -> 88482.719 | Q73: =_xlfn.XLOOKUP(B73,'Share Price'!D:D,'Share Price'!G:G) -> 220.68 | R73: =_xlfn.XLOOKUP(C3,'Share Price'!D:D,'Share Price'!G:G) -> 124.72 | S73: =R73/Q73 -> 0.56516223 | T73: =C73 * S73 -> 50007.09 | U73: =IF(D73="Net Asset Value",U72,-SUM(T11:T73)) -> 4578.6601 | V73: =IF(D73="Net Asset Value", U73, C73) -> 88482.719
B74: 40908 | C74: 203878.96 | D74: Distribution | E74: =_xlfn.XLOOKUP(B74,'Share Price'!D:D,'Share Price'!E:E) -> 55.5991 | F74: =_xlfn.XLOOKUP(C3,'Share Price'!D:D,'Share Price'!E:E) -> 267.26 | G74: =F74/E74 -> 4.8069123 | H74: =C74 * G74 -> 980028.29 | I74: =IF(D74="Net Asset Value",I73,-SUM(H11:H74)) -> -948494.08 | J74: =IF(D74="Net Asset Value", I74, C74) -> 203878.96 | K74: =_xlfn.XLOOKUP(B74,'Share Price'!D:D,'Share Price'!F:F) -> 125.5 | L74: =_xlfn.XLOOKUP(C3,'Share Price'!D:D,'Share Price'!F:F) -> 357.18 | M74: =L74/K74 -> 2.8460558 | N74: =C74 * M74 -> 580250.89 | O74: =IF(D74="Net Asset Value",O73,-SUM(N11:N74)) -> -1156405.9 | P74: =IF(D74="Net Asset Value", O74, C74) -> 203878.96 | Q74: =_xlfn.XLOOKUP(B74,'Share Price'!D:D,'Share Price'!G:G) -> 210.76 | R74: =_xlfn.XLOOKUP(C3,'Share Price'!D:D,'Share Price'!G:G) -> 124.72 | S74: =R74/Q74 -> 0.59176314 | T74: =C74 * S74 -> 120648.05 | U74: =IF(D74="Net Asset Value",U73,-SUM(T11:T74)) -> -116069.39 | V74: =IF(D74="Net Asset Value", U74, C74) -> 203878.96
B75: 40939 | C75: -19632 | D75: Contribution | E75: =_xlfn.XLOOKUP(B75,'Share Price'!D:D,'Share Price'!E:E) -> 60.2797 | F75: =_xlfn.XLOOKUP(C3,'Share Price'!D:D,'Share Price'!E:E) -> 267.26 | G75: =F75/E75 -> 4.4336651 | H75: =C75 * G75 -> -87041.713 | I75: =IF(D75="Net Asset Value",I74,-SUM(H11:H75)) -> -861452.37 | J75: =IF(D75="Net Asset Value", I75, C75) -> -19632 | K75: =_xlfn.XLOOKUP(B75,'Share Price'!D:D,'Share Price'!F:F) -> 131.32 | L75: =_xlfn.XLOOKUP(C3,'Share Price'!D:D,'Share Price'!F:F) -> 357.18 | M75: =L75/K75 -> 2.7199208 | N75: =C75 * M75 -> -53397.485 | O75: =IF(D75="Net Asset Value",O74,-SUM(N11:N75)) -> -1103008.5 | P75: =IF(D75="Net Asset Value", O75, C75) -> -19632 | Q75: =_xlfn.XLOOKUP(B75,'Share Price'!D:D,'Share Price'!G:G) -> 218.32 | R75: =_xlfn.XLOOKUP(C3,'Share Price'!D:D,'Share Price'!G:G) -> 124.72 | S75: =R75/Q75 -> 0.57127153 | T75: =C75 * S75 -> -11215.203 | U75: =IF(D75="Net Asset Value",U74,-SUM(T11:T75)) -> -104854.19 | V75: =IF(D75="Net Asset Value", U75, C75) -> -19632
B76: 40968 | C76: 135995.08 | D76: Distribution | E76: =_xlfn.XLOOKUP(B76,'Share Price'!D:D,'Share Price'!E:E) -> 64.1437 | F76: =_xlfn.XLOOKUP(C3,'Share Price'!D:D,'Share Price'!E:E) -> 267.26 | G76: =F76/E76 -> 4.1665822 | H76: =C76 * G76 -> 566634.7 | I76: =IF(D76="Net Asset Value",I75,-SUM(H11:H76)) -> -1428087.1 | J76: =IF(D76="Net Asset Value", I76, C76) -> 135995.08 | K76: =_xlfn.XLOOKUP(B76,'Share Price'!D:D,'Share Price'!F:F) -> 137.02 | L76: =_xlfn.XLOOKUP(C3,'Share Price'!D:D,'Share Price'!F:F) -> 357.18 | M76: =L76/K76 -> 2.6067727 | N76: =C76 * M76 -> 354508.28 | O76: =IF(D76="Net Asset Value",O75,-SUM(N11:N76)) -> -1457516.7 | P76: =IF(D76="Net Asset Value", O76, C76) -> 135995.08 | Q76: =_xlfn.XLOOKUP(B76,'Share Price'!D:D,'Share Price'!G:G) -> 237.28 | R76: =_xlfn.XLOOKUP(C3,'Share Price'!D:D,'Share Price'!G:G) -> 124.72 | S76: =R76/Q76 -> 0.52562374 | T76: =C76 * S76 -> 71482.244 | U76: =IF(D76="Net Asset Value",U75,-SUM(T11:T76)) -> -176336.44 | V76: =IF(D76="Net Asset Value", U76, C76) -> 135995.08
B77: 40999 | C77: 7676.2463 | D77: Distribution | E77: =_xlfn.XLOOKUP(B77,'Share Price'!D:D,'Share Price'!E:E) -> 67.2707 | F77: =_xlfn.XLOOKUP(C3,'Share Price'!D:D,'Share Price'!E:E) -> 267.26 | G77: =F77/E77 -> 3.9729035 | H77: =C77 * G77 -> 30496.986 | I77: =IF(D77="Net Asset Value",I76,-SUM(H11:H77)) -> -1458584.1 | J77: =IF(D77="Net Asset Value", I77, C77) -> 7676.2463 | K77: =_xlfn.XLOOKUP(B77,'Share Price'!D:D,'Share Price'!F:F) -> 140.81 | L77: =_xlfn.XLOOKUP(C3,'Share Price'!D:D,'Share Price'!F:F) -> 357.18 | M77: =L77/K77 -> 2.5366096 | N77: =C77 * M77 -> 19471.64 | O77: =IF(D77="Net Asset Value",O76,-SUM(N11:N77)) -> -1476988.4 | P77: =IF(D77="Net Asset Value", O77, C77) -> 7676.2463 | Q77: =_xlfn.XLOOKUP(B77,'Share Price'!D:D,'Share Price'!G:G) -> 227.64 | R77: =_xlfn.XLOOKUP(C3,'Share Price'!D:D,'Share Price'!G:G) -> 124.72 | S77: =R77/Q77 -> 0.54788262 | T77: =C77 * S77 -> 4205.6819 | U77: =IF(D77="Net Asset Value",U76,-SUM(T11:T77)) -> -180542.12 | V77: =IF(D77="Net Asset Value", U77, C77) -> 7676.2463
B78: 41029 | C78: 332309.18 | D78: Distribution | E78: =_xlfn.XLOOKUP(B78,'Share Price'!D:D,'Share Price'!E:E) -> 66.4839 | F78: =_xlfn.XLOOKUP(C3,'Share Price'!D:D,'Share Price'!E:E) -> 267.26 | G78: =F78/E78 -> 4.0199206 | H78: =C78 * G78 -> 1335856.5 | I78: =IF(D78="Net Asset Value",I77,-SUM(H11:H78)) -> -2794440.6 | J78: =IF(D78="Net Asset Value", I78, C78) -> 332309.18 | K78: =_xlfn.XLOOKUP(B78,'Share Price'!D:D,'Share Price'!F:F) -> 139.87 | L78: =_xlfn.XLOOKUP(C3,'Share Price'!D:D,'Share Price'!F:F) -> 357.18 | M78: =L78/K78 -> 2.553657 | N78: =C78 * M78 -> 848603.65 | O78: =IF(D78="Net Asset Value",O77,-SUM(N11:N78)) -> -2325592 | P78: =IF(D78="Net Asset Value", O78, C78) -> 332309.18 | Q78: =_xlfn.XLOOKUP(B78,'Share Price'!D:D,'Share Price'!G:G) -> 225.48 | R78: =_xlfn.XLOOKUP(C3,'Share Price'!D:D,'Share Price'!G:G) -> 124.72 | S78: =R78/Q78 -> 0.5531311 | T78: =C78 * S78 -> 183810.54 | U78: =IF(D78="Net Asset Value",U77,-SUM(T11:T78)) -> -364352.66 | V78: =IF(D78="Net Asset Value", U78, C78) -> 332309.18
B79: 41060 | C79: -19528.388 | D79: Contribution | E79: =_xlfn.XLOOKUP(B79,'Share Price'!D:D,'Share Price'!E:E) -> 61.8034 | F79: =_xlfn.XLOOKUP(C3,'Share Price'!D:D,'Share Price'!E:E) -> 267.26 | G79: =F79/E79 -> 4.3243576 | H79: =C79 * G79 -> -84447.73 | I79: =IF(D79="Net Asset Value",I78,-SUM(H11:H79)) -> -2709992.8 | J79: =IF(D79="Net Asset Value", I79, C79) -> -19528.388 | K79: =_xlfn.XLOOKUP(B79,'Share Price'!D:D,'Share Price'!F:F) -> 131.47 | L79: =_xlfn.XLOOKUP(C3,'Share Price'!D:D,'Share Price'!F:F) -> 357.18 | M79: =L79/K79 -> 2.7168175 | N79: =C79 * M79 -> -53055.065 | O79: =IF(D79="Net Asset Value",O78,-SUM(N11:N79)) -> -2272537 | P79: =IF(D79="Net Asset Value", O79, C79) -> -19528.388 | Q79: =_xlfn.XLOOKUP(B79,'Share Price'!D:D,'Share Price'!G:G) -> 191.72 | R79: =_xlfn.XLOOKUP(C3,'Share Price'!D:D,'Share Price'!G:G) -> 124.72 | S79: =R79/Q79 -> 0.65053203 | T79: =C79 * S79 -> -12703.841 | U79: =IF(D79="Net Asset Value",U78,-SUM(T11:T79)) -> -351648.82 | V79: =IF(D79="Net Asset Value", U79, C79) -> -19528.388
B80: 41090 | C80: 3459.1854 | D80: Distribution | E80: =_xlfn.XLOOKUP(B80,'Share Price'!D:D,'Share Price'!E:E) -> 63.8947 | F80: =_xlfn.XLOOKUP(C3,'Share Price'!D:D,'Share Price'!E:E) -> 267.26 | G80: =F80/E80 -> 4.1828195 | H80: =C80 * G80 -> 14469.148 | I80: =IF(D80="Net Asset Value",I79,-SUM(H11:H80)) -> -2724462 | J80: =IF(D80="Net Asset Value", I80, C80) -> 3459.1854 | K80: =_xlfn.XLOOKUP(B80,'Share Price'!D:D,'Share Price'!F:F) -> 136.105 | L80: =_xlfn.XLOOKUP(C3,'Share Price'!D:D,'Share Price'!F:F) -> 357.18 | M80: =L80/K80 -> 2.6242974 | N80: =C80 * M80 -> 9077.9312 | O80: =IF(D80="Net Asset Value",O79,-SUM(N11:N80)) -> -2281614.9 | P80: =IF(D80="Net Asset Value", O80, C80) -> 3459.1854 | Q80: =_xlfn.XLOOKUP(B80,'Share Price'!D:D,'Share Price'!G:G) -> 201.6 | R80: =_xlfn.XLOOKUP(C3,'Share Price'!D:D,'Share Price'!G:G) -> 124.72 | S80: =R80/Q80 -> 0.61865079 | T80: =C80 * S80 -> 2140.0278 | U80: =IF(D80="Net Asset Value",U79,-SUM(T11:T80)) -> -353788.84 | V80: =IF(D80="Net Asset Value", U80, C80) -> 3459.1854
B81: 41121 | C81: 494.93602 | D81: Distribution | E81: =_xlfn.XLOOKUP(B81,'Share Price'!D:D,'Share Price'!E:E) -> 64.5321 | F81: =_xlfn.XLOOKUP(C3,'Share Price'!D:D,'Share Price'!E:E) -> 267.26 | G81: =F81/E81 -> 4.1415048 | H81: =C81 * G81 -> 2049.7799 | I81: =IF(D81="Net Asset Value",I80,-SUM(H11:H81)) -> -2726511.8 | J81: =IF(D81="Net Asset Value", I81, C81) -> 494.93602 | K81: =_xlfn.XLOOKUP(B81,'Share Price'!D:D,'Share Price'!F:F) -> 137.71 | L81: =_xlfn.XLOOKUP(C3,'Share Price'!D:D,'Share Price'!F:F) -> 357.18 | M81: =L81/K81 -> 2.5937114 | N81: =C81 * M81 -> 1283.7212 | O81: =IF(D81="Net Asset Value",O80,-SUM(N11:N81)) -> -2282898.6 | P81: =IF(D81="Net Asset Value", O81, C81) -> 494.93602 | Q81: =_xlfn.XLOOKUP(B81,'Share Price'!D:D,'Share Price'!G:G) -> 204.92 | R81: =_xlfn.XLOOKUP(C3,'Share Price'!D:D,'Share Price'!G:G) -> 124.72 | S81: =R81/Q81 -> 0.60862776 | T81: =C81 * S81 -> 301.2318 | U81: =IF(D81="Net Asset Value",U80,-SUM(T11:T81)) -> -354090.08 | V81: =IF(D81="Net Asset Value", U81, C81) -> 494.93602
B82: 41152 | C82: 97143.606 | D82: Distribution | E82: =_xlfn.XLOOKUP(B82,'Share Price'!D:D,'Share Price'!E:E) -> 67.8782 | F82: =_xlfn.XLOOKUP(C3,'Share Price'!D:D,'Share Price'!E:E) -> 267.26 | G82: =F82/E82 -> 3.9373466 | H82: =C82 * G82 -> 382488.05 | I82: =IF(D82="Net Asset Value",I81,-SUM(H11:H82)) -> -3108999.8 | J82: =IF(D82="Net Asset Value", I82, C82) -> 97143.606 | K82: =_xlfn.XLOOKUP(B82,'Share Price'!D:D,'Share Price'!F:F) -> 141.16 | L82: =_xlfn.XLOOKUP(C3,'Share Price'!D:D,'Share Price'!F:F) -> 357.18 | M82: =L82/K82 -> 2.5303202 | N82: =C82 * M82 -> 245804.43 | O82: =IF(D82="Net Asset Value",O81,-SUM(N11:N82)) -> -2528703 | P82: =IF(D82="Net Asset Value", O82, C82) -> 97143.606 | Q82: =_xlfn.XLOOKUP(B82,'Share Price'!D:D,'Share Price'!G:G) -> 210.96 | R82: =_xlfn.XLOOKUP(C3,'Share Price'!D:D,'Share Price'!G:G) -> 124.72 | S82: =R82/Q82 -> 0.59120212 | T82: =C82 * S82 -> 57431.506 | U82: =IF(D82="Net Asset Value",U81,-SUM(T11:T82)) -> -411521.58 | V82: =IF(D82="Net Asset Value", U82, C82) -> 97143.606
B83: 41182 | C83: 5125.1181 | D83: Distribution | E83: =_xlfn.XLOOKUP(B83,'Share Price'!D:D,'Share Price'!E:E) -> 68.2865 | F83: =_xlfn.XLOOKUP(C3,'Share Price'!D:D,'Share Price'!E:E) -> 267.26 | G83: =F83/E83 -> 3.9138043 | H83: =C83 * G83 -> 20058.709 | I83: =IF(D83="Net Asset Value",I82,-SUM(H11:H83)) -> -3129058.5 | J83: =IF(D83="Net Asset Value", I83, C83) -> 5125.1181 | K83: =_xlfn.XLOOKUP(B83,'Share Price'!D:D,'Share Price'!F:F) -> 143.97 | L83: =_xlfn.XLOOKUP(C3,'Share Price'!D:D,'Share Price'!F:F) -> 357.18 | M83: =L83/K83 -> 2.4809335 | N83: =C83 * M83 -> 12715.077 | O83: =IF(D83="Net Asset Value",O82,-SUM(N11:N83)) -> -2541418.1 | P83: =IF(D83="Net Asset Value", O83, C83) -> 5125.1181 | Q83: =_xlfn.XLOOKUP(B83,'Share Price'!D:D,'Share Price'!G:G) -> 222.76 | R83: =_xlfn.XLOOKUP(C3,'Share Price'!D:D,'Share Price'!G:G) -> 124.72 | S83: =R83/Q83 -> 0.55988508 | T83: =C83 * S83 -> 2869.4771 | U83: =IF(D83="Net Asset Value",U82,-SUM(T11:T83)) -> -414391.06 | V83: =IF(D83="Net Asset Value", U83, C83) -> 5125.1181
B84: 41213 | C84: 10984.439 | D84: Distribution | E84: =_xlfn.XLOOKUP(B84,'Share Price'!D:D,'Share Price'!E:E) -> 64.6814 | F84: =_xlfn.XLOOKUP(C3,'Share Price'!D:D,'Share Price'!E:E) -> 267.26 | G84: =F84/E84 -> 4.1319452 | H84: =C84 * G84 -> 45387.101 | I84: =IF(D84="Net Asset Value",I83,-SUM(H11:H84)) -> -3174445.6 | J84: =IF(D84="Net Asset Value", I84, C84) -> 10984.439 | K84: =_xlfn.XLOOKUP(B84,'Share Price'!D:D,'Share Price'!F:F) -> 141.35 | L84: =_xlfn.XLOOKUP(C3,'Share Price'!D:D,'Share Price'!F:F) -> 357.18 | M84: =L84/K84 -> 2.526919 | N84: =C84 * M84 -> 27756.788 | O84: =IF(D84="Net Asset Value",O83,-SUM(N11:N84)) -> -2569174.9 | P84: =IF(D84="Net Asset Value", O84, C84) -> 10984.439 | Q84: =_xlfn.XLOOKUP(B84,'Share Price'!D:D,'Share Price'!G:G) -> 215.08 | R84: =_xlfn.XLOOKUP(C3,'Share Price'!D:D,'Share Price'!G:G) -> 124.72 | S84: =R84/Q84 -> 0.57987725 | T84: =C84 * S84 -> 6369.6265 | U84: =IF(D84="Net Asset Value",U83,-SUM(T11:T84)) -> -420760.69 | V84: =IF(D84="Net Asset Value", U84, C84) -> 10984.439
B85: 41243 | C85: 8254.7023 | D85: Distribution | E85: =_xlfn.XLOOKUP(B85,'Share Price'!D:D,'Share Price'!E:E) -> 65.5279 | F85: =_xlfn.XLOOKUP(C3,'Share Price'!D:D,'Share Price'!E:E) -> 267.26 | G85: =F85/E85 -> 4.0785681 | H85: =C85 * G85 -> 33667.365 | I85: =IF(D85="Net Asset Value",I84,-SUM(H11:H85)) -> -3208113 | J85: =IF(D85="Net Asset Value", I85, C85) -> 8254.7023 | K85: =_xlfn.XLOOKUP(B85,'Share Price'!D:D,'Share Price'!F:F) -> 142.155 | L85: =_xlfn.XLOOKUP(C3,'Share Price'!D:D,'Share Price'!F:F) -> 357.18 | M85: =L85/K85 -> 2.5126095 | N85: =C85 * M85 -> 20740.843 | O85: =IF(D85="Net Asset Value",O84,-SUM(N11:N85)) -> -2589915.7 | P85: =IF(D85="Net Asset Value", O85, C85) -> 8254.7023 | Q85: =_xlfn.XLOOKUP(B85,'Share Price'!D:D,'Share Price'!G:G) -> 212.04 | R85: =_xlfn.XLOOKUP(C3,'Share Price'!D:D,'Share Price'!G:G) -> 124.72 | S85: =R85/Q85 -> 0.58819091 | T85: =C85 * S85 -> 4855.3408 | U85: =IF(D85="Net Asset Value",U84,-SUM(T11:T85)) -> -425616.03 | V85: =IF(D85="Net Asset Value", U85, C85) -> 8254.7023
B86: 41274 | C86: 224839.18 | D86: Distribution | E86: =_xlfn.XLOOKUP(B86,'Share Price'!D:D,'Share Price'!E:E) -> 64.8608 | F86: =_xlfn.XLOOKUP(C3,'Share Price'!D:D,'Share Price'!E:E) -> 267.26 | G86: =F86/E86 -> 4.1205166 | H86: =C86 * G86 -> 926453.55 | I86: =IF(D86="Net Asset Value",I85,-SUM(H11:H86)) -> -4134566.5 | J86: =IF(D86="Net Asset Value", I86, C86) -> 224839.18 | K86: =_xlfn.XLOOKUP(B86,'Share Price'!D:D,'Share Price'!F:F) -> 142.41 | L86: =_xlfn.XLOOKUP(C3,'Share Price'!D:D,'Share Price'!F:F) -> 357.18 | M86: =L86/K86 -> 2.5081104 | N86: =C86 * M86 -> 563921.48 | O86: =IF(D86="Net Asset Value",O85,-SUM(N11:N86)) -> -3153837.2 | P86: =IF(D86="Net Asset Value", O86, C86) -> 224839.18 | Q86: =_xlfn.XLOOKUP(B86,'Share Price'!D:D,'Share Price'!G:G) -> 216.32 | R86: =_xlfn.XLOOKUP(C3,'Share Price'!D:D,'Share Price'!G:G) -> 124.72 | S86: =R86/Q86 -> 0.57655325 | T86: =C86 * S86 -> 129631.76 | U86: =IF(D86="Net Asset Value",U85,-SUM(T11:T86)) -> -555247.79 | V86: =IF(D86="Net Asset Value", U86, C86) -> 224839.18
B87: 41305 | C87: 2125.87 | D87: Distribution | E87: =_xlfn.XLOOKUP(B87,'Share Price'!D:D,'Share Price'!E:E) -> 66.5935 | F87: =_xlfn.XLOOKUP(C3,'Share Price'!D:D,'Share Price'!E:E) -> 267.26 | G87: =F87/E87 -> 4.0133046 | H87: =C87 * G87 -> 8531.7639 | I87: =IF(D87="Net Asset Value",I86,-SUM(H11:H87)) -> -4143098.3 | J87: =IF(D87="Net Asset Value", I87, C87) -> 2125.87 | K87: =_xlfn.XLOOKUP(B87,'Share Price'!D:D,'Share Price'!F:F) -> 149.7 | L87: =_xlfn.XLOOKUP(C3,'Share Price'!D:D,'Share Price'!F:F) -> 357.18 | M87: =L87/K87 -> 2.3859719 | N87: =C87 * M87 -> 5072.2662 | O87: =IF(D87="Net Asset Value",O86,-SUM(N11:N87)) -> -3158909.5 | P87: =IF(D87="Net Asset Value", O87, C87) -> 2125.87 | Q87: =_xlfn.XLOOKUP(B87,'Share Price'!D:D,'Share Price'!G:G) -> 232.4 | R87: =_xlfn.XLOOKUP(C3,'Share Price'!D:D,'Share Price'!G:G) -> 124.72 | S87: =R87/Q87 -> 0.53666093 | T87: =C87 * S87 -> 1140.8714 | U87: =IF(D87="Net Asset Value",U86,-SUM(T11:T87)) -> -556388.66 | V87: =IF(D87="Net Asset Value", U87, C87) -> 2125.87
B88: 41333 | C88: 10457.176 | D88: Distribution | E88: =_xlfn.XLOOKUP(B88,'Share Price'!D:D,'Share Price'!E:E) -> 66.8225 | F88: =_xlfn.XLOOKUP(C3,'Share Price'!D:D,'Share Price'!E:E) -> 267.26 | G88: =F88/E88 -> 3.999551 | H88: =C88 * G88 -> 41824.008 | I88: =IF(D88="Net Asset Value",I87,-SUM(H11:H88)) -> -4184922.3 | J88: =IF(D88="Net Asset Value", I88, C88) -> 10457.176 | K88: =_xlfn.XLOOKUP(B88,'Share Price'!D:D,'Share Price'!F:F) -> 151.61 | L88: =_xlfn.XLOOKUP(C3,'Share Price'!D:D,'Share Price'!F:F) -> 357.18 | M88: =L88/K88 -> 2.3559132 | N88: =C88 * M88 -> 24636.198 | O88: =IF(D88="Net Asset Value",O87,-SUM(N11:N88)) -> -3183545.7 | P88: =IF(D88="Net Asset Value", O88, C88) -> 10457.176 | Q88: =_xlfn.XLOOKUP(B88,'Share Price'!D:D,'Share Price'!G:G) -> 231.88 | R88: =_xlfn.XLOOKUP(C3,'Share Price'!D:D,'Share Price'!G:G) -> 124.72 | S88: =R88/Q88 -> 0.53786441 | T88: =C88 * S88 -> 5624.5426 | U88: =IF(D88="Net Asset Value",U87,-SUM(T11:T88)) -> -562013.2 | V88: =IF(D88="Net Asset Value", U88, C88) -> 10457.176
B89: 41364 | C89: -827.8125 | D89: Contribution | E89: =_xlfn.XLOOKUP(B89,'Share Price'!D:D,'Share Price'!E:E) -> 68.6848 | F89: =_xlfn.XLOOKUP(C3,'Share Price'!D:D,'Share Price'!E:E) -> 267.26 | G89: =F89/E89 -> 3.8911084 | H89: =C89 * G89 -> -3221.1081 | I89: =IF(D89="Net Asset Value",I88,-SUM(H11:H89)) -> -4181701.2 | J89: =IF(D89="Net Asset Value", I89, C89) -> -827.8125 | K89: =_xlfn.XLOOKUP(B89,'Share Price'!D:D,'Share Price'!F:F) -> 156.67 | L89: =_xlfn.XLOOKUP(C3,'Share Price'!D:D,'Share Price'!F:F) -> 357.18 | M89: =L89/K89 -> 2.2798238 | N89: =C89 * M89 -> -1887.2667 | O89: =IF(D89="Net Asset Value",O88,-SUM(N11:N89)) -> -3181658.4 | P89: =IF(D89="Net Asset Value", O89, C89) -> -827.8125 | Q89: =_xlfn.XLOOKUP(B89,'Share Price'!D:D,'Share Price'!G:G) -> 241.96 | R89: =_xlfn.XLOOKUP(C3,'Share Price'!D:D,'Share Price'!G:G) -> 124.72 | S89: =R89/Q89 -> 0.5154571 | T89: =C89 * S89 -> -426.70183 | U89: =IF(D89="Net Asset Value",U88,-SUM(T11:T89)) -> -561586.5 | V89: =IF(D89="Net Asset Value", U89, C89) -> -827.8125
B90: 41394 | C90: 8475.744 | D90: Distribution | E90: =_xlfn.XLOOKUP(B90,'Share Price'!D:D,'Share Price'!E:E) -> 70.4276 | F90: =_xlfn.XLOOKUP(C3,'Share Price'!D:D,'Share Price'!E:E) -> 267.26 | G90: =F90/E90 -> 3.7948191 | H90: =C90 * G90 -> 32163.915 | I90: =IF(D90="Net Asset Value",I89,-SUM(H11:H90)) -> -4213865.1 | J90: =IF(D90="Net Asset Value", I90, C90) -> 8475.744 | K90: =_xlfn.XLOOKUP(B90,'Share Price'!D:D,'Share Price'!F:F) -> 159.68 | L90: =_xlfn.XLOOKUP(C3,'Share Price'!D:D,'Share Price'!F:F) -> 357.18 | M90: =L90/K90 -> 2.2368487 | N90: =C90 * M90 -> 18958.957 | O90: =IF(D90="Net Asset Value",O89,-SUM(N11:N90)) -> -3200617.4 | P90: =IF(D90="Net Asset Value", O90, C90) -> 8475.744 | Q90: =_xlfn.XLOOKUP(B90,'Share Price'!D:D,'Share Price'!G:G) -> 229.48 | R90: =_xlfn.XLOOKUP(C3,'Share Price'!D:D,'Share Price'!G:G) -> 124.72 | S90: =R90/Q90 -> 0.54348963 | T90: =C90 * S90 -> 4606.4789 | U90: =IF(D90="Net Asset Value",U89,-SUM(T11:T90)) -> -566192.98 | V90: =IF(D90="Net Asset Value", U90, C90) -> 8475.744
B91: 41425 | C91: 22136.482 | D91: Distribution | E91: =_xlfn.XLOOKUP(B91,'Share Price'!D:D,'Share Price'!E:E) -> 72.9471 | F91: =_xlfn.XLOOKUP(C3,'Share Price'!D:D,'Share Price'!E:E) -> 267.26 | G91: =F91/E91 -> 3.6637509 | H91: =C91 * G91 -> 81102.555 | I91: =IF(D91="Net Asset Value",I90,-SUM(H11:H91)) -> -4294967.7 | J91: =IF(D91="Net Asset Value", I91, C91) -> 22136.482 | K91: =_xlfn.XLOOKUP(B91,'Share Price'!D:D,'Share Price'!F:F) -> 163.445 | L91: =_xlfn.XLOOKUP(C3,'Share Price'!D:D,'Share Price'!F:F) -> 357.18 | M91: =L91/K91 -> 2.1853223 | N91: =C91 * M91 -> 48375.347 | O91: =IF(D91="Net Asset Value",O90,-SUM(N11:N91)) -> -3248992.7 | P91: =IF(D91="Net Asset Value", O91, C91) -> 22136.482 | Q91: =_xlfn.XLOOKUP(B91,'Share Price'!D:D,'Share Price'!G:G) -> 241.564 | R91: =_xlfn.XLOOKUP(C3,'Share Price'!D:D,'Share Price'!G:G) -> 124.72 | S91: =R91/Q91 -> 0.5163021 | T91: =C91 * S91 -> 11429.112 | U91: =IF(D91="Net Asset Value",U90,-SUM(T11:T91)) -> -577622.09 | V91: =IF(D91="Net Asset Value", U91, C91) -> 22136.482
B92: 41455 | C92: 46775.837 | D92: Distribution | E92: =_xlfn.XLOOKUP(B92,'Share Price'!D:D,'Share Price'!E:E) -> 70.9753 | F92: =_xlfn.XLOOKUP(C3,'Share Price'!D:D,'Share Price'!E:E) -> 267.26 | G92: =F92/E92 -> 3.7655353 | H92: =C92 * G92 -> 176136.07 | I92: =IF(D92="Net Asset Value",I91,-SUM(H11:H92)) -> -4471103.7 | J92: =IF(D92="Net Asset Value", I92, C92) -> 46775.837 | K92: =_xlfn.XLOOKUP(B92,'Share Price'!D:D,'Share Price'!F:F) -> 160.42 | L92: =_xlfn.XLOOKUP(C3,'Share Price'!D:D,'Share Price'!F:F) -> 357.18 | M92: =L92/K92 -> 2.2265304 | N92: =C92 * M92 -> 104147.82 | O92: =IF(D92="Net Asset Value",O91,-SUM(N11:N92)) -> -3353140.5 | P92: =IF(D92="Net Asset Value", O92, C92) -> 46775.837 | Q92: =_xlfn.XLOOKUP(B92,'Share Price'!D:D,'Share Price'!G:G) -> 232.72 | R92: =_xlfn.XLOOKUP(C3,'Share Price'!D:D,'Share Price'!G:G) -> 124.72 | S92: =R92/Q92 -> 0.535923 | T92: =C92 * S92 -> 25068.247 | U92: =IF(D92="Net Asset Value",U91,-SUM(T11:T92)) -> -602690.34 | V92: =IF(D92="Net Asset Value", U92, C92) -> 46775.837
B93: 41486 | C93: 416.16298 | D93: Distribution | E93: =_xlfn.XLOOKUP(B93,'Share Price'!D:D,'Share Price'!E:E) -> 75.4567 | F93: =_xlfn.XLOOKUP(C3,'Share Price'!D:D,'Share Price'!E:E) -> 267.26 | G93: =F93/E93 -> 3.5418989 | H93: =C93 * G93 -> 1474.0072 | I93: =IF(D93="Net Asset Value",I92,-SUM(H11:H93)) -> -4472577.7 | J93: =IF(D93="Net Asset Value", I93, C93) -> 416.16298 | K93: =_xlfn.XLOOKUP(B93,'Share Price'!D:D,'Share Price'!F:F) -> 168.71 | L93: =_xlfn.XLOOKUP(C3,'Share Price'!D:D,'Share Price'!F:F) -> 357.18 | M93: =L93/K93 -> 2.1171241 | N93: =C93 * M93 -> 881.06866 | O93: =IF(D93="Net Asset Value",O92,-SUM(N11:N93)) -> -3354021.6 | P93: =IF(D93="Net Asset Value", O93, C93) -> 416.16298 | Q93: =_xlfn.XLOOKUP(B93,'Share Price'!D:D,'Share Price'!G:G) -> 249.4 | R93: =_xlfn.XLOOKUP(C3,'Share Price'!D:D,'Share Price'!G:G) -> 124.72 | S93: =R93/Q93 -> 0.50008019 | T93: =C93 * S93 -> 208.11486 | U93: =IF(D93="Net Asset Value",U92,-SUM(T11:T93)) -> -602898.45 | V93: =IF(D93="Net Asset Value", U93, C93) -> 416.16298
B94: 41517 | C94: 10498.593 | D94: Distribution | E94: =_xlfn.XLOOKUP(B94,'Share Price'!D:D,'Share Price'!E:E) -> 75.1579 | F94: =_xlfn.XLOOKUP(C3,'Share Price'!D:D,'Share Price'!E:E) -> 267.26 | G94: =F94/E94 -> 3.5559801 | H94: =C94 * G94 -> 37332.788 | I94: =IF(D94="Net Asset Value",I93,-SUM(H11:H94)) -> -4509910.5 | J94: =IF(D94="Net Asset Value", I94, C94) -> 10498.593 | K94: =_xlfn.XLOOKUP(B94,'Share Price'!D:D,'Share Price'!F:F) -> 163.65 | L94: =_xlfn.XLOOKUP(C3,'Share Price'!D:D,'Share Price'!F:F) -> 357.18 | M94: =L94/K94 -> 2.1825848 | N94: =C94 * M94 -> 22914.069 | O94: =IF(D94="Net Asset Value",O93,-SUM(N11:N94)) -> -3376935.7 | P94: =IF(D94="Net Asset Value", O94, C94) -> 10498.593 | Q94: =_xlfn.XLOOKUP(B94,'Share Price'!D:D,'Share Price'!G:G) -> 248 | R94: =_xlfn.XLOOKUP(C3,'Share Price'!D:D,'Share Price'!G:G) -> 124.72 | S94: =R94/Q94 -> 0.50290323 | T94: =C94 * S94 -> 5279.7763 | U94: =IF(D94="Net Asset Value",U93,-SUM(T11:T94)) -> -608178.23 | V94: =IF(D94="Net Asset Value", U94, C94) -> 10498.593
B95: 41547 | C95: 174520.07 | D95: Distribution | E95: =_xlfn.XLOOKUP(B95,'Share Price'!D:D,'Share Price'!E:E) -> 78.5538 | F95: =_xlfn.XLOOKUP(C3,'Share Price'!D:D,'Share Price'!E:E) -> 267.26 | G95: =F95/E95 -> 3.4022543 | H95: =C95 * G95 -> 593761.66 | I95: =IF(D95="Net Asset Value",I94,-SUM(H11:H95)) -> -5103672.2 | J95: =IF(D95="Net Asset Value", I95, C95) -> 174520.07 | K95: =_xlfn.XLOOKUP(B95,'Share Price'!D:D,'Share Price'!F:F) -> 168.01 | L95: =_xlfn.XLOOKUP(C3,'Share Price'!D:D,'Share Price'!F:F) -> 357.18 | M95: =L95/K95 -> 2.1259449 | N95: =C95 * M95 -> 371020.05 | O95: =IF(D95="Net Asset Value",O94,-SUM(N11:N95)) -> -3747955.7 | P95: =IF(D95="Net Asset Value", O95, C95) -> 174520.07 | Q95: =_xlfn.XLOOKUP(B95,'Share Price'!D:D,'Share Price'!G:G) -> 263.4 | R95: =_xlfn.XLOOKUP(C3,'Share Price'!D:D,'Share Price'!G:G) -> 124.72 | S95: =R95/Q95 -> 0.47350038 | T95: =C95 * S95 -> 82635.32 | U95: =IF(D95="Net Asset Value",U94,-SUM(T11:T95)) -> -690813.55 | V95: =IF(D95="Net Asset Value", U95, C95) -> 174520.07
B96: 41578 | C96: -800.23927 | D96: Contribution | E96: =_xlfn.XLOOKUP(B96,'Share Price'!D:D,'Share Price'!E:E) -> 82.4477 | F96: =_xlfn.XLOOKUP(C3,'Share Price'!D:D,'Share Price'!E:E) -> 267.26 | G96: =F96/E96 -> 3.2415701 | H96: =C96 * G96 -> -2594.0317 | I96: =IF(D96="Net Asset Value",I95,-SUM(H11:H96)) -> -5101078.2 | J96: =IF(D96="Net Asset Value", I96, C96) -> -800.23927 | K96: =_xlfn.XLOOKUP(B96,'Share Price'!D:D,'Share Price'!F:F) -> 175.79 | L96: =_xlfn.XLOOKUP(C3,'Share Price'!D:D,'Share Price'!F:F) -> 357.18 | M96: =L96/K96 -> 2.0318562 | N96: =C96 * M96 -> -1625.9711 | O96: =IF(D96="Net Asset Value",O95,-SUM(N11:N96)) -> -3746329.8 | P96: =IF(D96="Net Asset Value", O96, C96) -> -800.23927 | Q96: =_xlfn.XLOOKUP(B96,'Share Price'!D:D,'Share Price'!G:G) -> 278.32 | R96: =_xlfn.XLOOKUP(C3,'Share Price'!D:D,'Share Price'!G:G) -> 124.72 | S96: =R96/Q96 -> 0.44811728 | T96: =C96 * S96 -> -358.60104 | U96: =IF(D96="Net Asset Value",U95,-SUM(T11:T96)) -> -690454.95 | V96: =IF(D96="Net Asset Value", U96, C96) -> -800.23927
B97: 41608 | C97: 19561.141 | D97: Distribution | E97: =_xlfn.XLOOKUP(B97,'Share Price'!D:D,'Share Price'!E:E) -> 85.3755 | F97: =_xlfn.XLOOKUP(C3,'Share Price'!D:D,'Share Price'!E:E) -> 267.26 | G97: =F97/E97 -> 3.1304063 | H97: =C97 * G97 -> 61234.317 | I97: =IF(D97="Net Asset Value",I96,-SUM(H11:H97)) -> -5162312.5 | J97: =IF(D97="Net Asset Value", I97, C97) -> 19561.141 | K97: =_xlfn.XLOOKUP(B97,'Share Price'!D:D,'Share Price'!F:F) -> 181 | L97: =_xlfn.XLOOKUP(C3,'Share Price'!D:D,'Share Price'!F:F) -> 357.18 | M97: =L97/K97 -> 1.9733702 | N97: =C97 * M97 -> 38601.371 | O97: =IF(D97="Net Asset Value",O96,-SUM(N11:N97)) -> -3784931.1 | P97: =IF(D97="Net Asset Value", O97, C97) -> 19561.141 | Q97: =_xlfn.XLOOKUP(B97,'Share Price'!D:D,'Share Price'!G:G) -> 271.12 | R97: =_xlfn.XLOOKUP(C3,'Share Price'!D:D,'Share Price'!G:G) -> 124.72 | S97: =R97/Q97 -> 0.4600177 | T97: =C97 * S97 -> 8998.471 | U97: =IF(D97="Net Asset Value",U96,-SUM(T11:T97)) -> -699453.42 | V97: =IF(D97="Net Asset Value", U97, C97) -> 19561.141
B98: 41639 | C98: 9815.8999 | D98: Distribution | E98: =_xlfn.XLOOKUP(B98,'Share Price'!D:D,'Share Price'!E:E) -> 87.5963 | F98: =_xlfn.XLOOKUP(C3,'Share Price'!D:D,'Share Price'!E:E) -> 267.26 | G98: =F98/E98 -> 3.0510421 | H98: =C98 * G98 -> 29948.724 | I98: =IF(D98="Net Asset Value",I97,-SUM(H11:H98)) -> -5192261.2 | J98: =IF(D98="Net Asset Value", I98, C98) -> 9815.8999 | K98: =_xlfn.XLOOKUP(B98,'Share Price'!D:D,'Share Price'!F:F) -> 184.69 | L98: =_xlfn.XLOOKUP(C3,'Share Price'!D:D,'Share Price'!F:F) -> 357.18 | M98: =L98/K98 -> 1.9339434 | N98: =C98 * M98 -> 18983.394 | O98: =IF(D98="Net Asset Value",O97,-SUM(N11:N98)) -> -3803914.5 | P98: =IF(D98="Net Asset Value", O98, C98) -> 9815.8999 | Q98: =_xlfn.XLOOKUP(B98,'Share Price'!D:D,'Share Price'!G:G) -> 274.12 | R98: =_xlfn.XLOOKUP(C3,'Share Price'!D:D,'Share Price'!G:G) -> 124.72 | S98: =R98/Q98 -> 0.45498322 | T98: =C98 * S98 -> 4466.0697 | U98: =IF(D98="Net Asset Value",U97,-SUM(T11:T98)) -> -703919.49 | V98: =IF(D98="Net Asset Value", U98, C98) -> 9815.8999
B99: 41698 | C99: 416.70283 | D99: Distribution | E99: =_xlfn.XLOOKUP(B99,'Share Price'!D:D,'Share Price'!E:E) -> 90.34 | F99: =_xlfn.XLOOKUP(C3,'Share Price'!D:D,'Share Price'!E:E) -> 267.26 | G99: =F99/E99 -> 2.9583795 | H99: =C99 * G99 -> 1232.7651 | I99: =IF(D99="Net Asset Value",I98,-SUM(H11:H99)) -> -5193494 | J99: =IF(D99="Net Asset Value", I99, C99) -> 416.70283 | K99: =_xlfn.XLOOKUP(B99,'Share Price'!D:D,'Share Price'!F:F) -> 186.29 | L99: =_xlfn.XLOOKUP(C3,'Share Price'!D:D,'Share Price'!F:F) -> 357.18 | M99: =L99/K99 -> 1.9173332 | N99: =C99 * M99 -> 798.95817 | O99: =IF(D99="Net Asset Value",O98,-SUM(N11:N99)) -> -3804713.5 | P99: =IF(D99="Net Asset Value", O99, C99) -> 416.70283 | Q99: =_xlfn.XLOOKUP(B99,'Share Price'!D:D,'Share Price'!G:G) -> 278.76 | R99: =_xlfn.XLOOKUP(C3,'Share Price'!D:D,'Share Price'!G:G) -> 124.72 | S99: =R99/Q99 -> 0.44740996 | T99: =C99 * S99 -> 186.437 | U99: =IF(D99="Net Asset Value",U98,-SUM(T11:T99)) -> -704105.92 | V99: =IF(D99="Net Asset Value", U99, C99) -> 416.70283
B100: 41729 | C100: 214.90326 | D100: Distribution | E100: =_xlfn.XLOOKUP(B100,'Share Price'!D:D,'Share Price'!E:E) -> 87.67 | F100: =_xlfn.XLOOKUP(C3,'Share Price'!D:D,'Share Price'!E:E) -> 267.26 | G100: =F100/E100 -> 3.0484772 | H100: =C100 * G100 -> 655.1277 | I100: =IF(D100="Net Asset Value",I99,-SUM(H11:H100)) -> -5194149.1 | J100: =IF(D100="Net Asset Value", I100, C100) -> 214.90326 | K100: =_xlfn.XLOOKUP(B100,'Share Price'!D:D,'Share Price'!F:F) -> 187.01 | L100: =_xlfn.XLOOKUP(C3,'Share Price'!D:D,'Share Price'!F:F) -> 357.18 | M100: =L100/K100 -> 1.9099513 | N100: =C100 * M100 -> 410.45477 | O100: =IF(D100="Net Asset Value",O99,-SUM(N11:N100)) -> -3805123.9 | P100: =IF(D100="Net Asset Value", O100, C100) -> 214.90326 | Q100: =_xlfn.XLOOKUP(B100,'Share Price'!D:D,'Share Price'!G:G) -> 287.32 | R100: =_xlfn.XLOOKUP(C3,'Share Price'!D:D,'Share Price'!G:G) -> 124.72 | S100: =R100/Q100 -> 0.43408047 | T100: =C100 * S100 -> 93.285308 | U100: =IF(D100="Net Asset Value",U99,-SUM(T11:T100)) -> -704199.21 | V100: =IF(D100="Net Asset Value", U100, C100) -> 214.90326
B101: 41759 | C101: 6772.525 | D101: Distribution | E101: =_xlfn.XLOOKUP(B101,'Share Price'!D:D,'Share Price'!E:E) -> 87.39 | F101: =_xlfn.XLOOKUP(C3,'Share Price'!D:D,'Share Price'!E:E) -> 267.26 | G101: =F101/E101 -> 3.0582447 | H101: =C101 * G101 -> 20712.038 | I101: =IF(D101="Net Asset Value",I100,-SUM(H11:H101)) -> -5214861.1 | J101: =IF(D101="Net Asset Value", I101, C101) -> 6772.525 | K101: =_xlfn.XLOOKUP(B101,'Share Price'!D:D,'Share Price'!F:F) -> 188.31 | L101: =_xlfn.XLOOKUP(C3,'Share Price'!D:D,'Share Price'!F:F) -> 357.18 | M101: =L101/K101 -> 1.896766 | N101: =C101 * M101 -> 12845.895 | O101: =IF(D101="Net Asset Value",O100,-SUM(N11:N101)) -> -3817969.8 | P101: =IF(D101="Net Asset Value", O101, C101) -> 6772.525 | Q101: =_xlfn.XLOOKUP(B101,'Share Price'!D:D,'Share Price'!G:G) -> 310.44 | R101: =_xlfn.XLOOKUP(C3,'Share Price'!D:D,'Share Price'!G:G) -> 124.72 | S101: =R101/Q101 -> 0.40175235 | T101: =C101 * S101 -> 2720.8778 | U101: =IF(D101="Net Asset Value",U100,-SUM(T11:T101)) -> -706920.09 | V101: =IF(D101="Net Asset Value", U101, C101) -> 6772.525
...

Sheet Fund VII
B1: Inputs | E1: Outputs | K1: Cash Flow Summary
B2: Fund Name | C2: Fund VII | F2: PME Index 1 | G2: PME Index 2 | H2: PME Index 3 | L2: Actual | M2: PME Index 1 | N2: PME Index 2 | O2: PME Index 3
B3: End Date | C3: =B183 -> 45077 | E3: Actual IRR | F3: =IFERROR(XIRR(C11:C183, B11:B183, IF(SUM(C11:C183) > 0, 0.15, -0.15)), "NA") -> 0.24436759 | G3: =IFERROR(XIRR(C11:C183, B11:B183, IF(SUM(C11:C183) > 0, 0.15, -0.15)), "NA") -> 0.24436759 | H3: =IFERROR(XIRR(C11:C183, B11:B183, IF(SUM(C11:C183) > 0, 0.15, -0.15)), "NA") -> 0.24436759 | K3: Distribution | L3: =SUMIFS(C11:C183, D11:D183, K3) -> 3433106.2 | M3: =SUMIFS(H11:H183, D11:D183, K3) -> 16815328 | N3: =SUMIFS(N11:N183, D11:D183, K3) -> 9396881.7 | O3: =SUMIFS(T11:T183, D11:D183, K3) -> 2030075.8
B4: Index 1 | C4: ='Share Price'!B3 -> QQQ | E4: PME IRR | F4: =IFERROR(XIRR(J11:J183, B11:B183, IF(SUM(J11:J183) > 0, 0.15, -0.15)), "NA") -> 0.24436759 | G4: =IFERROR(XIRR(P11:P183, B11:B183, IF(SUM(P11:P183) > 0, 0.15, -0.15)), "NA") -> 0.24436759 | H4: =IFERROR(XIRR(V11:V183, B11:B183, IF(SUM(V11:V183) > 0, 0.15, -0.15)), "NA") -> 0.24436759 | K4: Contribution | L4: =SUMIFS(C11:C183, D11:D183, K4) -> -1921130.5 | M4: =SUMIFS(H11:H183, D11:D183, K4) -> -13836414 | N4: =SUMIFS(N11:N183, D11:D183, K4) -> -6646792.2 | O4: =SUMIFS(T11:T183, D11:D183, K4) -> -1266632.1
B5: Index 2 | C5: ='Share Price'!B4 -> SPY | E5: Direct Alpha IRR | F5: =IFERROR(XIRR(H11:H183, B11:B183, IF(SUM(H11:H183) > 0, 0.15, -0.15)), "NA") -> 0.081310822 | G5: =IFERROR(XIRR(N11:N183, B11:B183, IF(SUM(N11:N183) > 0, 0.15, -0.15)), "NA") -> 0.15234383 | H5: =IFERROR(XIRR(T11:T183, B11:B183, IF(SUM(T11:T183) > 0, 0.15, -0.15)), "NA") -> 0.16453523 | K5: Net Asset Value | L5: =SUMIFS(C11:C183, D11:D183, K5) -> 0 | M5: =SUMIFS(H11:H183, D11:D183, K5) -> 0 | N5: =SUMIFS(N11:N183, D11:D183, K5) -> 0 | O5: =SUMIFS(T11:T183, D11:D183, K5) -> 0
B6: Index 3 | C6: ='Share Price'!B5 -> XOP | E6: KS-PME | F6: =(M3 + M5) / -M4 -> 1.2152952 | G6: =(N3 + N5) / -N4 -> 1.4137469 | H6: =(O3 + O5) / -O4 -> 1.6027353
B8: Cash Flow Data | E8: Index 1 Portfolio | K8: Index 2 Portfolio | Q8: Index 3 Portfolio
E9: Index Value at | H9: NAV | I9: End Date | J9: PME | K9: Index Value at | N9: NAV | O9: End Date | P9: PME | Q9: Index Value at | T9: NAV | U9: End Date | V9: PME
B10: Date | C10: Amount | D10: Type | E10: CF Date | F10: End Date | G10: Factor | H10: Contribution | I10: NAV | J10: Cash Flow | K10: CF Date | L10: End Date | M10: Factor | N10: Contribution | O10: NAV | P10: Cash Flow | Q10: CF Date | R10: End Date | S10: Factor | T10: Contribution | U10: NAV | V10: Cash Flow
B11: 39355 | C11: -11834.62 | D11: Contribution | E11: =_xlfn.XLOOKUP(B11,'Share Price'!D:D,'Share Price'!E:E) -> 51.1974 | F11: =_xlfn.XLOOKUP(C3,'Share Price'!D:D,'Share Price'!E:E) -> 347.99 | G11: =F11/E11 -> 6.7970248 | H11: =C11 * G11 -> -80440.204 | I11: =IF(D11="Net Asset Value",I10,-SUM(H11:H11)) -> 80440.204 | J11: =IF(D11="Net Asset Value", I11, C11) -> -11834.62 | K11: =_xlfn.XLOOKUP(B11,'Share Price'!D:D,'Share Price'!F:F) -> 152.58 | L11: =_xlfn.XLOOKUP(C3,'Share Price'!D:D,'Share Price'!F:F) -> 417.85 | M11: =L11/K11 -> 2.7385634 | N11: =C11 * M11 -> -32409.856 | O11: =IF(D11="Net Asset Value",O10,-SUM(N11:N11)) -> 32409.856 | P11: =IF(D11="Net Asset Value", O11, C11) -> -11834.62 | Q11: =_xlfn.XLOOKUP(B11,'Share Price'!D:D,'Share Price'!G:G) -> 188.12 | R11: =_xlfn.XLOOKUP(C3,'Share Price'!D:D,'Share Price'!G:G) -> 118.09 | S11: =R11/Q11 -> 0.62773761 | T11: =C11 * S11 -> -7429.0359 | U11: =IF(D11="Net Asset Value",U10,-SUM(T11:T11)) -> 7429.0359 | V11: =IF(D11="Net Asset Value", U11, C11) -> -11834.62
B12: 39386 | C12: -36858.827 | D12: Contribution | E12: =_xlfn.XLOOKUP(B12,'Share Price'!D:D,'Share Price'!E:E) -> 54.8025 | F12: =_xlfn.XLOOKUP(C3,'Share Price'!D:D,'Share Price'!E:E) -> 347.99 | G12: =F12/E12 -> 6.3498928 | H12: =C12 * G12 -> -234049.6 | I12: =IF(D12="Net Asset Value",I11,-SUM(H11:H12)) -> 314489.8 | J12: =IF(D12="Net Asset Value", I12, C12) -> -36858.827 | K12: =_xlfn.XLOOKUP(B12,'Share Price'!D:D,'Share Price'!F:F) -> 154.65 | L12: =_xlfn.XLOOKUP(C3,'Share Price'!D:D,'Share Price'!F:F) -> 417.85 | M12: =L12/K12 -> 2.7019075 | N12: =C12 * M12 -> -99589.142 | O12: =IF(D12="Net Asset Value",O11,-SUM(N11:N12)) -> 131999 | P12: =IF(D12="Net Asset Value", O12, C12) -> -36858.827 | Q12: =_xlfn.XLOOKUP(B12,'Share Price'!D:D,'Share Price'!G:G) -> 211.64 | R12: =_xlfn.XLOOKUP(C3,'Share Price'!D:D,'Share Price'!G:G) -> 118.09 | S12: =R12/Q12 -> 0.55797581 | T12: =C12 * S12 -> -20566.334 | U12: =IF(D12="Net Asset Value",U11,-SUM(T11:T12)) -> 27995.37 | V12: =IF(D12="Net Asset Value", U12, C12) -> -36858.827
B13: 39416 | C13: 7854.55 | D13: Distribution | E13: =_xlfn.XLOOKUP(B13,'Share Price'!D:D,'Share Price'!E:E) -> 51.0978 | F13: =_xlfn.XLOOKUP(C3,'Share Price'!D:D,'Share Price'!E:E) -> 347.99 | G13: =F13/E13 -> 6.8102736 | H13: =C13 * G13 -> 53491.635 | I13: =IF(D13="Net Asset Value",I12,-SUM(H11:H13)) -> 260998.17 | J13: =IF(D13="Net Asset Value", I13, C13) -> 7854.55 | K13: =_xlfn.XLOOKUP(B13,'Share Price'!D:D,'Share Price'!F:F) -> 148.66 | L13: =_xlfn.XLOOKUP(C3,'Share Price'!D:D,'Share Price'!F:F) -> 417.85 | M13: =L13/K13 -> 2.8107763 | N13: =C13 * M13 -> 22077.383 | O13: =IF(D13="Net Asset Value",O12,-SUM(N11:N13)) -> 109921.62 | P13: =IF(D13="Net Asset Value", O13, C13) -> 7854.55 | Q13: =_xlfn.XLOOKUP(B13,'Share Price'!D:D,'Share Price'!G:G) -> 194.08 | R13: =_xlfn.XLOOKUP(C3,'Share Price'!D:D,'Share Price'!G:G) -> 118.09 | S13: =R13/Q13 -> 0.60846043 | T13: =C13 * S13 -> 4779.1829 | U13: =IF(D13="Net Asset Value",U12,-SUM(T11:T13)) -> 23216.187 | V13: =IF(D13="Net Asset Value", U13, C13) -> 7854.55
B14: 39447 | C14: -10049.244 | D14: Contribution | E14: =_xlfn.XLOOKUP(B14,'Share Price'!D:D,'Share Price'!E:E) -> 51.0082 | F14: =_xlfn.XLOOKUP(C3,'Share Price'!D:D,'Share Price'!E:E) -> 347.99 | G14: =F14/E14 -> 6.8222364 | H14: =C14 * G14 -> -68558.318 | I14: =IF(D14="Net Asset Value",I13,-SUM(H11:H14)) -> 329556.49 | J14: =IF(D14="Net Asset Value", I14, C14) -> -10049.244 | K14: =_xlfn.XLOOKUP(B14,'Share Price'!D:D,'Share Price'!F:F) -> 146.21 | L14: =_xlfn.XLOOKUP(C3,'Share Price'!D:D,'Share Price'!F:F) -> 417.85 | M14: =L14/K14 -> 2.8578757 | N14: =C14 * M14 -> -28719.489 | O14: =IF(D14="Net Asset Value",O13,-SUM(N11:N14)) -> 138641.1 | P14: =IF(D14="Net Asset Value", O14, C14) -> -10049.244 | Q14: =_xlfn.XLOOKUP(B14,'Share Price'!D:D,'Share Price'!G:G) -> 208 | R14: =_xlfn.XLOOKUP(C3,'Share Price'!D:D,'Share Price'!G:G) -> 118.09 | S14: =R14/Q14 -> 0.56774038 | T14: =C14 * S14 -> -5705.3616 | U14: =IF(D14="Net Asset Value",U13,-SUM(T11:T14)) -> 28921.548 | V14: =IF(D14="Net Asset Value", U14, C14) -> -10049.244
B15: 39478 | C15: -465.35324 | D15: Contribution | E15: =_xlfn.XLOOKUP(B15,'Share Price'!D:D,'Share Price'!E:E) -> 44.9434 | F15: =_xlfn.XLOOKUP(C3,'Share Price'!D:D,'Share Price'!E:E) -> 347.99 | G15: =F15/E15 -> 7.7428499 | H15: =C15 * G15 -> -3603.1603 | I15: =IF(D15="Net Asset Value",I14,-SUM(H11:H15)) -> 333159.65 | J15: =IF(D15="Net Asset Value", I15, C15) -> -465.35324 | K15: =_xlfn.XLOOKUP(B15,'Share Price'!D:D,'Share Price'!F:F) -> 137.37 | L15: =_xlfn.XLOOKUP(C3,'Share Price'!D:D,'Share Price'!F:F) -> 417.85 | M15: =L15/K15 -> 3.041785 | N15: =C15 * M15 -> -1415.5045 | O15: =IF(D15="Net Asset Value",O14,-SUM(N11:N15)) -> 140056.61 | P15: =IF(D15="Net Asset Value", O15, C15) -> -465.35324 | Q15: =_xlfn.XLOOKUP(B15,'Share Price'!D:D,'Share Price'!G:G) -> 192.16 | R15: =_xlfn.XLOOKUP(C3,'Share Price'!D:D,'Share Price'!G:G) -> 118.09 | S15: =R15/Q15 -> 0.61453997 | T15: =C15 * S15 -> -285.97817 | U15: =IF(D15="Net Asset Value",U14,-SUM(T11:T15)) -> 29207.526 | V15: =IF(D15="Net Asset Value", U15, C15) -> -465.35324
B16: 39507 | C16: -13137.586 | D16: Contribution | E16: =_xlfn.XLOOKUP(B16,'Share Price'!D:D,'Share Price'!E:E) -> 42.7724 | F16: =_xlfn.XLOOKUP(C3,'Share Price'!D:D,'Share Price'!E:E) -> 347.99 | G16: =F16/E16 -> 8.135854 | H16: =C16 * G16 -> -106885.48 | I16: =IF(D16="Net Asset Value",I15,-SUM(H11:H16)) -> 440045.12 | J16: =IF(D16="Net Asset Value", I16, C16) -> -13137.586 | K16: =_xlfn.XLOOKUP(B16,'Share Price'!D:D,'Share Price'!F:F) -> 133.82 | L16: =_xlfn.XLOOKUP(C3,'Share Price'!D:D,'Share Price'!F:F) -> 417.85 | M16: =L16/K16 -> 3.122478 | N16: =C16 * M16 -> -41021.822 | O16: =IF(D16="Net Asset Value",O15,-SUM(N11:N16)) -> 181078.43 | P16: =IF(D16="Net Asset Value", O16, C16) -> -13137.586 | Q16: =_xlfn.XLOOKUP(B16,'Share Price'!D:D,'Share Price'!G:G) -> 217.9196 | R16: =_xlfn.XLOOKUP(C3,'Share Price'!D:D,'Share Price'!G:G) -> 118.09 | S16: =R16/Q16 -> 0.5418971 | T16: =C16 * S16 -> -7119.2197 | U16: =IF(D16="Net Asset Value",U15,-SUM(T11:T16)) -> 36326.746 | V16: =IF(D16="Net Asset Value", U16, C16) -> -13137.586
B17: 39538 | C17: -19990.477 | D17: Contribution | E17: =_xlfn.XLOOKUP(B17,'Share Price'!D:D,'Share Price'!E:E) -> 43.5392 | F17: =_xlfn.XLOOKUP(C3,'Share Price'!D:D,'Share Price'!E:E) -> 347.99 | G17: =F17/E17 -> 7.9925676 | H17: =C17 * G17 -> -159775.24 | I17: =IF(D17="Net Asset Value",I16,-SUM(H11:H17)) -> 599820.36 | J17: =IF(D17="Net Asset Value", I17, C17) -> -19990.477 | K17: =_xlfn.XLOOKUP(B17,'Share Price'!D:D,'Share Price'!F:F) -> 131.97 | L17: =_xlfn.XLOOKUP(C3,'Share Price'!D:D,'Share Price'!F:F) -> 417.85 | M17: =L17/K17 -> 3.1662499 | N17: =C17 * M17 -> -63294.846 | O17: =IF(D17="Net Asset Value",O16,-SUM(N11:N17)) -> 244373.28 | P17: =IF(D17="Net Asset Value", O17, C17) -> -19990.477 | Q17: =_xlfn.XLOOKUP(B17,'Share Price'!D:D,'Share Price'!G:G) -> 215 | R17: =_xlfn.XLOOKUP(C3,'Share Price'!D:D,'Share Price'!G:G) -> 118.09 | S17: =R17/Q17 -> 0.54925581 | T17: =C17 * S17 -> -10979.886 | U17: =IF(D17="Net Asset Value",U16,-SUM(T11:T17)) -> 47306.632 | V17: =IF(D17="Net Asset Value", U17, C17) -> -19990.477
B18: 39568 | C18: -22116.806 | D18: Contribution | E18: =_xlfn.XLOOKUP(B18,'Share Price'!D:D,'Share Price'!E:E) -> 47.0148 | F18: =_xlfn.XLOOKUP(C3,'Share Price'!D:D,'Share Price'!E:E) -> 347.99 | G18: =F18/E18 -> 7.4017118 | H18: =C18 * G18 -> -163702.22 | I18: =IF(D18="Net Asset Value",I17,-SUM(H11:H18)) -> 763522.59 | J18: =IF(D18="Net Asset Value", I18, C18) -> -22116.806 | K18: =_xlfn.XLOOKUP(B18,'Share Price'!D:D,'Share Price'!F:F) -> 138.26 | L18: =_xlfn.XLOOKUP(C3,'Share Price'!D:D,'Share Price'!F:F) -> 417.85 | M18: =L18/K18 -> 3.0222045 | N18: =C18 * M18 -> -66841.512 | O18: =IF(D18="Net Asset Value",O17,-SUM(N11:N18)) -> 311214.79 | P18: =IF(D18="Net Asset Value", O18, C18) -> -22116.806 | Q18: =_xlfn.XLOOKUP(B18,'Share Price'!D:D,'Share Price'!G:G) -> 235.56 | R18: =_xlfn.XLOOKUP(C3,'Share Price'!D:D,'Share Price'!G:G) -> 118.09 | S18: =R18/Q18 -> 0.50131601 | T18: =C18 * S18 -> -11087.509 | U18: =IF(D18="Net Asset Value",U17,-SUM(T11:T18)) -> 58394.141 | V18: =IF(D18="Net Asset Value", U18, C18) -> -22116.806
B19: 39599 | C19: -46459.994 | D19: Contribution | E19: =_xlfn.XLOOKUP(B19,'Share Price'!D:D,'Share Price'!E:E) -> 49.8032 | F19: =_xlfn.XLOOKUP(C3,'Share Price'!D:D,'Share Price'!E:E) -> 347.99 | G19: =F19/E19 -> 6.987302 | H19: =C19 * G19 -> -324630.01 | I19: =IF(D19="Net Asset Value",I18,-SUM(H11:H19)) -> 1088152.6 | J19: =IF(D19="Net Asset Value", I19, C19) -> -46459.994 | K19: =_xlfn.XLOOKUP(B19,'Share Price'!D:D,'Share Price'!F:F) -> 140.35 | L19: =_xlfn.XLOOKUP(C3,'Share Price'!D:D,'Share Price'!F:F) -> 417.85 | M19: =L19/K19 -> 2.9771999 | N19: =C19 * M19 -> -138320.69 | O19: =IF(D19="Net Asset Value",O18,-SUM(N11:N19)) -> 449535.48 | P19: =IF(D19="Net Asset Value", O19, C19) -> -46459.994 | Q19: =_xlfn.XLOOKUP(B19,'Share Price'!D:D,'Share Price'!G:G) -> 259.08 | R19: =_xlfn.XLOOKUP(C3,'Share Price'!D:D,'Share Price'!G:G) -> 118.09 | S19: =R19/Q19 -> 0.45580516 | T19: =C19 * S19 -> -21176.705 | U19: =IF(D19="Net Asset Value",U18,-SUM(T11:T19)) -> 79570.846 | V19: =IF(D19="Net Asset Value", U19, C19) -> -46459.994
B20: 39629 | C20: -62158.13 | D20: Contribution | E20: =_xlfn.XLOOKUP(B20,'Share Price'!D:D,'Share Price'!E:E) -> 44.9832 | F20: =_xlfn.XLOOKUP(C3,'Share Price'!D:D,'Share Price'!E:E) -> 347.99 | G20: =F20/E20 -> 7.7359992 | H20: =C20 * G20 -> -480855.25 | I20: =IF(D20="Net Asset Value",I19,-SUM(H11:H20)) -> 1569007.8 | J20: =IF(D20="Net Asset Value", I20, C20) -> -62158.13 | K20: =_xlfn.XLOOKUP(B20,'Share Price'!D:D,'Share Price'!F:F) -> 127.98 | L20: =_xlfn.XLOOKUP(C3,'Share Price'!D:D,'Share Price'!F:F) -> 417.85 | M20: =L20/K20 -> 3.2649633 | N20: =C20 * M20 -> -202944.01 | O20: =IF(D20="Net Asset Value",O19,-SUM(N11:N20)) -> 652479.49 | P20: =IF(D20="Net Asset Value", O20, C20) -> -62158.13 | Q20: =_xlfn.XLOOKUP(B20,'Share Price'!D:D,'Share Price'!G:G) -> 281.12 | R20: =_xlfn.XLOOKUP(C3,'Share Price'!D:D,'Share Price'!G:G) -> 118.09 | S20: =R20/Q20 -> 0.42006972 | T20: =C20 * S20 -> -26110.748 | U20: =IF(D20="Net Asset Value",U19,-SUM(T11:T20)) -> 105681.59 | V20: =IF(D20="Net Asset Value", U20, C20) -> -62158.13
B21: 39660 | C21: -37011.148 | D21: Contribution | E21: =_xlfn.XLOOKUP(B21,'Share Price'!D:D,'Share Price'!E:E) -> 45.272 | F21: =_xlfn.XLOOKUP(C3,'Share Price'!D:D,'Share Price'!E:E) -> 347.99 | G21: =F21/E21 -> 7.6866496 | H21: =C21 * G21 -> -284491.72 | I21: =IF(D21="Net Asset Value",I20,-SUM(H11:H21)) -> 1853499.6 | J21: =IF(D21="Net Asset Value", I21, C21) -> -37011.148 | K21: =_xlfn.XLOOKUP(B21,'Share Price'!D:D,'Share Price'!F:F) -> 126.83 | L21: =_xlfn.XLOOKUP(C3,'Share Price'!D:D,'Share Price'!F:F) -> 417.85 | M21: =L21/K21 -> 3.2945675 | N21: =C21 * M21 -> -121935.73 | O21: =IF(D21="Net Asset Value",O20,-SUM(N11:N21)) -> 774415.21 | P21: =IF(D21="Net Asset Value", O21, C21) -> -37011.148 | Q21: =_xlfn.XLOOKUP(B21,'Share Price'!D:D,'Share Price'!G:G) -> 216.32 | R21: =_xlfn.XLOOKUP(C3,'Share Price'!D:D,'Share Price'!G:G) -> 118.09 | S21: =R21/Q21 -> 0.54590422 | T21: =C21 * S21 -> -20204.542 | U21: =IF(D21="Net Asset Value",U20,-SUM(T11:T21)) -> 125886.14 | V21: =IF(D21="Net Asset Value", U21, C21) -> -37011.148
B22: 39691 | C22: -77435.159 | D22: Contribution | E22: =_xlfn.XLOOKUP(B22,'Share Price'!D:D,'Share Price'!E:E) -> 45.9293 | F22: =_xlfn.XLOOKUP(C3,'Share Price'!D:D,'Share Price'!E:E) -> 347.99 | G22: =F22/E22 -> 7.576645 | H22: =C22 * G22 -> -586698.71 | I22: =IF(D22="Net Asset Value",I21,-SUM(H11:H22)) -> 2440198.3 | J22: =IF(D22="Net Asset Value", I22, C22) -> -77435.159 | K22: =_xlfn.XLOOKUP(B22,'Share Price'!D:D,'Share Price'!F:F) -> 128.79 | L22: =_xlfn.XLOOKUP(C3,'Share Price'!D:D,'Share Price'!F:F) -> 417.85 | M22: =L22/K22 -> 3.2444289 | N22: =C22 * M22 -> -251232.87 | O22: =IF(D22="Net Asset Value",O21,-SUM(N11:N22)) -> 1025648.1 | P22: =IF(D22="Net Asset Value", O22, C22) -> -77435.159 | Q22: =_xlfn.XLOOKUP(B22,'Share Price'!D:D,'Share Price'!G:G) -> 220.12 | R22: =_xlfn.XLOOKUP(C3,'Share Price'!D:D,'Share Price'!G:G) -> 118.09 | S22: =R22/Q22 -> 0.5364801 | T22: =C22 * S22 -> -41542.422 | U22: =IF(D22="Net Asset Value",U21,-SUM(T11:T22)) -> 167428.56 | V22: =IF(D22="Net Asset Value", U22, C22) -> -77435.159
B23: 39721 | C23: -11036.716 | D23: Contribution | E23: =_xlfn.XLOOKUP(B23,'Share Price'!D:D,'Share Price'!E:E) -> 38.7491 | F23: =_xlfn.XLOOKUP(C3,'Share Price'!D:D,'Share Price'!E:E) -> 347.99 | G23: =F23/E23 -> 8.9805957 | H23: =C23 * G23 -> -99116.283 | I23: =IF(D23="Net Asset Value",I22,-SUM(H11:H23)) -> 2539314.6 | J23: =IF(D23="Net Asset Value", I23, C23) -> -11036.716 | K23: =_xlfn.XLOOKUP(B23,'Share Price'!D:D,'Share Price'!F:F) -> 115.99 | L23: =_xlfn.XLOOKUP(C3,'Share Price'!D:D,'Share Price'!F:F) -> 417.85 | M23: =L23/K23 -> 3.6024657 | N23: =C23 * M23 -> -39759.391 | O23: =IF(D23="Net Asset Value",O22,-SUM(N11:N23)) -> 1065407.5 | P23: =IF(D23="Net Asset Value", O23, C23) -> -11036.716 | Q23: =_xlfn.XLOOKUP(B23,'Share Price'!D:D,'Share Price'!G:G) -> 179.32 | R23: =_xlfn.XLOOKUP(C3,'Share Price'!D:D,'Share Price'!G:G) -> 118.09 | S23: =R23/Q23 -> 0.65854339 | T23: =C23 * S23 -> -7268.1563 | U23: =IF(D23="Net Asset Value",U22,-SUM(T11:T23)) -> 174696.71 | V23: =IF(D23="Net Asset Value", U23, C23) -> -11036.716
B24: 39752 | C24: -19038.491 | D24: Contribution | E24: =_xlfn.XLOOKUP(B24,'Share Price'!D:D,'Share Price'!E:E) -> 32.754 | F24: =_xlfn.XLOOKUP(C3,'Share Price'!D:D,'Share Price'!E:E) -> 347.99 | G24: =F24/E24 -> 10.624351 | H24: =C24 * G24 -> -202271.61 | I24: =IF(D24="Net Asset Value",I23,-SUM(H11:H24)) -> 2741586.2 | J24: =IF(D24="Net Asset Value", I24, C24) -> -19038.491 | K24: =_xlfn.XLOOKUP(B24,'Share Price'!D:D,'Share Price'!F:F) -> 96.83 | L24: =_xlfn.XLOOKUP(C3,'Share Price'!D:D,'Share Price'!F:F) -> 417.85 | M24: =L24/K24 -> 4.3152948 | N24: =C24 * M24 -> -82156.701 | O24: =IF(D24="Net Asset Value",O23,-SUM(N11:N24)) -> 1147564.2 | P24: =IF(D24="Net Asset Value", O24, C24) -> -19038.491 | Q24: =_xlfn.XLOOKUP(B24,'Share Price'!D:D,'Share Price'!G:G) -> 136.04 | R24: =_xlfn.XLOOKUP(C3,'Share Price'!D:D,'Share Price'!G:G) -> 118.09 | S24: =R24/Q24 -> 0.86805351 | T24: =C24 * S24 -> -16526.429 | U24: =IF(D24="Net Asset Value",U23,-SUM(T11:T24)) -> 191223.14 | V24: =IF(D24="Net Asset Value", U24, C24) -> -19038.491
B25: 39782 | C25: -44797.408 | D25: Contribution | E25: =_xlfn.XLOOKUP(B25,'Share Price'!D:D,'Share Price'!E:E) -> 28.9996 | F25: =_xlfn.XLOOKUP(C3,'Share Price'!D:D,'Share Price'!E:E) -> 347.99 | G25: =F25/E25 -> 11.999821 | H25: =C25 * G25 -> -537560.87 | I25: =IF(D25="Net Asset Value",I24,-SUM(H11:H25)) -> 3279147 | J25: =IF(D25="Net Asset Value", I25, C25) -> -44797.408 | K25: =_xlfn.XLOOKUP(B25,'Share Price'!D:D,'Share Price'!F:F) -> 90.09 | L25: =_xlfn.XLOOKUP(C3,'Share Price'!D:D,'Share Price'!F:F) -> 417.85 | M25: =L25/K25 -> 4.6381396 | N25: =C25 * M25 -> -207776.63 | O25: =IF(D25="Net Asset Value",O24,-SUM(N11:N25)) -> 1355340.8 | P25: =IF(D25="Net Asset Value", O25, C25) -> -44797.408 | Q25: =_xlfn.XLOOKUP(B25,'Share Price'!D:D,'Share Price'!G:G) -> 124.32 | R25: =_xlfn.XLOOKUP(C3,'Share Price'!D:D,'Share Price'!G:G) -> 118.09 | S25: =R25/Q25 -> 0.94988739 | T25: =C25 * S25 -> -42552.493 | U25: =IF(D25="Net Asset Value",U24,-SUM(T11:T25)) -> 233775.64 | V25: =IF(D25="Net Asset Value", U25, C25) -> -44797.408
B26: 39813 | C26: -37446.28 | D26: Contribution | E26: =_xlfn.XLOOKUP(B26,'Share Price'!D:D,'Share Price'!E:E) -> 29.617 | F26: =_xlfn.XLOOKUP(C3,'Share Price'!D:D,'Share Price'!E:E) -> 347.99 | G26: =F26/E26 -> 11.749671 | H26: =C26 * G26 -> -439981.46 | I26: =IF(D26="Net Asset Value",I25,-SUM(H11:H26)) -> 3719128.5 | J26: =IF(D26="Net Asset Value", I26, C26) -> -37446.28 | K26: =_xlfn.XLOOKUP(B26,'Share Price'!D:D,'Share Price'!F:F) -> 90.24 | L26: =_xlfn.XLOOKUP(C3,'Share Price'!D:D,'Share Price'!F:F) -> 417.85 | M26: =L26/K26 -> 4.63043 | N26: =C26 * M26 -> -173392.38 | O26: =IF(D26="Net Asset Value",O25,-SUM(N11:N26)) -> 1528733.2 | P26: =IF(D26="Net Asset Value", O26, C26) -> -37446.28 | Q26: =_xlfn.XLOOKUP(B26,'Share Price'!D:D,'Share Price'!G:G) -> 118.56 | R26: =_xlfn.XLOOKUP(C3,'Share Price'!D:D,'Share Price'!G:G) -> 118.09 | S26: =R26/Q26 -> 0.99603576 | T26: =C26 * S26 -> -37297.834 | U26: =IF(D26="Net Asset Value",U25,-SUM(T11:T26)) -> 271073.47 | V26: =IF(D26="Net Asset Value", U26, C26) -> -37446.28
B27: 39844 | C27: -49394.592 | D27: Contribution | E27: =_xlfn.XLOOKUP(B27,'Share Price'!D:D,'Share Price'!E:E) -> 28.9398 | F27: =_xlfn.XLOOKUP(C3,'Share Price'!D:D,'Share Price'!E:E) -> 347.99 | G27: =F27/E27 -> 12.024617 | H27: =C27 * G27 -> -593951.03 | I27: =IF(D27="Net Asset Value",I26,-SUM(H11:H27)) -> 4313079.5 | J27: =IF(D27="Net Asset Value", I27, C27) -> -49394.592 | K27: =_xlfn.XLOOKUP(B27,'Share Price'!D:D,'Share Price'!F:F) -> 82.83 | L27: =_xlfn.XLOOKUP(C3,'Share Price'!D:D,'Share Price'!F:F) -> 417.85 | M27: =L27/K27 -> 5.0446698 | N27: =C27 * M27 -> -249179.41 | O27: =IF(D27="Net Asset Value",O26,-SUM(N11:N27)) -> 1777912.6 | P27: =IF(D27="Net Asset Value", O27, C27) -> -49394.592 | Q27: =_xlfn.XLOOKUP(B27,'Share Price'!D:D,'Share Price'!G:G) -> 119.64 | R27: =_xlfn.XLOOKUP(C3,'Share Price'!D:D,'Share Price'!G:G) -> 118.09 | S27: =R27/Q27 -> 0.98704447 | T27: =C27 * S27 -> -48754.659 | U27: =IF(D27="Net Asset Value",U26,-SUM(T11:T27)) -> 319828.13 | V27: =IF(D27="Net Asset Value", U27, C27) -> -49394.592
B28: 39872 | C28: -24805.729 | D28: Contribution | E28: =_xlfn.XLOOKUP(B28,'Share Price'!D:D,'Share Price'!E:E) -> 27.4162 | F28: =_xlfn.XLOOKUP(C3,'Share Price'!D:D,'Share Price'!E:E) -> 347.99 | G28: =F28/E28 -> 12.69286 | H28: =C28 * G28 -> -314855.65 | I28: =IF(D28="Net Asset Value",I27,-SUM(H11:H28)) -> 4627935.2 | J28: =IF(D28="Net Asset Value", I28, C28) -> -24805.729 | K28: =_xlfn.XLOOKUP(B28,'Share Price'!D:D,'Share Price'!F:F) -> 73.93 | L28: =_xlfn.XLOOKUP(C3,'Share Price'!D:D,'Share Price'!F:F) -> 417.85 | M28: =L28/K28 -> 5.6519681 | N28: =C28 * M28 -> -140201.19 | O28: =IF(D28="Net Asset Value",O27,-SUM(N11:N28)) -> 1918113.8 | P28: =IF(D28="Net Asset Value", O28, C28) -> -24805.729 | Q28: =_xlfn.XLOOKUP(B28,'Share Price'!D:D,'Share Price'!G:G) -> 104.04 | R28: =_xlfn.XLOOKUP(C3,'Share Price'!D:D,'Share Price'!G:G) -> 118.09 | S28: =R28/Q28 -> 1.1350442 | T28: =C28 * S28 -> -28155.599 | U28: =IF(D28="Net Asset Value",U27,-SUM(T11:T28)) -> 347983.73 | V28: =IF(D28="Net Asset Value", U28, C28) -> -24805.729
B29: 39903 | C29: -21680.389 | D29: Contribution | E29: =_xlfn.XLOOKUP(B29,'Share Price'!D:D,'Share Price'!E:E) -> 30.1946 | F29: =_xlfn.XLOOKUP(C3,'Share Price'!D:D,'Share Price'!E:E) -> 347.99 | G29: =F29/E29 -> 11.524908 | H29: =C29 * G29 -> -249864.5 | I29: =IF(D29="Net Asset Value",I28,-SUM(H11:H29)) -> 4877799.7 | J29: =IF(D29="Net Asset Value", I29, C29) -> -21680.389 | K29: =_xlfn.XLOOKUP(B29,'Share Price'!D:D,'Share Price'!F:F) -> 79.52 | L29: =_xlfn.XLOOKUP(C3,'Share Price'!D:D,'Share Price'!F:F) -> 417.85 | M29: =L29/K29 -> 5.2546529 | N29: =C29 * M29 -> -113922.92 | O29: =IF(D29="Net Asset Value",O28,-SUM(N11:N29)) -> 2032036.7 | P29: =IF(D29="Net Asset Value", O29, C29) -> -21680.389 | Q29: =_xlfn.XLOOKUP(B29,'Share Price'!D:D,'Share Price'!G:G) -> 106.4 | R29: =_xlfn.XLOOKUP(C3,'Share Price'!D:D,'Share Price'!G:G) -> 118.09 | S29: =R29/Q29 -> 1.1098684 | T29: =C29 * S29 -> -24062.379 | U29: =IF(D29="Net Asset Value",U28,-SUM(T11:T29)) -> 372046.11 | V29: =IF(D29="Net Asset Value", U29, C29) -> -21680.389
B30: 39933 | C30: -20367.789 | D30: Contribution | E30: =_xlfn.XLOOKUP(B30,'Share Price'!D:D,'Share Price'!E:E) -> 34.1383 | F30: =_xlfn.XLOOKUP(C3,'Share Price'!D:D,'Share Price'!E:E) -> 347.99 | G30: =F30/E30 -> 10.193536 | H30: =C30 * G30 -> -207619.8 | I30: =IF(D30="Net Asset Value",I29,-SUM(H11:H30)) -> 5085419.5 | J30: =IF(D30="Net Asset Value", I30, C30) -> -20367.789 | K30: =_xlfn.XLOOKUP(B30,'Share Price'!D:D,'Share Price'!F:F) -> 87.42 | L30: =_xlfn.XLOOKUP(C3,'Share Price'!D:D,'Share Price'!F:F) -> 417.85 | M30: =L30/K30 -> 4.7797987 | N30: =C30 * M30 -> -97353.93 | O30: =IF(D30="Net Asset Value",O29,-SUM(N11:N30)) -> 2129390.6 | P30: =IF(D30="Net Asset Value", O30, C30) -> -20367.789 | Q30: =_xlfn.XLOOKUP(B30,'Share Price'!D:D,'Share Price'!G:G) -> 123.44 | R30: =_xlfn.XLOOKUP(C3,'Share Price'!D:D,'Share Price'!G:G) -> 118.09 | S30: =R30/Q30 -> 0.95665911 | T30: =C30 * S30 -> -19485.031 | U30: =IF(D30="Net Asset Value",U29,-SUM(T11:T30)) -> 391531.14 | V30: =IF(D30="Net Asset Value", U30, C30) -> -20367.789
B31: 39964 | C31: -20722.156 | D31: Contribution | E31: =_xlfn.XLOOKUP(B31,'Share Price'!D:D,'Share Price'!E:E) -> 35.2337 | F31: =_xlfn.XLOOKUP(C3,'Share Price'!D:D,'Share Price'!E:E) -> 347.99 | G31: =F31/E31 -> 9.8766238 | H31: =C31 * G31 -> -204664.94 | I31: =IF(D31="Net Asset Value",I30,-SUM(H11:H31)) -> 5290084.4 | J31: =IF(D31="Net Asset Value", I31, C31) -> -20722.156 | K31: =_xlfn.XLOOKUP(B31,'Share Price'!D:D,'Share Price'!F:F) -> 92.53 | L31: =_xlfn.XLOOKUP(C3,'Share Price'!D:D,'Share Price'!F:F) -> 417.85 | M31: =L31/K31 -> 4.5158327 | N31: =C31 * M31 -> -93577.789 | O31: =IF(D31="Net Asset Value",O30,-SUM(N11:N31)) -> 2222968.4 | P31: =IF(D31="Net Asset Value", O31, C31) -> -20722.156 | Q31: =_xlfn.XLOOKUP(B31,'Share Price'!D:D,'Share Price'!G:G) -> 144.52 | R31: =_xlfn.XLOOKUP(C3,'Share Price'!D:D,'Share Price'!G:G) -> 118.09 | S31: =R31/Q31 -> 0.81711874 | T31: =C31 * S31 -> -16932.462 | U31: =IF(D31="Net Asset Value",U30,-SUM(T11:T31)) -> 408463.6 | V31: =IF(D31="Net Asset Value", U31, C31) -> -20722.156
B32: 39994 | C32: -39179.363 | D32: Contribution | E32: =_xlfn.XLOOKUP(B32,'Share Price'!D:D,'Share Price'!E:E) -> 36.2296 | F32: =_xlfn.XLOOKUP(C3,'Share Price'!D:D,'Share Price'!E:E) -> 347.99 | G32: =F32/E32 -> 9.6051295 | H32: =C32 * G32 -> -376322.86 | I32: =IF(D32="Net Asset Value",I31,-SUM(H11:H32)) -> 5666407.3 | J32: =IF(D32="Net Asset Value", I32, C32) -> -39179.363 | K32: =_xlfn.XLOOKUP(B32,'Share Price'!D:D,'Share Price'!F:F) -> 91.95 | L32: =_xlfn.XLOOKUP(C3,'Share Price'!D:D,'Share Price'!F:F) -> 417.85 | M32: =L32/K32 -> 4.5443176 | N32: =C32 * M32 -> -178043.47 | O32: =IF(D32="Net Asset Value",O31,-SUM(N11:N32)) -> 2401011.9 | P32: =IF(D32="Net Asset Value", O32, C32) -> -39179.363 | Q32: =_xlfn.XLOOKUP(B32,'Share Price'!D:D,'Share Price'!G:G) -> 126.88 | R32: =_xlfn.XLOOKUP(C3,'Share Price'!D:D,'Share Price'!G:G) -> 118.09 | S32: =R32/Q32 -> 0.93072194 | T32: =C32 * S32 -> -36465.093 | U32: =IF(D32="Net Asset Value",U31,-SUM(T11:T32)) -> 444928.69 | V32: =IF(D32="Net Asset Value", U32, C32) -> -39179.363
B33: 40025 | C33: -27037.636 | D33: Contribution | E33: =_xlfn.XLOOKUP(B33,'Share Price'!D:D,'Share Price'!E:E) -> 39.2869 | F33: =_xlfn.XLOOKUP(C3,'Share Price'!D:D,'Share Price'!E:E) -> 347.99 | G33: =F33/E33 -> 8.8576599 | H33: =C33 * G33 -> -239490.18 | I33: =IF(D33="Net Asset Value",I32,-SUM(H11:H33)) -> 5905897.5 | J33: =IF(D33="Net Asset Value", I33, C33) -> -27037.636 | K33: =_xlfn.XLOOKUP(B33,'Share Price'!D:D,'Share Price'!F:F) -> 98.81 | L33: =_xlfn.XLOOKUP(C3,'Share Price'!D:D,'Share Price'!F:F) -> 417.85 | M33: =L33/K33 -> 4.228823 | N33: =C33 * M33 -> -114337.38 | O33: =IF(D33="Net Asset Value",O32,-SUM(N11:N33)) -> 2515349.3 | P33: =IF(D33="Net Asset Value", O33, C33) -> -27037.636 | Q33: =_xlfn.XLOOKUP(B33,'Share Price'!D:D,'Share Price'!G:G) -> 139.68 | R33: =_xlfn.XLOOKUP(C3,'Share Price'!D:D,'Share Price'!G:G) -> 118.09 | S33: =R33/Q33 -> 0.84543242 | T33: =C33 * S33 -> -22858.494 | U33: =IF(D33="Net Asset Value",U32,-SUM(T11:T33)) -> 467787.19 | V33: =IF(D33="Net Asset Value", U33, C33) -> -27037.636
B34: 40056 | C34: -12999.765 | D34: Contribution | E34: =_xlfn.XLOOKUP(B34,'Share Price'!D:D,'Share Price'!E:E) -> 39.8645 | F34: =_xlfn.XLOOKUP(C3,'Share Price'!D:D,'Share Price'!E:E) -> 347.99 | G34: =F34/E34 -> 8.7293206 | H34: =C34 * G34 -> -113479.11 | I34: =IF(D34="Net Asset Value",I33,-SUM(H11:H34)) -> 6019376.6 | J34: =IF(D34="Net Asset Value", I34, C34) -> -12999.765 | K34: =_xlfn.XLOOKUP(B34,'Share Price'!D:D,'Share Price'!F:F) -> 102.46 | L34: =_xlfn.XLOOKUP(C3,'Share Price'!D:D,'Share Price'!F:F) -> 417.85 | M34: =L34/K34 -> 4.0781768 | N34: =C34 * M34 -> -53015.339 | O34: =IF(D34="Net Asset Value",O33,-SUM(N11:N34)) -> 2568364.6 | P34: =IF(D34="Net Asset Value", O34, C34) -> -12999.765 | Q34: =_xlfn.XLOOKUP(B34,'Share Price'!D:D,'Share Price'!G:G) -> 140.84 | R34: =_xlfn.XLOOKUP(C3,'Share Price'!D:D,'Share Price'!G:G) -> 118.09 | S34: =R34/Q34 -> 0.83846918 | T34: =C34 * S34 -> -10899.902 | U34: =IF(D34="Net Asset Value",U33,-SUM(T11:T34)) -> 478687.09 | V34: =IF(D34="Net Asset Value", U34, C34) -> -12999.765
B35: 40086 | C35: -25039.345 | D35: Contribution | E35: =_xlfn.XLOOKUP(B35,'Share Price'!D:D,'Share Price'!E:E) -> 42.0753 | F35: =_xlfn.XLOOKUP(C3,'Share Price'!D:D,'Share Price'!E:E) -> 347.99 | G35: =F35/E35 -> 8.2706481 | H35: =C35 * G35 -> -207091.62 | I35: =IF(D35="Net Asset Value",I34,-SUM(H11:H35)) -> 6226468.2 | J35: =IF(D35="Net Asset Value", I35, C35) -> -25039.345 | K35: =_xlfn.XLOOKUP(B35,'Share Price'!D:D,'Share Price'!F:F) -> 105.59 | L35: =_xlfn.XLOOKUP(C3,'Share Price'!D:D,'Share Price'!F:F) -> 417.85 | M35: =L35/K35 -> 3.9572876 | N35: =C35 * M35 -> -99087.892 | O35: =IF(D35="Net Asset Value",O34,-SUM(N11:N35)) -> 2667452.5 | P35: =IF(D35="Net Asset Value", O35, C35) -> -25039.345 | Q35: =_xlfn.XLOOKUP(B35,'Share Price'!D:D,'Share Price'!G:G) -> 154.64 | R35: =_xlfn.XLOOKUP(C3,'Share Price'!D:D,'Share Price'!G:G) -> 118.09 | S35: =R35/Q35 -> 0.76364459 | T35: =C35 * S35 -> -19121.161 | U35: =IF(D35="Net Asset Value",U34,-SUM(T11:T35)) -> 497808.25 | V35: =IF(D35="Net Asset Value", U35, C35) -> -25039.345
B36: 40117 | C36: -19800.571 | D36: Contribution | E36: =_xlfn.XLOOKUP(B36,'Share Price'!D:D,'Share Price'!E:E) -> 40.7906 | F36: =_xlfn.XLOOKUP(C3,'Share Price'!D:D,'Share Price'!E:E) -> 347.99 | G36: =F36/E36 -> 8.5311322 | H36: =C36 * G36 -> -168921.29 | I36: =IF(D36="Net Asset Value",I35,-SUM(H11:H36)) -> 6395389.5 | J36: =IF(D36="Net Asset Value", I36, C36) -> -19800.571 | K36: =_xlfn.XLOOKUP(B36,'Share Price'!D:D,'Share Price'!F:F) -> 103.56 | L36: =_xlfn.XLOOKUP(C3,'Share Price'!D:D,'Share Price'!F:F) -> 417.85 | M36: =L36/K36 -> 4.034859 | N36: =C36 * M36 -> -79892.514 | O36: =IF(D36="Net Asset Value",O35,-SUM(N11:N36)) -> 2747345 | P36: =IF(D36="Net Asset Value", O36, C36) -> -19800.571 | Q36: =_xlfn.XLOOKUP(B36,'Share Price'!D:D,'Share Price'!G:G) -> 153.8 | R36: =_xlfn.XLOOKUP(C3,'Share Price'!D:D,'Share Price'!G:G) -> 118.09 | S36: =R36/Q36 -> 0.76781534 | T36: =C36 * S36 -> -15203.182 | U36: =IF(D36="Net Asset Value",U35,-SUM(T11:T36)) -> 513011.43 | V36: =IF(D36="Net Asset Value", U36, C36) -> -19800.571
B37: 40147 | C37: -22127.976 | D37: Contribution | E37: =_xlfn.XLOOKUP(B37,'Share Price'!D:D,'Share Price'!E:E) -> 43.3799 | F37: =_xlfn.XLOOKUP(C3,'Share Price'!D:D,'Share Price'!E:E) -> 347.99 | G37: =F37/E37 -> 8.021918 | H37: =C37 * G37 -> -177508.81 | I37: =IF(D37="Net Asset Value",I36,-SUM(H11:H37)) -> 6572898.3 | J37: =IF(D37="Net Asset Value", I37, C37) -> -22127.976 | K37: =_xlfn.XLOOKUP(B37,'Share Price'!D:D,'Share Price'!F:F) -> 109.94 | L37: =_xlfn.XLOOKUP(C3,'Share Price'!D:D,'Share Price'!F:F) -> 417.85 | M37: =L37/K37 -> 3.8007095 | N37: =C37 * M37 -> -84102.008 | O37: =IF(D37="Net Asset Value",O36,-SUM(N11:N37)) -> 2831447 | P37: =IF(D37="Net Asset Value", O37, C37) -> -22127.976 | Q37: =_xlfn.XLOOKUP(B37,'Share Price'!D:D,'Share Price'!G:G) -> 153.64 | R37: =_xlfn.XLOOKUP(C3,'Share Price'!D:D,'Share Price'!G:G) -> 118.09 | S37: =R37/Q37 -> 0.76861494 | T37: =C37 * S37 -> -17007.893 | U37: =IF(D37="Net Asset Value",U36,-SUM(T11:T37)) -> 530019.32 | V37: =IF(D37="Net Asset Value", U37, C37) -> -22127.976
B38: 40178 | C38: -46229.172 | D38: Contribution | E38: =_xlfn.XLOOKUP(B38,'Share Price'!D:D,'Share Price'!E:E) -> 45.5608 | F38: =_xlfn.XLOOKUP(C3,'Share Price'!D:D,'Share Price'!E:E) -> 347.99 | G38: =F38/E38 -> 7.6379256 | H38: =C38 * G38 -> -353094.97 | I38: =IF(D38="Net Asset Value",I37,-SUM(H11:H38)) -> 6925993.3 | J38: =IF(D38="Net Asset Value", I38, C38) -> -46229.172 | K38: =_xlfn.XLOOKUP(B38,'Share Price'!D:D,'Share Price'!F:F) -> 111.44 | L38: =_xlfn.XLOOKUP(C3,'Share Price'!D:D,'Share Price'!F:F) -> 417.85 | M38: =L38/K38 -> 3.7495513 | N38: =C38 * M38 -> -173338.65 | O38: =IF(D38="Net Asset Value",O37,-SUM(N11:N38)) -> 3004785.7 | P38: =IF(D38="Net Asset Value", O38, C38) -> -46229.172 | Q38: =_xlfn.XLOOKUP(B38,'Share Price'!D:D,'Share Price'!G:G) -> 164.84 | R38: =_xlfn.XLOOKUP(C3,'Share Price'!D:D,'Share Price'!G:G) -> 118.09 | S38: =R38/Q38 -> 0.71639165 | T38: =C38 * S38 -> -33118.193 | U38: =IF(D38="Net Asset Value",U37,-SUM(T11:T38)) -> 563137.52 | V38: =IF(D38="Net Asset Value", U38, C38) -> -46229.172
B39: 40209 | C39: -9210.4658 | D39: Contribution | E39: =_xlfn.XLOOKUP(B39,'Share Price'!D:D,'Share Price'!E:E) -> 42.6131 | F39: =_xlfn.XLOOKUP(C3,'Share Price'!D:D,'Share Price'!E:E) -> 347.99 | G39: =F39/E39 -> 8.1662681 | H39: =C39 * G39 -> -75215.133 | I39: =IF(D39="Net Asset Value",I38,-SUM(H11:H39)) -> 7001208.4 | J39: =IF(D39="Net Asset Value", I39, C39) -> -9210.4658 | K39: =_xlfn.XLOOKUP(B39,'Share Price'!D:D,'Share Price'!F:F) -> 107.39 | L39: =_xlfn.XLOOKUP(C3,'Share Price'!D:D,'Share Price'!F:F) -> 417.85 | M39: =L39/K39 -> 3.8909582 | N39: =C39 * M39 -> -35837.537 | O39: =IF(D39="Net Asset Value",O38,-SUM(N11:N39)) -> 3040623.2 | P39: =IF(D39="Net Asset Value", O39, C39) -> -9210.4658 | Q39: =_xlfn.XLOOKUP(B39,'Share Price'!D:D,'Share Price'!G:G) -> 157.84 | R39: =_xlfn.XLOOKUP(C3,'Share Price'!D:D,'Share Price'!G:G) -> 118.09 | S39: =R39/Q39 -> 0.7481627 | T39: =C39 * S39 -> -6890.927 | U39: =IF(D39="Net Asset Value",U38,-SUM(T11:T39)) -> 570028.44 | V39: =IF(D39="Net Asset Value", U39, C39) -> -9210.4658
B40: 40237 | C40: -28639.601 | D40: Contribution | E40: =_xlfn.XLOOKUP(B40,'Share Price'!D:D,'Share Price'!E:E) -> 44.5749 | F40: =_xlfn.XLOOKUP(C3,'Share Price'!D:D,'Share Price'!E:E) -> 347.99 | G40: =F40/E40 -> 7.8068599 | H40: =C40 * G40 -> -223585.36 | I40: =IF(D40="Net Asset Value",I39,-SUM(H11:H40)) -> 7224793.7 | J40: =IF(D40="Net Asset Value", I40, C40) -> -28639.601 | K40: =_xlfn.XLOOKUP(B40,'Share Price'!D:D,'Share Price'!F:F) -> 110.74 | L40: =_xlfn.XLOOKUP(C3,'Share Price'!D:D,'Share Price'!F:F) -> 417.85 | M40: =L40/K40 -> 3.7732527 | N40: =C40 * M40 -> -108064.45 | O40: =IF(D40="Net Asset Value",O39,-SUM(N11:N40)) -> 3148687.7 | P40: =IF(D40="Net Asset Value", O40, C40) -> -28639.601 | Q40: =_xlfn.XLOOKUP(B40,'Share Price'!D:D,'Share Price'!G:G) -> 164.12 | R40: =_xlfn.XLOOKUP(C3,'Share Price'!D:D,'Share Price'!G:G) -> 118.09 | S40: =R40/Q40 -> 0.71953449 | T40: =C40 * S40 -> -20607.181 | U40: =IF(D40="Net Asset Value",U39,-SUM(T11:T40)) -> 590635.62 | V40: =IF(D40="Net Asset Value", U40, C40) -> -28639.601
B41: 40268 | C41: -65926.828 | D41: Contribution | E41: =_xlfn.XLOOKUP(B41,'Share Price'!D:D,'Share Price'!E:E) -> 47.9609 | F41: =_xlfn.XLOOKUP(C3,'Share Price'!D:D,'Share Price'!E:E) -> 347.99 | G41: =F41/E41 -> 7.255702 | H41: =C41 * G41 -> -478345.42 | I41: =IF(D41="Net Asset Value",I40,-SUM(H11:H41)) -> 7703139.2 | J41: =IF(D41="Net Asset Value", I41, C41) -> -65926.828 | K41: =_xlfn.XLOOKUP(B41,'Share Price'!D:D,'Share Price'!F:F) -> 117 | L41: =_xlfn.XLOOKUP(C3,'Share Price'!D:D,'Share Price'!F:F) -> 417.85 | M41: =L41/K41 -> 3.5713675 | N41: =C41 * M41 -> -235448.93 | O41: =IF(D41="Net Asset Value",O40,-SUM(N11:N41)) -> 3384136.6 | P41: =IF(D41="Net Asset Value", O41, C41) -> -65926.828 | Q41: =_xlfn.XLOOKUP(B41,'Share Price'!D:D,'Share Price'!G:G) -> 168.52 | R41: =_xlfn.XLOOKUP(C3,'Share Price'!D:D,'Share Price'!G:G) -> 118.09 | S41: =R41/Q41 -> 0.70074769 | T41: =C41 * S41 -> -46198.072 | U41: =IF(D41="Net Asset Value",U40,-SUM(T11:T41)) -> 636833.7 | V41: =IF(D41="Net Asset Value", U41, C41) -> -65926.828
B42: 40298 | C42: -71203.043 | D42: Contribution | E42: =_xlfn.XLOOKUP(B42,'Share Price'!D:D,'Share Price'!E:E) -> 49.0339 | F42: =_xlfn.XLOOKUP(C3,'Share Price'!D:D,'Share Price'!E:E) -> 347.99 | G42: =F42/E42 -> 7.0969268 | H42: =C42 * G42 -> -505322.79 | I42: =IF(D42="Net Asset Value",I41,-SUM(H11:H42)) -> 8208462 | J42: =IF(D42="Net Asset Value", I42, C42) -> -71203.043 | K42: =_xlfn.XLOOKUP(B42,'Share Price'!D:D,'Share Price'!F:F) -> 118.8125 | L42: =_xlfn.XLOOKUP(C3,'Share Price'!D:D,'Share Price'!F:F) -> 417.85 | M42: =L42/K42 -> 3.5168858 | N42: =C42 * M42 -> -250412.98 | O42: =IF(D42="Net Asset Value",O41,-SUM(N11:N42)) -> 3634549.6 | P42: =IF(D42="Net Asset Value", O42, C42) -> -71203.043 | Q42: =_xlfn.XLOOKUP(B42,'Share Price'!D:D,'Share Price'!G:G) -> 178.72 | R42: =_xlfn.XLOOKUP(C3,'Share Price'!D:D,'Share Price'!G:G) -> 118.09 | S42: =R42/Q42 -> 0.66075425 | T42: =C42 * S42 -> -47047.714 | U42: =IF(D42="Net Asset Value",U41,-SUM(T11:T42)) -> 683881.41 | V42: =IF(D42="Net Asset Value", U42, C42) -> -71203.043
B43: 40329 | C43: 64516.415 | D43: Distribution | E43: =_xlfn.XLOOKUP(B43,'Share Price'!D:D,'Share Price'!E:E) -> 45.4114 | F43: =_xlfn.XLOOKUP(C3,'Share Price'!D:D,'Share Price'!E:E) -> 347.99 | G43: =F43/E43 -> 7.6630538 | H43: =C43 * G43 -> 494392.76 | I43: =IF(D43="Net Asset Value",I42,-SUM(H11:H43)) -> 7714069.2 | J43: =IF(D43="Net Asset Value", I43, C43) -> 64516.415 | K43: =_xlfn.XLOOKUP(B43,'Share Price'!D:D,'Share Price'!F:F) -> 109.369 | L43: =_xlfn.XLOOKUP(C3,'Share Price'!D:D,'Share Price'!F:F) -> 417.85 | M43: =L43/K43 -> 3.8205524 | N43: =C43 * M43 -> 246488.35 | O43: =IF(D43="Net Asset Value",O42,-SUM(N11:N43)) -> 3388061.2 | P43: =IF(D43="Net Asset Value", O43, C43) -> 64516.415 | Q43: =_xlfn.XLOOKUP(B43,'Share Price'!D:D,'Share Price'!G:G) -> 163.88 | R43: =_xlfn.XLOOKUP(C3,'Share Price'!D:D,'Share Price'!G:G) -> 118.09 | S43: =R43/Q43 -> 0.72058824 | T43: =C43 * S43 -> 46489.77 | U43: =IF(D43="Net Asset Value",U42,-SUM(T11:T43)) -> 637391.64 | V43: =IF(D43="Net Asset Value", U43, C43) -> 64516.415
B44: 40359 | C44: 66884.72 | D44: Distribution | E44: =_xlfn.XLOOKUP(B44,'Share Price'!D:D,'Share Price'!E:E) -> 42.5334 | F44: =_xlfn.XLOOKUP(C3,'Share Price'!D:D,'Share Price'!E:E) -> 347.99 | G44: =F44/E44 -> 8.1815702 | H44: =C44 * G44 -> 547222.03 | I44: =IF(D44="Net Asset Value",I43,-SUM(H11:H44)) -> 7166847.2 | J44: =IF(D44="Net Asset Value", I44, C44) -> 66884.72 | K44: =_xlfn.XLOOKUP(B44,'Share Price'!D:D,'Share Price'!F:F) -> 103.22 | L44: =_xlfn.XLOOKUP(C3,'Share Price'!D:D,'Share Price'!F:F) -> 417.85 | M44: =L44/K44 -> 4.0481496 | N44: =C44 * M44 -> 270759.35 | O44: =IF(D44="Net Asset Value",O43,-SUM(N11:N44)) -> 3117301.9 | P44: =IF(D44="Net Asset Value", O44, C44) -> 66884.72 | Q44: =_xlfn.XLOOKUP(B44,'Share Price'!D:D,'Share Price'!G:G) -> 155.96 | R44: =_xlfn.XLOOKUP(C3,'Share Price'!D:D,'Share Price'!G:G) -> 118.09 | S44: =R44/Q44 -> 0.75718133 | T44: =C44 * S44 -> 50643.861 | U44: =IF(D44="Net Asset Value",U43,-SUM(T11:T44)) -> 586747.78 | V44: =IF(D44="Net Asset Value", U44, C44) -> 66884.72
B45: 40390 | C45: -98847.228 | D45: Contribution | E45: =_xlfn.XLOOKUP(B45,'Share Price'!D:D,'Share Price'!E:E) -> 45.6206 | F45: =_xlfn.XLOOKUP(C3,'Share Price'!D:D,'Share Price'!E:E) -> 347.99 | G45: =F45/E45 -> 7.6279137 | H45: =C45 * G45 -> -753998.13 | I45: =IF(D45="Net Asset Value",I44,-SUM(H11:H45)) -> 7920845.3 | J45: =IF(D45="Net Asset Value", I45, C45) -> -98847.228 | K45: =_xlfn.XLOOKUP(B45,'Share Price'!D:D,'Share Price'!F:F) -> 110.27 | L45: =_xlfn.XLOOKUP(C3,'Share Price'!D:D,'Share Price'!F:F) -> 417.85 | M45: =L45/K45 -> 3.7893353 | N45: =C45 * M45 -> -374565.29 | O45: =IF(D45="Net Asset Value",O44,-SUM(N11:N45)) -> 3491867.2 | P45: =IF(D45="Net Asset Value", O45, C45) -> -98847.228 | Q45: =_xlfn.XLOOKUP(B45,'Share Price'!D:D,'Share Price'!G:G) -> 162.32 | R45: =_xlfn.XLOOKUP(C3,'Share Price'!D:D,'Share Price'!G:G) -> 118.09 | S45: =R45/Q45 -> 0.72751355 | T45: =C45 * S45 -> -71912.698 | U45: =IF(D45="Net Asset Value",U44,-SUM(T11:T45)) -> 658660.48 | V45: =IF(D45="Net Asset Value", U45, C45) -> -98847.228
B46: 40421 | C46: -28034.978 | D46: Contribution | E46: =_xlfn.XLOOKUP(B46,'Share Price'!D:D,'Share Price'!E:E) -> 43.2803 | F46: =_xlfn.XLOOKUP(C3,'Share Price'!D:D,'Share Price'!E:E) -> 347.99 | G46: =F46/E46 -> 8.0403786 | H46: =C46 * G46 -> -225411.84 | I46: =IF(D46="Net Asset Value",I45,-SUM(H11:H46)) -> 8146257.1 | J46: =IF(D46="Net Asset Value", I46, C46) -> -28034.978 | K46: =_xlfn.XLOOKUP(B46,'Share Price'!D:D,'Share Price'!F:F) -> 105.31 | L46: =_xlfn.XLOOKUP(C3,'Share Price'!D:D,'Share Price'!F:F) -> 417.85 | M46: =L46/K46 -> 3.9678093 | N46: =C46 * M46 -> -111237.45 | O46: =IF(D46="Net Asset Value",O45,-SUM(N11:N46)) -> 3603104.6 | P46: =IF(D46="Net Asset Value", O46, C46) -> -28034.978 | Q46: =_xlfn.XLOOKUP(B46,'Share Price'!D:D,'Share Price'!G:G) -> 154.08 | R46: =_xlfn.XLOOKUP(C3,'Share Price'!D:D,'Share Price'!G:G) -> 118.09 | S46: =R46/Q46 -> 0.76642004 | T46: =C46 * S46 -> -21486.569 | U46: =IF(D46="Net Asset Value",U45,-SUM(T11:T46)) -> 680147.05 | V46: =IF(D46="Net Asset Value", U46, C46) -> -28034.978
B47: 40451 | C47: -36800.997 | D47: Contribution | E47: =_xlfn.XLOOKUP(B47,'Share Price'!D:D,'Share Price'!E:E) -> 48.8671 | F47: =_xlfn.XLOOKUP(C3,'Share Price'!D:D,'Share Price'!E:E) -> 347.99 | G47: =F47/E47 -> 7.121151 | H47: =C47 * G47 -> -262065.45 | I47: =IF(D47="Net Asset Value",I46,-SUM(H11:H47)) -> 8408322.6 | J47: =IF(D47="Net Asset Value", I47, C47) -> -36800.997 | K47: =_xlfn.XLOOKUP(B47,'Share Price'!D:D,'Share Price'!F:F) -> 114.13 | L47: =_xlfn.XLOOKUP(C3,'Share Price'!D:D,'Share Price'!F:F) -> 417.85 | M47: =L47/K47 -> 3.6611759 | N47: =C47 * M47 -> -134734.92 | O47: =IF(D47="Net Asset Value",O46,-SUM(N11:N47)) -> 3737839.5 | P47: =IF(D47="Net Asset Value", O47, C47) -> -36800.997 | Q47: =_xlfn.XLOOKUP(B47,'Share Price'!D:D,'Share Price'!G:G) -> 169.04 | R47: =_xlfn.XLOOKUP(C3,'Share Price'!D:D,'Share Price'!G:G) -> 118.09 | S47: =R47/Q47 -> 0.69859205 | T47: =C47 * S47 -> -25708.884 | U47: =IF(D47="Net Asset Value",U46,-SUM(T11:T47)) -> 705855.93 | V47: =IF(D47="Net Asset Value", U47, C47) -> -36800.997
B48: 40482 | C48: 123364.24 | D48: Distribution | E48: =_xlfn.XLOOKUP(B48,'Share Price'!D:D,'Share Price'!E:E) -> 51.9642 | F48: =_xlfn.XLOOKUP(C3,'Share Price'!D:D,'Share Price'!E:E) -> 347.99 | G48: =F48/E48 -> 6.6967258 | H48: =C48 * G48 -> 826136.51 | I48: =IF(D48="Net Asset Value",I47,-SUM(H11:H48)) -> 7582186.1 | J48: =IF(D48="Net Asset Value", I48, C48) -> 123364.24 | K48: =_xlfn.XLOOKUP(B48,'Share Price'!D:D,'Share Price'!F:F) -> 118.49 | L48: =_xlfn.XLOOKUP(C3,'Share Price'!D:D,'Share Price'!F:F) -> 417.85 | M48: =L48/K48 -> 3.5264579 | N48: =C48 * M48 -> 435038.81 | O48: =IF(D48="Net Asset Value",O47,-SUM(N11:N48)) -> 3302800.7 | P48: =IF(D48="Net Asset Value", O48, C48) -> 123364.24 | Q48: =_xlfn.XLOOKUP(B48,'Share Price'!D:D,'Share Price'!G:G) -> 175.4 | R48: =_xlfn.XLOOKUP(C3,'Share Price'!D:D,'Share Price'!G:G) -> 118.09 | S48: =R48/Q48 -> 0.67326112 | T48: =C48 * S48 -> 83056.348 | U48: =IF(D48="Net Asset Value",U47,-SUM(T11:T48)) -> 622799.58 | V48: =IF(D48="Net Asset Value", U48, C48) -> 123364.24
B49: 40512 | C49: -141394.19 | D49: Contribution | E49: =_xlfn.XLOOKUP(B49,'Share Price'!D:D,'Share Price'!E:E) -> 51.8696 | F49: =_xlfn.XLOOKUP(C3,'Share Price'!D:D,'Share Price'!E:E) -> 347.99 | G49: =F49/E49 -> 6.7089393 | H49: =C49 * G49 -> -948605.04 | I49: =IF(D49="Net Asset Value",I48,-SUM(H11:H49)) -> 8530791.1 | J49: =IF(D49="Net Asset Value", I49, C49) -> -141394.19 | K49: =_xlfn.XLOOKUP(B49,'Share Price'!D:D,'Share Price'!F:F) -> 118.4925 | L49: =_xlfn.XLOOKUP(C3,'Share Price'!D:D,'Share Price'!F:F) -> 417.85 | M49: =L49/K49 -> 3.5263835 | N49: =C49 * M49 -> -498610.14 | O49: =IF(D49="Net Asset Value",O48,-SUM(N11:N49)) -> 3801410.8 | P49: =IF(D49="Net Asset Value", O49, C49) -> -141394.19 | Q49: =_xlfn.XLOOKUP(B49,'Share Price'!D:D,'Share Price'!G:G) -> 192.96 | R49: =_xlfn.XLOOKUP(C3,'Share Price'!D:D,'Share Price'!G:G) -> 118.09 | S49: =R49/Q49 -> 0.61199212 | T49: =C49 * S49 -> -86532.13 | U49: =IF(D49="Net Asset Value",U48,-SUM(T11:T49)) -> 709331.71 | V49: =IF(D49="Net Asset Value", U49, C49) -> -141394.19
B50: 40543 | C50: 160207.24 | D50: Distribution | E50: =_xlfn.XLOOKUP(B50,'Share Price'!D:D,'Share Price'!E:E) -> 54.2348 | F50: =_xlfn.XLOOKUP(C3,'Share Price'!D:D,'Share Price'!E:E) -> 347.99 | G50: =F50/E50 -> 6.41636 | H50: =C50 * G50 -> 1027947.3 | I50: =IF(D50="Net Asset Value",I49,-SUM(H11:H50)) -> 7502843.8 | J50: =IF(D50="Net Asset Value", I50, C50) -> 160207.24 | K50: =_xlfn.XLOOKUP(B50,'Share Price'!D:D,'Share Price'!F:F) -> 125.75 | L50: =_xlfn.XLOOKUP(C3,'Share Price'!D:D,'Share Price'!F:F) -> 417.85 | M50: =L50/K50 -> 3.3228628 | N50: =C50 * M50 -> 532346.68 | O50: =IF(D50="Net Asset Value",O49,-SUM(N11:N50)) -> 3269064.2 | P50: =IF(D50="Net Asset Value", O50, C50) -> 160207.24 | Q50: =_xlfn.XLOOKUP(B50,'Share Price'!D:D,'Share Price'!G:G) -> 211 | R50: =_xlfn.XLOOKUP(C3,'Share Price'!D:D,'Share Price'!G:G) -> 118.09 | S50: =R50/Q50 -> 0.55966825 | T50: =C50 * S50 -> 89662.905 | U50: =IF(D50="Net Asset Value",U49,-SUM(T11:T50)) -> 619668.81 | V50: =IF(D50="Net Asset Value", U50, C50) -> 160207.24
B51: 40574 | C51: -20854.107 | D51: Contribution | E51: =_xlfn.XLOOKUP(B51,'Share Price'!D:D,'Share Price'!E:E) -> 55.7684 | F51: =_xlfn.XLOOKUP(C3,'Share Price'!D:D,'Share Price'!E:E) -> 347.99 | G51: =F51/E51 -> 6.2399136 | H51: =C51 * G51 -> -130127.83 | I51: =IF(D51="Net Asset Value",I50,-SUM(H11:H51)) -> 7632971.6 | J51: =IF(D51="Net Asset Value", I51, C51) -> -20854.107 | K51: =_xlfn.XLOOKUP(B51,'Share Price'!D:D,'Share Price'!F:F) -> 128.68 | L51: =_xlfn.XLOOKUP(C3,'Share Price'!D:D,'Share Price'!F:F) -> 417.85 | M51: =L51/K51 -> 3.2472024 | N51: =C51 * M51 -> -67717.506 | O51: =IF(D51="Net Asset Value",O50,-SUM(N11:N51)) -> 3336781.7 | P51: =IF(D51="Net Asset Value", O51, C51) -> -20854.107 | Q51: =_xlfn.XLOOKUP(B51,'Share Price'!D:D,'Share Price'!G:G) -> 227 | R51: =_xlfn.XLOOKUP(C3,'Share Price'!D:D,'Share Price'!G:G) -> 118.09 | S51: =R51/Q51 -> 0.52022026 | T51: =C51 * S51 -> -10848.729 | U51: =IF(D51="Net Asset Value",U50,-SUM(T11:T51)) -> 630517.54 | V51: =IF(D51="Net Asset Value", U51, C51) -> -20854.107
B52: 40602 | C52: -26522.748 | D52: Contribution | E52: =_xlfn.XLOOKUP(B52,'Share Price'!D:D,'Share Price'!E:E) -> 57.53 | F52: =_xlfn.XLOOKUP(C3,'Share Price'!D:D,'Share Price'!E:E) -> 347.99 | G52: =F52/E52 -> 6.0488441 | H52: =C52 * G52 -> -160431.97 | I52: =IF(D52="Net Asset Value",I51,-SUM(H11:H52)) -> 7793403.6 | J52: =IF(D52="Net Asset Value", I52, C52) -> -26522.748 | K52: =_xlfn.XLOOKUP(B52,'Share Price'!D:D,'Share Price'!F:F) -> 133.15 | L52: =_xlfn.XLOOKUP(C3,'Share Price'!D:D,'Share Price'!F:F) -> 417.85 | M52: =L52/K52 -> 3.13819 | N52: =C52 * M52 -> -83233.422 | O52: =IF(D52="Net Asset Value",O51,-SUM(N11:N52)) -> 3420015.1 | P52: =IF(D52="Net Asset Value", O52, C52) -> -26522.748 | Q52: =_xlfn.XLOOKUP(B52,'Share Price'!D:D,'Share Price'!G:G) -> 246.76 | R52: =_xlfn.XLOOKUP(C3,'Share Price'!D:D,'Share Price'!G:G) -> 118.09 | S52: =R52/Q52 -> 0.47856217 | T52: =C52 * S52 -> -12692.784 | U52: =IF(D52="Net Asset Value",U51,-SUM(T11:T52)) -> 643210.32 | V52: =IF(D52="Net Asset Value", U52, C52) -> -26522.748
B53: 40633 | C53: 13024.691 | D53: Distribution | E53: =_xlfn.XLOOKUP(B53,'Share Price'!D:D,'Share Price'!E:E) -> 57.1925 | F53: =_xlfn.XLOOKUP(C3,'Share Price'!D:D,'Share Price'!E:E) -> 347.99 | G53: =F53/E53 -> 6.0845391 | H53: =C53 * G53 -> 79249.244 | I53: =IF(D53="Net Asset Value",I52,-SUM(H11:H53)) -> 7714154.3 | J53: =IF(D53="Net Asset Value", I53, C53) -> 13024.691 | K53: =_xlfn.XLOOKUP(B53,'Share Price'!D:D,'Share Price'!F:F) -> 132.59 | L53: =_xlfn.XLOOKUP(C3,'Share Price'!D:D,'Share Price'!F:F) -> 417.85 | M53: =L53/K53 -> 3.1514443 | N53: =C53 * M53 -> 41046.59 | O53: =IF(D53="Net Asset Value",O52,-SUM(N11:N53)) -> 3378968.5 | P53: =IF(D53="Net Asset Value", O53, C53) -> 13024.691 | Q53: =_xlfn.XLOOKUP(B53,'Share Price'!D:D,'Share Price'!G:G) -> 257.68 | R53: =_xlfn.XLOOKUP(C3,'Share Price'!D:D,'Share Price'!G:G) -> 118.09 | S53: =R53/Q53 -> 0.45828159 | T53: =C53 * S53 -> 5968.9763 | U53: =IF(D53="Net Asset Value",U52,-SUM(T11:T53)) -> 637241.34 | V53: =IF(D53="Net Asset Value", U53, C53) -> 13024.691
B54: 40663 | C54: -63943.428 | D54: Contribution | E54: =_xlfn.XLOOKUP(B54,'Share Price'!D:D,'Share Price'!E:E) -> 58.8357 | F54: =_xlfn.XLOOKUP(C3,'Share Price'!D:D,'Share Price'!E:E) -> 347.99 | G54: =F54/E54 -> 5.9146063 | H54: =C54 * G54 -> -378200.2 | I54: =IF(D54="Net Asset Value",I53,-SUM(H11:H54)) -> 8092354.5 | J54: =IF(D54="Net Asset Value", I54, C54) -> -63943.428 | K54: =_xlfn.XLOOKUP(B54,'Share Price'!D:D,'Share Price'!F:F) -> 136.43 | L54: =_xlfn.XLOOKUP(C3,'Share Price'!D:D,'Share Price'!F:F) -> 417.85 | M54: =L54/K54 -> 3.0627428 | N54: =C54 * M54 -> -195842.27 | O54: =IF(D54="Net Asset Value",O53,-SUM(N11:N54)) -> 3574810.8 | P54: =IF(D54="Net Asset Value", O54, C54) -> -63943.428 | Q54: =_xlfn.XLOOKUP(B54,'Share Price'!D:D,'Share Price'!G:G) -> 254.88 | R54: =_xlfn.XLOOKUP(C3,'Share Price'!D:D,'Share Price'!G:G) -> 118.09 | S54: =R54/Q54 -> 0.46331607 | T54: =C54 * S54 -> -29626.018 | U54: =IF(D54="Net Asset Value",U53,-SUM(T11:T54)) -> 666867.36 | V54: =IF(D54="Net Asset Value", U54, C54) -> -63943.428
B55: 40694 | C55: 57597.464 | D55: Distribution | E55: =_xlfn.XLOOKUP(B55,'Share Price'!D:D,'Share Price'!E:E) -> 58.1187 | F55: =_xlfn.XLOOKUP(C3,'Share Price'!D:D,'Share Price'!E:E) -> 347.99 | G55: =F55/E55 -> 5.9875737 | H55: =C55 * G55 -> 344869.06 | I55: =IF(D55="Net Asset Value",I54,-SUM(H11:H55)) -> 7747485.5 | J55: =IF(D55="Net Asset Value", I55, C55) -> 57597.464 | K55: =_xlfn.XLOOKUP(B55,'Share Price'!D:D,'Share Price'!F:F) -> 134.9 | L55: =_xlfn.XLOOKUP(C3,'Share Price'!D:D,'Share Price'!F:F) -> 417.85 | M55: =L55/K55 -> 3.0974796 | N55: =C55 * M55 -> 178406.97 | O55: =IF(D55="Net Asset Value",O54,-SUM(N11:N55)) -> 3396403.8 | P55: =IF(D55="Net Asset Value", O55, C55) -> 57597.464 | Q55: =_xlfn.XLOOKUP(B55,'Share Price'!D:D,'Share Price'!G:G) -> 243.6 | R55: =_xlfn.XLOOKUP(C3,'Share Price'!D:D,'Share Price'!G:G) -> 118.09 | S55: =R55/Q55 -> 0.48477011 | T55: =C55 * S55 -> 27921.529 | U55: =IF(D55="Net Asset Value",U54,-SUM(T11:T55)) -> 638945.83 | V55: =IF(D55="Net Asset Value", U55, C55) -> 57597.464
B56: 40724 | C56: -60478.371 | D56: Contribution | E56: =_xlfn.XLOOKUP(B56,'Share Price'!D:D,'Share Price'!E:E) -> 56.8141 | F56: =_xlfn.XLOOKUP(C3,'Share Price'!D:D,'Share Price'!E:E) -> 347.99 | G56: =F56/E56 -> 6.125064 | H56: =C56 * G56 -> -370433.89 | I56: =IF(D56="Net Asset Value",I55,-SUM(H11:H56)) -> 8117919.4 | J56: =IF(D56="Net Asset Value", I56, C56) -> -60478.371 | K56: =_xlfn.XLOOKUP(B56,'Share Price'!D:D,'Share Price'!F:F) -> 131.97 | L56: =_xlfn.XLOOKUP(C3,'Share Price'!D:D,'Share Price'!F:F) -> 417.85 | M56: =L56/K56 -> 3.1662499 | N56: =C56 * M56 -> -191489.64 | O56: =IF(D56="Net Asset Value",O55,-SUM(N11:N56)) -> 3587893.4 | P56: =IF(D56="Net Asset Value", O56, C56) -> -60478.371 | Q56: =_xlfn.XLOOKUP(B56,'Share Price'!D:D,'Share Price'!G:G) -> 235.12 | R56: =_xlfn.XLOOKUP(C3,'Share Price'!D:D,'Share Price'!G:G) -> 118.09 | S56: =R56/Q56 -> 0.50225417 | T56: =C56 * S56 -> -30375.514 | U56: =IF(D56="Net Asset Value",U55,-SUM(T11:T56)) -> 669321.35 | V56: =IF(D56="Net Asset Value", U56, C56) -> -60478.371
B57: 40755 | C57: -38555.151 | D57: Contribution | E57: =_xlfn.XLOOKUP(B57,'Share Price'!D:D,'Share Price'!E:E) -> 57.7602 | F57: =_xlfn.XLOOKUP(C3,'Share Price'!D:D,'Share Price'!E:E) -> 347.99 | G57: =F57/E57 -> 6.0247368 | H57: =C57 * G57 -> -232284.64 | I57: =IF(D57="Net Asset Value",I56,-SUM(H11:H57)) -> 8350204 | J57: =IF(D57="Net Asset Value", I57, C57) -> -38555.151 | K57: =_xlfn.XLOOKUP(B57,'Share Price'!D:D,'Share Price'!F:F) -> 129.33 | L57: =_xlfn.XLOOKUP(C3,'Share Price'!D:D,'Share Price'!F:F) -> 417.85 | M57: =L57/K57 -> 3.2308822 | N57: =C57 * M57 -> -124567.15 | O57: =IF(D57="Net Asset Value",O56,-SUM(N11:N57)) -> 3712460.6 | P57: =IF(D57="Net Asset Value", O57, C57) -> -38555.151 | Q57: =_xlfn.XLOOKUP(B57,'Share Price'!D:D,'Share Price'!G:G) -> 248.8 | R57: =_xlfn.XLOOKUP(C3,'Share Price'!D:D,'Share Price'!G:G) -> 118.09 | S57: =R57/Q57 -> 0.47463826 | T57: =C57 * S57 -> -18299.75 | U57: =IF(D57="Net Asset Value",U56,-SUM(T11:T57)) -> 687621.1 | V57: =IF(D57="Net Asset Value", U57, C57) -> -38555.151
B58: 40786 | C58: 115268.31 | D58: Distribution | E58: =_xlfn.XLOOKUP(B58,'Share Price'!D:D,'Share Price'!E:E) -> 54.8323 | F58: =_xlfn.XLOOKUP(C3,'Share Price'!D:D,'Share Price'!E:E) -> 347.99 | G58: =F58/E58 -> 6.3464418 | H58: =C58 * G58 -> 731543.6 | I58: =IF(D58="Net Asset Value",I57,-SUM(H11:H58)) -> 7618660.4 | J58: =IF(D58="Net Asset Value", I58, C58) -> 115268.31 | K58: =_xlfn.XLOOKUP(B58,'Share Price'!D:D,'Share Price'!F:F) -> 122.22 | L58: =_xlfn.XLOOKUP(C3,'Share Price'!D:D,'Share Price'!F:F) -> 417.85 | M58: =L58/K58 -> 3.4188349 | N58: =C58 * M58 -> 394083.31 | O58: =IF(D58="Net Asset Value",O57,-SUM(N11:N58)) -> 3318377.3 | P58: =IF(D58="Net Asset Value", O58, C58) -> 115268.31 | Q58: =_xlfn.XLOOKUP(B58,'Share Price'!D:D,'Share Price'!G:G) -> 214.68 | R58: =_xlfn.XLOOKUP(C3,'Share Price'!D:D,'Share Price'!G:G) -> 118.09 | S58: =R58/Q58 -> 0.55007453 | T58: =C58 * S58 -> 63406.16 | U58: =IF(D58="Net Asset Value",U57,-SUM(T11:T58)) -> 624214.94 | V58: =IF(D58="Net Asset Value", U58, C58) -> 115268.31
B59: 40816 | C59: 6460.4326 | D59: Distribution | E59: =_xlfn.XLOOKUP(B59,'Share Price'!D:D,'Share Price'!E:E) -> 52.273 | F59: =_xlfn.XLOOKUP(C3,'Share Price'!D:D,'Share Price'!E:E) -> 347.99 | G59: =F59/E59 -> 6.6571653 | H59: =C59 * G59 -> 43008.167 | I59: =IF(D59="Net Asset Value",I58,-SUM(H11:H59)) -> 7575652.2 | J59: =IF(D59="Net Asset Value", I59, C59) -> 6460.4326 | K59: =_xlfn.XLOOKUP(B59,'Share Price'!D:D,'Share Price'!F:F) -> 113.15 | L59: =_xlfn.XLOOKUP(C3,'Share Price'!D:D,'Share Price'!F:F) -> 417.85 | M59: =L59/K59 -> 3.6928856 | N59: =C59 * M59 -> 23857.638 | O59: =IF(D59="Net Asset Value",O58,-SUM(N11:N59)) -> 3294519.7 | P59: =IF(D59="Net Asset Value", O59, C59) -> 6460.4326 | Q59: =_xlfn.XLOOKUP(B59,'Share Price'!D:D,'Share Price'!G:G) -> 171.44 | R59: =_xlfn.XLOOKUP(C3,'Share Price'!D:D,'Share Price'!G:G) -> 118.09 | S59: =R59/Q59 -> 0.68881241 | T59: =C59 * S59 -> 4450.0262 | U59: =IF(D59="Net Asset Value",U58,-SUM(T11:T59)) -> 619764.91 | V59: =IF(D59="Net Asset Value", U59, C59) -> 6460.4326
B60: 40847 | C60: -49089.927 | D60: Contribution | E60: =_xlfn.XLOOKUP(B60,'Share Price'!D:D,'Share Price'!E:E) -> 57.7104 | F60: =_xlfn.XLOOKUP(C3,'Share Price'!D:D,'Share Price'!E:E) -> 347.99 | G60: =F60/E60 -> 6.0299357 | H60: =C60 * G60 -> -296009.1 | I60: =IF(D60="Net Asset Value",I59,-SUM(H11:H60)) -> 7871661.3 | J60: =IF(D60="Net Asset Value", I60, C60) -> -49089.927 | K60: =_xlfn.XLOOKUP(B60,'Share Price'!D:D,'Share Price'!F:F) -> 125.5 | L60: =_xlfn.XLOOKUP(C3,'Share Price'!D:D,'Share Price'!F:F) -> 417.85 | M60: =L60/K60 -> 3.3294821 | N60: =C60 * M60 -> -163444.03 | O60: =IF(D60="Net Asset Value",O59,-SUM(N11:N60)) -> 3457963.7 | P60: =IF(D60="Net Asset Value", O60, C60) -> -49089.927 | Q60: =_xlfn.XLOOKUP(B60,'Share Price'!D:D,'Share Price'!G:G) -> 215.4 | R60: =_xlfn.XLOOKUP(C3,'Share Price'!D:D,'Share Price'!G:G) -> 118.09 | S60: =R60/Q60 -> 0.54823584 | T60: =C60 * S60 -> -26912.857 | U60: =IF(D60="Net Asset Value",U59,-SUM(T11:T60)) -> 646677.77 | V60: =IF(D60="Net Asset Value", U60, C60) -> -49089.927
B61: 40877 | C61: 177647.23 | D61: Distribution | E61: =_xlfn.XLOOKUP(B61,'Share Price'!D:D,'Share Price'!E:E) -> 56.1568 | F61: =_xlfn.XLOOKUP(C3,'Share Price'!D:D,'Share Price'!E:E) -> 347.99 | G61: =F61/E61 -> 6.1967562 | H61: =C61 * G61 -> 1100836.6 | I61: =IF(D61="Net Asset Value",I60,-SUM(H11:H61)) -> 6770824.8 | J61: =IF(D61="Net Asset Value", I61, C61) -> 177647.23 | K61: =_xlfn.XLOOKUP(B61,'Share Price'!D:D,'Share Price'!F:F) -> 124.99 | L61: =_xlfn.XLOOKUP(C3,'Share Price'!D:D,'Share Price'!F:F) -> 417.85 | M61: =L61/K61 -> 3.3430674 | N61: =C61 * M61 -> 593886.67 | O61: =IF(D61="Net Asset Value",O60,-SUM(N11:N61)) -> 2864077 | P61: =IF(D61="Net Asset Value", O61, C61) -> 177647.23 | Q61: =_xlfn.XLOOKUP(B61,'Share Price'!D:D,'Share Price'!G:G) -> 220.68 | R61: =_xlfn.XLOOKUP(C3,'Share Price'!D:D,'Share Price'!G:G) -> 118.09 | S61: =R61/Q61 -> 0.53511872 | T61: =C61 * S61 -> 95062.36 | U61: =IF(D61="Net Asset Value",U60,-SUM(T11:T61)) -> 551615.41 | V61: =IF(D61="Net Asset Value", U61, C61) -> 177647.23
B62: 40908 | C62: 71388.155 | D62: Distribution | E62: =_xlfn.XLOOKUP(B62,'Share Price'!D:D,'Share Price'!E:E) -> 55.5991 | F62: =_xlfn.XLOOKUP(C3,'Share Price'!D:D,'Share Price'!E:E) -> 347.99 | G62: =F62/E62 -> 6.2589143 | H62: =C62 * G62 -> 446812.34 | I62: =IF(D62="Net Asset Value",I61,-SUM(H11:H62)) -> 6324012.4 | J62: =IF(D62="Net Asset Value", I62, C62) -> 71388.155 | K62: =_xlfn.XLOOKUP(B62,'Share Price'!D:D,'Share Price'!F:F) -> 125.5 | L62: =_xlfn.XLOOKUP(C3,'Share Price'!D:D,'Share Price'!F:F) -> 417.85 | M62: =L62/K62 -> 3.3294821 | N62: =C62 * M62 -> 237685.58 | O62: =IF(D62="Net Asset Value",O61,-SUM(N11:N62)) -> 2626391.4 | P62: =IF(D62="Net Asset Value", O62, C62) -> 71388.155 | Q62: =_xlfn.XLOOKUP(B62,'Share Price'!D:D,'Share Price'!G:G) -> 210.76 | R62: =_xlfn.XLOOKUP(C3,'Share Price'!D:D,'Share Price'!G:G) -> 118.09 | S62: =R62/Q62 -> 0.56030556 | T62: =C62 * S62 -> 39999.18 | U62: =IF(D62="Net Asset Value",U61,-SUM(T11:T62)) -> 511616.23 | V62: =IF(D62="Net Asset Value", U62, C62) -> 71388.155
B63: 40939 | C63: -17997.631 | D63: Contribution | E63: =_xlfn.XLOOKUP(B63,'Share Price'!D:D,'Share Price'!E:E) -> 60.2797 | F63: =_xlfn.XLOOKUP(C3,'Share Price'!D:D,'Share Price'!E:E) -> 347.99 | G63: =F63/E63 -> 5.7729219 | H63: =C63 * G63 -> -103898.92 | I63: =IF(D63="Net Asset Value",I62,-SUM(H11:H63)) -> 6427911.3 | J63: =IF(D63="Net Asset Value", I63, C63) -> -17997.631 | K63: =_xlfn.XLOOKUP(B63,'Share Price'!D:D,'Share Price'!F:F) -> 131.32 | L63: =_xlfn.XLOOKUP(C3,'Share Price'!D:D,'Share Price'!F:F) -> 417.85 | M63: =L63/K63 -> 3.181922 | N63: =C63 * M63 -> -57267.059 | O63: =IF(D63="Net Asset Value",O62,-SUM(N11:N63)) -> 2683658.5 | P63: =IF(D63="Net Asset Value", O63, C63) -> -17997.631 | Q63: =_xlfn.XLOOKUP(B63,'Share Price'!D:D,'Share Price'!G:G) -> 218.32 | R63: =_xlfn.XLOOKUP(C3,'Share Price'!D:D,'Share Price'!G:G) -> 118.09 | S63: =R63/Q63 -> 0.54090326 | T63: =C63 * S63 -> -9734.9774 | U63: =IF(D63="Net Asset Value",U62,-SUM(T11:T63)) -> 521351.21 | V63: =IF(D63="Net Asset Value", U63, C63) -> -17997.631
B64: 40968 | C64: 57106.409 | D64: Distribution | E64: =_xlfn.XLOOKUP(B64,'Share Price'!D:D,'Share Price'!E:E) -> 64.1437 | F64: =_xlfn.XLOOKUP(C3,'Share Price'!D:D,'Share Price'!E:E) -> 347.99 | G64: =F64/E64 -> 5.4251626 | H64: =C64 * G64 -> 309811.55 | I64: =IF(D64="Net Asset Value",I63,-SUM(H11:H64)) -> 6118099.8 | J64: =IF(D64="Net Asset Value", I64, C64) -> 57106.409 | K64: =_xlfn.XLOOKUP(B64,'Share Price'!D:D,'Share Price'!F:F) -> 137.02 | L64: =_xlfn.XLOOKUP(C3,'Share Price'!D:D,'Share Price'!F:F) -> 417.85 | M64: =L64/K64 -> 3.0495548 | N64: =C64 * M64 -> 174149.13 | O64: =IF(D64="Net Asset Value",O63,-SUM(N11:N64)) -> 2509509.4 | P64: =IF(D64="Net Asset Value", O64, C64) -> 57106.409 | Q64: =_xlfn.XLOOKUP(B64,'Share Price'!D:D,'Share Price'!G:G) -> 237.28 | R64: =_xlfn.XLOOKUP(C3,'Share Price'!D:D,'Share Price'!G:G) -> 118.09 | S64: =R64/Q64 -> 0.49768206 | T64: =C64 * S64 -> 28420.836 | U64: =IF(D64="Net Asset Value",U63,-SUM(T11:T64)) -> 492930.37 | V64: =IF(D64="Net Asset Value", U64, C64) -> 57106.409
B65: 40999 | C65: -46354.925 | D65: Contribution | E65: =_xlfn.XLOOKUP(B65,'Share Price'!D:D,'Share Price'!E:E) -> 67.2707 | F65: =_xlfn.XLOOKUP(C3,'Share Price'!D:D,'Share Price'!E:E) -> 347.99 | G65: =F65/E65 -> 5.1729802 | H65: =C65 * G65 -> -239793.11 | I65: =IF(D65="Net Asset Value",I64,-SUM(H11:H65)) -> 6357892.9 | J65: =IF(D65="Net Asset Value", I65, C65) -> -46354.925 | K65: =_xlfn.XLOOKUP(B65,'Share Price'!D:D,'Share Price'!F:F) -> 140.81 | L65: =_xlfn.XLOOKUP(C3,'Share Price'!D:D,'Share Price'!F:F) -> 417.85 | M65: =L65/K65 -> 2.9674739 | N65: =C65 * M65 -> -137557.03 | O65: =IF(D65="Net Asset Value",O64,-SUM(N11:N65)) -> 2647066.4 | P65: =IF(D65="Net Asset Value", O65, C65) -> -46354.925 | Q65: =_xlfn.XLOOKUP(B65,'Share Price'!D:D,'Share Price'!G:G) -> 227.64 | R65: =_xlfn.XLOOKUP(C3,'Share Price'!D:D,'Share Price'!G:G) -> 118.09 | S65: =R65/Q65 -> 0.51875769 | T65: =C65 * S65 -> -24046.974 | U65: =IF(D65="Net Asset Value",U64,-SUM(T11:T65)) -> 516977.34 | V65: =IF(D65="Net Asset Value", U65, C65) -> -46354.925
B66: 41029 | C66: 276949.42 | D66: Distribution | E66: =_xlfn.XLOOKUP(B66,'Share Price'!D:D,'Share Price'!E:E) -> 66.4839 | F66: =_xlfn.XLOOKUP(C3,'Share Price'!D:D,'Share Price'!E:E) -> 347.99 | G66: =F66/E66 -> 5.2341996 | H66: =C66 * G66 -> 1449608.6 | I66: =IF(D66="Net Asset Value",I65,-SUM(H11:H66)) -> 4908284.3 | J66: =IF(D66="Net Asset Value", I66, C66) -> 276949.42 | K66: =_xlfn.XLOOKUP(B66,'Share Price'!D:D,'Share Price'!F:F) -> 139.87 | L66: =_xlfn.XLOOKUP(C3,'Share Price'!D:D,'Share Price'!F:F) -> 417.85 | M66: =L66/K66 -> 2.9874169 | N66: =C66 * M66 -> 827363.39 | O66: =IF(D66="Net Asset Value",O65,-SUM(N11:N66)) -> 1819703 | P66: =IF(D66="Net Asset Value", O66, C66) -> 276949.42 | Q66: =_xlfn.XLOOKUP(B66,'Share Price'!D:D,'Share Price'!G:G) -> 225.48 | R66: =_xlfn.XLOOKUP(C3,'Share Price'!D:D,'Share Price'!G:G) -> 118.09 | S66: =R66/Q66 -> 0.52372716 | T66: =C66 * S66 -> 145045.94 | U66: =IF(D66="Net Asset Value",U65,-SUM(T11:T66)) -> 371931.41 | V66: =IF(D66="Net Asset Value", U66, C66) -> 276949.42
B67: 41060 | C67: -77213.179 | D67: Contribution | E67: =_xlfn.XLOOKUP(B67,'Share Price'!D:D,'Share Price'!E:E) -> 61.8034 | F67: =_xlfn.XLOOKUP(C3,'Share Price'!D:D,'Share Price'!E:E) -> 347.99 | G67: =F67/E67 -> 5.6305964 | H67: =C67 * G67 -> -434756.24 | I67: =IF(D67="Net Asset Value",I66,-SUM(H11:H67)) -> 5343040.6 | J67: =IF(D67="Net Asset Value", I67, C67) -> -77213.179 | K67: =_xlfn.XLOOKUP(B67,'Share Price'!D:D,'Share Price'!F:F) -> 131.47 | L67: =_xlfn.XLOOKUP(C3,'Share Price'!D:D,'Share Price'!F:F) -> 417.85 | M67: =L67/K67 -> 3.1782916 | N67: =C67 * M67 -> -245406 | O67: =IF(D67="Net Asset Value",O66,-SUM(N11:N67)) -> 2065109 | P67: =IF(D67="Net Asset Value", O67, C67) -> -77213.179 | Q67: =_xlfn.XLOOKUP(B67,'Share Price'!D:D,'Share Price'!G:G) -> 191.72 | R67: =_xlfn.XLOOKUP(C3,'Share Price'!D:D,'Share Price'!G:G) -> 118.09 | S67: =R67/Q67 -> 0.61595034 | T67: =C67 * S67 -> -47559.484 | U67: =IF(D67="Net Asset Value",U66,-SUM(T11:T67)) -> 419490.89 | V67: =IF(D67="Net Asset Value", U67, C67) -> -77213.179
B68: 41090 | C68: -9454.4493 | D68: Contribution | E68: =_xlfn.XLOOKUP(B68,'Share Price'!D:D,'Share Price'!E:E) -> 63.8947 | F68: =_xlfn.XLOOKUP(C3,'Share Price'!D:D,'Share Price'!E:E) -> 347.99 | G68: =F68/E68 -> 5.4463046 | H68: =C68 * G68 -> -51491.811 | I68: =IF(D68="Net Asset Value",I67,-SUM(H11:H68)) -> 5394532.4 | J68: =IF(D68="Net Asset Value", I68, C68) -> -9454.4493 | K68: =_xlfn.XLOOKUP(B68,'Share Price'!D:D,'Share Price'!F:F) -> 136.105 | L68: =_xlfn.XLOOKUP(C3,'Share Price'!D:D,'Share Price'!F:F) -> 417.85 | M68: =L68/K68 -> 3.0700562 | N68: =C68 * M68 -> -29025.691 | O68: =IF(D68="Net Asset Value",O67,-SUM(N11:N68)) -> 2094134.7 | P68: =IF(D68="Net Asset Value", O68, C68) -> -9454.4493 | Q68: =_xlfn.XLOOKUP(B68,'Share Price'!D:D,'Share Price'!G:G) -> 201.6 | R68: =_xlfn.XLOOKUP(C3,'Share Price'!D:D,'Share Price'!G:G) -> 118.09 | S68: =R68/Q68 -> 0.58576389 | T68: =C68 * S68 -> -5538.075 | U68: =IF(D68="Net Asset Value",U67,-SUM(T11:T68)) -> 425028.97 | V68: =IF(D68="Net Asset Value", U68, C68) -> -9454.4493
B69: 41121 | C69: 22862.088 | D69: Distribution | E69: =_xlfn.XLOOKUP(B69,'Share Price'!D:D,'Share Price'!E:E) -> 64.5321 | F69: =_xlfn.XLOOKUP(C3,'Share Price'!D:D,'Share Price'!E:E) -> 347.99 | G69: =F69/E69 -> 5.3925101 | H69: =C69 * G69 -> 123284.04 | I69: =IF(D69="Net Asset Value",I68,-SUM(H11:H69)) -> 5271248.3 | J69: =IF(D69="Net Asset Value", I69, C69) -> 22862.088 | K69: =_xlfn.XLOOKUP(B69,'Share Price'!D:D,'Share Price'!F:F) -> 137.71 | L69: =_xlfn.XLOOKUP(C3,'Share Price'!D:D,'Share Price'!F:F) -> 417.85 | M69: =L69/K69 -> 3.0342749 | N69: =C69 * M69 -> 69369.861 | O69: =IF(D69="Net Asset Value",O68,-SUM(N11:N69)) -> 2024764.8 | P69: =IF(D69="Net Asset Value", O69, C69) -> 22862.088 | Q69: =_xlfn.XLOOKUP(B69,'Share Price'!D:D,'Share Price'!G:G) -> 204.92 | R69: =_xlfn.XLOOKUP(C3,'Share Price'!D:D,'Share Price'!G:G) -> 118.09 | S69: =R69/Q69 -> 0.57627367 | T69: =C69 * S69 -> 13174.819 | U69: =IF(D69="Net Asset Value",U68,-SUM(T11:T69)) -> 411854.15 | V69: =IF(D69="Net Asset Value", U69, C69) -> 22862.088
B70: 41152 | C70: 409326.72 | D70: Distribution | E70: =_xlfn.XLOOKUP(B70,'Share Price'!D:D,'Share Price'!E:E) -> 67.8782 | F70: =_xlfn.XLOOKUP(C3,'Share Price'!D:D,'Share Price'!E:E) -> 347.99 | G70: =F70/E70 -> 5.1266828 | H70: =C70 * G70 -> 2098488.3 | I70: =IF(D70="Net Asset Value",I69,-SUM(H11:H70)) -> 3172760.1 | J70: =IF(D70="Net Asset Value", I70, C70) -> 409326.72 | K70: =_xlfn.XLOOKUP(B70,'Share Price'!D:D,'Share Price'!F:F) -> 141.16 | L70: =_xlfn.XLOOKUP(C3,'Share Price'!D:D,'Share Price'!F:F) -> 417.85 | M70: =L70/K70 -> 2.9601162 | N70: =C70 * M70 -> 1211654.7 | O70: =IF(D70="Net Asset Value",O69,-SUM(N11:N70)) -> 813110.17 | P70: =IF(D70="Net Asset Value", O70, C70) -> 409326.72 | Q70: =_xlfn.XLOOKUP(B70,'Share Price'!D:D,'Share Price'!G:G) -> 210.96 | R70: =_xlfn.XLOOKUP(C3,'Share Price'!D:D,'Share Price'!G:G) -> 118.09 | S70: =R70/Q70 -> 0.55977436 | T70: =C70 * S70 -> 229130.61 | U70: =IF(D70="Net Asset Value",U69,-SUM(T11:T70)) -> 182723.54 | V70: =IF(D70="Net Asset Value", U70, C70) -> 409326.72
B71: 41182 | C71: -9459.0204 | D71: Contribution | E71: =_xlfn.XLOOKUP(B71,'Share Price'!D:D,'Share Price'!E:E) -> 68.2865 | F71: =_xlfn.XLOOKUP(C3,'Share Price'!D:D,'Share Price'!E:E) -> 347.99 | G71: =F71/E71 -> 5.0960292 | H71: =C71 * G71 -> -48203.444 | I71: =IF(D71="Net Asset Value",I70,-SUM(H11:H71)) -> 3220963.5 | J71: =IF(D71="Net Asset Value", I71, C71) -> -9459.0204 | K71: =_xlfn.XLOOKUP(B71,'Share Price'!D:D,'Share Price'!F:F) -> 143.97 | L71: =_xlfn.XLOOKUP(C3,'Share Price'!D:D,'Share Price'!F:F) -> 417.85 | M71: =L71/K71 -> 2.9023408 | N71: =C71 * M71 -> -27453.3 | O71: =IF(D71="Net Asset Value",O70,-SUM(N11:N71)) -> 840563.48 | P71: =IF(D71="Net Asset Value", O71, C71) -> -9459.0204 | Q71: =_xlfn.XLOOKUP(B71,'Share Price'!D:D,'Share Price'!G:G) -> 222.76 | R71: =_xlfn.XLOOKUP(C3,'Share Price'!D:D,'Share Price'!G:G) -> 118.09 | S71: =R71/Q71 -> 0.5301221 | T71: =C71 * S71 -> -5014.4358 | U71: =IF(D71="Net Asset Value",U70,-SUM(T11:T71)) -> 187737.98 | V71: =IF(D71="Net Asset Value", U71, C71) -> -9459.0204
B72: 41213 | C72: -10310.155 | D72: Contribution | E72: =_xlfn.XLOOKUP(B72,'Share Price'!D:D,'Share Price'!E:E) -> 64.6814 | F72: =_xlfn.XLOOKUP(C3,'Share Price'!D:D,'Share Price'!E:E) -> 347.99 | G72: =F72/E72 -> 5.3800629 | H72: =C72 * G72 -> -55469.281 | I72: =IF(D72="Net Asset Value",I71,-SUM(H11:H72)) -> 3276432.8 | J72: =IF(D72="Net Asset Value", I72, C72) -> -10310.155 | K72: =_xlfn.XLOOKUP(B72,'Share Price'!D:D,'Share Price'!F:F) -> 141.35 | L72: =_xlfn.XLOOKUP(C3,'Share Price'!D:D,'Share Price'!F:F) -> 417.85 | M72: =L72/K72 -> 2.9561372 | N72: =C72 * M72 -> -30478.232 | O72: =IF(D72="Net Asset Value",O71,-SUM(N11:N72)) -> 871041.71 | P72: =IF(D72="Net Asset Value", O72, C72) -> -10310.155 | Q72: =_xlfn.XLOOKUP(B72,'Share Price'!D:D,'Share Price'!G:G) -> 215.08 | R72: =_xlfn.XLOOKUP(C3,'Share Price'!D:D,'Share Price'!G:G) -> 118.09 | S72: =R72/Q72 -> 0.54905152 | T72: =C72 * S72 -> -5660.8061 | U72: =IF(D72="Net Asset Value",U71,-SUM(T11:T72)) -> 193398.78 | V72: =IF(D72="Net Asset Value", U72, C72) -> -10310.155
B73: 41243 | C73: -29501.949 | D73: Contribution | E73: =_xlfn.XLOOKUP(B73,'Share Price'!D:D,'Share Price'!E:E) -> 65.5279 | F73: =_xlfn.XLOOKUP(C3,'Share Price'!D:D,'Share Price'!E:E) -> 347.99 | G73: =F73/E73 -> 5.3105624 | H73: =C73 * G73 -> -156671.94 | I73: =IF(D73="Net Asset Value",I72,-SUM(H11:H73)) -> 3433104.7 | J73: =IF(D73="Net Asset Value", I73, C73) -> -29501.949 | K73: =_xlfn.XLOOKUP(B73,'Share Price'!D:D,'Share Price'!F:F) -> 142.155 | L73: =_xlfn.XLOOKUP(C3,'Share Price'!D:D,'Share Price'!F:F) -> 417.85 | M73: =L73/K73 -> 2.9393971 | N73: =C73 * M73 -> -86717.945 | O73: =IF(D73="Net Asset Value",O72,-SUM(N11:N73)) -> 957759.65 | P73: =IF(D73="Net Asset Value", O73, C73) -> -29501.949 | Q73: =_xlfn.XLOOKUP(B73,'Share Price'!D:D,'Share Price'!G:G) -> 212.04 | R73: =_xlfn.XLOOKUP(C3,'Share Price'!D:D,'Share Price'!G:G) -> 118.09 | S73: =R73/Q73 -> 0.55692322 | T73: =C73 * S73 -> -16430.321 | U73: =IF(D73="Net Asset Value",U72,-SUM(T11:T73)) -> 209829.1 | V73: =IF(D73="Net Asset Value", U73, C73) -> -29501.949
B74: 41274 | C74: 631463.82 | D74: Distribution | E74: =_xlfn.XLOOKUP(B74,'Share Price'!D:D,'Share Price'!E:E) -> 64.8608 | F74: =_xlfn.XLOOKUP(C3,'Share Price'!D:D,'Share Price'!E:E) -> 347.99 | G74: =F74/E74 -> 5.3651821 | H74: =C74 * G74 -> 3387918.4 | I74: =IF(D74="Net Asset Value",I73,-SUM(H11:H74)) -> 45186.381 | J74: =IF(D74="Net Asset Value", I74, C74) -> 631463.82 | K74: =_xlfn.XLOOKUP(B74,'Share Price'!D:D,'Share Price'!F:F) -> 142.41 | L74: =_xlfn.XLOOKUP(C3,'Share Price'!D:D,'Share Price'!F:F) -> 417.85 | M74: =L74/K74 -> 2.9341338 | N74: =C74 * M74 -> 1852799.4 | O74: =IF(D74="Net Asset Value",O73,-SUM(N11:N74)) -> -895039.72 | P74: =IF(D74="Net Asset Value", O74, C74) -> 631463.82 | Q74: =_xlfn.XLOOKUP(B74,'Share Price'!D:D,'Share Price'!G:G) -> 216.32 | R74: =_xlfn.XLOOKUP(C3,'Share Price'!D:D,'Share Price'!G:G) -> 118.09 | S74: =R74/Q74 -> 0.54590422 | T74: =C74 * S74 -> 344718.76 | U74: =IF(D74="Net Asset Value",U73,-SUM(T11:T74)) -> -134889.66 | V74: =IF(D74="Net Asset Value", U74, C74) -> 631463.82
B75: 41305 | C75: -1813 | D75: Contribution | E75: =_xlfn.XLOOKUP(B75,'Share Price'!D:D,'Share Price'!E:E) -> 66.5935 | F75: =_xlfn.XLOOKUP(C3,'Share Price'!D:D,'Share Price'!E:E) -> 347.99 | G75: =F75/E75 -> 5.2255851 | H75: =C75 * G75 -> -9473.9857 | I75: =IF(D75="Net Asset Value",I74,-SUM(H11:H75)) -> 54660.367 | J75: =IF(D75="Net Asset Value", I75, C75) -> -1813 | K75: =_xlfn.XLOOKUP(B75,'Share Price'!D:D,'Share Price'!F:F) -> 149.7 | L75: =_xlfn.XLOOKUP(C3,'Share Price'!D:D,'Share Price'!F:F) -> 417.85 | M75: =L75/K75 -> 2.7912492 | N75: =C75 * M75 -> -5060.5347 | O75: =IF(D75="Net Asset Value",O74,-SUM(N11:N75)) -> -889979.18 | P75: =IF(D75="Net Asset Value", O75, C75) -> -1813 | Q75: =_xlfn.XLOOKUP(B75,'Share Price'!D:D,'Share Price'!G:G) -> 232.4 | R75: =_xlfn.XLOOKUP(C3,'Share Price'!D:D,'Share Price'!G:G) -> 118.09 | S75: =R75/Q75 -> 0.50813253 | T75: =C75 * S75 -> -921.24428 | U75: =IF(D75="Net Asset Value",U74,-SUM(T11:T75)) -> -133968.41 | V75: =IF(D75="Net Asset Value", U75, C75) -> -1813
B76: 41333 | C76: 31319.691 | D76: Distribution | E76: =_xlfn.XLOOKUP(B76,'Share Price'!D:D,'Share Price'!E:E) -> 66.8225 | F76: =_xlfn.XLOOKUP(C3,'Share Price'!D:D,'Share Price'!E:E) -> 347.99 | G76: =F76/E76 -> 5.2076771 | H76: =C76 * G76 -> 163102.83 | I76: =IF(D76="Net Asset Value",I75,-SUM(H11:H76)) -> -108442.47 | J76: =IF(D76="Net Asset Value", I76, C76) -> 31319.691 | K76: =_xlfn.XLOOKUP(B76,'Share Price'!D:D,'Share Price'!F:F) -> 151.61 | L76: =_xlfn.XLOOKUP(C3,'Share Price'!D:D,'Share Price'!F:F) -> 417.85 | M76: =L76/K76 -> 2.7560847 | N76: =C76 * M76 -> 86319.72 | O76: =IF(D76="Net Asset Value",O75,-SUM(N11:N76)) -> -976298.9 | P76: =IF(D76="Net Asset Value", O76, C76) -> 31319.691 | Q76: =_xlfn.XLOOKUP(B76,'Share Price'!D:D,'Share Price'!G:G) -> 231.88 | R76: =_xlfn.XLOOKUP(C3,'Share Price'!D:D,'Share Price'!G:G) -> 118.09 | S76: =R76/Q76 -> 0.50927204 | T76: =C76 * S76 -> 15950.243 | U76: =IF(D76="Net Asset Value",U75,-SUM(T11:T76)) -> -149918.66 | V76: =IF(D76="Net Asset Value", U76, C76) -> 31319.691
B77: 41364 | C77: -20762.29 | D77: Contribution | E77: =_xlfn.XLOOKUP(B77,'Share Price'!D:D,'Share Price'!E:E) -> 68.6848 | F77: =_xlfn.XLOOKUP(C3,'Share Price'!D:D,'Share Price'!E:E) -> 347.99 | G77: =F77/E77 -> 5.0664776 | H77: =C77 * G77 -> -105191.67 | I77: =IF(D77="Net Asset Value",I76,-SUM(H11:H77)) -> -3250.7931 | J77: =IF(D77="Net Asset Value", I77, C77) -> -20762.29 | K77: =_xlfn.XLOOKUP(B77,'Share Price'!D:D,'Share Price'!F:F) -> 156.67 | L77: =_xlfn.XLOOKUP(C3,'Share Price'!D:D,'Share Price'!F:F) -> 417.85 | M77: =L77/K77 -> 2.6670709 | N77: =C77 * M77 -> -55374.499 | O77: =IF(D77="Net Asset Value",O76,-SUM(N11:N77)) -> -920924.4 | P77: =IF(D77="Net Asset Value", O77, C77) -> -20762.29 | Q77: =_xlfn.XLOOKUP(B77,'Share Price'!D:D,'Share Price'!G:G) -> 241.96 | R77: =_xlfn.XLOOKUP(C3,'Share Price'!D:D,'Share Price'!G:G) -> 118.09 | S77: =R77/Q77 -> 0.48805588 | T77: =C77 * S77 -> -10133.157 | U77: =IF(D77="Net Asset Value",U76,-SUM(T11:T77)) -> -139785.5 | V77: =IF(D77="Net Asset Value", U77, C77) -> -20762.29
B78: 41394 | C78: 3.80917 | D78: Distribution | E78: =_xlfn.XLOOKUP(B78,'Share Price'!D:D,'Share Price'!E:E) -> 70.4276 | F78: =_xlfn.XLOOKUP(C3,'Share Price'!D:D,'Share Price'!E:E) -> 347.99 | G78: =F78/E78 -> 4.9411026 | H78: =C78 * G78 -> 18.8215 | I78: =IF(D78="Net Asset Value",I77,-SUM(H11:H78)) -> -3269.6146 | J78: =IF(D78="Net Asset Value", I78, C78) -> 3.80917 | K78: =_xlfn.XLOOKUP(B78,'Share Price'!D:D,'Share Price'!F:F) -> 159.68 | L78: =_xlfn.XLOOKUP(C3,'Share Price'!D:D,'Share Price'!F:F) -> 417.85 | M78: =L78/K78 -> 2.6167961 | N78: =C78 * M78 -> 9.9678212 | O78: =IF(D78="Net Asset Value",O77,-SUM(N11:N78)) -> -920934.37 | P78: =IF(D78="Net Asset Value", O78, C78) -> 3.80917 | Q78: =_xlfn.XLOOKUP(B78,'Share Price'!D:D,'Share Price'!G:G) -> 229.48 | R78: =_xlfn.XLOOKUP(C3,'Share Price'!D:D,'Share Price'!G:G) -> 118.09 | S78: =R78/Q78 -> 0.51459822 | T78: =C78 * S78 -> 1.9601921 | U78: =IF(D78="Net Asset Value",U77,-SUM(T11:T78)) -> -139787.46 | V78: =IF(D78="Net Asset Value", U78, C78) -> 3.80917
B79: 41425 | C79: 5316.1016 | D79: Distribution | E79: =_xlfn.XLOOKUP(B79,'Share Price'!D:D,'Share Price'!E:E) -> 72.9471 | F79: =_xlfn.XLOOKUP(C3,'Share Price'!D:D,'Share Price'!E:E) -> 347.99 | G79: =F79/E79 -> 4.7704432 | H79: =C79 * G79 -> 25360.161 | I79: =IF(D79="Net Asset Value",I78,-SUM(H11:H79)) -> -28629.775 | J79: =IF(D79="Net Asset Value", I79, C79) -> 5316.1016 | K79: =_xlfn.XLOOKUP(B79,'Share Price'!D:D,'Share Price'!F:F) -> 163.445 | L79: =_xlfn.XLOOKUP(C3,'Share Price'!D:D,'Share Price'!F:F) -> 417.85 | M79: =L79/K79 -> 2.5565175 | N79: =C79 * M79 -> 13590.707 | O79: =IF(D79="Net Asset Value",O78,-SUM(N11:N79)) -> -934525.08 | P79: =IF(D79="Net Asset Value", O79, C79) -> 5316.1016 | Q79: =_xlfn.XLOOKUP(B79,'Share Price'!D:D,'Share Price'!G:G) -> 241.564 | R79: =_xlfn.XLOOKUP(C3,'Share Price'!D:D,'Share Price'!G:G) -> 118.09 | S79: =R79/Q79 -> 0.48885596 | T79: =C79 * S79 -> 2598.8079 | U79: =IF(D79="Net Asset Value",U78,-SUM(T11:T79)) -> -142386.27 | V79: =IF(D79="Net Asset Value", U79, C79) -> 5316.1016
B80: 41455 | C80: 73317.052 | D80: Distribution | E80: =_xlfn.XLOOKUP(B80,'Share Price'!D:D,'Share Price'!E:E) -> 70.9753 | F80: =_xlfn.XLOOKUP(C3,'Share Price'!D:D,'Share Price'!E:E) -> 347.99 | G80: =F80/E80 -> 4.9029733 | H80: =C80 * G80 -> 359471.55 | I80: =IF(D80="Net Asset Value",I79,-SUM(H11:H80)) -> -388101.32 | J80: =IF(D80="Net Asset Value", I80, C80) -> 73317.052 | K80: =_xlfn.XLOOKUP(B80,'Share Price'!D:D,'Share Price'!F:F) -> 160.42 | L80: =_xlfn.XLOOKUP(C3,'Share Price'!D:D,'Share Price'!F:F) -> 417.85 | M80: =L80/K80 -> 2.6047251 | N80: =C80 * M80 -> 190970.76 | O80: =IF(D80="Net Asset Value",O79,-SUM(N11:N80)) -> -1125495.8 | P80: =IF(D80="Net Asset Value", O80, C80) -> 73317.052 | Q80: =_xlfn.XLOOKUP(B80,'Share Price'!D:D,'Share Price'!G:G) -> 232.72 | R80: =_xlfn.XLOOKUP(C3,'Share Price'!D:D,'Share Price'!G:G) -> 118.09 | S80: =R80/Q80 -> 0.50743383 | T80: =C80 * S80 -> 37203.552 | U80: =IF(D80="Net Asset Value",U79,-SUM(T11:T80)) -> -179589.82 | V80: =IF(D80="Net Asset Value", U80, C80) -> 73317.052
B81: 41486 | C81: -24523.801 | D81: Contribution | E81: =_xlfn.XLOOKUP(B81,'Share Price'!D:D,'Share Price'!E:E) -> 75.4567 | F81: =_xlfn.XLOOKUP(C3,'Share Price'!D:D,'Share Price'!E:E) -> 347.99 | G81: =F81/E81 -> 4.611784 | H81: =C81 * G81 -> -113098.47 | I81: =IF(D81="Net Asset Value",I80,-SUM(H11:H81)) -> -275002.85 | J81: =IF(D81="Net Asset Value", I81, C81) -> -24523.801 | K81: =_xlfn.XLOOKUP(B81,'Share Price'!D:D,'Share Price'!F:F) -> 168.71 | L81: =_xlfn.XLOOKUP(C3,'Share Price'!D:D,'Share Price'!F:F) -> 417.85 | M81: =L81/K81 -> 2.4767352 | N81: =C81 * M81 -> -60738.963 | O81: =IF(D81="Net Asset Value",O80,-SUM(N11:N81)) -> -1064756.9 | P81: =IF(D81="Net Asset Value", O81, C81) -> -24523.801 | Q81: =_xlfn.XLOOKUP(B81,'Share Price'!D:D,'Share Price'!G:G) -> 249.4 | R81: =_xlfn.XLOOKUP(C3,'Share Price'!D:D,'Share Price'!G:G) -> 118.09 | S81: =R81/Q81 -> 0.47349639 | T81: =C81 * S81 -> -11611.932 | U81: =IF(D81="Net Asset Value",U80,-SUM(T11:T81)) -> -167977.89 | V81: =IF(D81="Net Asset Value", U81, C81) -> -24523.801
B82: 41517 | C82: 48633.852 | D82: Distribution | E82: =_xlfn.XLOOKUP(B82,'Share Price'!D:D,'Share Price'!E:E) -> 75.1579 | F82: =_xlfn.XLOOKUP(C3,'Share Price'!D:D,'Share Price'!E:E) -> 347.99 | G82: =F82/E82 -> 4.6301187 | H82: =C82 * G82 -> 225180.51 | I82: =IF(D82="Net Asset Value",I81,-SUM(H11:H82)) -> -500183.35 | J82: =IF(D82="Net Asset Value", I82, C82) -> 48633.852 | K82: =_xlfn.XLOOKUP(B82,'Share Price'!D:D,'Share Price'!F:F) -> 163.65 | L82: =_xlfn.XLOOKUP(C3,'Share Price'!D:D,'Share Price'!F:F) -> 417.85 | M82: =L82/K82 -> 2.553315 | N82: =C82 * M82 -> 124177.54 | O82: =IF(D82="Net Asset Value",O81,-SUM(N11:N82)) -> -1188934.4 | P82: =IF(D82="Net Asset Value", O82, C82) -> 48633.852 | Q82: =_xlfn.XLOOKUP(B82,'Share Price'!D:D,'Share Price'!G:G) -> 248 | R82: =_xlfn.XLOOKUP(C3,'Share Price'!D:D,'Share Price'!G:G) -> 118.09 | S82: =R82/Q82 -> 0.47616935 | T82: =C82 * S82 -> 23157.95 | U82: =IF(D82="Net Asset Value",U81,-SUM(T11:T82)) -> -191135.84 | V82: =IF(D82="Net Asset Value", U82, C82) -> 48633.852
B83: 41547 | C83: 2236.1625 | D83: Distribution | E83: =_xlfn.XLOOKUP(B83,'Share Price'!D:D,'Share Price'!E:E) -> 78.5538 | F83: =_xlfn.XLOOKUP(C3,'Share Price'!D:D,'Share Price'!E:E) -> 347.99 | G83: =F83/E83 -> 4.4299576 | H83: =C83 * G83 -> 9906.1049 | I83: =IF(D83="Net Asset Value",I82,-SUM(H11:H83)) -> -510089.46 | J83: =IF(D83="Net Asset Value", I83, C83) -> 2236.1625 | K83: =_xlfn.XLOOKUP(B83,'Share Price'!D:D,'Share Price'!F:F) -> 168.01 | L83: =_xlfn.XLOOKUP(C3,'Share Price'!D:D,'Share Price'!F:F) -> 417.85 | M83: =L83/K83 -> 2.4870543 | N83: =C83 * M83 -> 5561.4576 | O83: =IF(D83="Net Asset Value",O82,-SUM(N11:N83)) -> -1194495.9 | P83: =IF(D83="Net Asset Value", O83, C83) -> 2236.1625 | Q83: =_xlfn.XLOOKUP(B83,'Share Price'!D:D,'Share Price'!G:G) -> 263.4 | R83: =_xlfn.XLOOKUP(C3,'Share Price'!D:D,'Share Price'!G:G) -> 118.09 | S83: =R83/Q83 -> 0.44832954 | T83: =C83 * S83 -> 1002.5377 | U83: =IF(D83="Net Asset Value",U82,-SUM(T11:T83)) -> -192138.38 | V83: =IF(D83="Net Asset Value", U83, C83) -> 2236.1625
B84: 41578 | C84: 1187.084 | D84: Distribution | E84: =_xlfn.XLOOKUP(B84,'Share Price'!D:D,'Share Price'!E:E) -> 82.4477 | F84: =_xlfn.XLOOKUP(C3,'Share Price'!D:D,'Share Price'!E:E) -> 347.99 | G84: =F84/E84 -> 4.2207363 | H84: =C84 * G84 -> 5010.3684 | I84: =IF(D84="Net Asset Value",I83,-SUM(H11:H84)) -> -515099.83 | J84: =IF(D84="Net Asset Value", I84, C84) -> 1187.084 | K84: =_xlfn.XLOOKUP(B84,'Share Price'!D:D,'Share Price'!F:F) -> 175.79 | L84: =_xlfn.XLOOKUP(C3,'Share Price'!D:D,'Share Price'!F:F) -> 417.85 | M84: =L84/K84 -> 2.3769839 | N84: =C84 * M84 -> 2821.6795 | O84: =IF(D84="Net Asset Value",O83,-SUM(N11:N84)) -> -1197317.6 | P84: =IF(D84="Net Asset Value", O84, C84) -> 1187.084 | Q84: =_xlfn.XLOOKUP(B84,'Share Price'!D:D,'Share Price'!G:G) -> 278.32 | R84: =_xlfn.XLOOKUP(C3,'Share Price'!D:D,'Share Price'!G:G) -> 118.09 | S84: =R84/Q84 -> 0.42429577 | T84: =C84 * S84 -> 503.67471 | U84: =IF(D84="Net Asset Value",U83,-SUM(T11:T84)) -> -192642.05 | V84: =IF(D84="Net Asset Value", U84, C84) -> 1187.084
B85: 41608 | C85: 23600.495 | D85: Distribution | E85: =_xlfn.XLOOKUP(B85,'Share Price'!D:D,'Share Price'!E:E) -> 85.3755 | F85: =_xlfn.XLOOKUP(C3,'Share Price'!D:D,'Share Price'!E:E) -> 347.99 | G85: =F85/E85 -> 4.0759937 | H85: =C85 * G85 -> 96195.47 | I85: =IF(D85="Net Asset Value",I84,-SUM(H11:H85)) -> -611295.3 | J85: =IF(D85="Net Asset Value", I85, C85) -> 23600.495 | K85: =_xlfn.XLOOKUP(B85,'Share Price'!D:D,'Share Price'!F:F) -> 181 | L85: =_xlfn.XLOOKUP(C3,'Share Price'!D:D,'Share Price'!F:F) -> 417.85 | M85: =L85/K85 -> 2.3085635 | N85: =C85 * M85 -> 54483.243 | O85: =IF(D85="Net Asset Value",O84,-SUM(N11:N85)) -> -1251800.8 | P85: =IF(D85="Net Asset Value", O85, C85) -> 23600.495 | Q85: =_xlfn.XLOOKUP(B85,'Share Price'!D:D,'Share Price'!G:G) -> 271.12 | R85: =_xlfn.XLOOKUP(C3,'Share Price'!D:D,'Share Price'!G:G) -> 118.09 | S85: =R85/Q85 -> 0.43556359 | T85: =C85 * S85 -> 10279.516 | U85: =IF(D85="Net Asset Value",U84,-SUM(T11:T85)) -> -202921.57 | V85: =IF(D85="Net Asset Value", U85, C85) -> 23600.495
B86: 41639 | C86: 49284.718 | D86: Distribution | E86: =_xlfn.XLOOKUP(B86,'Share Price'!D:D,'Share Price'!E:E) -> 87.5963 | F86: =_xlfn.XLOOKUP(C3,'Share Price'!D:D,'Share Price'!E:E) -> 347.99 | G86: =F86/E86 -> 3.9726564 | H86: =C86 * G86 -> 195791.25 | I86: =IF(D86="Net Asset Value",I85,-SUM(H11:H86)) -> -807086.55 | J86: =IF(D86="Net Asset Value", I86, C86) -> 49284.718 | K86: =_xlfn.XLOOKUP(B86,'Share Price'!D:D,'Share Price'!F:F) -> 184.69 | L86: =_xlfn.XLOOKUP(C3,'Share Price'!D:D,'Share Price'!F:F) -> 417.85 | M86: =L86/K86 -> 2.2624398 | N86: =C86 * M86 -> 111503.71 | O86: =IF(D86="Net Asset Value",O85,-SUM(N11:N86)) -> -1363304.5 | P86: =IF(D86="Net Asset Value", O86, C86) -> 49284.718 | Q86: =_xlfn.XLOOKUP(B86,'Share Price'!D:D,'Share Price'!G:G) -> 274.12 | R86: =_xlfn.XLOOKUP(C3,'Share Price'!D:D,'Share Price'!G:G) -> 118.09 | S86: =R86/Q86 -> 0.43079673 | T86: =C86 * S86 -> 21231.695 | U86: =IF(D86="Net Asset Value",U85,-SUM(T11:T86)) -> -224153.26 | V86: =IF(D86="Net Asset Value", U86, C86) -> 49284.718
B87: 41670 | C87: -6926.7254 | D87: Contribution | E87: =_xlfn.XLOOKUP(B87,'Share Price'!D:D,'Share Price'!E:E) -> 85.9133 | F87: =_xlfn.XLOOKUP(C3,'Share Price'!D:D,'Share Price'!E:E) -> 347.99 | G87: =F87/E87 -> 4.0504788 | H87: =C87 * G87 -> -28056.554 | I87: =IF(D87="Net Asset Value",I86,-SUM(H11:H87)) -> -779029.99 | J87: =IF(D87="Net Asset Value", I87, C87) -> -6926.7254 | K87: =_xlfn.XLOOKUP(B87,'Share Price'!D:D,'Share Price'!F:F) -> 178.18 | L87: =_xlfn.XLOOKUP(C3,'Share Price'!D:D,'Share Price'!F:F) -> 417.85 | M87: =L87/K87 -> 2.3451005 | N87: =C87 * M87 -> -16243.867 | O87: =IF(D87="Net Asset Value",O86,-SUM(N11:N87)) -> -1347060.6 | P87: =IF(D87="Net Asset Value", O87, C87) -> -6926.7254 | Q87: =_xlfn.XLOOKUP(B87,'Share Price'!D:D,'Share Price'!G:G) -> 263 | R87: =_xlfn.XLOOKUP(C3,'Share Price'!D:D,'Share Price'!G:G) -> 118.09 | S87: =R87/Q87 -> 0.44901141 | T87: =C87 * S87 -> -3110.1787 | U87: =IF(D87="Net Asset Value",U86,-SUM(T11:T87)) -> -221043.08 | V87: =IF(D87="Net Asset Value", U87, C87) -> -6926.7254
B88: 41698 | C88: 488.12442 | D88: Distribution | E88: =_xlfn.XLOOKUP(B88,'Share Price'!D:D,'Share Price'!E:E) -> 90.34 | F88: =_xlfn.XLOOKUP(C3,'Share Price'!D:D,'Share Price'!E:E) -> 347.99 | G88: =F88/E88 -> 3.8520035 | H88: =C88 * G88 -> 1880.257 | I88: =IF(D88="Net Asset Value",I87,-SUM(H11:H88)) -> -780910.25 | J88: =IF(D88="Net Asset Value", I88, C88) -> 488.12442 | K88: =_xlfn.XLOOKUP(B88,'Share Price'!D:D,'Share Price'!F:F) -> 186.29 | L88: =_xlfn.XLOOKUP(C3,'Share Price'!D:D,'Share Price'!F:F) -> 417.85 | M88: =L88/K88 -> 2.2430082 | N88: =C88 * M88 -> 1094.8671 | O88: =IF(D88="Net Asset Value",O87,-SUM(N11:N88)) -> -1348155.5 | P88: =IF(D88="Net Asset Value", O88, C88) -> 488.12442 | Q88: =_xlfn.XLOOKUP(B88,'Share Price'!D:D,'Share Price'!G:G) -> 278.76 | R88: =_xlfn.XLOOKUP(C3,'Share Price'!D:D,'Share Price'!G:G) -> 118.09 | S88: =R88/Q88 -> 0.42362606 | T88: =C88 * S88 -> 206.78222 | U88: =IF(D88="Net Asset Value",U87,-SUM(T11:T88)) -> -221249.87 | V88: =IF(D88="Net Asset Value", U88, C88) -> 488.12442
B89: 41729 | C89: 701.28676 | D89: Distribution | E89: =_xlfn.XLOOKUP(B89,'Share Price'!D:D,'Share Price'!E:E) -> 87.67 | F89: =_xlfn.XLOOKUP(C3,'Share Price'!D:D,'Share Price'!E:E) -> 347.99 | G89: =F89/E89 -> 3.9693168 | H89: =C89 * G89 -> 2783.6293 | I89: =IF(D89="Net Asset Value",I88,-SUM(H11:H89)) -> -783693.88 | J89: =IF(D89="Net Asset Value", I89, C89) -> 701.28676 | K89: =_xlfn.XLOOKUP(B89,'Share Price'!D:D,'Share Price'!F:F) -> 187.01 | L89: =_xlfn.XLOOKUP(C3,'Share Price'!D:D,'Share Price'!F:F) -> 417.85 | M89: =L89/K89 -> 2.2343725 | N89: =C89 * M89 -> 1566.9358 | O89: =IF(D89="Net Asset Value",O88,-SUM(N11:N89)) -> -1349722.4 | P89: =IF(D89="Net Asset Value", O89, C89) -> 701.28676 | Q89: =_xlfn.XLOOKUP(B89,'Share Price'!D:D,'Share Price'!G:G) -> 287.32 | R89: =_xlfn.XLOOKUP(C3,'Share Price'!D:D,'Share Price'!G:G) -> 118.09 | S89: =R89/Q89 -> 0.41100515 | T89: =C89 * S89 -> 288.23247 | U89: =IF(D89="Net Asset Value",U88,-SUM(T11:T89)) -> -221538.1 | V89: =IF(D89="Net Asset Value", U89, C89) -> 701.28676
B90: 41759 | C90: -1151.7812 | D90: Contribution | E90: =_xlfn.XLOOKUP(B90,'Share Price'!D:D,'Share Price'!E:E) -> 87.39 | F90: =_xlfn.XLOOKUP(C3,'Share Price'!D:D,'Share Price'!E:E) -> 347.99 | G90: =F90/E90 -> 3.9820346 | H90: =C90 * G90 -> -4586.4325 | I90: =IF(D90="Net Asset Value",I89,-SUM(H11:H90)) -> -779107.45 | J90: =IF(D90="Net Asset Value", I90, C90) -> -1151.7812 | K90: =_xlfn.XLOOKUP(B90,'Share Price'!D:D,'Share Price'!F:F) -> 188.31 | L90: =_xlfn.XLOOKUP(C3,'Share Price'!D:D,'Share Price'!F:F) -> 417.85 | M90: =L90/K90 -> 2.2189475 | N90: =C90 * M90 -> -2555.742 | O90: =IF(D90="Net Asset Value",O89,-SUM(N11:N90)) -> -1347166.7 | P90: =IF(D90="Net Asset Value", O90, C90) -> -1151.7812 | Q90: =_xlfn.XLOOKUP(B90,'Share Price'!D:D,'Share Price'!G:G) -> 310.44 | R90: =_xlfn.XLOOKUP(C3,'Share Price'!D:D,'Share Price'!G:G) -> 118.09 | S90: =R90/Q90 -> 0.38039557 | T90: =C90 * S90 -> -438.13246 | U90: =IF(D90="Net Asset Value",U89,-SUM(T11:T90)) -> -221099.97 | V90: =IF(D90="Net Asset Value", U90, C90) -> -1151.7812
B91: 41790 | C91: 1363.3871 | D91: Distribution | E91: =_xlfn.XLOOKUP(B91,'Share Price'!D:D,'Share Price'!E:E) -> 91.31 | F91: =_xlfn.XLOOKUP(C3,'Share Price'!D:D,'Share Price'!E:E) -> 347.99 | G91: =F91/E91 -> 3.8110831 | H91: =C91 * G91 -> 5195.9817 | I91: =IF(D91="Net Asset Value",I90,-SUM(H11:H91)) -> -784303.43 | J91: =IF(D91="Net Asset Value", I91, C91) -> 1363.3871 | K91: =_xlfn.XLOOKUP(B91,'Share Price'!D:D,'Share Price'!F:F) -> 192.68 | L91: =_xlfn.XLOOKUP(C3,'Share Price'!D:D,'Share Price'!F:F) -> 417.85 | M91: =L91/K91 -> 2.1686215 | N91: =C91 * M91 -> 2956.6707 | O91: =IF(D91="Net Asset Value",O90,-SUM(N11:N91)) -> -1350123.4 | P91: =IF(D91="Net Asset Value", O91, C91) -> 1363.3871 | Q91: =_xlfn.XLOOKUP(B91,'Share Price'!D:D,'Share Price'!G:G) -> 308.16 | R91: =_xlfn.XLOOKUP(C3,'Share Price'!D:D,'Share Price'!G:G) -> 118.09 | S91: =R91/Q91 -> 0.38321002 | T91: =C91 * S91 -> 522.46361 | U91: =IF(D91="Net Asset Value",U90,-SUM(T11:T91)) -> -221622.43 | V91: =IF(D91="Net Asset Value", U91, C91) -> 1363.3871
B92: 41820 | C92: 189098.08 | D92: Distribution | E92: =_xlfn.XLOOKUP(B92,'Share Price'!D:D,'Share Price'!E:E) -> 93.91 | F92: =_xlfn.XLOOKUP(C3,'Share Price'!D:D,'Share Price'!E:E) -> 347.99 | G92: =F92/E92 -> 3.7055692 | H92: =C92 * G92 -> 700716 | I92: =IF(D92="Net Asset Value",I91,-SUM(H11:H92)) -> -1485019.4 | J92: =IF(D92="Net Asset Value", I92, C92) -> 189098.08 | K92: =_xlfn.XLOOKUP(B92,'Share Price'!D:D,'Share Price'!F:F) -> 195.72 | L92: =_xlfn.XLOOKUP(C3,'Share Price'!D:D,'Share Price'!F:F) -> 417.85 | M92: =L92/K92 -> 2.1349377 | N92: =C92 * M92 -> 403712.6 | O92: =IF(D92="Net Asset Value",O91,-SUM(N11:N92)) -> -1753836 | P92: =IF(D92="Net Asset Value", O92, C92) -> 189098.08 | Q92: =_xlfn.XLOOKUP(B92,'Share Price'!D:D,'Share Price'!G:G) -> 329.12 | R92: =_xlfn.XLOOKUP(C3,'Share Price'!D:D,'Share Price'!G:G) -> 118.09 | S92: =R92/Q92 -> 0.3588053 | T92: =C92 * S92 -> 67849.391 | U92: =IF(D92="Net Asset Value",U91,-SUM(T11:T92)) -> -289471.82 | V92: =IF(D92="Net Asset Value", U92, C92) -> 189098.08
B93: 41851 | C93: 281232.23 | D93: Distribution | E93: =_xlfn.XLOOKUP(B93,'Share Price'!D:D,'Share Price'!E:E) -> 95.02 | F93: =_xlfn.XLOOKUP(C3,'Share Price'!D:D,'Share Price'!E:E) -> 347.99 | G93: =F93/E93 -> 3.6622816 | H93: =C93 * G93 -> 1029951.6 | I93: =IF(D93="Net Asset Value",I92,-SUM(H11:H93)) -> -2514971 | J93: =IF(D93="Net Asset Value", I93, C93) -> 281232.23 | K93: =_xlfn.XLOOKUP(B93,'Share Price'!D:D,'Share Price'!F:F) -> 193.09 | L93: =_xlfn.XLOOKUP(C3,'Share Price'!D:D,'Share Price'!F:F) -> 417.85 | M93: =L93/K93 -> 2.1640168 | N93: =C93 * M93 -> 608591.26 | O93: =IF(D93="Net Asset Value",O92,-SUM(N11:N93)) -> -2362427.2 | P93: =IF(D93="Net Asset Value", O93, C93) -> 281232.23 | Q93: =_xlfn.XLOOKUP(B93,'Share Price'!D:D,'Share Price'!G:G) -> 301.16 | R93: =_xlfn.XLOOKUP(C3,'Share Price'!D:D,'Share Price'!G:G) -> 118.09 | S93: =R93/Q93 -> 0.39211715 | T93: =C93 * S93 -> 110275.98 | U93: =IF(D93="Net Asset Value",U92,-SUM(T11:T93)) -> -399747.8 | V93: =IF(D93="Net Asset Value", U93, C93) -> 281232.23
B94: 41882 | C94: 17886.513 | D94: Distribution | E94: =_xlfn.XLOOKUP(B94,'Share Price'!D:D,'Share Price'!E:E) -> 99.78 | F94: =_xlfn.XLOOKUP(C3,'Share Price'!D:D,'Share Price'!E:E) -> 347.99 | G94: =F94/E94 -> 3.4875727 | H94: =C94 * G94 -> 62380.514 | I94: =IF(D94="Net Asset Value",I93,-SUM(H11:H94)) -> -2577351.6 | J94: =IF(D94="Net Asset Value", I94, C94) -> 17886.513 | K94: =_xlfn.XLOOKUP(B94,'Share Price'!D:D,'Share Price'!F:F) -> 200.71 | L94: =_xlfn.XLOOKUP(C3,'Share Price'!D:D,'Share Price'!F:F) -> 417.85 | M94: =L94/K94 -> 2.0818594 | N94: =C94 * M94 -> 37237.205 | O94: =IF(D94="Net Asset Value",O93,-SUM(N11:N94)) -> -2399664.4 | P94: =IF(D94="Net Asset Value", O94, C94) -> 17886.513 | Q94: =_xlfn.XLOOKUP(B94,'Share Price'!D:D,'Share Price'!G:G) -> 316.2 | R94: =_xlfn.XLOOKUP(C3,'Share Price'!D:D,'Share Price'!G:G) -> 118.09 | S94: =R94/Q94 -> 0.37346616 | T94: =C94 * S94 -> 6680.0074 | U94: =IF(D94="Net Asset Value",U93,-SUM(T11:T94)) -> -406427.81 | V94: =IF(D94="Net Asset Value", U94, C94) -> 17886.513
B95: 41912 | C95: -7571.0318 | D95: Contribution | E95: =_xlfn.XLOOKUP(B95,'Share Price'!D:D,'Share Price'!E:E) -> 98.79 | F95: =_xlfn.XLOOKUP(C3,'Share Price'!D:D,'Share Price'!E:E) -> 347.99 | G95: =F95/E95 -> 3.5225225 | H95: =C95 * G95 -> -26669.13 | I95: =IF(D95="Net Asset Value",I94,-SUM(H11:H95)) -> -2550682.4 | J95: =IF(D95="Net Asset Value", I95, C95) -> -7571.0318 | K95: =_xlfn.XLOOKUP(B95,'Share Price'!D:D,'Share Price'!F:F) -> 197.02 | L95: =_xlfn.XLOOKUP(C3,'Share Price'!D:D,'Share Price'!F:F) -> 417.85 | M95: =L95/K95 -> 2.1208507 | N95: =C95 * M95 -> -16057.028 | O95: =IF(D95="Net Asset Value",O94,-SUM(N11:N95)) -> -2383607.4 | P95: =IF(D95="Net Asset Value", O95, C95) -> -7571.0318 | Q95: =_xlfn.XLOOKUP(B95,'Share Price'!D:D,'Share Price'!G:G) -> 275.32 | R95: =_xlfn.XLOOKUP(C3,'Share Price'!D:D,'Share Price'!G:G) -> 118.09 | S95: =R95/Q95 -> 0.42891908 | T95: =C95 * S95 -> -3247.36 | U95: =IF(D95="Net Asset Value",U94,-SUM(T11:T95)) -> -403180.45 | V95: =IF(D95="Net Asset Value", U95, C95) -> -7571.0318
B96: 41943 | C96: 4496.8595 | D96: Distribution | E96: =_xlfn.XLOOKUP(B96,'Share Price'!D:D,'Share Price'!E:E) -> 101.4 | F96: =_xlfn.XLOOKUP(C3,'Share Price'!D:D,'Share Price'!E:E) -> 347.99 | G96: =F96/E96 -> 3.431854 | H96: =C96 * G96 -> 15432.565 | I96: =IF(D96="Net Asset Value",I95,-SUM(H11:H96)) -> -2566115 | J96: =IF(D96="Net Asset Value", I96, C96) -> 4496.8595 | K96: =_xlfn.XLOOKUP(B96,'Share Price'!D:D,'Share Price'!F:F) -> 201.66 | L96: =_xlfn.XLOOKUP(C3,'Share Price'!D:D,'Share Price'!F:F) -> 417.85 | M96: =L96/K96 -> 2.072052 | N96: =C96 * M96 -> 9317.7266 | O96: =IF(D96="Net Asset Value",O95,-SUM(N11:N96)) -> -2392925.1 | P96: =IF(D96="Net Asset Value", O96, C96) -> 4496.8595 | Q96: =_xlfn.XLOOKUP(B96,'Share Price'!D:D,'Share Price'!G:G) -> 243.48 | R96: =_xlfn.XLOOKUP(C3,'Share Price'!D:D,'Share Price'!G:G) -> 118.09 | S96: =R96/Q96 -> 0.48500904 | T96: =C96 * S96 -> 2181.0175 | U96: =IF(D96="Net Asset Value",U95,-SUM(T11:T96)) -> -405361.47 | V96: =IF(D96="Net Asset Value", U96, C96) -> 4496.8595
B97: 41973 | C97: -1932.737 | D97: Contribution | E97: =_xlfn.XLOOKUP(B97,'Share Price'!D:D,'Share Price'!E:E) -> 106.01 | F97: =_xlfn.XLOOKUP(C3,'Share Price'!D:D,'Share Price'!E:E) -> 347.99 | G97: =F97/E97 -> 3.2826148 | H97: =C97 * G97 -> -6344.4311 | I97: =IF(D97="Net Asset Value",I96,-SUM(H11:H97)) -> -2559770.6 | J97: =IF(D97="Net Asset Value", I97, C97) -> -1932.737 | K97: =_xlfn.XLOOKUP(B97,'Share Price'!D:D,'Share Price'!F:F) -> 207.2 | L97: =_xlfn.XLOOKUP(C3,'Share Price'!D:D,'Share Price'!F:F) -> 417.85 | M97: =L97/K97 -> 2.0166506 | N97: =C97 * M97 -> -3897.6551 | O97: =IF(D97="Net Asset Value",O96,-SUM(N11:N97)) -> -2389027.5 | P97: =IF(D97="Net Asset Value", O97, C97) -> -1932.737 | Q97: =_xlfn.XLOOKUP(B97,'Share Price'!D:D,'Share Price'!G:G) -> 204.32 | R97: =_xlfn.XLOOKUP(C3,'Share Price'!D:D,'Share Price'!G:G) -> 118.09 | S97: =R97/Q97 -> 0.57796594 | T97: =C97 * S97 -> -1117.0561 | U97: =IF(D97="Net Asset Value",U96,-SUM(T11:T97)) -> -404244.41 | V97: =IF(D97="Net Asset Value", U97, C97) -> -1932.737
B98: 42004 | C98: -78320.735 | D98: Contribution | E98: =_xlfn.XLOOKUP(B98,'Share Price'!D:D,'Share Price'!E:E) -> 103.25 | F98: =_xlfn.XLOOKUP(C3,'Share Price'!D:D,'Share Price'!E:E) -> 347.99 | G98: =F98/E98 -> 3.3703632 | H98: =C98 * G98 -> -263969.32 | I98: =IF(D98="Net Asset Value",I97,-SUM(H11:H98)) -> -2295801.2 | J98: =IF(D98="Net Asset Value", I98, C98) -> -78320.735 | K98: =_xlfn.XLOOKUP(B98,'Share Price'!D:D,'Share Price'!F:F) -> 205.54 | L98: =_xlfn.XLOOKUP(C3,'Share Price'!D:D,'Share Price'!F:F) -> 417.85 | M98: =L98/K98 -> 2.0329376 | N98: =C98 * M98 -> -159221.17 | O98: =IF(D98="Net Asset Value",O97,-SUM(N11:N98)) -> -2229806.3 | P98: =IF(D98="Net Asset Value", O98, C98) -> -78320.735 | Q98: =_xlfn.XLOOKUP(B98,'Share Price'!D:D,'Share Price'!G:G) -> 191.44 | R98: =_xlfn.XLOOKUP(C3,'Share Price'!D:D,'Share Price'!G:G) -> 118.09 | S98: =R98/Q98 -> 0.61685123 | T98: =C98 * S98 -> -48312.242 | U98: =IF(D98="Net Asset Value",U97,-SUM(T11:T98)) -> -355932.17 | V98: =IF(D98="Net Asset Value", U98, C98) -> -78320.735
B99: 42035 | C99: 309.42814 | D99: Distribution | E99: =_xlfn.XLOOKUP(B99,'Share Price'!D:D,'Share Price'!E:E) -> 101.1 | F99: =_xlfn.XLOOKUP(C3,'Share Price'!D:D,'Share Price'!E:E) -> 347.99 | G99: =F99/E99 -> 3.4420376 | H99: =C99 * G99 -> 1065.0633 | I99: =IF(D99="Net Asset Value",I98,-SUM(H11:H99)) -> -2296866.3 | J99: =IF(D99="Net Asset Value", I99, C99) -> 309.42814 | K99: =_xlfn.XLOOKUP(B99,'Share Price'!D:D,'Share Price'!F:F) -> 199.45 | L99: =_xlfn.XLOOKUP(C3,'Share Price'!D:D,'Share Price'!F:F) -> 417.85 | M99: =L99/K99 -> 2.0950113 | N99: =C99 * M99 -> 648.25544 | O99: =IF(D99="Net Asset Value",O98,-SUM(N11:N99)) -> -2230454.6 | P99: =IF(D99="Net Asset Value", O99, C99) -> 309.42814 | Q99: =_xlfn.XLOOKUP(B99,'Share Price'!D:D,'Share Price'!G:G) -> 184.72 | R99: =_xlfn.XLOOKUP(C3,'Share Price'!D:D,'Share Price'!G:G) -> 118.09 | S99: =R99/Q99 -> 0.6392919 | T99: =C99 * S99 -> 197.8149 | U99: =IF(D99="Net Asset Value",U98,-SUM(T11:T99)) -> -356129.98 | V99: =IF(D99="Net Asset Value", U99, C99) -> 309.42814
B100: 42063 | C100: 18884.705 | D100: Distribution | E100: =_xlfn.XLOOKUP(B100,'Share Price'!D:D,'Share Price'!E:E) -> 108.4 | F100: =_xlfn.XLOOKUP(C3,'Share Price'!D:D,'Share Price'!E:E) -> 347.99 | G100: =F100/E100 -> 3.2102399 | H100: =C100 * G100 -> 60624.431 | I100: =IF(D100="Net Asset Value",I99,-SUM(H11:H100)) -> -2357490.7 | J100: =IF(D100="Net Asset Value", I100, C100) -> 18884.705 | K100: =_xlfn.XLOOKUP(B100,'Share Price'!D:D,'Share Price'!F:F) -> 210.66 | L100: =_xlfn.XLOOKUP(C3,'Share Price'!D:D,'Share Price'!F:F) -> 417.85 | M100: =L100/K100 -> 1.983528 | N100: =C100 * M100 -> 37458.34 | O100: =IF(D100="Net Asset Value",O99,-SUM(N11:N100)) -> -2267912.9 | P100: =IF(D100="Net Asset Value", O100, C100) -> 18884.705 | Q100: =_xlfn.XLOOKUP(B100,'Share Price'!D:D,'Share Price'!G:G) -> 203.24 | R100: =_xlfn.XLOOKUP(C3,'Share Price'!D:D,'Share Price'!G:G) -> 118.09 | S100: =R100/Q100 -> 0.5810372 | T100: =C100 * S100 -> 10972.716 | U100: =IF(D100="Net Asset Value",U99,-SUM(T11:T100)) -> -367102.7 | V100: =IF(D100="Net Asset Value", U100, C100) -> 18884.705
B101: 42094 | C101: -1860.1809 | D101: Contribution | E101: =_xlfn.XLOOKUP(B101,'Share Price'!D:D,'Share Price'!E:E) -> 105.6 | F101: =_xlfn.XLOOKUP(C3,'Share Price'!D:D,'Share Price'!E:E) -> 347.99 | G101: =F101/E101 -> 3.2953598 | H101: =C101 * G101 -> -6129.9655 | I101: =IF(D101="Net Asset Value",I100,-SUM(H11:H101)) -> -2351360.8 | J101: =IF(D101="Net Asset Value", I101, C101) -> -1860.1809 | K101: =_xlfn.XLOOKUP(B101,'Share Price'!D:D,'Share Price'!F:F) -> 206.43 | L101: =_xlfn.XLOOKUP(C3,'Share Price'!D:D,'Share Price'!F:F) -> 417.85 | M101: =L101/K101 -> 2.0241728 | N101: =C101 * M101 -> -3765.3277 | O101: =IF(D101="Net Asset Value",O100,-SUM(N11:N101)) -> -2264147.6 | P101: =IF(D101="Net Asset Value", O101, C101) -> -1860.1809 | Q101: =_xlfn.XLOOKUP(B101,'Share Price'!D:D,'Share Price'!G:G) -> 206.64 | R101: =_xlfn.XLOOKUP(C3,'Share Price'!D:D,'Share Price'!G:G) -> 118.09 | S101: =R101/Q101 -> 0.57147696 | T101: =C101 * S101 -> -1063.0506 | U101: =IF(D101="Net Asset Value",U100,-SUM(T11:T101)) -> -366039.65 | V101: =IF(D101="Net Asset Value", U101, C101) -> -1860.1809
...

Sheet Fund VIII
B1: Inputs | E1: Outputs | K1: Cash Flow Summary
B2: Fund Name | C2: Fund VIII | F2: PME Index 1 | G2: PME Index 2 | H2: PME Index 3 | L2: Actual | M2: PME Index 1 | N2: PME Index 2 | O2: PME Index 3
B3: End Date | C3: =B166 -> 45473 | E3: Actual IRR | F3: =IFERROR(XIRR(C11:C166, B11:B166, IF(SUM(C11:C166) > 0, 0.15, -0.15)), "NA") -> 0.023659725 | G3: =IFERROR(XIRR(C11:C166, B11:B166, IF(SUM(C11:C166) > 0, 0.15, -0.15)), "NA") -> 0.023659725 | H3: =IFERROR(XIRR(C11:C166, B11:B166, IF(SUM(C11:C166) > 0, 0.15, -0.15)), "NA") -> 0.023659725 | K3: Distribution | L3: =SUMIFS(C11:C166, D11:D166, K3) -> 2398711.6 | M3: =SUMIFS(H11:H166, D11:D166, K3) -> 9114069.8 | N3: =SUMIFS(N11:N166, D11:D166, K3) -> 5635469.8 | O3: =SUMIFS(T11:T166, D11:D166, K3) -> 2178642.2
B4: Index 1 | C4: ='Share Price'!B3 -> QQQ | E4: PME IRR | F4: =IFERROR(XIRR(J11:J166, B11:B166, IF(SUM(J11:J166) > 0, 0.15, -0.15)), "NA") -> 0.18215999 | G4: =IFERROR(XIRR(P11:P166, B11:B166, IF(SUM(P11:P166) > 0, 0.15, -0.15)), "NA") -> 0.11802168 | H4: =IFERROR(XIRR(V11:V166, B11:B166, IF(SUM(V11:V166) > 0, 0.15, -0.15)), "NA") -> -0.036528256 | K4: Contribution | L4: =SUMIFS(C11:C166, D11:D166, K4) -> -3243053.1 | M4: =SUMIFS(H11:H166, D11:D166, K4) -> -19925900 | N4: =SUMIFS(N11:N166, D11:D166, K4) -> -10731641 | O4: =SUMIFS(T11:T166, D11:D166, K4) -> -2519405.5
B5: Index 2 | C5: ='Share Price'!B4 -> SPY | E5: Direct Alpha IRR | F5: =IFERROR(XIRR(H11:H166, B11:B166, IF(SUM(H11:H166) > 0, 0.15, -0.15)), "NA") -> -0.13168127 | G5: =IFERROR(XIRR(N11:N166, B11:B166, IF(SUM(N11:N166) > 0, 0.15, -0.15)), "NA") -> -0.083309886 | H5: =IFERROR(XIRR(T11:T166, B11:B166, IF(SUM(T11:T166) > 0, 0.15, -0.15)), "NA") -> 0.062880971 | K5: Net Asset Value | L5: =SUMIFS(C11:C166, D11:D166, K5) -> 1313003.9 | M5: =SUMIFS(H11:H166, D11:D166, K5) -> 1313003.9 | N5: =SUMIFS(N11:N166, D11:D166, K5) -> 1313003.9 | O5: =SUMIFS(T11:T166, D11:D166, K5) -> 1313003.9
B6: Index 3 | C6: ='Share Price'!B5 -> XOP | E6: KS-PME | F6: =(M3 + M5) / -M4 -> 0.52329248 | G6: =(N3 + N5) / -N4 -> 0.64747542 | H6: =(O3 + O5) / -O4 -> 1.3859008
B8: Cash Flow Data | E8: Index 1 Portfolio | K8: Index 2 Portfolio | Q8: Index 3 Portfolio
E9: Index Value at | H9: NAV | I9: End Date | J9: PME | K9: Index Value at | N9: NAV | O9: End Date | P9: PME | Q9: Index Value at | T9: NAV | U9: End Date | V9: PME
B10: Date | C10: Amount | D10: Type | E10: CF Date | F10: End Date | G10: Factor | H10: Contribution | I10: NAV | J10: Cash Flow | K10: CF Date | L10: End Date | M10: Factor | N10: Contribution | O10: NAV | P10: Cash Flow | Q10: CF Date | R10: End Date | S10: Factor | T10: Contribution | U10: NAV | V10: Cash Flow
