Workbook

Sheet Fund-Level Alpha
B2: EnCap Investments - Fund-level Alpha Analysis
B4: Fund | C4: Vintage | D4: Net IRR | E4: MSCI Natural Resources | F4: Alpha | G4: Pitchbook O&G | H4: Alpha | I4: Average Fund Alpha
B5: Upstream Fund XI | C5: 2017 | D5: 22.2% | E5: =VLOOKUP(C5,'MSCI Natural Resources'!B4:C19,2) -> 0.092 | F5: =$D5-E5 -> 0.13 | G5: =VLOOKUP(C5,'Pitchbook O&G'!$B$3:$C$22,2) -> 0.0974 | H5: =$D5-G5 -> 0.1246 | I5: =AVERAGE(F5,H5) -> 0.1273
B6: Upstream Fund X | C6: 2015 | D6: 16.4% | E6: =VLOOKUP(C6,'MSCI Natural Resources'!B5:C20,2) -> 0.08 | F6: =$D6-E6 -> 0.084 | G6: =VLOOKUP(C6,'Pitchbook O&G'!$B$3:$C$22,2) -> 0.093 | H6: =$D6-G6 -> 0.071 | I6: =AVERAGE(F6,H6) -> 0.0775
B7: Upstream Fund IX | C7: 2013 | D7: 10.9% | E7: =VLOOKUP(C7,'MSCI Natural Resources'!B6:C21,2) -> 0.037 | F7: =$D7-E7 -> 0.072 | G7: =VLOOKUP(C7,'Pitchbook O&G'!$B$3:$C$22,2) -> 0.013 | H7: =$D7-G7 -> 0.096 | I7: =AVERAGE(F7,H7) -> 0.084
B8: Upstream Fund VIII | C8: 2010 | D8: 0.6% | E8: =VLOOKUP(C8,'MSCI Natural Resources'!B4:C19,2) -> 0.012 | F8: =$D8-E8 -> -0.006 | G8: =VLOOKUP(C8,'Pitchbook O&G'!$B$3:$C$22,2) -> -0.148 | H8: =$D8-G8 -> 0.154 | I8: =AVERAGE(F8,H8) -> 0.074
B9: Upstream Fund VII | C9: 2007 | D9: 14.5% | G9: =VLOOKUP(C9,'Pitchbook O&G'!$B$3:$C$22,2) -> 0.011 | H9: =$D9-G9 -> 0.134 | I9: =AVERAGE(F9,H9) -> 0.134
B10: Upstream Fund VI | C10: 2006 | D10: 23.4% | G10: =VLOOKUP(C10,'Pitchbook O&G'!$B$3:$C$22,2) -> 0.0189 | H10: =$D10-G10 -> 0.2151 | I10: =AVERAGE(F10,H10) -> 0.2151
B11: Upstream Fund V | C11: 2004 | D11: 26.9% | G11: =VLOOKUP(C11,'Pitchbook O&G'!$B$3:$C$22,2) -> 0.1858 | H11: =$D11-G11 -> 0.0832 | I11: =AVERAGE(F11,H11) -> 0.0832
B12: Upstream Fund IV | C12: 2001 | D12: 68.4% | G12: =VLOOKUP(C12,'Pitchbook O&G'!$B$3:$C$22,2) -> 0.5053 | H12: =$D12-G12 -> 0.1787 | I12: =AVERAGE(F12,H12) -> 0.1787
B13: Upstream Fund III | C13: 1997 | D13: 23.5%
B14: Upstream Fund II | C14: 1996 | D14: 3.6%
B15: Upstream Fund I | C15: 1994 | D15: 24.8%
B17: Average | F17: =AVERAGE(F5:F8) -> 0.07 | H17: =AVERAGE(H5:H12) -> 0.132075

Sheet Company-Level Alpha
B2: Fund | C2: Company | D2: Year | E2: IRR | F2: MSCI Natural Resources | G2: Alpha | H2: Pitchbook O&G | I2: Alpha | J2: MSCI PE | K2: Alpha | M2: Company Level Alpha Summary
B3: Fund XII | C3: Grayson Mill III | D3: 2023 | E3: 1.0174752 | F3: 0.092 | G3: 0.92547521 | H3: 0 | I3: 1.0174752 | J3: 0.012 | K3: 1.0054752
B4: Fund XII | C4: Double Eagle IV | D4: 2023 | E4: 1.1155497 | F4: 0.092 | G4: 1.0235497 | H4: 0 | I4: 1.1155497 | J4: 0.012 | K4: 1.1035497
B5: Fund XII | C5: Ridge Runner (at Cost) | D5: 2023 | E5: 2.9802322e-09 | F5: 0.092 | G5: -0.091999997 | H5: 0 | I5: 2.9802322e-09 | J5: 0.012 | K5: -0.011999997 | O5: MSCI Natural | P5: Pitchbook | R5: Fund
B6: Fund XII | C6: Black Swan II (at Cost) | D6: 2023 | E6: 2.9802322e-09 | F6: 0.092 | G6: -0.091999997 | H6: 0 | I6: 2.9802322e-09 | J6: 0.012 | K6: -0.011999997 | M6: Fund | N6: Vintage | O6: Resources | P6: Oil & Gas | Q6: MSCI PE | R6: Average
B7: Fund XII | C7: Paloma VII (at Cost) | D7: 2024 | E7: 2.9802322e-09 | F7: 0.04 | G7: -0.039999997 | H7: 0 | I7: 2.9802322e-09 | J7: -0.076 | K7: 0.076000003 | M7: Fund XII | N7: 20.23 | O7: =AVERAGEIF($B:$B,$M7,F:F) -> 0.066 | P7: =AVERAGEIF($B:$B,$M7,I:I) -> 0.26662812 | Q7: =AVERAGEIF(B:B,$M7,K:K) -> 0.29862812 | R7: =AVERAGE(O7:Q7) -> 0.21041874
B8: Fund XII | C8: Novo II (at Cost) | D8: 2024 | E8: 2.9802322e-09 | F8: 0.04 | G8: -0.039999997 | H8: 0 | I8: 2.9802322e-09 | J8: -0.076 | K8: 0.076000003 | M8: Fund XI | N8: 2017 | O8: =AVERAGEIF($B:$B,$M8,F:F) -> 0.123 | P8: =AVERAGEIF($B:$B,$M8,I:I) -> 0.25048618 | Q8: =AVERAGEIF(B:B,$M8,K:K) -> 0.18276118 | R8: =AVERAGE(O8:Q8) -> 0.18541579
B9: Fund XII | C9: Pegasus III (at Cost) | D9: 2024 | E9: 2.9802322e-09 | F9: 0.04 | G9: -0.039999997 | H9: 0 | I9: 2.9802322e-09 | J9: -0.076 | K9: 0.076000003 | M9: Fund X | N9: 2015 | O9: =AVERAGEIF($B:$B,$M9,F:F) -> 0.087846154 | P9: =AVERAGEIF($B:$B,$M9,I:I) -> 0.28090058 | Q9: =AVERAGEIF(B:B,$M9,K:K) -> 0.21796981 | R9: =AVERAGE(O9:Q9) -> 0.19557218
B10: Fund XII | C10: Verdun III (at Cost) | D10: 2024 | E10: 0 | F10: 0.04 | G10: -0.04 | H10: 0 | I10: 0 | J10: -0.076 | K10: 0.076 | M10: Fund IX | N10: 2013 | O10: =AVERAGEIF($B:$B,$M10,F:F) -> 0.048047619 | P10: =AVERAGEIF($B:$B,$M10,I:I) -> 0.093887465 | Q10: =AVERAGEIF(B:B,$M10,K:K) -> 0.012430322 | R10: =AVERAGE(O10:Q10) -> 0.051455135
B11: Fund XI | C11: Sable Bay | D11: 2017 | E11: N/A | F11: 0.092 | G11: 0 | H11: 0.0974 | I11: 0 | J11: 0.171 | K11: 0 | M11: Fund VIII | N11: 2010 | O11: =AVERAGEIF($B:$B,$M11,F:F) -> -0.028521739 | P11: =AVERAGEIF($B:$B,$M11,I:I) -> 0.037136926 | Q11: =AVERAGEIF(B:B,$M11,K:K) -> -0.057989161 | R11: =AVERAGE(O11:Q11) -> -0.016457991
B12: Fund XI | C12: Black Swan | D12: 2017 | E12: 0.50300847 | F12: 0.092 | G12: 0.41100847 | H12: 0.0974 | I12: 0.40560847 | J12: 0.171 | K12: 0.33200847
B13: Fund XI | C13: Piedra IV | D13: 2018 | E13: 0.22318929 | F13: 0.086 | G13: 0.13718929 | H13: 0 | I13: 0.22318929 | J13: 0.142 | K13: 0.081189288 | M13: Limited Benchmark Data, exclude
B14: Fund XI | C14: Silverado | D14: 2019 | E14: -0.559 | F14: 0.12 | G14: -0.679 | H14: 0 | I14: -0.559 | J14: 0.112 | K14: -0.671 | M14: Fund VII | N14: 2007 | O14: =AVERAGEIF($B:$B,$M14,F:F) -> -0.00775 | P14: =AVERAGEIF($B:$B,$M14,I:I) -> 1.9114052 | Q14: =AVERAGEIF(B:B,$M14,K:K) -> 0.14498212 | R14: =AVERAGE(O14:Q14) -> 0.68287912
B15: Fund XI | C15: Forge II | D15: 2018 | E15: 0.15750422 | F15: 0.086 | G15: 0.071504219 | H15: 0 | I15: 0.15750422 | J15: 0.142 | K15: 0.015504219 | M15: Fund VI | N15: 2006 | P15: =AVERAGEIF($B:$B,$M15,I:I) -> 0.28515624 | R15: =AVERAGE(O15:Q15) -> 0.28515624
B16: Fund XI | C16: XCL | D16: 2018 | E16: 0.26769766 | F16: 0.086 | G16: 0.18169766 | H16: 0 | I16: 0.26769766 | J16: 0.142 | K16: 0.12569766 | M16: Fund V | N16: 2004 | O16: =AVERAGEIF($B:$B,$M16,F:F) -> -0.067 | P16: =AVERAGEIF($B:$B,$M16,I:I) -> 0.54412988 | Q16: =AVERAGEIF(B:B,$M16,K:K) -> -0.013178571 | R16: =AVERAGE(O16:Q16) -> 0.15465044
B17: Fund XI | C17: Raisa III | D17: 2019 | E17: -0.198 | F17: 0.12 | G17: -0.318 | H17: 0 | I17: -0.198 | J17: 0.112 | K17: -0.31 | M17: Fund IV | N17: 2001 | P17: =AVERAGEIF($B:$B,$M17,I:I) -> 0.57840286 | R17: =AVERAGE(O17:Q17) -> 0.57840286
B18: Fund XI | C18: Paloma V (Solar & Wind) | D18: 2020 | E18: 0.12959318 | F18: 0.069 | G18: 0.060593176 | H18: 0 | I18: 0.12959318 | J18: 0.096 | K18: 0.033593176 | M18: Fund III | N18: 1997 | P18: =AVERAGEIF($B:$B,$M18,I:I) -> -0.015584879 | R18: =AVERAGE(O18:Q18) -> -0.015584879
B19: Fund XI | C19: Special Opportunities | D19: 2020 | E19: 1.3644676 | F19: 0.069 | G19: 1.2954676 | H19: 0 | I19: 1.3644676 | J19: 0.096 | K19: 1.2684676 | M19: Fund II | N19: 1996 | P19: =AVERAGEIF($B:$B,$M19,I:I) -> 0 | R19: =AVERAGE(O19:Q19) -> 0
B20: Fund XI | C20: Grayson Mill II | D20: 2021 | E20: 1.0639263 | F20: 0.188 | G20: 0.87592633 | H20: 0 | I20: 1.0639263 | J20: 0.055 | K20: 1.0089263 | M20: Fund I | N20: 1994 | P20: =AVERAGEIF($B:$B,$M20,I:I) -> 0 | R20: =AVERAGE(O20:Q20) -> 0
B21: Fund XI | C21: Grayson Mill III | D21: 2023 | E21: 0.93797346 | F21: 0.092 | G21: 0.84597346 | H21: 0 | I21: 0.93797346 | J21: 0.012 | K21: 0.92597346
B22: Fund XI | C22: Silverback II | D22: 2017 | E22: -0.046 | F22: 0.092 | G22: -0.138 | H22: 0.0974 | I22: -0.1434 | J22: 0.171 | K22: -0.217
B23: Fund XI | C23: Enduring IV | D23: 2017 | E23: 0.032610252 | F23: 0.092 | G23: -0.059389748 | H23: 0.0974 | I23: -0.064789748 | J23: 0.171 | K23: -0.13838975
B24: Fund XI | C24: EnCap Minerals | D24: 2017 | E24: 0.21583549 | F24: 0.092 | G24: 0.12383549 | H24: 0.0974 | I24: 0.11843549 | J24: 0.171 | K24: 0.044835494
B25: Fund XI | C25: Arbor Gas | D25: 2021 | E25: -0.265 | F25: 0.188 | G25: -0.453 | H25: 0 | I25: -0.265 | J25: 0.055 | K25: -0.32
B26: Fund XI | C26: Grenadier III (at Cost) | D26: 2021 | E26: 2.9802322e-09 | F26: 0.188 | G26: -0.188 | H26: 0 | I26: 2.9802322e-09 | J26: 0.055 | K26: -0.054999997
B27: Fund XI | C27: Pegasus II | D27: 2021 | E27: 0.29104708 | F27: 0.188 | G27: 0.10304708 | H27: 0 | I27: 0.29104708 | J27: 0.055 | K27: 0.23604708
B28: Fund XI | C28: Verdun II | D28: 2021 | E28: 0.67269831 | F28: 0.188 | G28: 0.48469831 | H28: 0 | I28: 0.67269831 | J28: 0.055 | K28: 0.61769831
B29: Fund XI | C29: Sabalo II (at Cost) | D29: 2021 | E29: 0 | F29: 0.188 | G29: -0.188 | H29: 0 | I29: 0 | J29: 0.055 | K29: -0.055
B30: Fund XI | C30: Paloma VI | D30: 2021 | E30: 0.01320059 | F30: 0.188 | G30: -0.17479941 | H30: 0 | I30: 0.01320059 | J30: 0.055 | K30: -0.04179941
B31: Fund XI | C31: Double Eagle IV | D31: 2022 | E31: 0.63827073 | F31: 0.112 | G31: 0.52627073 | H31: 0 | I31: 0.63827073 | J31: 0.023 | K31: 0.61527073
B32: Fund XI | C32: Tumbleweed IV | D32: 2022 | E32: 0.28240415 | F32: 0.112 | G32: 0.17040415 | H32: 0 | I32: 0.28240415 | J32: 0.023 | K32: 0.25940415
... B34: Fund XI | C34: M6 | D34: 2022 | E34: 0.25542266 | F34: 0.112 | G34: 0.14342266 | H34: 0 | I34: 0.25542266 | J34: 0.023 | K34: 0.23242266
B35: Fund X | C35: Southland | D35: 2015 | E35: N/A | F35: 0.08 | G35: 0 | H35: 0.093 | I35: 0 | J35: 0.144 | K35: 0
B36: Fund X | C36: Ameredev | D36: 2015 | E36: 2.7324644 | F36: 0.08 | G36: 2.6524644 | H36: 0.093 | I36: 2.6394644 | J36: 0.144 | K36: 2.5884644
B37: Fund X | C37: Talon III | D37: 2015 | E37: 2.4348221 | F37: 0.08 | G37: 2.3548221 | H37: 0.093 | I37: 2.3418221 | J37: 0.144 | K37: 2.2908221
B38: Fund X | C38: Grenadier II | D38: 2015 | E38: 0.085849246 | F38: 0.08 | G38: 0.0058492464 | H38: 0.093 | I38: -0.0071507536 | J38: 0.144 | K38: -0.058150754
B39: Fund X | C39: Moda | D39: 2015 | E39: 0.17043261 | F39: 0.08 | G39: 0.090432609 | H39: 0.093 | I39: 0.077432609 | J39: 0.144 | K39: 0.026432609
B40: Fund X | C40: Staghorn II | D40: 2015 | E40: 1.5487023 | F40: 0.08 | G40: 1.4687023 | H40: 0.093 | I40: 1.4557023 | J40: 0.144 | K40: 1.4047023
B41: Fund X | C41: Felix II | D41: 2015 | E41: 0.46304989 | F41: 0.08 | G41: 0.38304989 | H41: 0.093 | I41: 0.37004989 | J41: 0.144 | K41: 0.31904989
B42: Fund X | C42: Raisa | D42: 2016 | E42: 0.014658883 | F42: 0.068 | G42: -0.053341117 | H42: 0.082 | I42: -0.067341117 | J42: 0.159 | K42: -0.14434112
B43: Fund X | C43: Advance | D43: 2016 | E43: 0.20691759 | F43: 0.068 | G43: 0.13891759 | H43: 0.082 | I43: 0.12491759 | J43: 0.159 | K43: 0.04791759
B44: Fund X | C44: Novo | D44: 2016 | E44: 0.23808632 | F44: 0.068 | G44: 0.17008632 | H44: 0.082 | I44: 0.15608632 | J44: 0.159 | K44: 0.079086325
B45: Fund X | C45: PetroLegacy | D45: 2016 | E45: 0.18680008 | F45: 0.068 | G45: 0.11880008 | H45: 0.082 | I45: 0.10480008 | J45: 0.159 | K45: 0.027800081
B46: Fund X | C46: Grayson Mill | D46: 2016 | E46: -0.063 | F46: 0.068 | G46: -0.131 | H46: 0.082 | I46: -0.145 | J46: 0.159 | K46: -0.222
B47: Fund X | C47: Royal Holly | D47: 2017 | E47: -0.464 | F47: 0.092 | G47: -0.556 | H47: 0.0974 | I47: -0.5614 | J47: 0.171 | K47: -0.635
... B73: Fund IX | C73: OGX III VNOM Shares | D73: 2015 | E73: 0.20663437 | F73: 0.08 | G73: 0.12663437 | H73: 0.093 | I73: 0.11363437 | J73: 0.144 | K73: 0.062634372
B74: Fund IX | C74: Southland | D74: 2015 | E74: N/A | F74: 0.08 | G74: 0 | H74: 0.093 | I74: 0 | J74: 0.144 | K74: 0
B75: Fund IX | C75: Phillips IV | D75: 2015 | E75: 0.071503881 | F75: 0.08 | G75: -0.0084961194 | H75: 0.093 | I75: -0.021496119 | J75: 0.144 | K75: -0.072496119
B76: Fund IX | C76: QStar II | D76: 2017 | E76: -0.889 | F76: 0.092 | G76: -0.981 | H76: 0.0974 | I76: -0.9864 | J76: 0.171 | K76: -1.06
B77: Fund IX | C77: Bold III (Permian Resources) | D77: 2013 | E77: 0.13548452 | F77: 0.037 | G77: 0.098484523 | H77: 0.013 | I77: 0.12248452 | J77: 0.127 | K77: 0.0084845226
B78: Fund IX | C78: Montage (Southwestern Energy) | D78: 2013 | E78: -0.179 | F78: 0.037 | G78: -0.216 | H78: 0.013 | I78: -0.192 | J78: 0.127 | K78: -0.306
B79: Fund IX | C79: Protege III | D79: 2013 | E79: 0.028684816 | F79: 0.037 | G79: -0.0083151842 | H79: 0.013 | I79: 0.015684816 | J79: 0.127 | K79: -0.098315184
B80: Fund IX | C80: Excalibur | D80: 2013 | E80: -0.17 | F80: 0.037 | G80: -0.207 | H80: 0.013 | I80: -0.183 | J80: 0.127 | K80: -0.297
B81: Fund IX | C81: EnCap Minerals | D81: 2015 | E81: 0.13220865 | F81: 0.08 | G81: 0.052208651 | H81: 0.093 | I81: 0.039208651 | J81: 0.144 | K81: -0.011791349
B82: Fund VIII | C82: Caiman | D82: 2010 | E82: 1.7826369 | F82: 0.012 | G82: 1.7706369 | H82: -0.148 | I82: 1.9306369 | J82: 0.122 | K82: 1.6606369
B83: Fund VIII | C83: Common II | D83: 2010 | E83: 0.53663012 | F83: 0.012 | G83: 0.52463012 | H83: -0.148 | I83: 0.68463012 | J83: 0.122 | K83: 0.41463012
B84: Fund VIII | C84: Lone Star II | D84: 2010 | E84: -0.302 | F84: 0.012 | G84: -0.314 | H84: -0.148 | I84: -0.154 | J84: 0.122 | K84: -0.424
B85: Fund VIII | C85: Silver Oak | D85: 2011 | E85: -0.282 | F85: -0.067 | G85: -0.215 | H85: 0.0419 | I85: -0.3239 | J85: 0.146 | K85: -0.428
B86: Fund VIII | C86: Talon II | D86: 2011 | E86: N/A | F86: -0.067 | G86: 0 | H86: 0.0419 | I86: 0 | J86: 0.146 | K86: 0
B87: Fund VIII | C87: Venado | D87: 2011 | E87: N/A | F87: -0.067 | G87: 0 | H87: 0.0419 | I87: 0 | J87: 0.146 | K87: 0
B88: Fund VIII | C88: Enduring II | D88: 2011 | E88: 0.68222627 | F88: -0.067 | G88: 0.74922627 | H88: 0.0419 | I88: 0.64032627 | J88: 0.146 | K88: 0.53622627
B89: Fund VIII | C89: Tracker III (Permian Resources) | D89: 2011 | E89: -0.112 | F89: -0.067 | G89: -0.045 | H89: 0.0419 | I89: -0.1539 | J89: 0.146 | K89: -0.258
B90: Fund VIII | C90: Dorado | D90: 2011 | E90: -0.025 | F90: -0.067 | G90: 0.042 | H90: 0.0419 | I90: -0.0669 | J90: 0.146 | K90: -0.171
B91: Fund VIII | C91: Forge | D91: 2011 | E91: -0.016 | F91: -0.067 | G91: 0.051 | H91: 0.0419 | I91: -0.0579 | J91: 0.146 | K91: -0.162
B92: Fund VIII | C92: Firewheel | D92: 2011 | E92: -0.005 | F92: -0.067 | G92: 0.062 | H92: 0.0419 | I92: -0.0469 | J92: 0.146 | K92: -0.151
B93: Fund VIII | C93: Plantation V | D93: 2011 | E93: -0.498 | F93: -0.067 | G93: -0.431 | H93: 0.0419 | I93: -0.5399 | J93: 0.146 | K93: -0.644
B94: Fund VIII | C94: Halcon | D94: 2012 | E94: 0.04503831 | F94: 0.005 | G94: 0.04003831 | H94: 0.092 | I94: -0.04696169 | J94: 0.141 | K94: -0.09596169
B95: Fund VIII | C95: Brigadier | D95: 2012 | E95: -0.848 | F95: 0.005 | G95: -0.853 | H95: 0.092 | I95: -0.94 | J95: 0.141 | K95: -0.989
B96: Fund VIII | C96: Broad Oak | D96: 2012 | E96: -0.001 | F96: 0.005 | G96: -0.006 | H96: 0.092 | I96: -0.093 | J96: 0.141 | K96: -0.142
B97: Fund VIII | C97: Phillips III (Kimbell Royalty) | D97: 2012 | E97: 0.043167952 | F97: 0.005 | G97: 0.038167952 | H97: 0.092 | I97: -0.048832048 | J97: 0.141 | K97: -0.097832048
B98: Fund VIII | C98: Grenadier II | D98: 2012 | E98: 0.079262808 | F98: 0.005 | G98: 0.074262808 | H98: 0.092 | I98: -0.012737192 | J98: 0.141 | K98: -0.061737192
B99: Fund VIII | C99: Common III | D99: 2012 | E99: -0.419 | F99: 0.005 | G99: -0.424 | H99: 0.092 | I99: -0.511 | J99: 0.141 | K99: -0.56
... B104: Fund VIII | C104: PennEnergy | D104: 2011 | E104: 0.1252775 | F104: -0.067 | G104: 0.1922775 | H104: 0.0419 | I104: 0.083377501 | J104: 0.146 | K104: -0.020722499
B105: Fund VII | C105: Common | D105: 2007 | E105: 1.194423 | F105: N/A | G105: 0 | H105: 0.011 | I105: 1.183423 | J105: N/A | K105: 0
B106: Fund VII | C106: Red Arrow | D106: 2007 | E106: 0.54310456 | F106: N/A | G106: 0 | H106: 0.011 | I106: 0.53210456 | J106: N/A | K106: 0
B107: Fund VII | C107: Plantation IV | D107: 2007 | E107: 0.32696596 | F107: N/A | G107: 0 | H107: 0.011 | I107: 0.31596596 | J107: N/A | K107: 0
B108: Fund VII | C108: Cordillera III | D108: 2007 | E108: 0.48624941 | F108: N/A | G108: 0 | H108: 0.011 | I108: 0.47524941 | J108: N/A | K108: 0
B109: Fund VII | C109: Legado | D109: 2007 | E109: -0.021 | F109: N/A | G109: 0 | H109: 0.011 | I109: -0.032 | J109: N/A | K109: 0
B110: Fund VII | C110: Cheyenne River | D110: 2007 | E110: -0.266 | F110: N/A | G110: 0 | H110: 0.011 | I110: -0.277 | J110: N/A | K110: 0
B111: Fund VII | C111: Oasis | D111: 2007 | E111: 0.72620217 | F111: N/A | G111: 0 | H111: 0.011 | I111: 0.71520217 | J111: N/A | K111: 0
B112: Fund VII | C112: Piedra | D112: 2007 | E112: 0.46563666 | F112: N/A | G112: 0 | H112: 0.011 | I112: 0.45463666 | J112: N/A | K112: 0
B113: Fund VII | C113: ER Energy Group | D113: 2007 | E113: -0.628 | F113: N/A | G113: 0 | H113: 0.011 | I113: -0.639 | J113: N/A | K113: 0
B114: Fund VII | C114: Earthstone | D114: 2007 | E114: -0.147 | F114: N/A | G114: 0 | H114: 0.011 | I114: -0.158 | J114: N/A | K114: 0
B115: Fund VII | C115: Limestone | D115: 2008 | E115: 1.0134082 | F115: N/A | G115: 0 | H115: 0.0835 | I115: 0.92990817 | J115: N/A | K115: 0
B116: Fund VII | C116: RiverStone | D116: 2008 | E116: 46.06859 | F116: N/A | G116: 0 | H116: 0.0835 | I116: 45.98509 | J116: N/A | K116: 0
... B129: Fund VII | C129: Paloma II | D129: 2009 | E129: 0.81307839 | F129: N/A | G129: 0 | H129: -0.0016 | I129: 0.81467839 | J129: N/A | K129: 0
B130: Fund VII | C130: Enduring | D130: 2010 | E130: 3.3343865 | F130: 0.012 | G130: 3.3223865 | H130: -0.148 | I130: 3.4823865 | J130: 0.122 | K130: 3.2123865
B131: Fund VII | C131: Phillips Energy II | D131: 2010 | E131: 0.072205153 | F131: 0.012 | G131: 0.060205153 | H131: -0.148 | I131: 0.22020515 | J131: 0.122 | K131: -0.049794847
B132: Fund VII | C132: Common II | D132: 2010 | E132: 0.496124 | F132: 0.012 | G132: 0.484124 | H132: -0.148 | I132: 0.644124 | J132: 0.122 | K132: 0.374124
B133: Fund VII | C133: Caiman | D133: 2010 | E133: 1.406409 | F133: 0.012 | G133: 1.394409 | H133: -0.148 | I133: 1.554409 | J133: 0.122 | K133: 1.284409
B134: Fund VII | C134: Lone Star II | D134: 2010 | E134: -0.3 | F134: 0.012 | G134: -0.312 | H134: -0.148 | I134: -0.152 | J134: 0.122 | K134: -0.422
B135: Fund VII | C135: Limestone II | D135: 2010 | E135: -0.366 | F135: 0.012 | G135: -0.378 | H135: -0.148 | I135: -0.218 | J135: 0.122 | K135: -0.488
B136: Fund VII | C136: Enduring II | D136: 2011 | E136: 0.68217567 | F136: -0.067 | G136: 0.74917567 | H136: 0.0419 | I136: 0.64027567 | J136: 0.146 | K136: 0.53617567
B137: Fund VII | C137: Piedra II | D137: 2011 | E137: 0.48310953 | F137: -0.067 | G137: 0.55010953 | H137: 0.0419 | I137: 0.44120953 | J137: 0.146 | K137: 0.33710953
B138: Fund VI | C138: Core | D138: 2006 | E138: 0.11154211 | F138: N/A | G138: 0 | H138: 0.0189 | I138: 0.092642112 | J138: N/A | K138: 0
B139: Fund VI | C139: Lobos | D139: 2006 | E139: 0.20856358 | F139: N/A | G139: 0 | H139: 0.0189 | I139: 0.18966358 | J139: N/A | K139: 0
B140: Fund VI | C140: Marquette | D140: 2006 | E140: 0.62391786 | F140: N/A | G140: 0 | H140: 0.0189 | I140: 0.60501786 | J140: N/A | K140: 0
B141: Fund VI | C141: GulfTex | D141: 2006 | E141: 0.3155559 | F141: N/A | G141: 0 | H141: 0.0189 | I141: 0.2966559 | J141: N/A | K141: 0
B142: Fund VI | C142: GFI (SMDR) | D142: 2006 | E142: 0.27946 | F142: N/A | G142: 0 | H142: 0.0189 | I142: 0.26056 | J142: N/A | K142: 0
B143: Fund VI | C143: Manti | D143: 2006 | E143: 0.024409553 | F143: N/A | G143: 0 | H143: 0.0189 | I143: 0.0055095534 | J143: N/A | K143: 0
...

Sheet Pitchbook O&G
B2: Vintage | C2: IRR
B3: 1998 | C3: 0.209
B4: 1999 | C4: 0.24
B5: 2000 | C5: 0.7259
B6: 2001 | C6: 0.5053
B7: 2002 | C7: 0.3605
B8: 2003 | C8: 0.247
B9: 2004 | C9: 0.1858
B10: 2005 | C10: 0.0784
B11: 2006 | C11: 0.0189
B12: 2007 | C12: 0.011
B13: 2008 | C13: 0.0835
B14: 2009 | C14: -0.0016
... B22: 2017 | C22: 0.0974

Sheet MSCI Natural Resources
C3: Natural Resources
B4: 2010 | C4: 0.012
B5: 2011 | C5: -0.067
B6: 2012 | C6: 0.005
B7: 2013 | C7: 0.037
B8: 2014 | C8: 0.038
B9: 2015 | C9: 0.08
B10: 2016 | C10: 0.068
B11: 2017 | C11: 0.092
B12: 2018 | C12: 0.086
B13: 2019 | C13: 0.12
B14: 2020 | C14: 0.069
B15: 2021 | C15: 0.188
... B18: 2024 | C18: 0.04
B19: All | C19: 0.062
