Workbook

Sheet Funds
A1: Fund Name | B1: Vintage Year
A2: Fund I | B2: 1994
A3: Fund II | B3: 1996
A4: Fund III | B4: 1997
A5: Fund IV | B5: 2001
A6: Fund V | B6: 2004
A7: Fund VI | B7: 2006
A8: Fund VII | B8: 2007
A9: Fund VIII | B9: 2010
A10: Fund IX | B10: 2013
A11: Fund X | B11: 2015
A12: Fund XI | B12: 2017
A13: Fund XII | B13: 2023

Sheet Portfolios
A1: Portfolio Name | B1: Fund Name | C1: Committed Capital (M) | D1: Invested Capital (M) | E1: Total Value (M) | F1: Realized | G1: MOIC | H1: Held at 0.0x | I1: Between 0.0x to 1.0x | J1: Held at 1.0x (cost) | K1: Between 1.0x to 2.0x | L1: Between 2.0x to 3.0x | M1: Above 3.0x | N1: Impaired Capital (M)
A2: Duck Lake | B2: =Funds!A2 -> Fund I | C2: 15.2 | D2: 15.2 | E2: 28 | F2: TRUE | G2: =E2/D2 -> 1.8421053 | H2: =G2=0 -> FALSE | I2: =AND(G2>0, G2<1) -> FALSE | J2: =G2=1 -> FALSE | K2: =AND(G2>1, G2<2) -> TRUE | L2: =AND(G2>=2, G2<3) -> FALSE | M2: =G2>3 -> FALSE | N2: =IF(OR(H2, I2), -D2 * (G2 - 1), 0) -> 0
A3: Paloma | B3: =Funds!A2 -> Fund I | C3: 3.6 | D3: 3.6 | E3: 7.2 | F3: TRUE | G3: =E3/D3 -> 2 | H3: =G3=0 -> FALSE | I3: =AND(G3>0, G3<1) -> FALSE | J3: =G3=1 -> FALSE | K3: =AND(G3>1, G3<2) -> FALSE | L3: =AND(G3>=2, G3<3) -> TRUE | M3: =G3>3 -> FALSE | N3: =IF(OR(H3, I3), -D3 * (G3 - 1), 0) -> 0
A4: Sierra 94 | B4: =Funds!A2 -> Fund I | C4: 6.6 | D4: 6.6 | E4: 8.2 | F4: TRUE | G4: =E4/D4 -> 1.2424242 | H4: =G4=0 -> FALSE | I4: =AND(G4>0, G4<1) -> FALSE | J4: =G4=1 -> FALSE | K4: =AND(G4>1, G4<2) -> TRUE | L4: =AND(G4>=2, G4<3) -> FALSE | M4: =G4>3 -> FALSE | N4: =IF(OR(H4, I4), -D4 * (G4 - 1), 0) -> 0
A5: ATP | B5: =Funds!A2 -> Fund I | C5: 9.6 | D5: 9.6 | E5: 11.5 | F5: TRUE | G5: =E5/D5 -> 1.1979167 | H5: =G5=0 -> FALSE | I5: =AND(G5>0, G5<1) -> FALSE | J5: =G5=1 -> FALSE | K5: =AND(G5>1, G5<2) -> TRUE | L5: =AND(G5>=2, G5<3) -> FALSE | M5: =G5>3 -> FALSE | N5: =IF(OR(H5, I5), -D5 * (G5 - 1), 0) -> 0
A6: Future | B6: =Funds!A2 -> Fund I | C6: 9.6 | D6: 9.6 | E6: 14.5 | F6: TRUE | G6: =E6/D6 -> 1.5104167 | H6: =G6=0 -> FALSE | I6: =AND(G6>0, G6<1) -> FALSE | J6: =G6=1 -> FALSE | K6: =AND(G6>1, G6<2) -> TRUE | L6: =AND(G6>=2, G6<3) -> FALSE | M6: =G6>3 -> FALSE | N6: =IF(OR(H6, I6), -D6 * (G6 - 1), 0) -> 0
A7: TAP | B7: =Funds!A2 -> Fund I | C7: 0.4 | D7: 0.4 | E7: 0 | F7: TRUE | G7: =E7/D7 -> 0 | H7: =G7=0 -> TRUE | I7: =AND(G7>0, G7<1) -> FALSE | J7: =G7=1 -> FALSE | K7: =AND(G7>1, G7<2) -> FALSE | L7: =AND(G7>=2, G7<3) -> FALSE | M7: =G7>3 -> FALSE | N7: =IF(OR(H7, I7), -D7 * (G7 - 1), 0) -> 0.4
A8: EnerVest | B8: =Funds!A2 -> Fund I | C8: 11.5 | D8: 11.5 | E8: 16.8 | F8: TRUE | G8: =E8/D8 -> 1.4608696 | H8: =G8=0 -> FALSE | I8: =AND(G8>0, G8<1) -> FALSE | J8: =G8=1 -> FALSE | K8: =AND(G8>1, G8<2) -> TRUE | L8: =AND(G8>=2, G8<3) -> FALSE | M8: =G8>3 -> FALSE | N8: =IF(OR(H8, I8), -D8 * (G8 - 1), 0) -> 0
A9: Sotex Frio | B9: =Funds!A2 -> Fund I | C9: 9.2 | D9: 9.2 | E9: 14.8 | F9: TRUE | G9: =E9/D9 -> 1.6086957 | H9: =G9=0 -> FALSE | I9: =AND(G9>0, G9<1) -> FALSE | J9: =G9=1 -> FALSE | K9: =AND(G9>1, G9<2) -> TRUE | L9: =AND(G9>=2, G9<3) -> FALSE | M9: =G9>3 -> FALSE | N9: =IF(OR(H9, I9), -D9 * (G9 - 1), 0) -> 0
A10: Matrix I | B10: =Funds!A2 -> Fund I | C10: 7.4 | D10: 7.4 | E10: 12.1 | F10: TRUE | G10: =E10/D10 -> 1.6351351 | H10: =G10=0 -> FALSE | I10: =AND(G10>0, G10<1) -> FALSE | J10: =G10=1 -> FALSE | K10: =AND(G10>1, G10<2) -> TRUE | L10: =AND(G10>=2, G10<3) -> FALSE | M10: =G10>3 -> FALSE | N10: =IF(OR(H10, I10), -D10 * (G10 - 1), 0) -> 0
A11: Double Diamond | B11: =Funds!A2 -> Fund I | C11: 3.1 | D11: 3.1 | E11: 4.8 | F11: TRUE | G11: =E11/D11 -> 1.5483871 | H11: =G11=0 -> FALSE | I11: =AND(G11>0, G11<1) -> FALSE | J11: =G11=1 -> FALSE | K11: =AND(G11>1, G11<2) -> TRUE | L11: =AND(G11>=2, G11<3) -> FALSE | M11: =G11>3 -> FALSE | N11: =IF(OR(H11, I11), -D11 * (G11 - 1), 0) -> 0
A12: MPAC I | B12: =Funds!A2 -> Fund I | C12: 13.1 | D12: 13.1 | E12: 18.4 | F12: TRUE | G12: =E12/D12 -> 1.4045802 | H12: =G12=0 -> FALSE | I12: =AND(G12>0, G12<1) -> FALSE | J12: =G12=1 -> FALSE | K12: =AND(G12>1, G12<2) -> TRUE | L12: =AND(G12>=2, G12<3) -> FALSE | M12: =G12>3 -> FALSE | N12: =IF(OR(H12, I12), -D12 * (G12 - 1), 0) -> 0
A13: Sierra 96 | B13: =Funds!A2 -> Fund I | C13: 14.8 | D13: 14.8 | E13: 59.7 | F13: TRUE | G13: =E13/D13 -> 4.0337838 | H13: =G13=0 -> FALSE | I13: =AND(G13>0, G13<1) -> FALSE | J13: =G13=1 -> FALSE | K13: =AND(G13>1, G13<2) -> FALSE | L13: =AND(G13>=2, G13<3) -> FALSE | M13: =G13>3 -> TRUE | N13: =IF(OR(H13, I13), -D13 * (G13 - 1), 0) -> 0
A14: MPAC II | B14: =Funds!A3 -> Fund II | C14: 96.7 | D14: 96.7 | E14: 114.5 | F14: TRUE | G14: =E14/D14 -> 1.1840745 | H14: =G14=0 -> FALSE | I14: =AND(G14>0, G14<1) -> FALSE | J14: =G14=1 -> FALSE | K14: =AND(G14>1, G14<2) -> TRUE | L14: =AND(G14>=2, G14<3) -> FALSE | M14: =G14>3 -> FALSE | N14: =IF(OR(H14, I14), -D14 * (G14 - 1), 0) -> 0
A15: Cliffwood | B15: =Funds!A3 -> Fund II | C15: 7.1 | D15: 7.1 | E15: 13.6 | F15: TRUE | G15: =E15/D15 -> 1.915493 | H15: =G15=0 -> FALSE | I15: =AND(G15>0, G15<1) -> FALSE | J15: =G15=1 -> FALSE | K15: =AND(G15>1, G15<2) -> TRUE | L15: =AND(G15>=2, G15<3) -> FALSE | M15: =G15>3 -> FALSE | N15: =IF(OR(H15, I15), -D15 * (G15 - 1), 0) -> 0
A16: Sierra-Harris | B16: =Funds!A3 -> Fund II | C16: 2.3 | D16: 2.3 | E16: 3.4 | F16: TRUE | G16: =E16/D16 -> 1.4782609 | H16: =G16=0 -> FALSE | I16: =AND(G16>0, G16<1) -> FALSE | J16: =G16=1 -> FALSE | K16: =AND(G16>1, G16<2) -> TRUE | L16: =AND(G16>=2, G16<3) -> FALSE | M16: =G16>3 -> FALSE | N16: =IF(OR(H16, I16), -D16 * (G16 - 1), 0) -> 0
A17: Matrix II | B17: =Funds!A3 -> Fund II | C17: 8.5 | D17: 8.5 | E17: 10.5 | F17: TRUE | G17: =E17/D17 -> 1.2352941 | H17: =G17=0 -> FALSE | I17: =AND(G17>0, G17<1) -> FALSE | J17: =G17=1 -> FALSE | K17: =AND(G17>1, G17<2) -> TRUE | L17: =AND(G17>=2, G17<3) -> FALSE | M17: =G17>3 -> FALSE | N17: =IF(OR(H17, I17), -D17 * (G17 - 1), 0) -> 0
A18: Benz | B18: =Funds!A4 -> Fund III | C18: 24.9 | D18: 24.9 | E18: 33.3 | F18: TRUE | G18: =E18/D18 -> 1.3373494 | H18: =G18=0 -> FALSE | I18: =AND(G18>0, G18<1) -> FALSE | J18: =G18=1 -> FALSE | K18: =AND(G18>1, G18<2) -> TRUE | L18: =AND(G18>=2, G18<3) -> FALSE | M18: =G18>3 -> FALSE | N18: =IF(OR(H18, I18), -D18 * (G18 - 1), 0) -> 0
A19: Harken | B19: =Funds!A4 -> Fund III | C19: 25 | D19: 25 | E19: 21.3 | F19: TRUE | G19: =E19/D19 -> 0.852 | H19: =G19=0 -> FALSE | I19: =AND(G19>0, G19<1) -> TRUE | J19: =G19=1 -> FALSE | K19: =AND(G19>1, G19<2) -> FALSE | L19: =AND(G19>=2, G19<3) -> FALSE | M19: =G19>3 -> FALSE | N19: =IF(OR(H19, I19), -D19 * (G19 - 1), 0) -> 3.7
A20: San Juan | B20: =Funds!A4 -> Fund III | C20: 15.6 | D20: 15.6 | E20: 27.7 | F20: TRUE | G20: =E20/D20 -> 1.775641 | H20: =G20=0 -> FALSE | I20: =AND(G20>0, G20<1) -> FALSE | J20: =G20=1 -> FALSE | K20: =AND(G20>1, G20<2) -> TRUE | L20: =AND(G20>=2, G20<3) -> FALSE | M20: =G20>3 -> FALSE | N20: =IF(OR(H20, I20), -D20 * (G20 - 1), 0) -> 0
A21: Sharpe | B21: =Funds!A4 -> Fund III | C21: 3 | D21: 3 | E21: 3.7 | F21: TRUE | G21: =E21/D21 -> 1.2333333 | H21: =G21=0 -> FALSE | I21: =AND(G21>0, G21<1) -> FALSE | J21: =G21=1 -> FALSE | K21: =AND(G21>1, G21<2) -> TRUE | L21: =AND(G21>=2, G21<3) -> FALSE | M21: =G21>3 -> FALSE | N21: =IF(OR(H21, I21), -D21 * (G21 - 1), 0) -> 0
A22: BreitBurn | B22: =Funds!A4 -> Fund III | C22: 30 | D22: 30 | E22: 58.4 | F22: TRUE | G22: =E22/D22 -> 1.9466667 | H22: =G22=0 -> FALSE | I22: =AND(G22>0, G22<1) -> FALSE | J22: =G22=1 -> FALSE | K22: =AND(G22>1, G22<2) -> TRUE | L22: =AND(G22>=2, G22<3) -> FALSE | M22: =G22>3 -> FALSE | N22: =IF(OR(H22, I22), -D22 * (G22 - 1), 0) -> 0
A23: Plains Resources | B23: =Funds!A4 -> Fund III | C23: 48.5 | D23: 48.5 | E23: 115.6 | F23: TRUE | G23: =E23/D23 -> 2.3835052 | H23: =G23=0 -> FALSE | I23: =AND(G23>0, G23<1) -> FALSE | J23: =G23=1 -> FALSE | K23: =AND(G23>1, G23<2) -> FALSE | L23: =AND(G23>=2, G23<3) -> TRUE | M23: =G23>3 -> FALSE | N23: =IF(OR(H23, I23), -D23 * (G23 - 1), 0) -> 0
A24: CERES | B24: =Funds!A4 -> Fund III | C24: 14.6 | D24: 14.6 | E24: 26.1 | F24: TRUE | G24: =E24/D24 -> 1.7876712 | H24: =G24=0 -> FALSE | I24: =AND(G24>0, G24<1) -> FALSE | J24: =G24=1 -> FALSE | K24: =AND(G24>1, G24<2) -> TRUE | L24: =AND(G24>=2, G24<3) -> FALSE | M24: =G24>3 -> FALSE | N24: =IF(OR(H24, I24), -D24 * (G24 - 1), 0) -> 0
A25: Matrix III | B25: =Funds!A4 -> Fund III | C25: 28.6 | D25: 28.6 | E25: 99.4 | F25: TRUE | G25: =E25/D25 -> 3.4755245 | H25: =G25=0 -> FALSE | I25: =AND(G25>0, G25<1) -> FALSE | J25: =G25=1 -> FALSE | K25: =AND(G25>1, G25<2) -> FALSE | L25: =AND(G25>=2, G25<3) -> FALSE | M25: =G25>3 -> TRUE | N25: =IF(OR(H25, I25), -D25 * (G25 - 1), 0) -> 0
A26: 3TEC | B26: =Funds!A4 -> Fund III | C26: 48.4 | D26: 48.4 | E26: 104.2 | F26: TRUE | G26: =E26/D26 -> 2.1528926 | H26: =G26=0 -> FALSE | I26: =AND(G26>0, G26<1) -> FALSE | J26: =G26=1 -> FALSE | K26: =AND(G26>1, G26<2) -> FALSE | L26: =AND(G26>=2, G26<3) -> TRUE | M26: =G26>3 -> FALSE | N26: =IF(OR(H26, I26), -D26 * (G26 - 1), 0) -> 0
A27: Bargo | B27: =Funds!A4 -> Fund III | C27: 15 | D27: 15 | E27: 26.7 | F27: TRUE | G27: =E27/D27 -> 1.78 | H27: =G27=0 -> FALSE | I27: =AND(G27>0, G27<1) -> FALSE | J27: =G27=1 -> FALSE | K27: =AND(G27>1, G27<2) -> TRUE | L27: =AND(G27>=2, G27<3) -> FALSE | M27: =G27>3 -> FALSE | N27: =IF(OR(H27, I27), -D27 * (G27 - 1), 0) -> 0
A28: Cordillera | B28: =Funds!A4 -> Fund III | C28: 48.5 | D28: 48.5 | E28: 133.7 | F28: TRUE | G28: =E28/D28 -> 2.756701 | H28: =G28=0 -> FALSE | I28: =AND(G28>0, G28<1) -> FALSE | J28: =G28=1 -> FALSE | K28: =AND(G28>1, G28<2) -> FALSE | L28: =AND(G28>=2, G28<3) -> TRUE | M28: =G28>3 -> FALSE | N28: =IF(OR(H28, I28), -D28 * (G28 - 1), 0) -> 0
A29: Cheniere | B29: =Funds!A4 -> Fund III | C29: 3.7 | D29: 3.7 | E29: 4.6 | F29: TRUE | G29: =E29/D29 -> 1.2432432 | H29: =G29=0 -> FALSE | I29: =AND(G29>0, G29<1) -> FALSE | J29: =G29=1 -> FALSE | K29: =AND(G29>1, G29<2) -> TRUE | L29: =AND(G29>=2, G29<3) -> FALSE | M29: =G29>3 -> FALSE | N29: =IF(OR(H29, I29), -D29 * (G29 - 1), 0) -> 0
A30: First Permian | B30: =Funds!A4 -> Fund III | C30: 16 | D30: 16 | E30: 27.2 | F30: TRUE | G30: =E30/D30 -> 1.7 | H30: =G30=0 -> FALSE | I30: =AND(G30>0, G30<1) -> FALSE | J30: =G30=1 -> FALSE | K30: =AND(G30>1, G30<2) -> TRUE | L30: =AND(G30>=2, G30<3) -> FALSE | M30: =G30>3 -> FALSE | N30: =IF(OR(H30, I30), -D30 * (G30 - 1), 0) -> 0
A31: American Coastal | B31: =Funds!A4 -> Fund III | C31: 12 | D31: 12 | E31: 14.3 | F31: TRUE | G31: =E31/D31 -> 1.1916667 | H31: =G31=0 -> FALSE | I31: =AND(G31>0, G31<1) -> FALSE | J31: =G31=1 -> FALSE | K31: =AND(G31>1, G31<2) -> TRUE | L31: =AND(G31>=2, G31<3) -> FALSE | M31: =G31>3 -> FALSE | N31: =IF(OR(H31, I31), -D31 * (G31 - 1), 0) -> 0
A32: Dallas Production | B32: =Funds!A4 -> Fund III | C32: 22.3 | D32: 22.3 | E32: 37.3 | F32: TRUE | G32: =E32/D32 -> 1.6726457 | H32: =G32=0 -> FALSE | I32: =AND(G32>0, G32<1) -> FALSE | J32: =G32=1 -> FALSE | K32: =AND(G32>1, G32<2) -> TRUE | L32: =AND(G32>=2, G32<3) -> FALSE | M32: =G32>3 -> FALSE | N32: =IF(OR(H32, I32), -D32 * (G32 - 1), 0) -> 0
A33: PetroQuest | B33: =Funds!A4 -> Fund III | C33: 7.5 | D33: 7.5 | E33: 8.9 | F33: TRUE | G33: =E33/D33 -> 1.1866667 | H33: =G33=0 -> FALSE | I33: =AND(G33>0, G33<1) -> FALSE | J33: =G33=1 -> FALSE | K33: =AND(G33>1, G33<2) -> TRUE | L33: =AND(G33>=2, G33<3) -> FALSE | M33: =G33>3 -> FALSE | N33: =IF(OR(H33, I33), -D33 * (G33 - 1), 0) -> 0
A34: Plains All-American LP Units | B34: =Funds!A4 -> Fund III | C34: 19.9 | D34: 19.9 | E34: 33.3 | F34: TRUE | G34: =E34/D34 -> 1.6733668 | H34: =G34=0 -> FALSE | I34: =AND(G34>0, G34<1) -> FALSE | J34: =G34=1 -> FALSE | K34: =AND(G34>1, G34<2) -> TRUE | L34: =AND(G34>=2, G34<3) -> FALSE | M34: =G34>3 -> FALSE | N34: =IF(OR(H34, I34), -D34 * (G34 - 1), 0) -> 0
A35: Copano | B35: =Funds!A4 -> Fund III | C35: 30 | D35: 30 | E35: 103 | F35: TRUE | G35: =E35/D35 -> 3.4333333 | H35: =G35=0 -> FALSE | I35: =AND(G35>0, G35<1) -> FALSE | J35: =G35=1 -> FALSE | K35: =AND(G35>1, G35<2) -> FALSE | L35: =AND(G35>=2, G35<3) -> FALSE | M35: =G35>3 -> TRUE | N35: =IF(OR(H35, I35), -D35 * (G35 - 1), 0) -> 0
A36: NCX | B36: =Funds!A4 -> Fund III | C36: 18.2 | D36: 18.2 | E36: 88.6 | F36: TRUE | G36: =E36/D36 -> 4.8681319 | H36: =G36=0 -> FALSE | I36: =AND(G36>0, G36<1) -> FALSE | J36: =G36=1 -> FALSE | K36: =AND(G36>1, G36<2) -> FALSE | L36: =AND(G36>=2, G36<3) -> FALSE | M36: =G36>3 -> TRUE | N36: =IF(OR(H36, I36), -D36 * (G36 - 1), 0) -> 0
A37: Plains All-American GP & LP Units | B37: =Funds!A4 -> Fund III | C37: 36.9 | D37: 36.9 | E37: 338.5 | F37: TRUE | G37: =E37/D37 -> 9.1734417 | H37: =G37=0 -> FALSE | I37: =AND(G37>0, G37<1) -> FALSE | J37: =G37=1 -> FALSE | K37: =AND(G37>1, G37<2) -> FALSE | L37: =AND(G37>=2, G37<3) -> FALSE | M37: =G37>3 -> TRUE | N37: =IF(OR(H37, I37), -D37 * (G37 - 1), 0) -> 0
A38: Laredo I | B38: =Funds!A5 -> Fund IV | C38: 14 | D38: 14 | E38: 70.4 | F38: TRUE | G38: =E38/D38 -> 5.0285714 | H38: =G38=0 -> FALSE | I38: =AND(G38>0, G38<1) -> FALSE | J38: =G38=1 -> FALSE | K38: =AND(G38>1, G38<2) -> FALSE | L38: =AND(G38>=2, G38<3) -> FALSE | M38: =G38>3 -> TRUE | N38: =IF(OR(H38, I38), -D38 * (G38 - 1), 0) -> 0
A39: Ovation I | B39: =Funds!A5 -> Fund IV | C39: 17.8 | D39: 17.8 | E39: 40.4 | F39: TRUE | G39: =E39/D39 -> 2.2696629 | H39: =G39=0 -> FALSE | I39: =AND(G39>0, G39<1) -> FALSE | J39: =G39=1 -> FALSE | K39: =AND(G39>1, G39<2) -> FALSE | L39: =AND(G39>=2, G39<3) -> TRUE | M39: =G39>3 -> FALSE | N39: =IF(OR(H39, I39), -D39 * (G39 - 1), 0) -> 0
A40: Sawtooth | B40: =Funds!A5 -> Fund IV | C40: 6.7 | D40: 6.7 | E40: 22.8 | F40: TRUE | G40: =E40/D40 -> 3.4029851 | H40: =G40=0 -> FALSE | I40: =AND(G40>0, G40<1) -> FALSE | J40: =G40=1 -> FALSE | K40: =AND(G40>1, G40<2) -> FALSE | L40: =AND(G40>=2, G40<3) -> FALSE | M40: =G40>3 -> TRUE | N40: =IF(OR(H40, I40), -D40 * (G40 - 1), 0) -> 0
A41: Sierra 2002 (bridge) | B41: =Funds!A5 -> Fund IV | C41: 7.8 | D41: 7.8 | E41: 9.1 | F41: TRUE | G41: =E41/D41 -> 1.1666667 | H41: =G41=0 -> FALSE | I41: =AND(G41>0, G41<1) -> FALSE | J41: =G41=1 -> FALSE | K41: =AND(G41>1, G41<2) -> TRUE | L41: =AND(G41>=2, G41<3) -> FALSE | M41: =G41>3 -> FALSE | N41: =IF(OR(H41, I41), -D41 * (G41 - 1), 0) -> 0
A42: Medicine Bow | B42: =Funds!A5 -> Fund IV | C42: 57.3 | D42: 57.3 | E42: 232.1 | F42: TRUE | G42: =E42/D42 -> 4.0506108 | H42: =G42=0 -> FALSE | I42: =AND(G42>0, G42<1) -> FALSE | J42: =G42=1 -> FALSE | K42: =AND(G42>1, G42<2) -> FALSE | L42: =AND(G42>=2, G42<3) -> FALSE | M42: =G42>3 -> TRUE | N42: =IF(OR(H42, I42), -D42 * (G42 - 1), 0) -> 0
A43: Plantation I | B43: =Funds!A5 -> Fund IV | C43: 30 | D43: 30 | E43: 64.4 | F43: TRUE | G43: =E43/D43 -> 2.1466667 | H43: =G43=0 -> FALSE | I43: =AND(G43>0, G43<1) -> FALSE | J43: =G43=1 -> FALSE | K43: =AND(G43>1, G43<2) -> FALSE | L43: =AND(G43>=2, G43<3) -> TRUE | M43: =G43>3 -> FALSE | N43: =IF(OR(H43, I43), -D43 * (G43 - 1), 0) -> 0
A44: Nautilus | B44: =Funds!A5 -> Fund IV | C44: 30 | D44: 30 | E44: 44.4 | F44: TRUE | G44: =E44/D44 -> 1.48 | H44: =G44=0 -> FALSE | I44: =AND(G44>0, G44<1) -> FALSE | J44: =G44=1 -> FALSE | K44: =AND(G44>1, G44<2) -> TRUE | L44: =AND(G44>=2, G44<3) -> FALSE | M44: =G44>3 -> FALSE | N44: =IF(OR(H44, I44), -D44 * (G44 - 1), 0) -> 0
A45: Laredo II | B45: =Funds!A5 -> Fund IV | C45: 20.6 | D45: 20.6 | E45: 126.1 | F45: TRUE | G45: =E45/D45 -> 6.1213592 | H45: =G45=0 -> FALSE | I45: =AND(G45>0, G45<1) -> FALSE | J45: =G45=1 -> FALSE | K45: =AND(G45>1, G45<2) -> FALSE | L45: =AND(G45>=2, G45<3) -> FALSE | M45: =G45>3 -> TRUE | N45: =IF(OR(H45, I45), -D45 * (G45 - 1), 0) -> 0
A46: Plantation II | B46: =Funds!A5 -> Fund IV | C46: 10 | D46: 10 | E46: 59.3 | F46: TRUE | G46: =E46/D46 -> 5.93 | H46: =G46=0 -> FALSE | I46: =AND(G46>0, G46<1) -> FALSE | J46: =G46=1 -> FALSE | K46: =AND(G46>1, G46<2) -> FALSE | L46: =AND(G46>=2, G46<3) -> FALSE | M46: =G46>3 -> TRUE | N46: =IF(OR(H46, I46), -D46 * (G46 - 1), 0) -> 0
A47: Petrohawk | B47: =Funds!A5 -> Fund IV | C47: 39.1 | D47: 39.1 | E47: 127.8 | F47: TRUE | G47: =E47/D47 -> 3.2685422 | H47: =G47=0 -> FALSE | I47: =AND(G47>0, G47<1) -> FALSE | J47: =G47=1 -> FALSE | K47: =AND(G47>1, G47<2) -> FALSE | L47: =AND(G47>=2, G47<3) -> FALSE | M47: =G47>3 -> TRUE | N47: =IF(OR(H47, I47), -D47 * (G47 - 1), 0) -> 0
A48: Stroud | B48: =Funds!A5 -> Fund IV | C48: 27 | D48: 27 | E48: 83.9 | F48: TRUE | G48: =E48/D48 -> 3.1074074 | H48: =G48=0 -> FALSE | I48: =AND(G48>0, G48<1) -> FALSE | J48: =G48=1 -> FALSE | K48: =AND(G48>1, G48<2) -> FALSE | L48: =AND(G48>=2, G48<3) -> FALSE | M48: =G48>3 -> TRUE | N48: =IF(OR(H48, I48), -D48 * (G48 - 1), 0) -> 0
A49: Tempest | B49: =Funds!A5 -> Fund IV | C49: 33.9 | D49: 33.9 | E49: 1.1 | F49: TRUE | G49: =E49/D49 -> 0.032448378 | H49: =G49=0 -> FALSE | I49: =AND(G49>0, G49<1) -> TRUE | J49: =G49=1 -> FALSE | K49: =AND(G49>1, G49<2) -> FALSE | L49: =AND(G49>=2, G49<3) -> FALSE | M49: =G49>3 -> FALSE | N49: =IF(OR(H49, I49), -D49 * (G49 - 1), 0) -> 32.8
A50: NGL | B50: =Funds!A5 -> Fund IV | C50: 50 | D50: 50 | E50: 75.7 | F50: TRUE | G50: =E50/D50 -> 1.514 | H50: =G50=0 -> FALSE | I50: =AND(G50>0, G50<1) -> FALSE | J50: =G50=1 -> FALSE | K50: =AND(G50>1, G50<2) -> TRUE | L50: =AND(G50>=2, G50<3) -> FALSE | M50: =G50>3 -> FALSE | N50: =IF(OR(H50, I50), -D50 * (G50 - 1), 0) -> 0
A51: Laramie | B51: =Funds!A5 -> Fund IV | C51: 77.3 | D51: 77.3 | E51: 265.5 | F51: TRUE | G51: =E51/D51 -> 3.4346701 | H51: =G51=0 -> FALSE | I51: =AND(G51>0, G51<1) -> FALSE | J51: =G51=1 -> FALSE | K51: =AND(G51>1, G51<2) -> FALSE | L51: =AND(G51>=2, G51<3) -> FALSE | M51: =G51>3 -> TRUE | N51: =IF(OR(H51, I51), -D51 * (G51 - 1), 0) -> 0
A52: Protege | B52: =Funds!A5 -> Fund IV | C52: 30 | D52: 30 | E52: 64.7 | F52: TRUE | G52: =E52/D52 -> 2.1566667 | H52: =G52=0 -> FALSE | I52: =AND(G52>0, G52<1) -> FALSE | J52: =G52=1 -> FALSE | K52: =AND(G52>1, G52<2) -> FALSE | L52: =AND(G52>=2, G52<3) -> TRUE | M52: =G52>3 -> FALSE | N52: =IF(OR(H52, I52), -D52 * (G52 - 1), 0) -> 0
A53: Peregrine I | B53: =Funds!A5 -> Fund IV | C53: 25 | D53: 25.05 | E53: 19.5 | F53: TRUE | G53: =E53/D53 -> 0.77844311 | H53: =G53=0 -> FALSE | I53: =AND(G53>0, G53<1) -> TRUE | J53: =G53=1 -> FALSE | K53: =AND(G53>1, G53<2) -> FALSE | L53: =AND(G53>=2, G53<3) -> FALSE | M53: =G53>3 -> FALSE | N53: =IF(OR(H53, I53), -D53 * (G53 - 1), 0) -> 5.55
A54: Ovation II | B54: =Funds!A5 -> Fund IV | C54: 36.2 | D54: 36.2 | E54: 7.2 | F54: TRUE | G54: =E54/D54 -> 0.19889503 | H54: =G54=0 -> FALSE | I54: =AND(G54>0, G54<1) -> TRUE | J54: =G54=1 -> FALSE | K54: =AND(G54>1, G54<2) -> FALSE | L54: =AND(G54>=2, G54<3) -> FALSE | M54: =G54>3 -> FALSE | N54: =IF(OR(H54, I54), -D54 * (G54 - 1), 0) -> 29
A55: Laredo III | B55: =Funds!A5 -> Fund IV | C55: 24.6 | D55: 24.6 | E55: 104.4 | F55: TRUE | G55: =E55/D55 -> 4.2439024 | H55: =G55=0 -> FALSE | I55: =AND(G55>0, G55<1) -> FALSE | J55: =G55=1 -> FALSE | K55: =AND(G55>1, G55<2) -> FALSE | L55: =AND(G55>=2, G55<3) -> FALSE | M55: =G55>3 -> TRUE | N55: =IF(OR(H55, I55), -D55 * (G55 - 1), 0) -> 0
A56: Plantation III | B56: =Funds!A5 -> Fund IV | C56: 33.1 | D56: 33.1 | E56: 66.2 | F56: TRUE | G56: =E56/D56 -> 2 | H56: =G56=0 -> FALSE | I56: =AND(G56>0, G56<1) -> FALSE | J56: =G56=1 -> FALSE | K56: =AND(G56>1, G56<2) -> FALSE | L56: =AND(G56>=2, G56<3) -> TRUE | M56: =G56>3 -> FALSE | N56: =IF(OR(H56, I56), -D56 * (G56 - 1), 0) -> 0
A57: Ovation II | B57: =Funds!A6 -> Fund V | C57: 9 | D57: 9 | E57: 1.9 | F57: TRUE | G57: =E57/D57 -> 0.21111111 | H57: =G57=0 -> FALSE | I57: =AND(G57>0, G57<1) -> TRUE | J57: =G57=1 -> FALSE | K57: =AND(G57>1, G57<2) -> FALSE | L57: =AND(G57>=2, G57<3) -> FALSE | M57: =G57>3 -> FALSE | N57: =IF(OR(H57, I57), -D57 * (G57 - 1), 0) -> 7.1
A58: Escondido I | B58: =Funds!A6 -> Fund V | C58: 53.7 | D58: 53.7 | E58: 131.7 | F58: TRUE | G58: =E58/D58 -> 2.452514 | H58: =G58=0 -> FALSE | I58: =AND(G58>0, G58<1) -> FALSE | J58: =G58=1 -> FALSE | K58: =AND(G58>1, G58<2) -> FALSE | L58: =AND(G58>=2, G58<3) -> TRUE | M58: =G58>3 -> FALSE | N58: =IF(OR(H58, I58), -D58 * (G58 - 1), 0) -> 0
A59: Cordillera II | B59: =Funds!A6 -> Fund V | C59: 99.5 | D59: 99.5 | E59: 193.2 | F59: TRUE | G59: =E59/D59 -> 1.9417085 | H59: =G59=0 -> FALSE | I59: =AND(G59>0, G59<1) -> FALSE | J59: =G59=1 -> FALSE | K59: =AND(G59>1, G59<2) -> TRUE | L59: =AND(G59>=2, G59<3) -> FALSE | M59: =G59>3 -> FALSE | N59: =IF(OR(H59, I59), -D59 * (G59 - 1), 0) -> 0
A60: Empresa | B60: =Funds!A6 -> Fund V | C60: 86.2 | D60: 86.2 | E60: 337.9 | F60: TRUE | G60: =E60/D60 -> 3.9199536 | H60: =G60=0 -> FALSE | I60: =AND(G60>0, G60<1) -> FALSE | J60: =G60=1 -> FALSE | K60: =AND(G60>1, G60<2) -> FALSE | L60: =AND(G60>=2, G60<3) -> FALSE | M60: =G60>3 -> TRUE | N60: =IF(OR(H60, I60), -D60 * (G60 - 1), 0) -> 0
A61: Enduring | B61: =Funds!A6 -> Fund V | C61: 162.2 | D61: 162.2 | E61: 408.9 | F61: TRUE | G61: =E61/D61 -> 2.5209618 | H61: =G61=0 -> FALSE | I61: =AND(G61>0, G61<1) -> FALSE | J61: =G61=1 -> FALSE | K61: =AND(G61>1, G61<2) -> FALSE | L61: =AND(G61>=2, G61<3) -> TRUE | M61: =G61>3 -> FALSE | N61: =IF(OR(H61, I61), -D61 * (G61 - 1), 0) -> 0
A62: Shona | B62: =Funds!A6 -> Fund V | C62: 13 | D62: 13 | E62: 29.6 | F62: TRUE | G62: =E62/D62 -> 2.2769231 | H62: =G62=0 -> FALSE | I62: =AND(G62>0, G62<1) -> FALSE | J62: =G62=1 -> FALSE | K62: =AND(G62>1, G62<2) -> FALSE | L62: =AND(G62>=2, G62<3) -> TRUE | M62: =G62>3 -> FALSE | N62: =IF(OR(H62, I62), -D62 * (G62 - 1), 0) -> 0
A63: Bold | B63: =Funds!A6 -> Fund V | C63: 22.8 | D63: 22.8 | E63: 54.9 | F63: TRUE | G63: =E63/D63 -> 2.4078947 | H63: =G63=0 -> FALSE | I63: =AND(G63>0, G63<1) -> FALSE | J63: =G63=1 -> FALSE | K63: =AND(G63>1, G63<2) -> FALSE | L63: =AND(G63>=2, G63<3) -> TRUE | M63: =G63>3 -> FALSE | N63: =IF(OR(H63, I63), -D63 * (G63 - 1), 0) -> 0
A64: Crimson | B64: =Funds!A6 -> Fund V | C64: 27.3 | D64: 27.3 | E64: 35.3 | F64: TRUE | G64: =E64/D64 -> 1.2930403 | H64: =G64=0 -> FALSE | I64: =AND(G64>0, G64<1) -> FALSE | J64: =G64=1 -> FALSE | K64: =AND(G64>1, G64<2) -> TRUE | L64: =AND(G64>=2, G64<3) -> FALSE | M64: =G64>3 -> FALSE | N64: =IF(OR(H64, I64), -D64 * (G64 - 1), 0) -> 0
A65: Savant | B65: =Funds!A6 -> Fund V | C65: 4.2 | D65: 4.2 | E65: 11.6 | F65: TRUE | G65: =E65/D65 -> 2.7619048 | H65: =G65=0 -> FALSE | I65: =AND(G65>0, G65<1) -> FALSE | J65: =G65=1 -> FALSE | K65: =AND(G65>1, G65<2) -> FALSE | L65: =AND(G65>=2, G65<3) -> TRUE | M65: =G65>3 -> FALSE | N65: =IF(OR(H65, I65), -D65 * (G65 - 1), 0) -> 0
A66: Plantation III | B66: =Funds!A6 -> Fund V | C66: 6.6 | D66: 6.6 | E66: 13.4 | F66: TRUE | G66: =E66/D66 -> 2.030303 | H66: =G66=0 -> FALSE | I66: =AND(G66>0, G66<1) -> FALSE | J66: =G66=1 -> FALSE | K66: =AND(G66>1, G66<2) -> FALSE | L66: =AND(G66>=2, G66<3) -> TRUE | M66: =G66>3 -> FALSE | N66: =IF(OR(H66, I66), -D66 * (G66 - 1), 0) -> 0
A67: NCX II | B67: =Funds!A6 -> Fund V | C67: 9 | D67: 9 | E67: 3.3 | F67: TRUE | G67: =E67/D67 -> 0.36666667 | H67: =G67=0 -> FALSE | I67: =AND(G67>0, G67<1) -> TRUE | J67: =G67=1 -> FALSE | K67: =AND(G67>1, G67<2) -> FALSE | L67: =AND(G67>=2, G67<3) -> FALSE | M67: =G67>3 -> FALSE | N67: =IF(OR(H67, I67), -D67 * (G67 - 1), 0) -> 5.7
A68: JOG | B68: =Funds!A6 -> Fund V | C68: 21.9 | D68: 21.9 | E68: 24.7 | F68: TRUE | G68: =E68/D68 -> 1.1278539 | H68: =G68=0 -> FALSE | I68: =AND(G68>0, G68<1) -> FALSE | J68: =G68=1 -> FALSE | K68: =AND(G68>1, G68<2) -> TRUE | L68: =AND(G68>=2, G68<3) -> FALSE | M68: =G68>3 -> FALSE | N68: =IF(OR(H68, I68), -D68 * (G68 - 1), 0) -> 0
A69: PAA | B69: =Funds!A6 -> Fund V | C69: 15.9 | D69: 15.9 | E69: 78.8 | F69: TRUE | G69: =E69/D69 -> 4.9559748 | H69: =G69=0 -> FALSE | I69: =AND(G69>0, G69<1) -> FALSE | J69: =G69=1 -> FALSE | K69: =AND(G69>1, G69<2) -> FALSE | L69: =AND(G69>=2, G69<3) -> FALSE | M69: =G69>3 -> TRUE | N69: =IF(OR(H69, I69), -D69 * (G69 - 1), 0) -> 0
A70: GFI (SMDR) | B70: =Funds!A6 -> Fund V | C70: 6 | D70: 6 | E70: 16.7 | F70: TRUE | G70: =E70/D70 -> 2.7833333 | H70: =G70=0 -> FALSE | I70: =AND(G70>0, G70<1) -> FALSE | J70: =G70=1 -> FALSE | K70: =AND(G70>1, G70<2) -> FALSE | L70: =AND(G70>=2, G70<3) -> TRUE | M70: =G70>3 -> FALSE | N70: =IF(OR(H70, I70), -D70 * (G70 - 1), 0) -> 0
A71: Mediterranean | B71: =Funds!A6 -> Fund V | C71: 33.7 | D71: 33.7 | E71: 56.7 | F71: TRUE | G71: =E71/D71 -> 1.6824926 | H71: =G71=0 -> FALSE | I71: =AND(G71>0, G71<1) -> FALSE | J71: =G71=1 -> FALSE | K71: =AND(G71>1, G71<2) -> TRUE | L71: =AND(G71>=2, G71<3) -> FALSE | M71: =G71>3 -> FALSE | N71: =IF(OR(H71, I71), -D71 * (G71 - 1), 0) -> 0
A72: Cornerstone | B72: =Funds!A6 -> Fund V | C72: 29.2 | D72: 29.2 | E72: 4.7 | F72: TRUE | G72: =E72/D72 -> 0.1609589 | H72: =G72=0 -> FALSE | I72: =AND(G72>0, G72<1) -> TRUE | J72: =G72=1 -> FALSE | K72: =AND(G72>1, G72<2) -> FALSE | L72: =AND(G72>=2, G72<3) -> FALSE | M72: =G72>3 -> FALSE | N72: =IF(OR(H72, I72), -D72 * (G72 - 1), 0) -> 24.5
A73: OGX | B73: =Funds!A6 -> Fund V | C73: 32.2 | D73: 32.2 | E73: 90.5 | F73: TRUE | G73: =E73/D73 -> 2.810559 | H73: =G73=0 -> FALSE | I73: =AND(G73>0, G73<1) -> FALSE | J73: =G73=1 -> FALSE | K73: =AND(G73>1, G73<2) -> FALSE | L73: =AND(G73>=2, G73<3) -> TRUE | M73: =G73>3 -> FALSE | N73: =IF(OR(H73, I73), -D73 * (G73 - 1), 0) -> 0
A74: Riverbend | B74: =Funds!A6 -> Fund V | C74: 7.5 | D74: 7.5 | E74: 21.4 | F74: TRUE | G74: =E74/D74 -> 2.8533333 | H74: =G74=0 -> FALSE | I74: =AND(G74>0, G74<1) -> FALSE | J74: =G74=1 -> FALSE | K74: =AND(G74>1, G74<2) -> FALSE | L74: =AND(G74>=2, G74<3) -> TRUE | M74: =G74>3 -> FALSE | N74: =IF(OR(H74, I74), -D74 * (G74 - 1), 0) -> 0
A75: Tracker | B75: =Funds!A6 -> Fund V | C75: 50.3 | D75: 50.3 | E75: 145.9 | F75: TRUE | G75: =E75/D75 -> 2.9005964 | H75: =G75=0 -> FALSE | I75: =AND(G75>0, G75<1) -> FALSE | J75: =G75=1 -> FALSE | K75: =AND(G75>1, G75<2) -> FALSE | L75: =AND(G75>=2, G75<3) -> TRUE | M75: =G75>3 -> FALSE | N75: =IF(OR(H75, I75), -D75 * (G75 - 1), 0) -> 0
A76: EV Energy (Harvest Oil & Gas) | B76: =Funds!A6 -> Fund V | C76: 22.5 | D76: 22.5 | E76: 47.7 | F76: TRUE | G76: =E76/D76 -> 2.12 | H76: =G76=0 -> FALSE | I76: =AND(G76>0, G76<1) -> FALSE | J76: =G76=1 -> FALSE | K76: =AND(G76>1, G76<2) -> FALSE | L76: =AND(G76>=2, G76<3) -> TRUE | M76: =G76>3 -> FALSE | N76: =IF(OR(H76, I76), -D76 * (G76 - 1), 0) -> 0
A77: RiverStone | B77: =Funds!A6 -> Fund V | C77: 47 | D77: 47 | E77: 75.1 | F77: TRUE | G77: =E77/D77 -> 1.5978723 | H77: =G77=0 -> FALSE | I77: =AND(G77>0, G77<1) -> FALSE | J77: =G77=1 -> FALSE | K77: =AND(G77>1, G77<2) -> TRUE | L77: =AND(G77>=2, G77<3) -> FALSE | M77: =G77>3 -> FALSE | N77: =IF(OR(H77, I77), -D77 * (G77 - 1), 0) -> 0
A78: Destiny | B78: =Funds!A6 -> Fund V | C78: 12.7 | D78: 12.7 | E78: 12.7 | F78: TRUE | G78: =E78/D78 -> 1 | H78: =G78=0 -> FALSE | I78: =AND(G78>0, G78<1) -> FALSE | J78: =G78=1 -> TRUE | K78: =AND(G78>1, G78<2) -> FALSE | L78: =AND(G78>=2, G78<3) -> FALSE | M78: =G78>3 -> FALSE | N78: =IF(OR(H78, I78), -D78 * (G78 - 1), 0) -> 0
A79: O'BENCO II | B79: =Funds!A6 -> Fund V | C79: 35.1 | D79: 35.1 | E79: 70.3 | F79: TRUE | G79: =E79/D79 -> 2.002849 | H79: =G79=0 -> FALSE | I79: =AND(G79>0, G79<1) -> FALSE | J79: =G79=1 -> FALSE | K79: =AND(G79>1, G79<2) -> FALSE | L79: =AND(G79>=2, G79<3) -> TRUE | M79: =G79>3 -> FALSE | N79: =IF(OR(H79, I79), -D79 * (G79 - 1), 0) -> 0
A80: Phillips Royalty | B80: =Funds!A6 -> Fund V | C80: 1.5 | D80: 1.5 | E80: 2.5 | F80: TRUE | G80: =E80/D80 -> 1.6666667 | H80: =G80=0 -> FALSE | I80: =AND(G80>0, G80<1) -> FALSE | J80: =G80=1 -> FALSE | K80: =AND(G80>1, G80<2) -> TRUE | L80: =AND(G80>=2, G80<3) -> FALSE | M80: =G80>3 -> FALSE | N80: =IF(OR(H80, I80), -D80 * (G80 - 1), 0) -> 0
A81: PetroEdge | B81: =Funds!A6 -> Fund V | C81: 39.4 | D81: 39.4 | E81: 64 | F81: TRUE | G81: =E81/D81 -> 1.6243655 | H81: =G81=0 -> FALSE | I81: =AND(G81>0, G81<1) -> FALSE | J81: =G81=1 -> FALSE | K81: =AND(G81>1, G81<2) -> TRUE | L81: =AND(G81>=2, G81<3) -> FALSE | M81: =G81>3 -> FALSE | N81: =IF(OR(H81, I81), -D81 * (G81 - 1), 0) -> 0
A82: ER Energy Group | B82: =Funds!A6 -> Fund V | C82: 57 | D82: 57 | E82: 1.1 | F82: TRUE | G82: =E82/D82 -> 0.019298246 | H82: =G82=0 -> FALSE | I82: =AND(G82>0, G82<1) -> TRUE | J82: =G82=1 -> FALSE | K82: =AND(G82>1, G82<2) -> FALSE | L82: =AND(G82>=2, G82<3) -> FALSE | M82: =G82>3 -> FALSE | N82: =IF(OR(H82, I82), -D82 * (G82 - 1), 0) -> 55.9
A83: Laramie | B83: =Funds!A6 -> Fund V | C83: 10.2 | D83: 10.2 | E83: 35.2 | F83: TRUE | G83: =E83/D83 -> 3.4509804 | H83: =G83=0 -> FALSE | I83: =AND(G83>0, G83<1) -> FALSE | J83: =G83=1 -> FALSE | K83: =AND(G83>1, G83<2) -> FALSE | L83: =AND(G83>=2, G83<3) -> FALSE | M83: =G83>3 -> TRUE | N83: =IF(OR(H83, I83), -D83 * (G83 - 1), 0) -> 0
A84: Earthstone | B84: =Funds!A6 -> Fund V | C84: 6.7 | D84: 6.7 | E84: 0.6 | F84: TRUE | G84: =E84/D84 -> 0.089552239 | H84: =G84=0 -> FALSE | I84: =AND(G84>0, G84<1) -> TRUE | J84: =G84=1 -> FALSE | K84: =AND(G84>1, G84<2) -> FALSE | L84: =AND(G84>=2, G84<3) -> FALSE | M84: =G84>3 -> FALSE | N84: =IF(OR(H84, I84), -D84 * (G84 - 1), 0) -> 6.1
A85: Core | B85: =Funds!A7 -> Fund VI | C85: 27.6 | D85: 27.6 | E85: 38.7 | F85: TRUE | G85: =E85/D85 -> 1.4021739 | H85: =G85=0 -> FALSE | I85: =AND(G85>0, G85<1) -> FALSE | J85: =G85=1 -> FALSE | K85: =AND(G85>1, G85<2) -> TRUE | L85: =AND(G85>=2, G85<3) -> FALSE | M85: =G85>3 -> FALSE | N85: =IF(OR(H85, I85), -D85 * (G85 - 1), 0) -> 0
A86: Lobos | B86: =Funds!A7 -> Fund VI | C86: 51.7 | D86: 51.7 | E86: 86.7 | F86: TRUE | G86: =E86/D86 -> 1.6769826 | H86: =G86=0 -> FALSE | I86: =AND(G86>0, G86<1) -> FALSE | J86: =G86=1 -> FALSE | K86: =AND(G86>1, G86<2) -> TRUE | L86: =AND(G86>=2, G86<3) -> FALSE | M86: =G86>3 -> FALSE | N86: =IF(OR(H86, I86), -D86 * (G86 - 1), 0) -> 0
A87: Marquette | B87: =Funds!A7 -> Fund VI | C87: 50 | D87: 50 | E87: 330.2 | F87: TRUE | G87: =E87/D87 -> 6.604 | H87: =G87=0 -> FALSE | I87: =AND(G87>0, G87<1) -> FALSE | J87: =G87=1 -> FALSE | K87: =AND(G87>1, G87<2) -> FALSE | L87: =AND(G87>=2, G87<3) -> FALSE | M87: =G87>3 -> TRUE | N87: =IF(OR(H87, I87), -D87 * (G87 - 1), 0) -> 0
A88: GulfTex | B88: =Funds!A7 -> Fund VI | C88: 25.7 | D88: 25.7 | E88: 44.2 | F88: TRUE | G88: =E88/D88 -> 1.7198444 | H88: =G88=0 -> FALSE | I88: =AND(G88>0, G88<1) -> FALSE | J88: =G88=1 -> FALSE | K88: =AND(G88>1, G88<2) -> TRUE | L88: =AND(G88>=2, G88<3) -> FALSE | M88: =G88>3 -> FALSE | N88: =IF(OR(H88, I88), -D88 * (G88 - 1), 0) -> 0
A89: GFI (SMDR) | B89: =Funds!A7 -> Fund VI | C89: 12 | D89: 12 | E89: 21.1 | F89: TRUE | G89: =E89/D89 -> 1.7583333 | H89: =G89=0 -> FALSE | I89: =AND(G89>0, G89<1) -> FALSE | J89: =G89=1 -> FALSE | K89: =AND(G89>1, G89<2) -> TRUE | L89: =AND(G89>=2, G89<3) -> FALSE | M89: =G89>3 -> FALSE | N89: =IF(OR(H89, I89), -D89 * (G89 - 1), 0) -> 0
A90: Manti | B90: =Funds!A7 -> Fund VI | C90: 77.9 | D90: 77.9 | E90: 85.6 | F90: TRUE | G90: =E90/D90 -> 1.0988447 | H90: =G90=0 -> FALSE | I90: =AND(G90>0, G90<1) -> FALSE | J90: =G90=1 -> FALSE | K90: =AND(G90>1, G90<2) -> TRUE | L90: =AND(G90>=2, G90<3) -> FALSE | M90: =G90>3 -> FALSE | N90: =IF(OR(H90, I90), -D90 * (G90 - 1), 0) -> 0
A91: Talon | B91: =Funds!A7 -> Fund VI | C91: 135.8 | D91: 135.8 | E91: 368 | F91: TRUE | G91: =E91/D91 -> 2.7098675 | H91: =G91=0 -> FALSE | I91: =AND(G91>0, G91<1) -> FALSE | J91: =G91=1 -> FALSE | K91: =AND(G91>1, G91<2) -> FALSE | L91: =AND(G91>=2, G91<3) -> TRUE | M91: =G91>3 -> FALSE | N91: =IF(OR(H91, I91), -D91 * (G91 - 1), 0) -> 0
A92: Earthstone | B92: =Funds!A7 -> Fund VI | C92: 55.7 | D92: 55.7 | E92: 2.5 | F92: TRUE | G92: =E92/D92 -> 0.044883303 | H92: =G92=0 -> FALSE | I92: =AND(G92>0, G92<1) -> TRUE | J92: =G92=1 -> FALSE | K92: =AND(G92>1, G92<2) -> FALSE | L92: =AND(G92>=2, G92<3) -> FALSE | M92: =G92>3 -> FALSE | N92: =IF(OR(H92, I92), -D92 * (G92 - 1), 0) -> 53.2
A93: Paloma Barnett | B93: =Funds!A7 -> Fund VI | C93: 69.4 | D93: 69.4 | E93: 146.7 | F93: TRUE | G93: =E93/D93 -> 2.1138329 | H93: =G93=0 -> FALSE | I93: =AND(G93>0, G93<1) -> FALSE | J93: =G93=1 -> FALSE | K93: =AND(G93>1, G93<2) -> FALSE | L93: =AND(G93>=2, G93<3) -> TRUE | M93: =G93>3 -> FALSE | N93: =IF(OR(H93, I93), -D93 * (G93 - 1), 0) -> 0
A94: Oasis | B94: =Funds!A7 -> Fund VI | C94: 117 | D94: 117 | E94: 568.2 | F94: TRUE | G94: =E94/D94 -> 4.8564103 | H94: =G94=0 -> FALSE | I94: =AND(G94>0, G94<1) -> FALSE | J94: =G94=1 -> FALSE | K94: =AND(G94>1, G94<2) -> FALSE | L94: =AND(G94>=2, G94<3) -> FALSE | M94: =G94>3 -> TRUE | N94: =IF(OR(H94, I94), -D94 * (G94 - 1), 0) -> 0
A95: Crimson III | B95: =Funds!A7 -> Fund VI | C95: 3.9 | D95: 3.9 | E95: 0.5 | F95: TRUE | G95: =E95/D95 -> 0.12820513 | H95: =G95=0 -> FALSE | I95: =AND(G95>0, G95<1) -> TRUE | J95: =G95=1 -> FALSE | K95: =AND(G95>1, G95<2) -> FALSE | L95: =AND(G95>=2, G95<3) -> FALSE | M95: =G95>3 -> FALSE | N95: =IF(OR(H95, I95), -D95 * (G95 - 1), 0) -> 3.4
A96: Eagle | B96: =Funds!A7 -> Fund VI | C96: 83.7 | D96: 83.7 | E96: 152.8 | F96: TRUE | G96: =E96/D96 -> 1.8255675 | H96: =G96=0 -> FALSE | I96: =AND(G96>0, G96<1) -> FALSE | J96: =G96=1 -> FALSE | K96: =AND(G96>1, G96<2) -> TRUE | L96: =AND(G96>=2, G96<3) -> FALSE | M96: =G96>3 -> FALSE | N96: =IF(OR(H96, I96), -D96 * (G96 - 1), 0) -> 0
A97: Grenadier | B97: =Funds!A7 -> Fund VI | C97: 51.4 | D97: 51.4 | E97: 90 | F97: TRUE | G97: =E97/D97 -> 1.7509728 | H97: =G97=0 -> FALSE | I97: =AND(G97>0, G97<1) -> FALSE | J97: =G97=1 -> FALSE | K97: =AND(G97>1, G97<2) -> TRUE | L97: =AND(G97>=2, G97<3) -> FALSE | M97: =G97>3 -> FALSE | N97: =IF(OR(H97, I97), -D97 * (G97 - 1), 0) -> 0
A98: Mediterranean | B98: =Funds!A7 -> Fund VI | C98: 8.9 | D98: 8.9 | E98: 10.9 | F98: TRUE | G98: =E98/D98 -> 1.2247191 | H98: =G98=0 -> FALSE | I98: =AND(G98>0, G98<1) -> FALSE | J98: =G98=1 -> FALSE | K98: =AND(G98>1, G98<2) -> TRUE | L98: =AND(G98>=2, G98<3) -> FALSE | M98: =G98>3 -> FALSE | N98: =IF(OR(H98, I98), -D98 * (G98 - 1), 0) -> 0
A99: Staghorn | B99: =Funds!A7 -> Fund VI | C99: 9.5 | D99: 9.5 | E99: 24.6 | F99: TRUE | G99: =E99/D99 -> 2.5894737 | H99: =G99=0 -> FALSE | I99: =AND(G99>0, G99<1) -> FALSE | J99: =G99=1 -> FALSE | K99: =AND(G99>1, G99<2) -> FALSE | L99: =AND(G99>=2, G99<3) -> TRUE | M99: =G99>3 -> FALSE | N99: =IF(OR(H99, I99), -D99 * (G99 - 1), 0) -> 0
A100: Phillips Energy I | B100: =Funds!A7 -> Fund VI | C100: 30.6 | D100: 30.6 | E100: 77.5 | F100: TRUE | G100: =E100/D100 -> 2.5326797 | H100: =G100=0 -> FALSE | I100: =AND(G100>0, G100<1) -> FALSE | J100: =G100=1 -> FALSE | K100: =AND(G100>1, G100<2) -> FALSE | L100: =AND(G100>=2, G100<3) -> TRUE | M100: =G100>3 -> FALSE | N100: =IF(OR(H100, I100), -D100 * (G100 - 1), 0) -> 0
...

Sheet Loss Ratio Analysis
B2: Loss Ratio Analysis
B3: Encap Upstream Fund XII
B4: (millions) | C4: =Funds!A2 -> Fund I | F4: =Funds!A3 -> Fund II | I4: =Funds!A4 -> Fund III | L4: =Funds!A5 -> Fund IV | O4: =Funds!A6 -> Fund V | R4: =Funds!A7 -> Fund VI | U4: =Funds!A8 -> Fund VII | X4: =Funds!A9 -> Fund VIII | AA4: =Funds!A10 -> Fund IX | AD4: =Funds!A11 -> Fund X | AG4: =Funds!A12 -> Fund XI | AK4: Total
B5: Vintage Year | C5: =Funds!B2 -> 1994 | F5: =Funds!B3 -> 1996 | I5: =Funds!B4 -> 1997 | L5: =Funds!B5 -> 2001 | O5: =Funds!B6 -> 2004 | R5: =Funds!B7 -> 2006 | U5: =Funds!B8 -> 2007 | X5: =Funds!B9 -> 2010 | AA5: =Funds!B10 -> 2013 | AD5: =Funds!B11 -> 2015 | AG5: =Funds!B12 -> 2017
B6: Committed Capital | C6: =SUMIFS(Portfolios!C:C, Portfolios!B:B, Funds!A2) -> 104.1 | F6: =SUMIFS(Portfolios!C:C, Portfolios!B:B, Funds!A3) -> 114.6 | I6: =SUMIFS(Portfolios!C:C, Portfolios!B:B, Funds!A4) -> 468.6 | L6: =SUMIFS(Portfolios!C:C, Portfolios!B:B, Funds!A5) -> 570.4 | O6: =SUMIFS(Portfolios!C:C, Portfolios!B:B, Funds!A6) -> 922.3 | R6: =SUMIFS(Portfolios!C:C, Portfolios!B:B, Funds!A7) -> 1564.2 | U6: =SUMIFS(Portfolios!C:C, Portfolios!B:B, Funds!A8) -> 2553.1 | X6: =SUMIFS(Portfolios!C:C, Portfolios!B:B, Funds!A9) -> 3761.7 | AA6: =SUMIFS(Portfolios!C:C, Portfolios!B:B, Funds!A10) -> 5442 | AD6: =SUMIFS(Portfolios!C:C, Portfolios!B:B, Funds!A11) -> 6914.8 | AG6: =SUMIFS(Portfolios!C:C, Portfolios!B:B, Funds!A12) -> 7539
B8: Number of realized inv. | C8: =COUNTIFS(Portfolios!F:F, TRUE, Portfolios!B:B, Funds!A2) -> 12 | F8: =COUNTIFS(Portfolios!F:F, TRUE, Portfolios!B:B, Funds!A3) -> 4 | I8: =COUNTIFS(Portfolios!F:F, TRUE, Portfolios!B:B, Funds!A4) -> 20 | L8: =COUNTIFS(Portfolios!F:F, TRUE, Portfolios!B:B, Funds!A5) -> 19 | O8: =COUNTIFS(Portfolios!F:F, TRUE, Portfolios!B:B, Funds!A6) -> 28 | R8: =COUNTIFS(Portfolios!F:F, TRUE, Portfolios!B:B, Funds!A7) -> 27 | U8: =COUNTIFS(Portfolios!F:F, TRUE, Portfolios!B:B, Funds!A8) -> 33 | X8: =COUNTIFS(Portfolios!F:F, TRUE, Portfolios!B:B, Funds!A9) -> 17 | AA8: =COUNTIFS(Portfolios!F:F, TRUE, Portfolios!B:B, Funds!A10) -> 11 | AD8: =COUNTIFS(Portfolios!F:F, TRUE, Portfolios!B:B, Funds!A11) -> 10 | AG8: =COUNTIFS(Portfolios!F:F, TRUE, Portfolios!B:B, Funds!A12) -> 3 | AK8: =COUNTIFS(Portfolios!F:F, TRUE) -> 184
B9: Number of unrealized inv. | C9: =COUNTIFS(Portfolios!F:F, FALSE, Portfolios!B:B, Funds!A2) -> 0 | F9: =COUNTIFS(Portfolios!F:F, FALSE, Portfolios!B:B, Funds!A3) -> 0 | I9: =COUNTIFS(Portfolios!F:F, FALSE, Portfolios!B:B, Funds!A4) -> 0 | L9: =COUNTIFS(Portfolios!F:F, FALSE, Portfolios!B:B, Funds!A5) -> 0 | O9: =COUNTIFS(Portfolios!F:F, FALSE, Portfolios!B:B, Funds!A6) -> 0 | R9: =COUNTIFS(Portfolios!F:F, FALSE, Portfolios!B:B, Funds!A7) -> 0 | U9: =COUNTIFS(Portfolios!F:F, FALSE, Portfolios!B:B, Funds!A8) -> 0 | X9: =COUNTIFS(Portfolios!F:F, FALSE, Portfolios!B:B, Funds!A9) -> 4 | AA9: =COUNTIFS(Portfolios!F:F, FALSE, Portfolios!B:B, Funds!A10) -> 8 | AD9: =COUNTIFS(Portfolios!F:F, FALSE, Portfolios!B:B, Funds!A11) -> 15 | AG9: =COUNTIFS(Portfolios!F:F, FALSE, Portfolios!B:B, Funds!A12) -> 20 | AK9: =COUNTIFS(Portfolios!F:F, FALSE) -> 55
B10: Number of Investments | C10: =C8 + C9 -> 12 | F10: =F8 + F9 -> 4 | I10: =I8 + I9 -> 20 | L10: =L8 + L9 -> 19 | O10: =O8 + O9 -> 28 | R10: =R8 + R9 -> 27 | U10: =U8 + U9 -> 33 | X10: =X8 + X9 -> 21 | AA10: =AA8 + AA9 -> 19 | AD10: =AD8 + AD9 -> 25 | AG10: =AG8 + AG9 -> 23 | AK10: =AK8 + AK9 -> 239
B12: Number of Investments
B13: Held at 0.0x | C13: =COUNTIFS(Portfolios!H:H, TRUE, Portfolios!B:B, Funds!A2) -> 1 | D13: =C13 / C19 -> 0.083333333 | F13: =COUNTIFS(Portfolios!H:H, TRUE, Portfolios!B:B, Funds!A3) -> 0 | G13: =F13 / F19 -> 0 | I13: =COUNTIFS(Portfolios!H:H, TRUE, Portfolios!B:B, Funds!A4) -> 0 | J13: =I13 / I19 -> 0 | L13: =COUNTIFS(Portfolios!H:H, TRUE, Portfolios!B:B, Funds!A5) -> 0 | M13: =L13 / L19 -> 0 | O13: =COUNTIFS(Portfolios!H:H, TRUE, Portfolios!B:B, Funds!A6) -> 0 | P13: =O13 / O19 -> 0 | R13: =COUNTIFS(Portfolios!H:H, TRUE, Portfolios!B:B, Funds!A7) -> 0 | S13: =R13 / R19 -> 0 | U13: =COUNTIFS(Portfolios!H:H, TRUE, Portfolios!B:B, Funds!A8) -> 0 | V13: =U13 / U19 -> 0 | X13: =COUNTIFS(Portfolios!H:H, TRUE, Portfolios!B:B, Funds!A9) -> 2 | Y13: =X13 / X19 -> 0.086956522 | AA13: =COUNTIFS(Portfolios!H:H, TRUE, Portfolios!B:B, Funds!A10) -> 2 | AB13: =AA13 / AA19 -> 0.095238095 | AD13: =COUNTIFS(Portfolios!H:H, TRUE, Portfolios!B:B, Funds!A11) -> 1 | AE13: =AD13 / AD19 -> 0.038461538 | AG13: =COUNTIFS(Portfolios!H:H, TRUE, Portfolios!B:B, Funds!A12) -> 1 | AH13: =AG13 / AG19 -> 0.041666667 | AK13: =COUNTIFS(Portfolios!H:H, TRUE) -> 7 | AL13: =AK13 / AK19 -> 0.028571429
B14: Between 0.0x to 1.0x | C14: =COUNTIFS(Portfolios!I:I, TRUE, Portfolios!B:B, Funds!A2) -> 0 | D14: =C14 / C19 -> 0 | F14: =COUNTIFS(Portfolios!I:I, TRUE, Portfolios!B:B, Funds!A3) -> 0 | G14: =F14 / F19 -> 0 | I14: =COUNTIFS(Portfolios!I:I, TRUE, Portfolios!B:B, Funds!A4) -> 1 | J14: =I14 / I19 -> 0.05 | L14: =COUNTIFS(Portfolios!I:I, TRUE, Portfolios!B:B, Funds!A5) -> 3 | M14: =L14 / L19 -> 0.15789474 | O14: =COUNTIFS(Portfolios!I:I, TRUE, Portfolios!B:B, Funds!A6) -> 5 | P14: =O14 / O19 -> 0.17857143 | R14: =COUNTIFS(Portfolios!I:I, TRUE, Portfolios!B:B, Funds!A7) -> 6 | S14: =R14 / R19 -> 0.22222222 | U14: =COUNTIFS(Portfolios!I:I, TRUE, Portfolios!B:B, Funds!A8) -> 10 | V14: =U14 / U19 -> 0.3030303 | X14: =COUNTIFS(Portfolios!I:I, TRUE, Portfolios!B:B, Funds!A9) -> 12 | Y14: =X14 / X19 -> 0.52173913 | AA14: =COUNTIFS(Portfolios!I:I, TRUE, Portfolios!B:B, Funds!A10) -> 5 | AB14: =AA14 / AA19 -> 0.23809524 | AD14: =COUNTIFS(Portfolios!I:I, TRUE, Portfolios!B:B, Funds!A11) -> 5 | AE14: =AD14 / AD19 -> 0.19230769 | AG14: =COUNTIFS(Portfolios!I:I, TRUE, Portfolios!B:B, Funds!A12) -> 4 | AH14: =AG14 / AG19 -> 0.16666667 | AK14: =COUNTIFS(Portfolios!I:I, TRUE) -> 51 | AL14: =AK14 / AK19 -> 0.20816327
B15: Held at 1.0x (cost) | C15: =COUNTIFS(Portfolios!J:J, TRUE, Portfolios!B:B, Funds!A2) -> 0 | D15: =C15 / C19 -> 0 | F15: =COUNTIFS(Portfolios!J:J, TRUE, Portfolios!B:B, Funds!A3) -> 0 | G15: =F15 / F19 -> 0 | I15: =COUNTIFS(Portfolios!J:J, TRUE, Portfolios!B:B, Funds!A4) -> 0 | J15: =I15 / I19 -> 0 | L15: =COUNTIFS(Portfolios!J:J, TRUE, Portfolios!B:B, Funds!A5) -> 0 | M15: =L15 / L19 -> 0 | O15: =COUNTIFS(Portfolios!J:J, TRUE, Portfolios!B:B, Funds!A6) -> 1 | P15: =O15 / O19 -> 0.035714286 | R15: =COUNTIFS(Portfolios!J:J, TRUE, Portfolios!B:B, Funds!A7) -> 0 | S15: =R15 / R19 -> 0 | U15: =COUNTIFS(Portfolios!J:J, TRUE, Portfolios!B:B, Funds!A8) -> 0 | V15: =U15 / U19 -> 0 | X15: =COUNTIFS(Portfolios!J:J, TRUE, Portfolios!B:B, Funds!A9) -> 0 | Y15: =X15 / X19 -> 0 | AA15: =COUNTIFS(Portfolios!J:J, TRUE, Portfolios!B:B, Funds!A10) -> 0 | AB15: =AA15 / AA19 -> 0 | AD15: =COUNTIFS(Portfolios!J:J, TRUE, Portfolios!B:B, Funds!A11) -> 0 | AE15: =AD15 / AD19 -> 0 | AG15: =COUNTIFS(Portfolios!J:J, TRUE, Portfolios!B:B, Funds!A12) -> 2 | AH15: =AG15 / AG19 -> 0.083333333 | AK15: =COUNTIFS(Portfolios!J:J, TRUE) -> 9 | AL15: =AK15 / AK19 -> 0.036734694
B16: Between 1.0x to 2.0x | C16: =COUNTIFS(Portfolios!K:K, TRUE, Portfolios!B:B, Funds!A2) -> 9 | D16: =C16 / C19 -> 0.75 | F16: =COUNTIFS(Portfolios!K:K, TRUE, Portfolios!B:B, Funds!A3) -> 4 | G16: =F16 / F19 -> 1 | I16: =COUNTIFS(Portfolios!K:K, TRUE, Portfolios!B:B, Funds!A4) -> 12 | J16: =I16 / I19 -> 0.6 | L16: =COUNTIFS(Portfolios!K:K, TRUE, Portfolios!B:B, Funds!A5) -> 3 | M16: =L16 / L19 -> 0.15789474 | O16: =COUNTIFS(Portfolios!K:K, TRUE, Portfolios!B:B, Funds!A6) -> 7 | P16: =O16 / O19 -> 0.25 | R16: =COUNTIFS(Portfolios!K:K, TRUE, Portfolios!B:B, Funds!A7) -> 10 | S16: =R16 / R19 -> 0.37037037 | U16: =COUNTIFS(Portfolios!K:K, TRUE, Portfolios!B:B, Funds!A8) -> 7 | V16: =U16 / U19 -> 0.21212121 | X16: =COUNTIFS(Portfolios!K:K, TRUE, Portfolios!B:B, Funds!A9) -> 4 | Y16: =X16 / X19 -> 0.17391304 | AA16: =COUNTIFS(Portfolios!K:K, TRUE, Portfolios!B:B, Funds!A10) -> 3 | AB16: =AA16 / AA19 -> 0.14285714 | AD16: =COUNTIFS(Portfolios!K:K, TRUE, Portfolios!B:B, Funds!A11) -> 8 | AE16: =AD16 / AD19 -> 0.30769231 | AG16: =COUNTIFS(Portfolios!K:K, TRUE, Portfolios!B:B, Funds!A12) -> 8 | AH16: =AG16 / AG19 -> 0.33333333 | AK16: =COUNTIFS(Portfolios!K:K, TRUE) -> 75 | AL16: =AK16 / AK19 -> 0.30612245
B17: Between 2.0x to 3.0x | C17: =COUNTIFS(Portfolios!L:L, TRUE, Portfolios!B:B, Funds!A2) -> 1 | D17: =C17 / C19 -> 0.083333333 | F17: =COUNTIFS(Portfolios!L:L, TRUE, Portfolios!B:B, Funds!A3) -> 0 | G17: =F17 / F19 -> 0 | I17: =COUNTIFS(Portfolios!L:L, TRUE, Portfolios!B:B, Funds!A4) -> 3 | J17: =I17 / I19 -> 0.15 | L17: =COUNTIFS(Portfolios!L:L, TRUE, Portfolios!B:B, Funds!A5) -> 4 | M17: =L17 / L19 -> 0.21052632 | O17: =COUNTIFS(Portfolios!L:L, TRUE, Portfolios!B:B, Funds!A6) -> 12 | P17: =O17 / O19 -> 0.42857143 | R17: =COUNTIFS(Portfolios!L:L, TRUE, Portfolios!B:B, Funds!A7) -> 7 | S17: =R17 / R19 -> 0.25925926 | U17: =COUNTIFS(Portfolios!L:L, TRUE, Portfolios!B:B, Funds!A8) -> 7 | V17: =U17 / U19 -> 0.21212121 | X17: =COUNTIFS(Portfolios!L:L, TRUE, Portfolios!B:B, Funds!A9) -> 3 | Y17: =X17 / X19 -> 0.13043478 | AA17: =COUNTIFS(Portfolios!L:L, TRUE, Portfolios!B:B, Funds!A10) -> 6 | AB17: =AA17 / AA19 -> 0.28571429 | AD17: =COUNTIFS(Portfolios!L:L, TRUE, Portfolios!B:B, Funds!A11) -> 5 | AE17: =AD17 / AD19 -> 0.19230769 | AG17: =COUNTIFS(Portfolios!L:L, TRUE, Portfolios!B:B, Funds!A12) -> 7 | AH17: =AG17 / AG19 -> 0.29166667 | AK17: =COUNTIFS(Portfolios!L:L, TRUE) -> 57 | AL17: =AK17 / AK19 -> 0.23265306
B18: Above 3.0x | C18: =COUNTIFS(Portfolios!M:M, TRUE, Portfolios!B:B, Funds!A2) -> 1 | D18: =C18 / C19 -> 0.083333333 | F18: =COUNTIFS(Portfolios!M:M, TRUE, Portfolios!B:B, Funds!A3) -> 0 | G18: =F18 / F19 -> 0 | I18: =COUNTIFS(Portfolios!M:M, TRUE, Portfolios!B:B, Funds!A4) -> 4 | J18: =I18 / I19 -> 0.2 | L18: =COUNTIFS(Portfolios!M:M, TRUE, Portfolios!B:B, Funds!A5) -> 9 | M18: =L18 / L19 -> 0.47368421 | O18: =COUNTIFS(Portfolios!M:M, TRUE, Portfolios!B:B, Funds!A6) -> 3 | P18: =O18 / O19 -> 0.10714286 | R18: =COUNTIFS(Portfolios!M:M, TRUE, Portfolios!B:B, Funds!A7) -> 4 | S18: =R18 / R19 -> 0.14814815 | U18: =COUNTIFS(Portfolios!M:M, TRUE, Portfolios!B:B, Funds!A8) -> 9 | V18: =U18 / U19 -> 0.27272727 | X18: =COUNTIFS(Portfolios!M:M, TRUE, Portfolios!B:B, Funds!A9) -> 2 | Y18: =X18 / X19 -> 0.086956522 | AA18: =COUNTIFS(Portfolios!M:M, TRUE, Portfolios!B:B, Funds!A10) -> 5 | AB18: =AA18 / AA19 -> 0.23809524 | AD18: =COUNTIFS(Portfolios!M:M, TRUE, Portfolios!B:B, Funds!A11) -> 7 | AE18: =AD18 / AD19 -> 0.26923077 | AG18: =COUNTIFS(Portfolios!M:M, TRUE, Portfolios!B:B, Funds!A12) -> 2 | AH18: =AG18 / AG19 -> 0.083333333 | AK18: =COUNTIFS(Portfolios!M:M, TRUE) -> 46 | AL18: =AK18 / AK19 -> 0.1877551
B19: Total | C19: =SUM(C13:C18) -> 12 | D19: =SUM(D13:D18) -> 1 | F19: =SUM(F13:F18) -> 4 | G19: =SUM(G13:G18) -> 1 | I19: =SUM(I13:I18) -> 20 | J19: =SUM(J13:J18) -> 1 | L19: =SUM(L13:L18) -> 19 | M19: =SUM(M13:M18) -> 1 | O19: =SUM(O13:O18) -> 28 | P19: =SUM(P13:P18) -> 1 | R19: =SUM(R13:R18) -> 27 | S19: =SUM(S13:S18) -> 1 | U19: =SUM(U13:U18) -> 33 | V19: =SUM(V13:V18) -> 1 | X19: =SUM(X13:X18) -> 23 | Y19: =SUM(Y13:Y18) -> 1 | AA19: =SUM(AA13:AA18) -> 21 | AB19: =SUM(AB13:AB18) -> 1 | AD19: =SUM(AD13:AD18) -> 26 | AE19: =SUM(AE13:AE18) -> 1 | AG19: =SUM(AG13:AG18) -> 24 | AH19: =SUM(AH13:AH18) -> 1 | AK19: =SUM(AK13:AK18) -> 245 | AL19: =SUM(AL13:AL18) -> 1
B21: Capital Invested
B22: Held at 0.0x | C22: =SUMIFS(Portfolios!D:D, Portfolios!H:H, TRUE, Portfolios!B:B, Funds!A2) -> 0.4 | D22: =C22 / C28 -> 0.0038424592 | F22: =SUMIFS(Portfolios!D:D, Portfolios!H:H, TRUE, Portfolios!B:B, Funds!A3) -> 0 | G22: =F22 / F28 -> 0 | I22: =SUMIFS(Portfolios!D:D, Portfolios!H:H, TRUE, Portfolios!B:B, Funds!A4) -> 0 | J22: =I22 / I28 -> 0 | L22: =SUMIFS(Portfolios!D:D, Portfolios!H:H, TRUE, Portfolios!B:B, Funds!A5) -> 0 | M22: =L22 / L28 -> 0 | O22: =SUMIFS(Portfolios!D:D, Portfolios!H:H, TRUE, Portfolios!B:B, Funds!A6) -> 0 | P22: =O22 / O28 -> 0 | R22: =SUMIFS(Portfolios!D:D, Portfolios!H:H, TRUE, Portfolios!B:B, Funds!A7) -> 0 | S22: =R22 / R28 -> 0 | U22: =SUMIFS(Portfolios!D:D, Portfolios!H:H, TRUE, Portfolios!B:B, Funds!A8) -> 0 | V22: =U22 / U28 -> 0 | X22: =SUMIFS(Portfolios!D:D, Portfolios!H:H, TRUE, Portfolios!B:B, Funds!A9) -> 247.5 | Y22: =X22 / X28 -> 0.06579472 | AA22: =SUMIFS(Portfolios!D:D, Portfolios!H:H, TRUE, Portfolios!B:B, Funds!A10) -> 445 | AB22: =AA22 / AA28 -> 0.083531996 | AD22: =SUMIFS(Portfolios!D:D, Portfolios!H:H, TRUE, Portfolios!B:B, Funds!A11) -> 465.5 | AE22: =AD22 / AD28 -> 0.074607728 | AG22: =SUMIFS(Portfolios!D:D, Portfolios!H:H, TRUE, Portfolios!B:B, Funds!A12) -> 5.9 | AH22: =AG22 / AG28 -> 0.00099422004 | AK22: =SUMIFS(Portfolios!D:D, Portfolios!H:H, TRUE) -> 1164.3 | AL22: =AK22 / AK28 -> 0.040985727
B23: Between 0.0x to 1.0x | C23: =SUMIFS(Portfolios!D:D, Portfolios!I:I, TRUE, Portfolios!B:B, Funds!A2) -> 0 | D23: =C23 / C28 -> 0 | F23: =SUMIFS(Portfolios!D:D, Portfolios!I:I, TRUE, Portfolios!B:B, Funds!A3) -> 0 | G23: =F23 / F28 -> 0 | I23: =SUMIFS(Portfolios!D:D, Portfolios!I:I, TRUE, Portfolios!B:B, Funds!A4) -> 25 | J23: =I23 / I28 -> 0.053350405 | L23: =SUMIFS(Portfolios!D:D, Portfolios!I:I, TRUE, Portfolios!B:B, Funds!A5) -> 95.15 | M23: =L23 / L28 -> 0.16679814 | O23: =SUMIFS(Portfolios!D:D, Portfolios!I:I, TRUE, Portfolios!B:B, Funds!A6) -> 110.9 | P23: =O23 / O28 -> 0.12024287 | R23: =SUMIFS(Portfolios!D:D, Portfolios!I:I, TRUE, Portfolios!B:B, Funds!A7) -> 358.4 | S23: =R23 / R28 -> 0.22912671 | U23: =SUMIFS(Portfolios!D:D, Portfolios!I:I, TRUE, Portfolios!B:B, Funds!A8) -> 1180 | V23: =U23 / U28 -> 0.46216513 | X23: =SUMIFS(Portfolios!D:D, Portfolios!I:I, TRUE, Portfolios!B:B, Funds!A9) -> 2115.5 | Y23: =X23 / X28 -> 0.56237871 | AA23: =SUMIFS(Portfolios!D:D, Portfolios!I:I, TRUE, Portfolios!B:B, Funds!A10) -> 1295.1 | AB23: =AA23 / AA28 -> 0.24310626 | AD23: =SUMIFS(Portfolios!D:D, Portfolios!I:I, TRUE, Portfolios!B:B, Funds!A11) -> 574.4 | AE23: =AD23 / AD28 -> 0.092061609 | AG23: =SUMIFS(Portfolios!D:D, Portfolios!I:I, TRUE, Portfolios!B:B, Funds!A12) -> 272.9 | AH23: =AG23 / AG28 -> 0.04598689 | AK23: =SUMIFS(Portfolios!D:D, Portfolios!I:I, TRUE) -> 6027.35 | AL23: =AK23 / AK28 -> 0.21217498
B24: Held at 1.0x (cost) | C24: =SUMIFS(Portfolios!D:D, Portfolios!J:J, TRUE, Portfolios!B:B, Funds!A2) -> 0 | D24: =C24 / C28 -> 0 | F24: =SUMIFS(Portfolios!D:D, Portfolios!J:J, TRUE, Portfolios!B:B, Funds!A3) -> 0 | G24: =F24 / F28 -> 0 | I24: =SUMIFS(Portfolios!D:D, Portfolios!J:J, TRUE, Portfolios!B:B, Funds!A4) -> 0 | J24: =I24 / I28 -> 0 | L24: =SUMIFS(Portfolios!D:D, Portfolios!J:J, TRUE, Portfolios!B:B, Funds!A5) -> 0 | M24: =L24 / L28 -> 0 | O24: =SUMIFS(Portfolios!D:D, Portfolios!J:J, TRUE, Portfolios!B:B, Funds!A6) -> 12.7 | P24: =O24 / O28 -> 0.013769923 | R24: =SUMIFS(Portfolios!D:D, Portfolios!J:J, TRUE, Portfolios!B:B, Funds!A7) -> 0 | S24: =R24 / R28 -> 0 | U24: =SUMIFS(Portfolios!D:D, Portfolios!J:J, TRUE, Portfolios!B:B, Funds!A8) -> 0 | V24: =U24 / U28 -> 0 | X24: =SUMIFS(Portfolios!D:D, Portfolios!J:J, TRUE, Portfolios!B:B, Funds!A9) -> 0 | Y24: =X24 / X28 -> 0 | AA24: =SUMIFS(Portfolios!D:D, Portfolios!J:J, TRUE, Portfolios!B:B, Funds!A10) -> 0 | AB24: =AA24 / AA28 -> 0 | AD24: =SUMIFS(Portfolios!D:D, Portfolios!J:J, TRUE, Portfolios!B:B, Funds!A11) -> 0 | AE24: =AD24 / AD28 -> 0 | AG24: =SUMIFS(Portfolios!D:D, Portfolios!J:J, TRUE, Portfolios!B:B, Funds!A12) -> 135.9 | AH24: =AG24 / AG28 -> 0.022900763 | AK24: =SUMIFS(Portfolios!D:D, Portfolios!J:J, TRUE) -> 515.4 | AL24: =AK24 / AK28 -> 0.018143128
B25: Between 1.0x to 2.0x | C25: =SUMIFS(Portfolios!D:D, Portfolios!K:K, TRUE, Portfolios!B:B, Funds!A2) -> 85.3 | D25: =C25 / C28 -> 0.81940442 | F25: =SUMIFS(Portfolios!D:D, Portfolios!K:K, TRUE, Portfolios!B:B, Funds!A3) -> 114.6 | G25: =F25 / F28 -> 1 | I25: =SUMIFS(Portfolios!D:D, Portfolios!K:K, TRUE, Portfolios!B:B, Funds!A4) -> 184.5 | J25: =I25 / I28 -> 0.39372599 | L25: =SUMIFS(Portfolios!D:D, Portfolios!K:K, TRUE, Portfolios!B:B, Funds!A5) -> 87.8 | M25: =L25 / L28 -> 0.15391358 | O25: =SUMIFS(Portfolios!D:D, Portfolios!K:K, TRUE, Portfolios!B:B, Funds!A6) -> 270.3 | P25: =O25 / O28 -> 0.29307167 | R25: =SUMIFS(Portfolios!D:D, Portfolios!K:K, TRUE, Portfolios!B:B, Funds!A7) -> 512 | S25: =R25 / R28 -> 0.32732387 | U25: =SUMIFS(Portfolios!D:D, Portfolios!K:K, TRUE, Portfolios!B:B, Funds!A8) -> 461.7 | V25: =U25 / U28 -> 0.1808319 | X25: =SUMIFS(Portfolios!D:D, Portfolios!K:K, TRUE, Portfolios!B:B, Funds!A9) -> 482.8 | Y25: =X25 / X28 -> 0.12834623 | AA25: =SUMIFS(Portfolios!D:D, Portfolios!K:K, TRUE, Portfolios!B:B, Funds!A10) -> 1027.2 | AB25: =AA25 / AA28 -> 0.19281813 | AD25: =SUMIFS(Portfolios!D:D, Portfolios!K:K, TRUE, Portfolios!B:B, Funds!A11) -> 1537.4 | AE25: =AD25 / AD28 -> 0.24640585 | AG25: =SUMIFS(Portfolios!D:D, Portfolios!K:K, TRUE, Portfolios!B:B, Funds!A12) -> 2052.8 | AH25: =AG25 / AG28 -> 0.34592117 | AK25: =SUMIFS(Portfolios!D:D, Portfolios!K:K, TRUE) -> 6816.4 | AL25: =AK25 / AK28 -> 0.23995114
B26: Between 2.0x to 3.0x | C26: =SUMIFS(Portfolios!D:D, Portfolios!L:L, TRUE, Portfolios!B:B, Funds!A2) -> 3.6 | D26: =C26 / C28 -> 0.034582133 | F26: =SUMIFS(Portfolios!D:D, Portfolios!L:L, TRUE, Portfolios!B:B, Funds!A3) -> 0 | G26: =F26 / F28 -> 0 | I26: =SUMIFS(Portfolios!D:D, Portfolios!L:L, TRUE, Portfolios!B:B, Funds!A4) -> 145.4 | J26: =I26 / I28 -> 0.31028596 | L26: =SUMIFS(Portfolios!D:D, Portfolios!L:L, TRUE, Portfolios!B:B, Funds!A5) -> 110.9 | M26: =L26 / L28 -> 0.19440792 | O26: =SUMIFS(Portfolios!D:D, Portfolios!L:L, TRUE, Portfolios!B:B, Funds!A6) -> 416.1 | P26: =O26 / O28 -> 0.45115472 | R26: =SUMIFS(Portfolios!D:D, Portfolios!L:L, TRUE, Portfolios!B:B, Funds!A7) -> 361.9 | S26: =R26 / R28 -> 0.23136428 | U26: =SUMIFS(Portfolios!D:D, Portfolios!L:L, TRUE, Portfolios!B:B, Funds!A8) -> 374.3 | V26: =U26 / U28 -> 0.14660034 | X26: =SUMIFS(Portfolios!D:D, Portfolios!L:L, TRUE, Portfolios!B:B, Funds!A9) -> 805.5 | Y26: =X26 / X28 -> 0.21413191 | AA26: =SUMIFS(Portfolios!D:D, Portfolios!L:L, TRUE, Portfolios!B:B, Funds!A10) -> 1285.1 | AB26: =AA26 / AA28 -> 0.24122914 | AD26: =SUMIFS(Portfolios!D:D, Portfolios!L:L, TRUE, Portfolios!B:B, Funds!A11) -> 1624.7 | AE26: =AD26 / AD28 -> 0.2603978 | AG26: =SUMIFS(Portfolios!D:D, Portfolios!L:L, TRUE, Portfolios!B:B, Funds!A12) -> 2574.9 | AH26: =AG26 / AG28 -> 0.43390122 | AK26: =SUMIFS(Portfolios!D:D, Portfolios!L:L, TRUE) -> 8183 | AL26: =AK26 / AK28 -> 0.28805824
B27: Above 3.0x | C27: =SUMIFS(Portfolios!D:D, Portfolios!M:M, TRUE, Portfolios!B:B, Funds!A2) -> 14.8 | D27: =C27 / C28 -> 0.14217099 | F27: =SUMIFS(Portfolios!D:D, Portfolios!M:M, TRUE, Portfolios!B:B, Funds!A3) -> 0 | G27: =F27 / F28 -> 0 | I27: =SUMIFS(Portfolios!D:D, Portfolios!M:M, TRUE, Portfolios!B:B, Funds!A4) -> 113.7 | J27: =I27 / I28 -> 0.24263764 | L27: =SUMIFS(Portfolios!D:D, Portfolios!M:M, TRUE, Portfolios!B:B, Funds!A5) -> 276.6 | M27: =L27 / L28 -> 0.48488036 | O27: =SUMIFS(Portfolios!D:D, Portfolios!M:M, TRUE, Portfolios!B:B, Funds!A6) -> 112.3 | P27: =O27 / O28 -> 0.12176082 | R27: =SUMIFS(Portfolios!D:D, Portfolios!M:M, TRUE, Portfolios!B:B, Funds!A7) -> 331.9 | S27: =R27 / R28 -> 0.21218514 | U27: =SUMIFS(Portfolios!D:D, Portfolios!M:M, TRUE, Portfolios!B:B, Funds!A8) -> 537.2 | V27: =U27 / U28 -> 0.21040263 | X27: =SUMIFS(Portfolios!D:D, Portfolios!M:M, TRUE, Portfolios!B:B, Funds!A9) -> 110.4 | Y27: =X27 / X28 -> 0.029348433 | AA27: =SUMIFS(Portfolios!D:D, Portfolios!M:M, TRUE, Portfolios!B:B, Funds!A10) -> 1274.9 | AB27: =AA27 / AA28 -> 0.23931447 | AD27: =SUMIFS(Portfolios!D:D, Portfolios!M:M, TRUE, Portfolios!B:B, Funds!A11) -> 2037.3 | AE27: =AD27 / AD28 -> 0.32652701 | AG27: =SUMIFS(Portfolios!D:D, Portfolios!M:M, TRUE, Portfolios!B:B, Funds!A12) -> 891.9 | AH27: =AG27 / AG28 -> 0.15029574 | AK27: =SUMIFS(Portfolios!D:D, Portfolios!M:M, TRUE) -> 5701 | AL27: =AK27 / AK28 -> 0.20068679
B28: Total | C28: =SUM(C22:C27) -> 104.1 | D28: =SUM(D22:D27) -> 1 | F28: =SUM(F22:F27) -> 114.6 | G28: =SUM(G22:G27) -> 1 | I28: =SUM(I22:I27) -> 468.6 | J28: =SUM(J22:J27) -> 1 | L28: =SUM(L22:L27) -> 570.45 | M28: =SUM(M22:M27) -> 1 | O28: =SUM(O22:O27) -> 922.3 | P28: =SUM(P22:P27) -> 1 | R28: =SUM(R22:R27) -> 1564.2 | S28: =SUM(S22:S27) -> 1 | U28: =SUM(U22:U27) -> 2553.2 | V28: =SUM(V22:V27) -> 1 | X28: =SUM(X22:X27) -> 3761.7 | Y28: =SUM(Y22:Y27) -> 1 | AA28: =SUM(AA22:AA27) -> 5327.3 | AB28: =SUM(AB22:AB27) -> 1 | AD28: =SUM(AD22:AD27) -> 6239.3 | AE28: =SUM(AE22:AE27) -> 1 | AG28: =SUM(AG22:AG27) -> 5934.3 | AH28: =SUM(AH22:AH27) -> 1 | AK28: =SUM(AK22:AK27) -> 28407.45 | AL28: =SUM(AL22:AL27) -> 1
B30: Capital Invested in Impaired Deals
B31: Capital Invested in Impaired Deals | C31: =C22 + C23 -> 0.4 | F31: =F22 + F23 -> 0 | I31: =I22 + I23 -> 25 | L31: =L22 + L23 -> 95.15 | O31: =O22 + O23 -> 110.9 | R31: =R22 + R23 -> 358.4 | U31: =U22 + U23 -> 1180 | X31: =X22 + X23 -> 2363 | AA31: =AA22 + AA23 -> 1740.1 | AD31: =AD22 + AD23 -> 1039.9 | AG31: =AG22 + AG23 -> 278.8 | AK31: =AK22 + AK23 -> 7191.65
B32: Total capital invested | C32: =C28 -> 104.1 | F32: =F28 -> 114.6 | I32: =I28 -> 468.6 | L32: =L28 -> 570.45 | O32: =O28 -> 922.3 | R32: =R28 -> 1564.2 | U32: =U28 -> 2553.2 | X32: =X28 -> 3761.7 | AA32: =AA28 -> 5327.3 | AD32: =AD28 -> 6239.3 | AG32: =AG28 -> 5934.3 | AK32: =AK28 -> 28407.45
B33: % of capital invested in impaired deals | C33: =C31 / C32 -> 0.0038424592 | F33: =F31 / F32 -> 0 | I33: =I31 / I32 -> 0.053350405 | L33: =L31 / L32 -> 0.16679814 | O33: =O31 / O32 -> 0.12024287 | R33: =R31 / R32 -> 0.22912671 | U33: =U31 / U32 -> 0.46216513 | X33: =X31 / X32 -> 0.62817343 | AA33: =AA31 / AA32 -> 0.32663826 | AD33: =AD31 / AD32 -> 0.16666934 | AG33: =AG31 / AG32 -> 0.04698111 | AK33: =AK31 / AK32 -> 0.2531607
B35: Impaired Capital
B36: Total capital impaired | C36: =SUMIFS(Portfolios!N:N, Portfolios!B:B, Funds!A2) -> 0.4 | F36: =SUMIFS(Portfolios!N:N, Portfolios!B:B, Funds!A3) -> 0 | I36: =SUMIFS(Portfolios!N:N, Portfolios!B:B, Funds!A4) -> 3.7 | L36: =SUMIFS(Portfolios!N:N, Portfolios!B:B, Funds!A5) -> 67.35 | O36: =SUMIFS(Portfolios!N:N, Portfolios!B:B, Funds!A6) -> 99.3 | R36: =SUMIFS(Portfolios!N:N, Portfolios!B:B, Funds!A7) -> 243.4 | U36: =SUMIFS(Portfolios!N:N, Portfolios!B:B, Funds!A8) -> 936.6 | X36: =SUMIFS(Portfolios!N:N, Portfolios!B:B, Funds!A9) -> 1286.2 | AA36: =SUMIFS(Portfolios!N:N, Portfolios!B:B, Funds!A10) -> 1446.7 | AD36: =SUMIFS(Portfolios!N:N, Portfolios!B:B, Funds!A11) -> 930.8 | AG36: =SUMIFS(Portfolios!N:N, Portfolios!B:B, Funds!A12) -> 67.8 | AK36: =SUM(Portfolios!N:N) -> 5082.25
B37: Total capital invested | C37: =C28 -> 104.1 | F37: =F28 -> 114.6 | I37: =I28 -> 468.6 | L37: =L28 -> 570.45 | O37: =O28 -> 922.3 | R37: =R28 -> 1564.2 | U37: =U28 -> 2553.2 | X37: =X28 -> 3761.7 | AA37: =AA28 -> 5327.3 | AD37: =AD28 -> 6239.3 | AG37: =AG28 -> 5934.3 | AK37: =AK28 -> 28407.45
B38: % of capital impaired | C38: =C36 / C28 -> 0.0038424592 | F38: =F36 / F28 -> 0 | I38: =I36 / I28 -> 0.00789586 | L38: =L36 / L28 -> 0.11806469 | O38: =O36 / O28 -> 0.10766562 | R38: =R36 / R28 -> 0.1556067 | U38: =U36 / U28 -> 0.36683378 | X38: =X36 / X28 -> 0.34191988 | AA38: =AA36 / AA28 -> 0.27156346 | AD38: =AD36 / AD28 -> 0.1491834 | AG38: =AG36 / AG28 -> 0.011425105 | AK38: =AK36 / AK28 -> 0.17890553
AK40: =SUM(AL16:AL18)/SUM(AL13:AL14) -> 3.0689655
AK41: =SUM(AL25:AL27)/SUM(AL22:AL23) -> 2.8783937
AL43: =SUM(AL16:AL18) -> 0.72653061
AL44: =SUM(AL25:AL27) -> 0.72869617
